Workbook
Name Departamentos: '[1]BD Competencias'!$F$14:$F$41
Name Display_Week: [2]ProjectSchedule!$I$3
Name Project_Start: [2]ProjectSchedule!$I$2

Sheet SERVICIO
A1: GEOLIS
A2: PROYECTO:
A3: INGRESOS 2025 | B3: [USD] | C3: INSTALACIÓN | D3: M1 | E3: M2 | F3: M3 | G3: M4 | H3: M5 | I3: M6 | J3: M7 | K3: M8 | L3: M9 | M3: M10 | N3: M11 | O3: M12 | P3: M13
A4: DESCRIPCIÓN | B4: Total Presupuestado | C4: - | D4: ENE | E4: FEB | F4: MAR | G4: ABR | H4: MAY | I4: JUN | J4: JUL | K4: AGO | L4: SEP | M4: OCT | N4: NOV | O4: DIC | P4: ENE | Q4: Meses
A5: FACTURACION | B5: =SUM(C5:P5) -> 2633114.9 | C5: ='F08 INGRESOS'!M15 -> 0 | D5: ='F08 INGRESOS'!N15 -> 206127.68 | E5: ='F08 INGRESOS'!O15 -> 186179.84 | F5: ='F08 INGRESOS'!P15 -> 206127.68 | G5: ='F08 INGRESOS'!Q15 -> 199478.4 | H5: ='F08 INGRESOS'!R15 -> 206127.68 | I5: ='F08 INGRESOS'!S15 -> 199478.4 | J5: ='F08 INGRESOS'!T15 -> 206127.68 | ... P5: ='F08 INGRESOS'!Z15 -> 206127.68 | Q5: =COUNTA(E4:P4) -> 12 | S5: ='F08 INGRESOS'!M17 -> 2633114.9 | T5: =+B5-S5 -> 0
A6: INGRESOS 2025 | B6: [USD]
A7: DESCRIPCIÓN | B7: TOTAL PRESUPUESTADO | C7: - | D7: ENERO | E7: FEBRERO | F7: MARZO | G7: ABRIL | H7: MAYO | I7: JUNIO | J7: JULIO | K7: AGOSTO | L7: SEPTIEMBRE | M7: OCTUBRE | N7: NOVIEMBRE | O7: DICIEMBRE | P7: ENERO
A8: EQUIPO DE TRANSPORTE | B8: =SUM(C8:P8) -> 31800 | C8: ='F00 INVERSIÓN'!L11 -> 0 | D8: ='F00 INVERSIÓN'!M11 -> 0 | E8: ='F00 INVERSIÓN'!N11 -> 31800 | F8: ='F00 INVERSIÓN'!O11 -> 0 | G8: ='F00 INVERSIÓN'!P11 -> 0 | H8: ='F00 INVERSIÓN'!Q11 -> 0 | I8: ='F00 INVERSIÓN'!R11 -> 0 | J8: ='F00 INVERSIÓN'!S11 -> 0 | ... P8: ='F00 INVERSIÓN'!Y11 -> 0 | Q8: =B8/$B$166 -> 0.025042387
A9: EQUIPO DE MOBILIARIO | B9: =SUM(C9:P9) -> 0 | C9: ='F00 INVERSIÓN'!L17 -> 0 | D9: ='F00 INVERSIÓN'!M17 -> 0 | E9: ='F00 INVERSIÓN'!N17 -> 0 | F9: ='F00 INVERSIÓN'!O17 -> 0 | G9: ='F00 INVERSIÓN'!P17 -> 0 | H9: ='F00 INVERSIÓN'!Q17 -> 0 | I9: ='F00 INVERSIÓN'!R17 -> 0 | J9: ='F00 INVERSIÓN'!S17 -> 0 | ... P9: ='F00 INVERSIÓN'!Y17 -> 0 | Q9: =B9/$B$166 -> 0
A10: MAQUINARIA Y EQUIPO | B10: =SUM(C10:P10) -> 0 | C10: ='F00 INVERSIÓN'!L26 -> 0 | D10: ='F00 INVERSIÓN'!M26 -> 0 | E10: ='F00 INVERSIÓN'!N26 -> 0 | F10: ='F00 INVERSIÓN'!O26 -> 0 | G10: ='F00 INVERSIÓN'!P26 -> 0 | H10: ='F00 INVERSIÓN'!Q26 -> 0 | I10: ='F00 INVERSIÓN'!R26 -> 0 | J10: ='F00 INVERSIÓN'!S26 -> 0 | ... P10: ='F00 INVERSIÓN'!Y26 -> 0 | Q10: =B10/$B$166 -> 0
A11: OTROS ACTIVOS | B11: =SUM(C11:P11) -> 0 | C11: ='F00 INVERSIÓN'!L32 -> 0 | D11: ='F00 INVERSIÓN'!M32 -> 0 | E11: ='F00 INVERSIÓN'!N32 -> 0 | F11: ='F00 INVERSIÓN'!O32 -> 0 | G11: ='F00 INVERSIÓN'!P32 -> 0 | H11: ='F00 INVERSIÓN'!Q32 -> 0 | I11: ='F00 INVERSIÓN'!R32 -> 0 | J11: ='F00 INVERSIÓN'!S32 -> 0 | ... P11: ='F00 INVERSIÓN'!Y32 -> 0 | Q11: =B11/$B$166 -> 0
A12: SOFTWARE Y LICICENCIAS | B12: =SUM(C12:P12) -> 0 | C12: ='F00 INVERSIÓN'!L38 -> 0 | D12: ='F00 INVERSIÓN'!M38 -> 0 | E12: ='F00 INVERSIÓN'!N38 -> 0 | F12: ='F00 INVERSIÓN'!O38 -> 0 | G12: ='F00 INVERSIÓN'!P38 -> 0 | H12: ='F00 INVERSIÓN'!Q38 -> 0 | I12: ='F00 INVERSIÓN'!R38 -> 0 | J12: ='F00 INVERSIÓN'!S38 -> 0 | ... P12: ='F00 INVERSIÓN'!Y38 -> 0 | Q12: =B12/$B$166 -> 0
A13: ACTIVOS | B13: =SUM(B8:B12) -> 31800 | C13: =SUM(C8:C12) -> 0 | D13: =SUM(D8:D12) -> 0 | E13: =SUM(E8:E12) -> 31800 | F13: =SUM(F8:F12) -> 0 | G13: =SUM(G8:G12) -> 0 | H13: =SUM(H8:H12) -> 0 | I13: =SUM(I8:I12) -> 0 | ... P13: =SUM(P8:P12) -> 0 | Q13: =B13/$B$166 -> 0.025042387 | S13: ='F00 INVERSIÓN'!L42 -> 31800 | T13: =+B13-S13 -> 0
A14: ARRENDAMIENTO DE INMUEBLES | B14: =SUM(C14:P14) -> 0 | C14: ='F02 INMUEBLES Y S'!M7 -> 0 | D14: ='F02 INMUEBLES Y S'!N7 -> 0 | E14: ='F02 INMUEBLES Y S'!O7 -> 0 | F14: ='F02 INMUEBLES Y S'!P7 -> 0 | G14: ='F02 INMUEBLES Y S'!Q7 -> 0 | H14: ='F02 INMUEBLES Y S'!R7 -> 0 | I14: ='F02 INMUEBLES Y S'!S7 -> 0 | J14: ='F02 INMUEBLES Y S'!T7 -> 0 | ... P14: ='F02 INMUEBLES Y S'!Z7 -> 0 | Q14: =B14/$B$166 -> 0
A15: ENERGIA ELECTRICA | B15: =SUM(C15:P15) -> 0 | C15: ='F02 INMUEBLES Y S'!M8 -> 0 | D15: ='F02 INMUEBLES Y S'!N8 -> 0 | E15: ='F02 INMUEBLES Y S'!O8 -> 0 | F15: ='F02 INMUEBLES Y S'!P8 -> 0 | G15: ='F02 INMUEBLES Y S'!Q8 -> 0 | H15: ='F02 INMUEBLES Y S'!R8 -> 0 | I15: ='F02 INMUEBLES Y S'!S8 -> 0 | J15: ='F02 INMUEBLES Y S'!T8 -> 0 | ... P15: ='F02 INMUEBLES Y S'!Z8 -> 0 | Q15: =B15/$B$166 -> 0
A16: RENTA DE CASAS NO DEDUCIBLE | B16: =SUM(C16:P16) -> 0 | C16: ='F02 INMUEBLES Y S'!M9 -> 0 | D16: ='F02 INMUEBLES Y S'!N9 -> 0 | E16: ='F02 INMUEBLES Y S'!O9 -> 0 | F16: ='F02 INMUEBLES Y S'!P9 -> 0 | G16: ='F02 INMUEBLES Y S'!Q9 -> 0 | H16: ='F02 INMUEBLES Y S'!R9 -> 0 | I16: ='F02 INMUEBLES Y S'!S9 -> 0 | J16: ='F02 INMUEBLES Y S'!T9 -> 0 | ... P16: ='F02 INMUEBLES Y S'!Z9 -> 0 | Q16: =B16/$B$166 -> 0
A17: SERVICIOS DE LIMPIEZA | B17: =SUM(C17:P17) -> 0 | C17: ='F02 INMUEBLES Y S'!M10 -> 0 | D17: ='F02 INMUEBLES Y S'!N10 -> 0 | E17: ='F02 INMUEBLES Y S'!O10 -> 0 | F17: ='F02 INMUEBLES Y S'!P10 -> 0 | G17: ='F02 INMUEBLES Y S'!Q10 -> 0 | H17: ='F02 INMUEBLES Y S'!R10 -> 0 | I17: ='F02 INMUEBLES Y S'!S10 -> 0 | J17: ='F02 INMUEBLES Y S'!T10 -> 0 | ... P17: ='F02 INMUEBLES Y S'!Z10 -> 0 | Q17: =B17/$B$166 -> 0
A18: SERVICIOS DE VIGILANCIA | B18: =SUM(C18:P18) -> 0 | C18: ='F02 INMUEBLES Y S'!M11 -> 0 | D18: ='F02 INMUEBLES Y S'!N11 -> 0 | E18: ='F02 INMUEBLES Y S'!O11 -> 0 | F18: ='F02 INMUEBLES Y S'!P11 -> 0 | G18: ='F02 INMUEBLES Y S'!Q11 -> 0 | H18: ='F02 INMUEBLES Y S'!R11 -> 0 | I18: ='F02 INMUEBLES Y S'!S11 -> 0 | J18: ='F02 INMUEBLES Y S'!T11 -> 0 | ... P18: ='F02 INMUEBLES Y S'!Z11 -> 0 | Q18: =B18/$B$166 -> 0
A19: SERVICIOS DE FUMIGACION | B19: =SUM(C19:P19) -> 0 | C19: ='F02 INMUEBLES Y S'!M12 -> 0 | D19: ='F02 INMUEBLES Y S'!N12 -> 0 | E19: ='F02 INMUEBLES Y S'!O12 -> 0 | F19: ='F02 INMUEBLES Y S'!P12 -> 0 | G19: ='F02 INMUEBLES Y S'!Q12 -> 0 | H19: ='F02 INMUEBLES Y S'!R12 -> 0 | I19: ='F02 INMUEBLES Y S'!S12 -> 0 | J19: ='F02 INMUEBLES Y S'!T12 -> 0 | ... P19: ='F02 INMUEBLES Y S'!Z12 -> 0 | Q19: =B19/$B$166 -> 0
A20: TELEFONIA FIJA | B20: =SUM(C20:P20) -> 0 | C20: ='F02 INMUEBLES Y S'!M13 -> 0 | D20: ='F02 INMUEBLES Y S'!N13 -> 0 | E20: ='F02 INMUEBLES Y S'!O13 -> 0 | F20: ='F02 INMUEBLES Y S'!P13 -> 0 | G20: ='F02 INMUEBLES Y S'!Q13 -> 0 | H20: ='F02 INMUEBLES Y S'!R13 -> 0 | I20: ='F02 INMUEBLES Y S'!S13 -> 0 | J20: ='F02 INMUEBLES Y S'!T13 -> 0 | ... P20: ='F02 INMUEBLES Y S'!Z13 -> 0 | Q20: =B20/$B$166 -> 0
A21: AGUA Y ALCANTARILLADO | B21: =SUM(C21:P21) -> 11310 | C21: ='F02 INMUEBLES Y S'!M14 -> 0 | D21: ='F02 INMUEBLES Y S'!N14 -> 870 | E21: ='F02 INMUEBLES Y S'!O14 -> 870 | F21: ='F02 INMUEBLES Y S'!P14 -> 870 | G21: ='F02 INMUEBLES Y S'!Q14 -> 870 | H21: ='F02 INMUEBLES Y S'!R14 -> 870 | I21: ='F02 INMUEBLES Y S'!S14 -> 870 | J21: ='F02 INMUEBLES Y S'!T14 -> 870 | ... P21: ='F02 INMUEBLES Y S'!Z14 -> 870 | Q21: =B21/$B$166 -> 0.0089065849
A22: ARRENDAMIENTO DE OF. MOVILES | B22: =SUM(C22:P22) -> 14950 | C22: ='F02 INMUEBLES Y S'!M15 -> 0 | D22: ='F02 INMUEBLES Y S'!N15 -> 1150 | E22: ='F02 INMUEBLES Y S'!O15 -> 1150 | F22: ='F02 INMUEBLES Y S'!P15 -> 1150 | G22: ='F02 INMUEBLES Y S'!Q15 -> 1150 | H22: ='F02 INMUEBLES Y S'!R15 -> 1150 | I22: ='F02 INMUEBLES Y S'!S15 -> 1150 | J22: ='F02 INMUEBLES Y S'!T15 -> 1150 | ... P22: ='F02 INMUEBLES Y S'!Z15 -> 1150 | Q22: =B22/$B$166 -> 0.011773072
A23: ARRENDA DE INMUEBLES Y SERV | B23: =SUM(B14:B22) -> 26260 | C23: =SUM(C14:C22) -> 0 | D23: =SUM(D14:D22) -> 2020 | E23: =SUM(E14:E22) -> 2020 | F23: =SUM(F14:F22) -> 2020 | G23: =SUM(G14:G22) -> 2020 | H23: =SUM(H14:H22) -> 2020 | I23: =SUM(I14:I22) -> 2020 | ... P23: =SUM(P14:P22) -> 2020 | Q23: =B23/$B$166 -> 0.020679657 | S23: ='F02 INMUEBLES Y S'!M21 -> 26260 | T23: =+B23-S23 -> 0
A24: ROPA Y ARTICULOS DE PROTECCION | B24: =SUM(C24:P24) -> 5265 | C24: ='F01 EPP'!M19 -> 0 | D24: ='F01 EPP'!N19 -> 405 | E24: ='F01 EPP'!O19 -> 405 | F24: ='F01 EPP'!P19 -> 405 | G24: ='F01 EPP'!Q19 -> 405 | H24: ='F01 EPP'!R19 -> 405 | I24: ='F01 EPP'!S19 -> 405 | J24: ='F01 EPP'!T19 -> 405 | ... P24: ='F01 EPP'!Z19 -> 405 | Q24: =B24/$B$166 -> 0.0041461688
A25: ARTICULOS DE SEGURIDAD | B25: =B24 -> 5265 | C25: =C24 -> 0 | D25: =D24 -> 405 | E25: =E24 -> 405 | F25: =F24 -> 405 | G25: =G24 -> 405 | H25: =H24 -> 405 | I25: =I24 -> 405 | ... P25: =P24 -> 405 | Q25: =B25/$B$166 -> 0.0041461688 | S25: ='F01 EPP'!M21 -> 5265 | T25: =+B25-S25 -> 0
A26: EQUIPO DE COMPUTO (Adquisición) | B26: =SUM(C26:P26) -> 0 | C26: ='F03 COM Y EQ COM'!L47 -> 0 | D26: ='F03 COM Y EQ COM'!M47 -> 0 | E26: ='F03 COM Y EQ COM'!N47 -> 0 | F26: ='F03 COM Y EQ COM'!O47 -> 0 | G26: ='F03 COM Y EQ COM'!P47 -> 0 | H26: ='F03 COM Y EQ COM'!Q47 -> 0 | I26: ='F03 COM Y EQ COM'!R47 -> 0 | J26: ='F03 COM Y EQ COM'!S47 -> 0 | ... P26: ='F03 COM Y EQ COM'!Y47 -> 0 | Q26: =B26/$B$166 -> 0
A27: ARRENDAMIENTO DE EQ. COMPUTO | B27: =SUM(C27:P27) -> 0 | C27: ='F03 COM Y EQ COM'!L48 -> 0 | D27: ='F03 COM Y EQ COM'!M48 -> 0 | E27: ='F03 COM Y EQ COM'!N48 -> 0 | F27: ='F03 COM Y EQ COM'!O48 -> 0 | G27: ='F03 COM Y EQ COM'!P48 -> 0 | H27: ='F03 COM Y EQ COM'!Q48 -> 0 | I27: ='F03 COM Y EQ COM'!R48 -> 0 | J27: ='F03 COM Y EQ COM'!S48 -> 0 | ... P27: ='F03 COM Y EQ COM'!Y48 -> 0 | Q27: =B27/$B$166 -> 0
A28: EQUIPO DE COMPUTO | B28: =SUM(B26:B27) -> 0 | C28: =SUM(C26:C27) -> 0 | D28: =SUM(D26:D27) -> 0 | E28: =SUM(E26:E27) -> 0 | F28: =SUM(F26:F27) -> 0 | G28: =SUM(G26:G27) -> 0 | H28: =SUM(H26:H27) -> 0 | I28: =SUM(I26:I27) -> 0 | ... P28: =SUM(P26:P27) -> 0 | Q28: =B28/$B$166 -> 0 | S28: ='F03 COM Y EQ COM'!L52 -> 0 | T28: =+B28-S28 -> 0
A29: ENSERES MENORES DIVERSOS | B29: =SUM(C29:P29) -> 1072.5 | C29: ='F07 OPERAC. (MAT,SERV & EQUIPO)'!L21 -> 0 | D29: ='F07 OPERAC. (MAT,SERV & EQUIPO)'!M21 -> 82.5 | E29: ='F07 OPERAC. (MAT,SERV & EQUIPO)'!N21 -> 82.5 | F29: ='F07 OPERAC. (MAT,SERV & EQUIPO)'!O21 -> 82.5 | G29: ='F07 OPERAC. (MAT,SERV & EQUIPO)'!P21 -> 82.5 | H29: ='F07 OPERAC. (MAT,SERV & EQUIPO)'!Q21 -> 82.5 | I29: ='F07 OPERAC. (MAT,SERV & EQUIPO)'!R21 -> 82.5 | J29: ='F07 OPERAC. (MAT,SERV & EQUIPO)'!S21 -> 82.5 | ... P29: ='F07 OPERAC. (MAT,SERV & EQUIPO)'!Y21 -> 82.5 | Q29: =B29/$B$166 -> 0.00084458995
A30: EQUIPOS Y ENSERES | B30: =B29 -> 1072.5 | C30: =C29 -> 0 | D30: =D29 -> 82.5 | E30: =E29 -> 82.5 | F30: =F29 -> 82.5 | G30: =G29 -> 82.5 | H30: =H29 -> 82.5 | I30: =I29 -> 82.5 | ... P30: =P29 -> 82.5 | Q30: =B30/$B$166 -> 0.00084458995 | S30: ='F07 OPERAC. (MAT,SERV & EQUIPO)'!L23 -> 1072.5 | T30: =+B30-S30 -> 0
A31: INSUMOS AGRICOLAS | B31: =SUM(C31:P31) -> 750.2495 | C31: ='F07 OPERAC. (MAT,SERV & EQUIPO)'!L43 -> 0 | D31: ='F07 OPERAC. (MAT,SERV & EQUIPO)'!M43 -> 57.7115 | E31: ='F07 OPERAC. (MAT,SERV & EQUIPO)'!N43 -> 57.7115 | F31: ='F07 OPERAC. (MAT,SERV & EQUIPO)'!O43 -> 57.7115 | G31: ='F07 OPERAC. (MAT,SERV & EQUIPO)'!P43 -> 57.7115 | H31: ='F07 OPERAC. (MAT,SERV & EQUIPO)'!Q43 -> 57.7115 | I31: ='F07 OPERAC. (MAT,SERV & EQUIPO)'!R43 -> 57.7115 | J31: ='F07 OPERAC. (MAT,SERV & EQUIPO)'!S43 -> 57.7115 | ... P31: ='F07 OPERAC. (MAT,SERV & EQUIPO)'!Y43 -> 57.7115 | Q31: =B31/$B$166 -> 0.00059081882
A32: INSUMOS AGRICOLAS | B32: =B31 -> 750.2495 | C32: =C31 -> 0 | D32: =D31 -> 57.7115 | E32: =E31 -> 57.7115 | F32: =F31 -> 57.7115 | G32: =G31 -> 57.7115 | H32: =H31 -> 57.7115 | I32: =I31 -> 57.7115 | ... P32: =P31 -> 57.7115 | Q32: =B32/$B$166 -> 0.00059081882 | S32: ='F07 OPERAC. (MAT,SERV & EQUIPO)'!L45 -> 750.2495 | T32: =+B32-S32 -> 0
A33: PAPELERIA Y UTILES DE OFICINA | B33: =SUM(C33:P33) -> 325 | C33: ='F07 OPERAC. (MAT,SERV & EQUIPO)'!L125 -> 0 | D33: ='F07 OPERAC. (MAT,SERV & EQUIPO)'!M125 -> 25 | E33: ='F07 OPERAC. (MAT,SERV & EQUIPO)'!N125 -> 25 | F33: ='F07 OPERAC. (MAT,SERV & EQUIPO)'!O125 -> 25 | G33: ='F07 OPERAC. (MAT,SERV & EQUIPO)'!P125 -> 25 | H33: ='F07 OPERAC. (MAT,SERV & EQUIPO)'!Q125 -> 25 | I33: ='F07 OPERAC. (MAT,SERV & EQUIPO)'!R125 -> 25 | J33: ='F07 OPERAC. (MAT,SERV & EQUIPO)'!S125 -> 25 | ... P33: ='F07 OPERAC. (MAT,SERV & EQUIPO)'!Y125 -> 25 | Q33: =B33/$B$166 -> 0.00025593635
A34: ARTICULOS DE ASEO Y SANITARIOS | B34: =SUM(C34:P34) -> 195 | C34: ='F07 OPERAC. (MAT,SERV & EQUIPO)'!L126 -> 0 | D34: ='F07 OPERAC. (MAT,SERV & EQUIPO)'!M126 -> 15 | E34: ='F07 OPERAC. (MAT,SERV & EQUIPO)'!N126 -> 15 | F34: ='F07 OPERAC. (MAT,SERV & EQUIPO)'!O126 -> 15 | G34: ='F07 OPERAC. (MAT,SERV & EQUIPO)'!P126 -> 15 | H34: ='F07 OPERAC. (MAT,SERV & EQUIPO)'!Q126 -> 15 | I34: ='F07 OPERAC. (MAT,SERV & EQUIPO)'!R126 -> 15 | J34: ='F07 OPERAC. (MAT,SERV & EQUIPO)'!S126 -> 15 | ... P34: ='F07 OPERAC. (MAT,SERV & EQUIPO)'!Y126 -> 15 | Q34: =B34/$B$166 -> 0.00015356181
A35: ARTICULOS DE CAFETERIA | B35: =SUM(C35:P35) -> 0 | C35: ='F07 OPERAC. (MAT,SERV & EQUIPO)'!L127 -> 0 | D35: ='F07 OPERAC. (MAT,SERV & EQUIPO)'!M127 -> 0 | E35: ='F07 OPERAC. (MAT,SERV & EQUIPO)'!N127 -> 0 | F35: ='F07 OPERAC. (MAT,SERV & EQUIPO)'!O127 -> 0 | G35: ='F07 OPERAC. (MAT,SERV & EQUIPO)'!P127 -> 0 | H35: ='F07 OPERAC. (MAT,SERV & EQUIPO)'!Q127 -> 0 | I35: ='F07 OPERAC. (MAT,SERV & EQUIPO)'!R127 -> 0 | J35: ='F07 OPERAC. (MAT,SERV & EQUIPO)'!S127 -> 0 | ... P35: ='F07 OPERAC. (MAT,SERV & EQUIPO)'!Y127 -> 0 | Q35: =B35/$B$166 -> 0
A36: ARTICULOS DIGITALES Y DE COMPUTO | B36: =SUM(C36:P36) -> 0 | C36: ='F07 OPERAC. (MAT,SERV & EQUIPO)'!L128 -> 0 | D36: ='F07 OPERAC. (MAT,SERV & EQUIPO)'!M128 -> 0 | E36: ='F07 OPERAC. (MAT,SERV & EQUIPO)'!N128 -> 0 | F36: ='F07 OPERAC. (MAT,SERV & EQUIPO)'!O128 -> 0 | G36: ='F07 OPERAC. (MAT,SERV & EQUIPO)'!P128 -> 0 | H36: ='F07 OPERAC. (MAT,SERV & EQUIPO)'!Q128 -> 0 | I36: ='F07 OPERAC. (MAT,SERV & EQUIPO)'!R128 -> 0 | J36: ='F07 OPERAC. (MAT,SERV & EQUIPO)'!S128 -> 0 | ... P36: ='F07 OPERAC. (MAT,SERV & EQUIPO)'!Y128 -> 0 | Q36: =B36/$B$166 -> 0
A37: INSUMOS DE OFICINA | B37: =SUM(B33:B36) -> 520 | C37: =SUM(C33:C36) -> 0 | D37: =SUM(D33:D36) -> 40 | E37: =SUM(E33:E36) -> 40 | F37: =SUM(F33:F36) -> 40 | G37: =SUM(G33:G36) -> 40 | H37: =SUM(H33:H36) -> 40 | I37: =SUM(I33:I36) -> 40 | ... P37: =SUM(P33:P36) -> 40 | Q37: =B37/$B$166 -> 0.00040949816 | S37: ='F07 OPERAC. (MAT,SERV & EQUIPO)'!L132 -> 520 | T37: =+B37-S37 -> 0
A38: SERVICIOS DE MERCADOTECNIA | B38: =SUM(C38:P38) -> 0 | C38: ='F07 OPERAC. (MAT,SERV & EQUIPO)'!L139 -> 0 | D38: ='F07 OPERAC. (MAT,SERV & EQUIPO)'!M139 -> 0 | E38: ='F07 OPERAC. (MAT,SERV & EQUIPO)'!N139 -> 0 | F38: ='F07 OPERAC. (MAT,SERV & EQUIPO)'!O139 -> 0 | G38: ='F07 OPERAC. (MAT,SERV & EQUIPO)'!P139 -> 0 | H38: ='F07 OPERAC. (MAT,SERV & EQUIPO)'!Q139 -> 0 | I38: ='F07 OPERAC. (MAT,SERV & EQUIPO)'!R139 -> 0 | J38: ='F07 OPERAC. (MAT,SERV & EQUIPO)'!S139 -> 0 | ... P38: ='F07 OPERAC. (MAT,SERV & EQUIPO)'!Y139 -> 0 | Q38: =B38/$B$166 -> 0
A39: PUBLICIDAD Y PROPAGANDA | B39: =SUM(C39:P39) -> 0 | C39: ='F07 OPERAC. (MAT,SERV & EQUIPO)'!L140 -> 0 | D39: ='F07 OPERAC. (MAT,SERV & EQUIPO)'!M140 -> 0 | E39: ='F07 OPERAC. (MAT,SERV & EQUIPO)'!N140 -> 0 | F39: ='F07 OPERAC. (MAT,SERV & EQUIPO)'!O140 -> 0 | G39: ='F07 OPERAC. (MAT,SERV & EQUIPO)'!P140 -> 0 | H39: ='F07 OPERAC. (MAT,SERV & EQUIPO)'!Q140 -> 0 | I39: ='F07 OPERAC. (MAT,SERV & EQUIPO)'!R140 -> 0 | J39: ='F07 OPERAC. (MAT,SERV & EQUIPO)'!S140 -> 0 | ... P39: ='F07 OPERAC. (MAT,SERV & EQUIPO)'!Y140 -> 0 | Q39: =B39/$B$166 -> 0
A40: MARKETING | B40: =SUM(B38:B39) -> 0 | C40: =SUM(C38:C39) -> 0 | D40: =SUM(D38:D39) -> 0 | E40: =SUM(E38:E39) -> 0 | F40: =SUM(F38:F39) -> 0 | G40: =SUM(G38:G39) -> 0 | H40: =SUM(H38:H39) -> 0 | I40: =SUM(I38:I39) -> 0 | ... P40: =SUM(P38:P39) -> 0 | Q40: =B40/$B$166 -> 0 | S40: ='F07 OPERAC. (MAT,SERV & EQUIPO)'!L144 -> 0 | T40: =+B40-S40 -> 0
A41: ABRASIVOS | B41: =SUM(C41:P41) -> 1300 | C41: ='F06 (MAT,SERV & EQUIPO)'!L7 -> 0 | D41: ='F06 (MAT,SERV & EQUIPO)'!M7 -> 100 | E41: ='F06 (MAT,SERV & EQUIPO)'!N7 -> 100 | F41: ='F06 (MAT,SERV & EQUIPO)'!O7 -> 100 | G41: ='F06 (MAT,SERV & EQUIPO)'!P7 -> 100 | H41: ='F06 (MAT,SERV & EQUIPO)'!Q7 -> 100 | I41: ='F06 (MAT,SERV & EQUIPO)'!R7 -> 100 | J41: ='F06 (MAT,SERV & EQUIPO)'!S7 -> 100 | ... P41: ='F06 (MAT,SERV & EQUIPO)'!Y7 -> 100 | Q41: =B41/$B$166 -> 0.0010237454
A42: ACEITE LUBRICANTE P/MAQUINARIA | B42: =SUM(C42:P42) -> 0 | C42: ='F06 (MAT,SERV & EQUIPO)'!L8 -> 0 | D42: ='F06 (MAT,SERV & EQUIPO)'!M8 -> 0 | E42: ='F06 (MAT,SERV & EQUIPO)'!N8 -> 0 | F42: ='F06 (MAT,SERV & EQUIPO)'!O8 -> 0 | G42: ='F06 (MAT,SERV & EQUIPO)'!P8 -> 0 | H42: ='F06 (MAT,SERV & EQUIPO)'!Q8 -> 0 | I42: ='F06 (MAT,SERV & EQUIPO)'!R8 -> 0 | J42: ='F06 (MAT,SERV & EQUIPO)'!S8 -> 0 | ... P42: ='F06 (MAT,SERV & EQUIPO)'!Y8 -> 0 | Q42: =B42/$B$166 -> 0
A43: ACEITES Y LUBRICANTES | B43: =SUM(C43:P43) -> 0 | C43: ='F06 (MAT,SERV & EQUIPO)'!L9 -> 0 | D43: ='F06 (MAT,SERV & EQUIPO)'!M9 -> 0 | E43: ='F06 (MAT,SERV & EQUIPO)'!N9 -> 0 | F43: ='F06 (MAT,SERV & EQUIPO)'!O9 -> 0 | G43: ='F06 (MAT,SERV & EQUIPO)'!P9 -> 0 | H43: ='F06 (MAT,SERV & EQUIPO)'!Q9 -> 0 | I43: ='F06 (MAT,SERV & EQUIPO)'!R9 -> 0 | J43: ='F06 (MAT,SERV & EQUIPO)'!S9 -> 0 | ... P43: ='F06 (MAT,SERV & EQUIPO)'!Y9 -> 0 | Q43: =B43/$B$166 -> 0
A44: AISLANTES IMPERM REFRA | B44: =SUM(C44:P44) -> 0 | C44: ='F06 (MAT,SERV & EQUIPO)'!L10 -> 0 | D44: ='F06 (MAT,SERV & EQUIPO)'!M10 -> 0 | E44: ='F06 (MAT,SERV & EQUIPO)'!N10 -> 0 | F44: ='F06 (MAT,SERV & EQUIPO)'!O10 -> 0 | G44: ='F06 (MAT,SERV & EQUIPO)'!P10 -> 0 | H44: ='F06 (MAT,SERV & EQUIPO)'!Q10 -> 0 | I44: ='F06 (MAT,SERV & EQUIPO)'!R10 -> 0 | J44: ='F06 (MAT,SERV & EQUIPO)'!S10 -> 0 | ... P44: ='F06 (MAT,SERV & EQUIPO)'!Y10 -> 0 | Q44: =B44/$B$166 -> 0
A45: BANDA CADEN TRANS COPL | B45: =SUM(C45:P45) -> 0 | C45: ='F06 (MAT,SERV & EQUIPO)'!L11 -> 0 | D45: ='F06 (MAT,SERV & EQUIPO)'!M11 -> 0 | E45: ='F06 (MAT,SERV & EQUIPO)'!N11 -> 0 | F45: ='F06 (MAT,SERV & EQUIPO)'!O11 -> 0 | G45: ='F06 (MAT,SERV & EQUIPO)'!P11 -> 0 | H45: ='F06 (MAT,SERV & EQUIPO)'!Q11 -> 0 | I45: ='F06 (MAT,SERV & EQUIPO)'!R11 -> 0 | J45: ='F06 (MAT,SERV & EQUIPO)'!S11 -> 0 | ... P45: ='F06 (MAT,SERV & EQUIPO)'!Y11 -> 0 | Q45: =B45/$B$166 -> 0
A46: CONEXIONES PARA TUBERIA | B46: =SUM(C46:P46) -> 0 | C46: ='F06 (MAT,SERV & EQUIPO)'!L12 -> 0 | D46: ='F06 (MAT,SERV & EQUIPO)'!M12 -> 0 | E46: ='F06 (MAT,SERV & EQUIPO)'!N12 -> 0 | F46: ='F06 (MAT,SERV & EQUIPO)'!O12 -> 0 | G46: ='F06 (MAT,SERV & EQUIPO)'!P12 -> 0 | H46: ='F06 (MAT,SERV & EQUIPO)'!Q12 -> 0 | I46: ='F06 (MAT,SERV & EQUIPO)'!R12 -> 0 | J46: ='F06 (MAT,SERV & EQUIPO)'!S12 -> 0 | ... P46: ='F06 (MAT,SERV & EQUIPO)'!Y12 -> 0 | Q46: =B46/$B$166 -> 0
A47: EMPAQUETAD JTAS Y SELLOS | B47: =SUM(C47:P47) -> 0 | C47: ='F06 (MAT,SERV & EQUIPO)'!L13 -> 0 | D47: ='F06 (MAT,SERV & EQUIPO)'!M13 -> 0 | E47: ='F06 (MAT,SERV & EQUIPO)'!N13 -> 0 | F47: ='F06 (MAT,SERV & EQUIPO)'!O13 -> 0 | G47: ='F06 (MAT,SERV & EQUIPO)'!P13 -> 0 | H47: ='F06 (MAT,SERV & EQUIPO)'!Q13 -> 0 | I47: ='F06 (MAT,SERV & EQUIPO)'!R13 -> 0 | J47: ='F06 (MAT,SERV & EQUIPO)'!S13 -> 0 | ... P47: ='F06 (MAT,SERV & EQUIPO)'!Y13 -> 0 | Q47: =B47/$B$166 -> 0
A48: ENVASES | B48: =SUM(C48:P48) -> 0 | C48: ='F06 (MAT,SERV & EQUIPO)'!L14 -> 0 | D48: ='F06 (MAT,SERV & EQUIPO)'!M14 -> 0 | E48: ='F06 (MAT,SERV & EQUIPO)'!N14 -> 0 | F48: ='F06 (MAT,SERV & EQUIPO)'!O14 -> 0 | G48: ='F06 (MAT,SERV & EQUIPO)'!P14 -> 0 | H48: ='F06 (MAT,SERV & EQUIPO)'!Q14 -> 0 | I48: ='F06 (MAT,SERV & EQUIPO)'!R14 -> 0 | J48: ='F06 (MAT,SERV & EQUIPO)'!S14 -> 0 | ... P48: ='F06 (MAT,SERV & EQUIPO)'!Y14 -> 0 | Q48: =B48/$B$166 -> 0
A49: FIBRAS HILOS Y TELAS | B49: =SUM(C49:P49) -> 0 | C49: ='F06 (MAT,SERV & EQUIPO)'!L15 -> 0 | D49: ='F06 (MAT,SERV & EQUIPO)'!M15 -> 0 | E49: ='F06 (MAT,SERV & EQUIPO)'!N15 -> 0 | F49: ='F06 (MAT,SERV & EQUIPO)'!O15 -> 0 | G49: ='F06 (MAT,SERV & EQUIPO)'!P15 -> 0 | H49: ='F06 (MAT,SERV & EQUIPO)'!Q15 -> 0 | I49: ='F06 (MAT,SERV & EQUIPO)'!R15 -> 0 | J49: ='F06 (MAT,SERV & EQUIPO)'!S15 -> 0 | ... P49: ='F06 (MAT,SERV & EQUIPO)'!Y15 -> 0 | Q49: =B49/$B$166 -> 0
A50: GRASAS | B50: =SUM(C50:P50) -> 0 | C50: ='F06 (MAT,SERV & EQUIPO)'!L16 -> 0 | D50: ='F06 (MAT,SERV & EQUIPO)'!M16 -> 0 | E50: ='F06 (MAT,SERV & EQUIPO)'!N16 -> 0 | F50: ='F06 (MAT,SERV & EQUIPO)'!O16 -> 0 | G50: ='F06 (MAT,SERV & EQUIPO)'!P16 -> 0 | H50: ='F06 (MAT,SERV & EQUIPO)'!Q16 -> 0 | I50: ='F06 (MAT,SERV & EQUIPO)'!R16 -> 0 | J50: ='F06 (MAT,SERV & EQUIPO)'!S16 -> 0 | ... P50: ='F06 (MAT,SERV & EQUIPO)'!Y16 -> 0 | Q50: =B50/$B$166 -> 0
A51: HERRAMIENTAS MANUALES | B51: =SUM(C51:P51) -> 0 | C51: ='F06 (MAT,SERV & EQUIPO)'!L17 -> 0 | D51: ='F06 (MAT,SERV & EQUIPO)'!M17 -> 0 | E51: ='F06 (MAT,SERV & EQUIPO)'!N17 -> 0 | F51: ='F06 (MAT,SERV & EQUIPO)'!O17 -> 0 | G51: ='F06 (MAT,SERV & EQUIPO)'!P17 -> 0 | H51: ='F06 (MAT,SERV & EQUIPO)'!Q17 -> 0 | I51: ='F06 (MAT,SERV & EQUIPO)'!R17 -> 0 | J51: ='F06 (MAT,SERV & EQUIPO)'!S17 -> 0 | ... P51: ='F06 (MAT,SERV & EQUIPO)'!Y17 -> 0 | Q51: =B51/$B$166 -> 0
A52: INSTRUM DE MEDICION Y CONTROL | B52: =SUM(C52:P52) -> 203 | C52: ='F06 (MAT,SERV & EQUIPO)'!L18 -> 0 | D52: ='F06 (MAT,SERV & EQUIPO)'!M18 -> 0 | E52: ='F06 (MAT,SERV & EQUIPO)'!N18 -> 0 | F52: ='F06 (MAT,SERV & EQUIPO)'!O18 -> 0 | G52: ='F06 (MAT,SERV & EQUIPO)'!P18 -> 0 | H52: ='F06 (MAT,SERV & EQUIPO)'!Q18 -> 0 | I52: ='F06 (MAT,SERV & EQUIPO)'!R18 -> 203 | J52: ='F06 (MAT,SERV & EQUIPO)'!S18 -> 0 | ... P52: ='F06 (MAT,SERV & EQUIPO)'!Y18 -> 0 | Q52: =B52/$B$166 -> 0.00015986178
... A75: VALVULAS | B75: =SUM(C75:P75) -> 0 | C75: ='F06 (MAT,SERV & EQUIPO)'!L41 -> 0 | D75: ='F06 (MAT,SERV & EQUIPO)'!M41 -> 0 | E75: ='F06 (MAT,SERV & EQUIPO)'!N41 -> 0 | F75: ='F06 (MAT,SERV & EQUIPO)'!O41 -> 0 | G75: ='F06 (MAT,SERV & EQUIPO)'!P41 -> 0 | H75: ='F06 (MAT,SERV & EQUIPO)'!Q41 -> 0 | I75: ='F06 (MAT,SERV & EQUIPO)'!R41 -> 0 | J75: ='F06 (MAT,SERV & EQUIPO)'!S41 -> 0 | ... P75: ='F06 (MAT,SERV & EQUIPO)'!Y41 -> 0 | Q75: =B75/$B$166 -> 0
A76: MATERIALES | B76: =SUM(B41:B75) -> 23333 | C76: =SUM(C41:C75) -> 0 | D76: =SUM(D41:D75) -> 2760 | E76: =SUM(E41:E75) -> 1260 | F76: =SUM(F41:F75) -> 1260 | G76: =SUM(G41:G75) -> 3510 | H76: =SUM(H41:H75) -> 1260 | I76: =SUM(I41:I75) -> 2963 | ... P76: =SUM(P41:P75) -> 1260 | Q76: =B76/$B$166 -> 0.018374655 | S76: ='F06 (MAT,SERV & EQUIPO)'!L45 -> 23333 | T76: =+B76-S76 -> 0
A77: MATERIAL PRIMEROS AUXILIOS | B77: =SUM(C77:P77) -> 455 | C77: ='F07 OPERAC. (MAT,SERV & EQUIPO)'!L162 -> 0 | D77: ='F07 OPERAC. (MAT,SERV & EQUIPO)'!M162 -> 35 | E77: ='F07 OPERAC. (MAT,SERV & EQUIPO)'!N162 -> 35 | F77: ='F07 OPERAC. (MAT,SERV & EQUIPO)'!O162 -> 35 | G77: ='F07 OPERAC. (MAT,SERV & EQUIPO)'!P162 -> 35 | H77: ='F07 OPERAC. (MAT,SERV & EQUIPO)'!Q162 -> 35 | I77: ='F07 OPERAC. (MAT,SERV & EQUIPO)'!R162 -> 35 | J77: ='F07 OPERAC. (MAT,SERV & EQUIPO)'!S162 -> 35 | ... P77: ='F07 OPERAC. (MAT,SERV & EQUIPO)'!Y162 -> 35 | Q77: =B77/$B$166 -> 0.00035831089
A78: MATERIALES DE SALUD | B78: =SUM(B77) -> 455 | C78: =C77 -> 0 | D78: =D77 -> 35 | E78: =E77 -> 35 | F78: =F77 -> 35 | G78: =G77 -> 35 | H78: =H77 -> 35 | I78: =I77 -> 35 | J78: =J77 -> 35 | ... P78: =P77 -> 35 | Q78: =B78/$B$166 -> 0.00035831089 | S78: ='F07 OPERAC. (MAT,SERV & EQUIPO)'!L164 -> 455 | T78: =+B78-S78 -> 0
A79: NOMINA Y ADICIONALES | B79: =SUM(C79:P79) -> 228019.29 | C79: =NOMINA!V19 -> 0 | D79: =NOMINA!W19 -> 16104.273 | E79: =NOMINA!X19 -> 16104.273 | F79: =NOMINA!Y19 -> 16104.273 | G79: =NOMINA!Z19 -> 16104.273 | H79: =NOMINA!AA19 -> 21436.773 | I79: =NOMINA!AB19 -> 16104.273 | J79: =NOMINA!AC19 -> 16104.273 | ... P79: =NOMINA!AI19 -> 16104.273 | Q79: =B79/$B$166 -> 0.17956439
A80: NOMINA Y ADICIONALES | B80: =SUM(B79) -> 228019.29 | C80: =C79 -> 0 | D80: =D79 -> 16104.273 | E80: =E79 -> 16104.273 | F80: =F79 -> 16104.273 | G80: =G79 -> 16104.273 | H80: =H79 -> 21436.773 | I80: =I79 -> 16104.273 | J80: =J79 -> 16104.273 | ... P80: =P79 -> 16104.273 | Q80: =B80/$B$166 -> 0.17956439 | S80: =NOMINA!V21 -> 228019.29 | T80: =+B80-S80 -> 0
A81: SERV TELEFONIA CELULAR | B81: =SUM(C81:P81) -> 0 | C81: ='F03 COM Y EQ COM'!L11 -> 0 | D81: ='F03 COM Y EQ COM'!M11 -> 0 | E81: ='F03 COM Y EQ COM'!N11 -> 0 | F81: ='F03 COM Y EQ COM'!O11 -> 0 | G81: ='F03 COM Y EQ COM'!P11 -> 0 | H81: ='F03 COM Y EQ COM'!Q11 -> 0 | I81: ='F03 COM Y EQ COM'!R11 -> 0 | J81: ='F03 COM Y EQ COM'!S11 -> 0 | ... P81: ='F03 COM Y EQ COM'!Y11 -> 0 | Q81: =B81/$B$166 -> 0
A82: SERVICIO DE BANDA ANCHA | B82: =SUM(C82:P82) -> 975 | C82: ='F03 COM Y EQ COM'!L20 -> 0 | D82: ='F03 COM Y EQ COM'!M20 -> 75 | E82: ='F03 COM Y EQ COM'!N20 -> 75 | F82: ='F03 COM Y EQ COM'!O20 -> 75 | G82: ='F03 COM Y EQ COM'!P20 -> 75 | H82: ='F03 COM Y EQ COM'!Q20 -> 75 | I82: ='F03 COM Y EQ COM'!R20 -> 75 | J82: ='F03 COM Y EQ COM'!S20 -> 75 | ... P82: ='F03 COM Y EQ COM'!Y20 -> 75 | Q82: =B82/$B$166 -> 0.00076780904
A83: SERVICIO DE RADIOCOMUNICACION | B83: =SUM(C83:P83) -> 0 | C83: ='F03 COM Y EQ COM'!L29 -> 0 | D83: ='F03 COM Y EQ COM'!M29 -> 0 | E83: ='F03 COM Y EQ COM'!N29 -> 0 | F83: ='F03 COM Y EQ COM'!O29 -> 0 | G83: ='F03 COM Y EQ COM'!P29 -> 0 | H83: ='F03 COM Y EQ COM'!Q29 -> 0 | I83: ='F03 COM Y EQ COM'!R29 -> 0 | J83: ='F03 COM Y EQ COM'!S29 -> 0 | ... P83: ='F03 COM Y EQ COM'!Y29 -> 0 | Q83: =B83/$B$166 -> 0
A84: SERV TELEFONIA CELULAR Y RADIO | B84: =SUM(B81:B83) -> 975 | C84: =SUM(C81:C83) -> 0 | D84: =SUM(D81:D83) -> 75 | E84: =SUM(E81:E83) -> 75 | F84: =SUM(F81:F83) -> 75 | G84: =SUM(G81:G83) -> 75 | H84: =SUM(H81:H83) -> 75 | I84: =SUM(I81:I83) -> 75 | ... P84: =SUM(P81:P83) -> 75 | Q84: =B84/$B$166 -> 0.00076780904 | S84: ='F03 COM Y EQ COM'!L37 -> 975 | T84: =+B84-S84 -> 0
A85: ACONDICION DE CASA HABITACION | B85: =SUM(C85:P85) -> 0 | C85: ='F07 OPERAC. (MAT,SERV & EQUIPO)'!L52 -> 0 | D85: ='F07 OPERAC. (MAT,SERV & EQUIPO)'!M52 -> 0 | E85: ='F07 OPERAC. (MAT,SERV & EQUIPO)'!N52 -> 0 | F85: ='F07 OPERAC. (MAT,SERV & EQUIPO)'!O52 -> 0 | G85: ='F07 OPERAC. (MAT,SERV & EQUIPO)'!P52 -> 0 | H85: ='F07 OPERAC. (MAT,SERV & EQUIPO)'!Q52 -> 0 | I85: ='F07 OPERAC. (MAT,SERV & EQUIPO)'!R52 -> 0 | J85: ='F07 OPERAC. (MAT,SERV & EQUIPO)'!S52 -> 0 | ... P85: ='F07 OPERAC. (MAT,SERV & EQUIPO)'!Y52 -> 0 | Q85: =B85/$B$166 -> 0
A86: ADICION Y MODIFIC DE MATERIAL | B86: =SUM(C86:P86) -> 0 | C86: ='F07 OPERAC. (MAT,SERV & EQUIPO)'!L53 -> 0 | D86: ='F07 OPERAC. (MAT,SERV & EQUIPO)'!M53 -> 0 | E86: ='F07 OPERAC. (MAT,SERV & EQUIPO)'!N53 -> 0 | F86: ='F07 OPERAC. (MAT,SERV & EQUIPO)'!O53 -> 0 | G86: ='F07 OPERAC. (MAT,SERV & EQUIPO)'!P53 -> 0 | H86: ='F07 OPERAC. (MAT,SERV & EQUIPO)'!Q53 -> 0 | I86: ='F07 OPERAC. (MAT,SERV & EQUIPO)'!R53 -> 0 | J86: ='F07 OPERAC. (MAT,SERV & EQUIPO)'!S53 -> 0 | ... P86: ='F07 OPERAC. (MAT,SERV & EQUIPO)'!Y53 -> 0 | Q86: =B86/$B$166 -> 0
A87: ADQUISICION TARJET COMBUSTIBLE | B87: =SUM(C87:P87) -> 0 | C87: ='F07 OPERAC. (MAT,SERV & EQUIPO)'!L54 -> 0 | D87: ='F07 OPERAC. (MAT,SERV & EQUIPO)'!M54 -> 0 | E87: ='F07 OPERAC. (MAT,SERV & EQUIPO)'!N54 -> 0 | F87: ='F07 OPERAC. (MAT,SERV & EQUIPO)'!O54 -> 0 | G87: ='F07 OPERAC. (MAT,SERV & EQUIPO)'!P54 -> 0 | H87: ='F07 OPERAC. (MAT,SERV & EQUIPO)'!Q54 -> 0 | I87: ='F07 OPERAC. (MAT,SERV & EQUIPO)'!R54 -> 0 | J87: ='F07 OPERAC. (MAT,SERV & EQUIPO)'!S54 -> 0 | ... P87: ='F07 OPERAC. (MAT,SERV & EQUIPO)'!Y54 -> 0 | Q87: =B87/$B$166 -> 0
A88: ANALISIS CAUSA RAIZ | B88: =SUM(C88:P88) -> 1625 | C88: ='F07 OPERAC. (MAT,SERV & EQUIPO)'!L55 -> 0 | D88: ='F07 OPERAC. (MAT,SERV & EQUIPO)'!M55 -> 125 | E88: ='F07 OPERAC. (MAT,SERV & EQUIPO)'!N55 -> 125 | F88: ='F07 OPERAC. (MAT,SERV & EQUIPO)'!O55 -> 125 | G88: ='F07 OPERAC. (MAT,SERV & EQUIPO)'!P55 -> 125 | H88: ='F07 OPERAC. (MAT,SERV & EQUIPO)'!Q55 -> 125 | I88: ='F07 OPERAC. (MAT,SERV & EQUIPO)'!R55 -> 125 | J88: ='F07 OPERAC. (MAT,SERV & EQUIPO)'!S55 -> 125 | ... P88: ='F07 OPERAC. (MAT,SERV & EQUIPO)'!Y55 -> 125 | Q88: =B88/$B$166 -> 0.0012796817
A89: ANALISIS DE RIESGO | B89: =SUM(C89:P89) -> 0 | C89: ='F07 OPERAC. (MAT,SERV & EQUIPO)'!L56 -> 0 | D89: ='F07 OPERAC. (MAT,SERV & EQUIPO)'!M56 -> 0 | E89: ='F07 OPERAC. (MAT,SERV & EQUIPO)'!N56 -> 0 | F89: ='F07 OPERAC. (MAT,SERV & EQUIPO)'!O56 -> 0 | G89: ='F07 OPERAC. (MAT,SERV & EQUIPO)'!P56 -> 0 | H89: ='F07 OPERAC. (MAT,SERV & EQUIPO)'!Q56 -> 0 | I89: ='F07 OPERAC. (MAT,SERV & EQUIPO)'!R56 -> 0 | J89: ='F07 OPERAC. (MAT,SERV & EQUIPO)'!S56 -> 0 | ... P89: ='F07 OPERAC. (MAT,SERV & EQUIPO)'!Y56 -> 0 | Q89: =B89/$B$166 -> 0
A90: ANALISIS DE VIBRACION | B90: =SUM(C90:P90) -> 0 | C90: ='F07 OPERAC. (MAT,SERV & EQUIPO)'!L57 -> 0 | D90: ='F07 OPERAC. (MAT,SERV & EQUIPO)'!M57 -> 0 | E90: ='F07 OPERAC. (MAT,SERV & EQUIPO)'!N57 -> 0 | F90: ='F07 OPERAC. (MAT,SERV & EQUIPO)'!O57 -> 0 | G90: ='F07 OPERAC. (MAT,SERV & EQUIPO)'!P57 -> 0 | H90: ='F07 OPERAC. (MAT,SERV & EQUIPO)'!Q57 -> 0 | I90: ='F07 OPERAC. (MAT,SERV & EQUIPO)'!R57 -> 0 | J90: ='F07 OPERAC. (MAT,SERV & EQUIPO)'!S57 -> 0 | ... P90: ='F07 OPERAC. (MAT,SERV & EQUIPO)'!Y57 -> 0 | Q90: =B90/$B$166 -> 0
A91: BASES LICITACION Y CONCURSOS | B91: =SUM(C91:P91) -> 0 | C91: ='F07 OPERAC. (MAT,SERV & EQUIPO)'!L58 -> 0 | D91: ='F07 OPERAC. (MAT,SERV & EQUIPO)'!M58 -> 0 | E91: ='F07 OPERAC. (MAT,SERV & EQUIPO)'!N58 -> 0 | F91: ='F07 OPERAC. (MAT,SERV & EQUIPO)'!O58 -> 0 | G91: ='F07 OPERAC. (MAT,SERV & EQUIPO)'!P58 -> 0 | H91: ='F07 OPERAC. (MAT,SERV & EQUIPO)'!Q58 -> 0 | I91: ='F07 OPERAC. (MAT,SERV & EQUIPO)'!R58 -> 0 | J91: ='F07 OPERAC. (MAT,SERV & EQUIPO)'!S58 -> 0 | ... P91: ='F07 OPERAC. (MAT,SERV & EQUIPO)'!Y58 -> 0 | Q91: =B91/$B$166 -> 0
A92: CARGOS EXTRAORDINARIOS | B92: =SUM(C92:P92) -> 0 | C92: ='F07 OPERAC. (MAT,SERV & EQUIPO)'!L59 -> 0 | D92: ='F07 OPERAC. (MAT,SERV & EQUIPO)'!M59 -> 0 | E92: ='F07 OPERAC. (MAT,SERV & EQUIPO)'!N59 -> 0 | F92: ='F07 OPERAC. (MAT,SERV & EQUIPO)'!O59 -> 0 | G92: ='F07 OPERAC. (MAT,SERV & EQUIPO)'!P59 -> 0 | H92: ='F07 OPERAC. (MAT,SERV & EQUIPO)'!Q59 -> 0 | I92: ='F07 OPERAC. (MAT,SERV & EQUIPO)'!R59 -> 0 | J92: ='F07 OPERAC. (MAT,SERV & EQUIPO)'!S59 -> 0 | ... P92: ='F07 OPERAC. (MAT,SERV & EQUIPO)'!Y59 -> 0 | Q92: =B92/$B$166 -> 0
A93: CERTIFICACION | B93: =SUM(C93:P93) -> 0 | C93: ='F07 OPERAC. (MAT,SERV & EQUIPO)'!L60 -> 0 | D93: ='F07 OPERAC. (MAT,SERV & EQUIPO)'!M60 -> 0 | E93: ='F07 OPERAC. (MAT,SERV & EQUIPO)'!N60 -> 0 | F93: ='F07 OPERAC. (MAT,SERV & EQUIPO)'!O60 -> 0 | G93: ='F07 OPERAC. (MAT,SERV & EQUIPO)'!P60 -> 0 | H93: ='F07 OPERAC. (MAT,SERV & EQUIPO)'!Q60 -> 0 | I93: ='F07 OPERAC. (MAT,SERV & EQUIPO)'!R60 -> 0 | J93: ='F07 OPERAC. (MAT,SERV & EQUIPO)'!S60 -> 0 | ... P93: ='F07 OPERAC. (MAT,SERV & EQUIPO)'!Y60 -> 0 | Q93: =B93/$B$166 -> 0
A94: COLOCACION DE PILOTE | B94: =SUM(C94:P94) -> 0 | C94: ='F07 OPERAC. (MAT,SERV & EQUIPO)'!L61 -> 0 | D94: ='F07 OPERAC. (MAT,SERV & EQUIPO)'!M61 -> 0 | E94: ='F07 OPERAC. (MAT,SERV & EQUIPO)'!N61 -> 0 | F94: ='F07 OPERAC. (MAT,SERV & EQUIPO)'!O61 -> 0 | G94: ='F07 OPERAC. (MAT,SERV & EQUIPO)'!P61 -> 0 | H94: ='F07 OPERAC. (MAT,SERV & EQUIPO)'!Q61 -> 0 | I94: ='F07 OPERAC. (MAT,SERV & EQUIPO)'!R61 -> 0 | J94: ='F07 OPERAC. (MAT,SERV & EQUIPO)'!S61 -> 0 | ... P94: ='F07 OPERAC. (MAT,SERV & EQUIPO)'!Y61 -> 0 | Q94: =B94/$B$166 -> 0
A95: CORREOS Y MENSAJERIAS | B95: =SUM(C95:P95) -> 0 | C95: ='F07 OPERAC. (MAT,SERV & EQUIPO)'!L62 -> 0 | D95: ='F07 OPERAC. (MAT,SERV & EQUIPO)'!M62 -> 0 | E95: ='F07 OPERAC. (MAT,SERV & EQUIPO)'!N62 -> 0 | F95: ='F07 OPERAC. (MAT,SERV & EQUIPO)'!O62 -> 0 | G95: ='F07 OPERAC. (MAT,SERV & EQUIPO)'!P62 -> 0 | H95: ='F07 OPERAC. (MAT,SERV & EQUIPO)'!Q62 -> 0 | I95: ='F07 OPERAC. (MAT,SERV & EQUIPO)'!R62 -> 0 | J95: ='F07 OPERAC. (MAT,SERV & EQUIPO)'!S62 -> 0 | ... P95: ='F07 OPERAC. (MAT,SERV & EQUIPO)'!Y62 -> 0 | Q95: =B95/$B$166 -> 0
A96: CUOTAS Y SUSCRIPCIONES | B96: =SUM(C96:P96) -> 0 | C96: ='F07 OPERAC. (MAT,SERV & EQUIPO)'!L63 -> 0 | D96: ='F07 OPERAC. (MAT,SERV & EQUIPO)'!M63 -> 0 | E96: ='F07 OPERAC. (MAT,SERV & EQUIPO)'!N63 -> 0 | F96: ='F07 OPERAC. (MAT,SERV & EQUIPO)'!O63 -> 0 | G96: ='F07 OPERAC. (MAT,SERV & EQUIPO)'!P63 -> 0 | H96: ='F07 OPERAC. (MAT,SERV & EQUIPO)'!Q63 -> 0 | I96: ='F07 OPERAC. (MAT,SERV & EQUIPO)'!R63 -> 0 | J96: ='F07 OPERAC. (MAT,SERV & EQUIPO)'!S63 -> 0 | ... P96: ='F07 OPERAC. (MAT,SERV & EQUIPO)'!Y63 -> 0 | Q96: =B96/$B$166 -> 0
... A147: PAGO DE MULTAS | B147: =SUM(C147:P147) -> 195 | C147: ='F07 OPERAC. (MAT,SERV & EQUIPO)'!L114 -> 0 | D147: ='F07 OPERAC. (MAT,SERV & EQUIPO)'!M114 -> 15 | E147: ='F07 OPERAC. (MAT,SERV & EQUIPO)'!N114 -> 15 | F147: ='F07 OPERAC. (MAT,SERV & EQUIPO)'!O114 -> 15 | G147: ='F07 OPERAC. (MAT,SERV & EQUIPO)'!P114 -> 15 | H147: ='F07 OPERAC. (MAT,SERV & EQUIPO)'!Q114 -> 15 | I147: ='F07 OPERAC. (MAT,SERV & EQUIPO)'!R114 -> 15 | J147: ='F07 OPERAC. (MAT,SERV & EQUIPO)'!S114 -> 15 | ... P147: ='F07 OPERAC. (MAT,SERV & EQUIPO)'!Y114 -> 15 | Q147: =B147/$B$166 -> 0.00015356181
A148: SERVICIOS | B148: =SUM(B85:B147) -> 920937.5 | C148: =SUM(C85:C147) -> 0 | D148: =SUM(D85:D147) -> 70537.5 | E148: =SUM(E85:E147) -> 70837.5 | F148: =SUM(F85:F147) -> 70387.5 | G148: =SUM(G85:G147) -> 70387.5 | H148: =SUM(H85:H147) -> 70387.5 | I148: =SUM(I85:I147) -> 70537.5 | ... P148: =SUM(P85:P147) -> 75387.5 | Q148: =B148/$B$166 -> 0.72523502 | S148: ='F07 OPERAC. (MAT,SERV & EQUIPO)'!L118 -> 920937.5 | T148: =+B148-S148 -> 0
A149: SERVICIOS DE CAPACITACION | B149: =SUM(C149:P149) -> 3250 | C149: ='F07 OPERAC. (MAT,SERV & EQUIPO)'!L174 -> 0 | D149: ='F07 OPERAC. (MAT,SERV & EQUIPO)'!M174 -> 250 | E149: ='F07 OPERAC. (MAT,SERV & EQUIPO)'!N174 -> 250 | F149: ='F07 OPERAC. (MAT,SERV & EQUIPO)'!O174 -> 250 | G149: ='F07 OPERAC. (MAT,SERV & EQUIPO)'!P174 -> 250 | H149: ='F07 OPERAC. (MAT,SERV & EQUIPO)'!Q174 -> 250 | I149: ='F07 OPERAC. (MAT,SERV & EQUIPO)'!R174 -> 250 | J149: ='F07 OPERAC. (MAT,SERV & EQUIPO)'!S174 -> 250 | ... P149: ='F07 OPERAC. (MAT,SERV & EQUIPO)'!Y174 -> 250 | Q149: =B149/$B$166 -> 0.0025593635
A150: SERVICIOS DE CAPACITACION | B150: =SUM(B149) -> 3250 | C150: =SUM(C149) -> 0 | D150: =SUM(D149) -> 250 | E150: =SUM(E149) -> 250 | F150: =SUM(F149) -> 250 | G150: =SUM(G149) -> 250 | H150: =SUM(H149) -> 250 | I150: =SUM(I149) -> 250 | ... P150: =SUM(P149) -> 250 | Q150: =B150/$B$166 -> 0.0025593635 | S150: ='F07 OPERAC. (MAT,SERV & EQUIPO)'!L176 -> 3250 | T150: =+B150-S150 -> 0
A151: SERVICIOS MEDICOS | B151: =SUM(C151:P151) -> 1469.442 | C151: ='F07 OPERAC. (MAT,SERV & EQUIPO)'!L187 -> 0 | D151: ='F07 OPERAC. (MAT,SERV & EQUIPO)'!M187 -> 113.034 | E151: ='F07 OPERAC. (MAT,SERV & EQUIPO)'!N187 -> 113.034 | F151: ='F07 OPERAC. (MAT,SERV & EQUIPO)'!O187 -> 113.034 | G151: ='F07 OPERAC. (MAT,SERV & EQUIPO)'!P187 -> 113.034 | H151: ='F07 OPERAC. (MAT,SERV & EQUIPO)'!Q187 -> 113.034 | I151: ='F07 OPERAC. (MAT,SERV & EQUIPO)'!R187 -> 113.034 | J151: ='F07 OPERAC. (MAT,SERV & EQUIPO)'!S187 -> 113.034 | ... P151: ='F07 OPERAC. (MAT,SERV & EQUIPO)'!Y187 -> 113.034 | Q151: =B151/$B$166 -> 0.0011571804
A152: SERVICIOS DE SALUD | B152: =SUM(B151) -> 1469.442 | C152: =SUM(C151) -> 0 | D152: =SUM(D151) -> 113.034 | E152: =SUM(E151) -> 113.034 | F152: =SUM(F151) -> 113.034 | G152: =SUM(G151) -> 113.034 | H152: =SUM(H151) -> 113.034 | I152: =SUM(I151) -> 113.034 | ... P152: =SUM(P151) -> 113.034 | Q152: =B152/$B$166 -> 0.0011571804 | S152: ='F07 OPERAC. (MAT,SERV & EQUIPO)'!L189 -> 1469.442 | T152: =+B152-S152 -> 0
A153: UNIFORMES | B153: =SUM(C153:P153) -> 1872 | C153: ='F01 UNIFORMES'!M12 -> 0 | D153: ='F01 UNIFORMES'!N12 -> 144 | E153: ='F01 UNIFORMES'!O12 -> 144 | F153: ='F01 UNIFORMES'!P12 -> 144 | G153: ='F01 UNIFORMES'!Q12 -> 144 | H153: ='F01 UNIFORMES'!R12 -> 144 | I153: ='F01 UNIFORMES'!S12 -> 144 | J153: ='F01 UNIFORMES'!T12 -> 144 | ... P153: ='F01 UNIFORMES'!Z12 -> 144 | Q153: =B153/$B$166 -> 0.0014741934
A154: UNIFORMES | B154: =SUM(B153) -> 1872 | C154: =SUM(C153) -> 0 | D154: =SUM(D153) -> 144 | E154: =SUM(E153) -> 144 | F154: =SUM(F153) -> 144 | G154: =SUM(G153) -> 144 | H154: =SUM(H153) -> 144 | I154: =SUM(I153) -> 144 | ... P154: =SUM(P153) -> 144 | Q154: =B154/$B$166 -> 0.0014741934 | S154: ='F01 UNIFORMES'!M14 -> 1872 | T154: =+B154-S154 -> 0
A155: ARRENDAMIENTO DE VEHIC | B155: =SUM(C155:P155) -> 0 | C155: ='F04 VEHÍCULOS Y COMB. '!R11 -> 0 | D155: ='F04 VEHÍCULOS Y COMB. '!S11 -> 0 | E155: ='F04 VEHÍCULOS Y COMB. '!T11 -> 0 | F155: ='F04 VEHÍCULOS Y COMB. '!U11 -> 0 | G155: ='F04 VEHÍCULOS Y COMB. '!V11 -> 0 | H155: ='F04 VEHÍCULOS Y COMB. '!W11 -> 0 | I155: ='F04 VEHÍCULOS Y COMB. '!X11 -> 0 | J155: ='F04 VEHÍCULOS Y COMB. '!Y11 -> 0 | ... P155: ='F04 VEHÍCULOS Y COMB. '!AE11 -> 0 | Q155: =B155/$B$166 -> 0
A156: COMBUSTIBLES | B156: =SUM(C156:P156) -> 18018 | C156: ='F04 VEHÍCULOS Y COMB. '!R25 -> 0 | D156: ='F04 VEHÍCULOS Y COMB. '!S25 -> 1386 | E156: ='F04 VEHÍCULOS Y COMB. '!T25 -> 1386 | F156: ='F04 VEHÍCULOS Y COMB. '!U25 -> 1386 | G156: ='F04 VEHÍCULOS Y COMB. '!V25 -> 1386 | H156: ='F04 VEHÍCULOS Y COMB. '!W25 -> 1386 | I156: ='F04 VEHÍCULOS Y COMB. '!X25 -> 1386 | J156: ='F04 VEHÍCULOS Y COMB. '!Y25 -> 1386 | ... P156: ='F04 VEHÍCULOS Y COMB. '!AE25 -> 1386 | Q156: =B156/$B$166 -> 0.014189111
A157: VEHICULOS Y COMBUSTIBLE | B157: =SUM(B155:B156) -> 18018 | C157: =SUM(C155:C156) -> 0 | D157: =SUM(D155:D156) -> 1386 | E157: =SUM(E155:E156) -> 1386 | F157: =SUM(F155:F156) -> 1386 | G157: =SUM(G155:G156) -> 1386 | H157: =SUM(H155:H156) -> 1386 | I157: =SUM(I155:I156) -> 1386 | ... P157: =SUM(P155:P156) -> 1386 | Q157: =B157/$B$166 -> 0.014189111 | S157: ='F04 VEHÍCULOS Y COMB. '!R32 -> 18018 | T157: =+B157-S157 -> 0
A158: ALIMENTACION | B158: =SUM(C158:P158) -> 650 | C158: ='F05 VIÁTICOS'!K7 -> 0 | D158: ='F05 VIÁTICOS'!L7 -> 50 | E158: ='F05 VIÁTICOS'!M7 -> 50 | F158: ='F05 VIÁTICOS'!N7 -> 50 | G158: ='F05 VIÁTICOS'!O7 -> 50 | H158: ='F05 VIÁTICOS'!P7 -> 50 | I158: ='F05 VIÁTICOS'!Q7 -> 50 | J158: ='F05 VIÁTICOS'!R7 -> 50 | ... P158: ='F05 VIÁTICOS'!X7 -> 50 | Q158: =B158/$B$166 -> 0.0005118727
A159: CASETAS PUENTES Y PEAJES | B159: =SUM(C159:P159) -> 650 | C159: ='F05 VIÁTICOS'!K8 -> 0 | D159: ='F05 VIÁTICOS'!L8 -> 50 | E159: ='F05 VIÁTICOS'!M8 -> 50 | F159: ='F05 VIÁTICOS'!N8 -> 50 | G159: ='F05 VIÁTICOS'!O8 -> 50 | H159: ='F05 VIÁTICOS'!P8 -> 50 | I159: ='F05 VIÁTICOS'!Q8 -> 50 | J159: ='F05 VIÁTICOS'!R8 -> 50 | ... P159: ='F05 VIÁTICOS'!X8 -> 50 | Q159: =B159/$B$166 -> 0.0005118727
A160: SERV DE TRANSPORTAC AEREA | B160: =SUM(C160:P160) -> 1950 | C160: ='F05 VIÁTICOS'!K9 -> 0 | D160: ='F05 VIÁTICOS'!L9 -> 150 | E160: ='F05 VIÁTICOS'!M9 -> 150 | F160: ='F05 VIÁTICOS'!N9 -> 150 | G160: ='F05 VIÁTICOS'!O9 -> 150 | H160: ='F05 VIÁTICOS'!P9 -> 150 | I160: ='F05 VIÁTICOS'!Q9 -> 150 | J160: ='F05 VIÁTICOS'!R9 -> 150 | ... P160: ='F05 VIÁTICOS'!X9 -> 150 | Q160: =B160/$B$166 -> 0.0015356181
A161: SERV DE TRANSPORTAC TERRESTRE | B161: =SUM(C161:P161) -> 1300 | C161: ='F05 VIÁTICOS'!K10 -> 0 | D161: ='F05 VIÁTICOS'!L10 -> 100 | E161: ='F05 VIÁTICOS'!M10 -> 100 | F161: ='F05 VIÁTICOS'!N10 -> 100 | G161: ='F05 VIÁTICOS'!O10 -> 100 | H161: ='F05 VIÁTICOS'!P10 -> 100 | I161: ='F05 VIÁTICOS'!Q10 -> 100 | J161: ='F05 VIÁTICOS'!R10 -> 100 | ... P161: ='F05 VIÁTICOS'!X10 -> 100 | Q161: =B161/$B$166 -> 0.0010237454
A162: SERVICIOS DE HOSPEDAJE | B162: =SUM(C162:P162) -> 1300 | C162: ='F05 VIÁTICOS'!K11 -> 0 | D162: ='F05 VIÁTICOS'!L11 -> 100 | E162: ='F05 VIÁTICOS'!M11 -> 100 | F162: ='F05 VIÁTICOS'!N11 -> 100 | G162: ='F05 VIÁTICOS'!O11 -> 100 | H162: ='F05 VIÁTICOS'!P11 -> 100 | I162: ='F05 VIÁTICOS'!Q11 -> 100 | J162: ='F05 VIÁTICOS'!R11 -> 100 | ... P162: ='F05 VIÁTICOS'!X11 -> 100 | Q162: =B162/$B$166 -> 0.0010237454
A163: ='F05 VIÁTICOS'!B19 -> CAJA CHICA | B163: =SUM(C163:P163) -> 0 | C163: ='F05 VIÁTICOS'!K19 -> 0 | D163: ='F05 VIÁTICOS'!L19 -> 0 | E163: ='F05 VIÁTICOS'!M19 -> 0 | F163: ='F05 VIÁTICOS'!N19 -> 0 | G163: ='F05 VIÁTICOS'!O19 -> 0 | H163: ='F05 VIÁTICOS'!P19 -> 0 | I163: ='F05 VIÁTICOS'!Q19 -> 0 | J163: ='F05 VIÁTICOS'!R19 -> 0 | ... P163: ='F05 VIÁTICOS'!X19 -> 0 | Q163: =B163/$B$166 -> 0
A164: ='F05 VIÁTICOS'!B20 -> REEMBOLSOS | B164: =SUM(C164:P164) -> 0 | C164: ='F05 VIÁTICOS'!K20 -> 0 | D164: ='F05 VIÁTICOS'!L20 -> 0 | E164: ='F05 VIÁTICOS'!M20 -> 0 | F164: ='F05 VIÁTICOS'!N20 -> 0 | G164: ='F05 VIÁTICOS'!O20 -> 0 | H164: ='F05 VIÁTICOS'!P20 -> 0 | I164: ='F05 VIÁTICOS'!Q20 -> 0 | J164: ='F05 VIÁTICOS'!R20 -> 0 | ... P164: ='F05 VIÁTICOS'!X20 -> 0 | Q164: =B164/$B$166 -> 0
A165: VIATICOS | B165: =SUM(B158:B164) -> 5850 | C165: =SUM(C158:C164) -> 0 | D165: =SUM(D158:D164) -> 450 | E165: =SUM(E158:E164) -> 450 | F165: =SUM(F158:F164) -> 450 | G165: =SUM(G158:G164) -> 450 | H165: =SUM(H158:H164) -> 450 | I165: =SUM(I158:I164) -> 450 | ... P165: =SUM(P158:P164) -> 450 | Q165: =B165/$B$166 -> 0.0046068543 | S165: ='F05 VIÁTICOS'!K29 -> 5850 | T165: =+B165-S165 -> 0
A166: TOTAL | B166: =SUM(B165,B157,B154,B152,B150,B148,B84,B80,B78,B76,B40,B37,B32,B30,B28,B25,B23,B13) -> 1269847 | C166: =C13+C23+C25+C28+C30+C32+C37+C40+C76+C78+C80+C84+C148+C150+C152+C154+C157+C165 -> 0 | D166: =D13+D23+D25+D28+D30+D32+D37+D40+D76+D78+D80+D84+D148+D150+D152+D154+D157+D165 -> 94460.018 | E166: =E13+E23+E25+E28+E30+E32+E37+E40+E76+E78+E80+E84+E148+E150+E152+E154+E157+E165 -> 125060.02 | F166: =F13+F23+F25+F28+F30+F32+F37+F40+F76+F78+F80+F84+F148+F150+F152+F154+F157+F165 -> 92810.018 | G166: =G13+G23+G25+G28+G30+G32+G37+G40+G76+G78+G80+G84+G148+G150+G152+G154+G157+G165 -> 95060.018 | H166: =H13+H23+H25+H28+H30+H32+H37+H40+H76+H78+H80+H84+H148+H150+H152+H154+H157+H165 -> 98142.518 | I166: =I13+I23+I25+I28+I30+I32+I37+I40+I76+I78+I80+I84+I148+I150+I152+I154+I157+I165 -> 94663.018 | J166: =J13+J23+J25+J28+J30+J32+J37+J40+J76+J78+J80+J84+J148+J150+J152+J154+J157+J165 -> 92810.018 | ... P166: =P13+P23+P25+P28+P30+P32+P37+P40+P76+P78+P80+P84+P148+P150+P152+P154+P157+P165 -> 97810.018 | Q166: =SUM(Q165,Q157,Q154,Q152,Q150,Q148,Q84,Q80,Q78,Q76,Q40,Q37,Q32,Q30,Q28,Q25,Q23,Q13) -> 1
A167: OPEX | B167: =SUM(B165,B157,B154,B152,B150,B148,B84,B80,B78,B76,B40,B37,B32,B30,B28,B25,B23) -> 1238047 | C167: =SUM(C165,C157,C154,C152,C150,C148,C84,C80,C78,C76,C40,C37,C32,C30,C28,C25,C23) -> 0 | D167: =SUM(D165,D157,D154,D152,D150,D148,D84,D80,D78,D76,D40,D37,D32,D30,D28,D25,D23) -> 94460.018 | E167: =SUM(E165,E157,E154,E152,E150,E148,E84,E80,E78,E76,E40,E37,E32,E30,E28,E25,E23) -> 93260.018 | F167: =SUM(F165,F157,F154,F152,F150,F148,F84,F80,F78,F76,F40,F37,F32,F30,F28,F25,F23) -> 92810.018 | G167: =SUM(G165,G157,G154,G152,G150,G148,G84,G80,G78,G76,G40,G37,G32,G30,G28,G25,G23) -> 95060.018 | H167: =SUM(H165,H157,H154,H152,H150,H148,H84,H80,H78,H76,H40,H37,H32,H30,H28,H25,H23) -> 98142.518 | I167: =SUM(I165,I157,I154,I152,I150,I148,I84,I80,I78,I76,I40,I37,I32,I30,I28,I25,I23) -> 94663.018 | ... P167: =SUM(P165,P157,P154,P152,P150,P148,P84,P80,P78,P76,P40,P37,P32,P30,P28,P25,P23) -> 97810.018 | Q167: =B167/$B$166 -> 0.97495761
A168: ACUMULADO | B168: =B5-B166 -> 1363267.9 | C168: =C167 -> 0 | D168: =C168+D167 -> 94460.018 | E168: =D168+E167 -> 187720.04 | F168: =E168+F167 -> 280530.05 | G168: =F168+G167 -> 375590.07 | H168: =G168+H167 -> 473732.59 | I168: =H168+I167 -> 568395.61 | J168: =I168+J167 -> 661205.63 | K168: =J168+K167 -> 754015.64 | ... P168: =O168+P167 -> 1238047 | Q168: =B168/$B$166 -> 1.0735686
B169: =B168/B5 -> 0.51773962
A170: Compra | B170: 1
A171: Renta | B171: 1
A173: INGRESOS 2025 | B173: [MN] | C173: =C3 -> INSTALACIÓN | D173: =D3 -> M1 | E173: =E3 -> M2 | F173: =F3 -> M3 | G173: =G3 -> M4 | H173: =H3 -> M5 | I173: =I3 -> M6 | J173: =J3 -> M7 | ... P173: =P3 -> M13
...

Sheet GRÁFICA

Sheet GRÁFICA II
B32: OPEX | C32: Mes 0 | D32: Instalación | E32: Mes 2 | F32: Mes 3 | G32: Mes 4 | H32: Mes 5 | I32: Mes 6 | J32: Mes 7 | K32: Mes 8 | L32: Mes 9 | M32: Mes 10 | N32: Mes 11 | O32: Mes 12 | P32: Mes 13 | Q32: Mes 14 | R32: Total
A33: 1 | B33: =SERVICIO!A23 -> ARRENDA DE INMUEBLES Y SERV | C33: =SERVICIO!C23 -> 0 | D33: =SERVICIO!D23 -> 2020 | E33: =SERVICIO!E23 -> 2020 | F33: =SERVICIO!F23 -> 2020 | G33: =SERVICIO!G23 -> 2020 | H33: =SERVICIO!H23 -> 2020 | I33: =SERVICIO!I23 -> 2020 | J33: =SERVICIO!J23 -> 2020 | ... P33: =SERVICIO!P23 -> 2020 | Q33: =SERVICIO!#REF! -> #REF! | R33: =SERVICIO!B23 -> 26260
A34: 2 | B34: =SERVICIO!A25 -> ARTICULOS DE SEGURIDAD | C34: =SERVICIO!C25 -> 0 | D34: =SERVICIO!D25 -> 405 | E34: =SERVICIO!E25 -> 405 | F34: =SERVICIO!F25 -> 405 | G34: =SERVICIO!G25 -> 405 | H34: =SERVICIO!H25 -> 405 | I34: =SERVICIO!I25 -> 405 | J34: =SERVICIO!J25 -> 405 | ... P34: =SERVICIO!P25 -> 405 | Q34: =SERVICIO!#REF! -> #REF! | R34: =SERVICIO!B25 -> 5265
A35: 3 | B35: =SERVICIO!A28 -> EQUIPO DE COMPUTO | C35: =SERVICIO!C28 -> 0 | D35: =SERVICIO!D28 -> 0 | E35: =SERVICIO!E28 -> 0 | F35: =SERVICIO!F28 -> 0 | G35: =SERVICIO!G28 -> 0 | H35: =SERVICIO!H28 -> 0 | I35: =SERVICIO!I28 -> 0 | J35: =SERVICIO!J28 -> 0 | ... P35: =SERVICIO!P28 -> 0 | Q35: =SERVICIO!#REF! -> #REF! | R35: =SERVICIO!B28 -> 0
A36: 4 | B36: =SERVICIO!A30 -> EQUIPOS Y ENSERES | C36: =SERVICIO!C30 -> 0 | D36: =SERVICIO!D30 -> 82.5 | E36: =SERVICIO!E30 -> 82.5 | F36: =SERVICIO!F30 -> 82.5 | G36: =SERVICIO!G30 -> 82.5 | H36: =SERVICIO!H30 -> 82.5 | I36: =SERVICIO!I30 -> 82.5 | J36: =SERVICIO!J30 -> 82.5 | ... P36: =SERVICIO!P30 -> 82.5 | Q36: =SERVICIO!#REF! -> #REF! | R36: =SERVICIO!B30 -> 1072.5
A37: 5 | B37: =SERVICIO!A32 -> INSUMOS AGRICOLAS | C37: =SERVICIO!C32 -> 0 | D37: =SERVICIO!D32 -> 57.7115 | E37: =SERVICIO!E32 -> 57.7115 | F37: =SERVICIO!F32 -> 57.7115 | G37: =SERVICIO!G32 -> 57.7115 | H37: =SERVICIO!H32 -> 57.7115 | I37: =SERVICIO!I32 -> 57.7115 | J37: =SERVICIO!J32 -> 57.7115 | ... P37: =SERVICIO!P32 -> 57.7115 | Q37: =SERVICIO!#REF! -> #REF! | R37: =SERVICIO!B32 -> 750.2495
A38: 6 | B38: =SERVICIO!A37 -> INSUMOS DE OFICINA | C38: =SERVICIO!C37 -> 0 | D38: =SERVICIO!D37 -> 40 | E38: =SERVICIO!E37 -> 40 | F38: =SERVICIO!F37 -> 40 | G38: =SERVICIO!G37 -> 40 | H38: =SERVICIO!H37 -> 40 | I38: =SERVICIO!I37 -> 40 | J38: =SERVICIO!J37 -> 40 | ... P38: =SERVICIO!P37 -> 40 | Q38: =SERVICIO!#REF! -> #REF! | R38: =SERVICIO!B37 -> 520
A39: 7 | B39: =SERVICIO!A40 -> MARKETING | C39: =SERVICIO!C40 -> 0 | D39: =SERVICIO!D40 -> 0 | E39: =SERVICIO!E40 -> 0 | F39: =SERVICIO!F40 -> 0 | G39: =SERVICIO!G40 -> 0 | H39: =SERVICIO!H40 -> 0 | I39: =SERVICIO!I40 -> 0 | J39: =SERVICIO!J40 -> 0 | ... P39: =SERVICIO!P40 -> 0 | Q39: =SERVICIO!#REF! -> #REF! | R39: =SERVICIO!B40 -> 0
A40: 8 | B40: =SERVICIO!A76 -> MATERIALES | C40: =SERVICIO!C76 -> 0 | D40: =SERVICIO!D76 -> 2760 | E40: =SERVICIO!E76 -> 1260 | F40: =SERVICIO!F76 -> 1260 | G40: =SERVICIO!G76 -> 3510 | H40: =SERVICIO!H76 -> 1260 | I40: =SERVICIO!I76 -> 2963 | J40: =SERVICIO!J76 -> 1260 | ... P40: =SERVICIO!P76 -> 1260 | Q40: =SERVICIO!#REF! -> #REF! | R40: =SERVICIO!B76 -> 23333
A41: 9 | B41: =SERVICIO!A78 -> MATERIALES DE SALUD | C41: =SERVICIO!C78 -> 0 | D41: =SERVICIO!D78 -> 35 | E41: =SERVICIO!E78 -> 35 | F41: =SERVICIO!F78 -> 35 | G41: =SERVICIO!G78 -> 35 | H41: =SERVICIO!H78 -> 35 | I41: =SERVICIO!I78 -> 35 | J41: =SERVICIO!J78 -> 35 | ... P41: =SERVICIO!P78 -> 35 | Q41: =SERVICIO!#REF! -> #REF! | R41: =SERVICIO!B78 -> 455
A42: 10 | B42: =SERVICIO!A80 -> NOMINA Y ADICIONALES | C42: =SERVICIO!C80 -> 0 | D42: =SERVICIO!D80 -> 16104.273 | E42: =SERVICIO!E80 -> 16104.273 | F42: =SERVICIO!F80 -> 16104.273 | G42: =SERVICIO!G80 -> 16104.273 | H42: =SERVICIO!H80 -> 21436.773 | I42: =SERVICIO!I80 -> 16104.273 | J42: =SERVICIO!J80 -> 16104.273 | ... P42: =SERVICIO!P80 -> 16104.273 | Q42: =SERVICIO!#REF! -> #REF! | R42: =SERVICIO!B80 -> 228019.29
A43: 11 | B43: =SERVICIO!A84 -> SERV TELEFONIA CELULAR Y RADIO | C43: =SERVICIO!C84 -> 0 | D43: =SERVICIO!D84 -> 75 | E43: =SERVICIO!E84 -> 75 | F43: =SERVICIO!F84 -> 75 | G43: =SERVICIO!G84 -> 75 | H43: =SERVICIO!H84 -> 75 | I43: =SERVICIO!I84 -> 75 | J43: =SERVICIO!J84 -> 75 | ... P43: =SERVICIO!P84 -> 75 | Q43: =SERVICIO!#REF! -> #REF! | R43: =SERVICIO!B84 -> 975
A44: 12 | B44: =SERVICIO!A148 -> SERVICIOS | C44: =SERVICIO!C148 -> 0 | D44: =SERVICIO!D148 -> 70537.5 | E44: =SERVICIO!E148 -> 70837.5 | F44: =SERVICIO!F148 -> 70387.5 | G44: =SERVICIO!G148 -> 70387.5 | H44: =SERVICIO!H148 -> 70387.5 | I44: =SERVICIO!I148 -> 70537.5 | J44: =SERVICIO!J148 -> 70387.5 | ... P44: =SERVICIO!P148 -> 75387.5 | Q44: =SERVICIO!#REF! -> #REF! | R44: =SERVICIO!B148 -> 920937.5
A45: 13 | B45: =SERVICIO!A150 -> SERVICIOS DE CAPACITACION | C45: =SERVICIO!C150 -> 0 | D45: =SERVICIO!D150 -> 250 | E45: =SERVICIO!E150 -> 250 | F45: =SERVICIO!F150 -> 250 | G45: =SERVICIO!G150 -> 250 | H45: =SERVICIO!H150 -> 250 | I45: =SERVICIO!I150 -> 250 | J45: =SERVICIO!J150 -> 250 | ... P45: =SERVICIO!P150 -> 250 | Q45: =SERVICIO!#REF! -> #REF! | R45: =SERVICIO!B150 -> 3250
A46: 14 | B46: =SERVICIO!A152 -> SERVICIOS DE SALUD | C46: =SERVICIO!C152 -> 0 | D46: =SERVICIO!D152 -> 113.034 | E46: =SERVICIO!E152 -> 113.034 | F46: =SERVICIO!F152 -> 113.034 | G46: =SERVICIO!G152 -> 113.034 | H46: =SERVICIO!H152 -> 113.034 | I46: =SERVICIO!I152 -> 113.034 | J46: =SERVICIO!J152 -> 113.034 | ... P46: =SERVICIO!P152 -> 113.034 | Q46: =SERVICIO!#REF! -> #REF! | R46: =SERVICIO!B152 -> 1469.442
A47: 15 | B47: =SERVICIO!A154 -> UNIFORMES | C47: =SERVICIO!C154 -> 0 | D47: =SERVICIO!D154 -> 144 | E47: =SERVICIO!E154 -> 144 | F47: =SERVICIO!F154 -> 144 | G47: =SERVICIO!G154 -> 144 | H47: =SERVICIO!H154 -> 144 | I47: =SERVICIO!I154 -> 144 | J47: =SERVICIO!J154 -> 144 | ... P47: =SERVICIO!P154 -> 144 | Q47: =SERVICIO!#REF! -> #REF! | R47: =SERVICIO!B154 -> 1872
A48: 16 | B48: =SERVICIO!A157 -> VEHICULOS Y COMBUSTIBLE | C48: =SERVICIO!C157 -> 0 | D48: =SERVICIO!D157 -> 1386 | E48: =SERVICIO!E157 -> 1386 | F48: =SERVICIO!F157 -> 1386 | G48: =SERVICIO!G157 -> 1386 | H48: =SERVICIO!H157 -> 1386 | I48: =SERVICIO!I157 -> 1386 | J48: =SERVICIO!J157 -> 1386 | ... P48: =SERVICIO!P157 -> 1386 | Q48: =SERVICIO!#REF! -> #REF! | R48: =SERVICIO!B157 -> 18018
A49: 17 | B49: =SERVICIO!A165 -> VIATICOS | C49: =SERVICIO!C165 -> 0 | D49: =SERVICIO!D165 -> 450 | E49: =SERVICIO!E165 -> 450 | F49: =SERVICIO!F165 -> 450 | G49: =SERVICIO!G165 -> 450 | H49: =SERVICIO!H165 -> 450 | I49: =SERVICIO!I165 -> 450 | J49: =SERVICIO!J165 -> 450 | ... P49: =SERVICIO!P165 -> 450 | Q49: =SERVICIO!#REF! -> #REF! | R49: =SERVICIO!B165 -> 5850
R50: =SUM(R33:R49) -> 1238047

Sheet FLUJO
D1: 0 | E1: 1 | F1: 2 | G1: 3 | H1: 4 | I1: 5 | J1: 6 | K1: 7 | L1: 8 | M1: 9 | N1: 10 | O1: 11 | P1: 12
C3: Instalación | D3: Instalación | E3: Mes 1 | F3: Mes 2 | G3: Mes 3 | H3: Mes 4 | I3: Mes 5 | J3: Mes 6 | K3: Mes 7 | L3: Mes 8 | M3: Mes 9 | N3: Mes 10 | O3: Mes 11 | P3: Mes 12 | R3: =SUM(R6:R9) -> 0 | T3: =R3*1.16 -> 0 | V3: =+R3/$E$37 -> 0 | X3: =V3*1.16 -> 0
C4: JUN | D4: JUL | E4: AGO | F4: SEP | G4: OCT | H4: NOV | I4: DIC | J4: ENE | K4: FEB | L4: MAR | M4: ABR | N4: MAY | O4: JUN | P4: JUL | R4: TOTAL PROYECTO (MN) | T4: TOTAL PROYECTO IVA (MN) | V4: TOTAL PROYECTO (USD) | X4: TOTAL PROYECTO IVA (USD)
A5: Ingresos (MN) | C5: 31 | D5: 30 | E5: 31 | F5: 30 | G5: 31 | H5: 30 | I5: 31 | J5: 31 | K5: 28 | L5: 31 | M5: 30 | N5: 31 | O5: 30 | P5: 31
A6: =PREMISAS!C9 -> Patín con bomba electrocentrifuga horizontal con gasto de 10,000-20,000 BPD incluye la operación continua. | C6: ='F08 INGRESOS'!M7 -> 0 | D6: ='F08 INGRESOS'!N7 -> 0 | E6: ='F08 INGRESOS'!O7 -> 0 | F6: ='F08 INGRESOS'!P7 -> 0 | G6: ='F08 INGRESOS'!Q7 -> 0 | H6: ='F08 INGRESOS'!R7 -> 0 | I6: ='F08 INGRESOS'!S7 -> 0 | J6: ='F08 INGRESOS'!T7 -> 0 | ... P6: ='F08 INGRESOS'!Z7 -> 0 | R6: =SUM(C6:P6) -> 0 | T6: =R6*1.16 -> 0 | V6: =+R6/$E$37 -> 0 | X6: =V6*1.16 -> 0
A7: =PREMISAS!C10 -> Patín con bomba electrocentrifuga horizontal con gasto de 20,000-30,000 BPD incluye la operación continua. | C7: ='F08 INGRESOS'!M8 -> 0 | D7: ='F08 INGRESOS'!N8 -> 0 | E7: ='F08 INGRESOS'!O8 -> 0 | F7: ='F08 INGRESOS'!P8 -> 0 | G7: ='F08 INGRESOS'!Q8 -> 0 | H7: ='F08 INGRESOS'!R8 -> 0 | I7: ='F08 INGRESOS'!S8 -> 0 | J7: ='F08 INGRESOS'!T8 -> 0 | ... P7: ='F08 INGRESOS'!Z8 -> 0 | R7: =SUM(C7:P7) -> 0 | T7: =R7*1.16 -> 0 | V7: =+R7/$E$37 -> 0 | X7: =V7*1.16 -> 0
A8: =PREMISAS!C11 -> Generador de energía a gas de 300 KW/375 KVA. | C8: ='F08 INGRESOS'!M12 -> 0 | D8: ='F08 INGRESOS'!N12 -> 0 | E8: ='F08 INGRESOS'!O12 -> 0 | F8: ='F08 INGRESOS'!P12 -> 0 | G8: ='F08 INGRESOS'!Q12 -> 0 | H8: ='F08 INGRESOS'!R12 -> 0 | I8: ='F08 INGRESOS'!S12 -> 0 | J8: ='F08 INGRESOS'!T12 -> 0 | ... P8: ='F08 INGRESOS'!Z12 -> 0 | R8: =SUM(C8:P8) -> 0 | T8: =R8*1.16 -> 0 | V8: =+R8/$E$37 -> 0 | X8: =V8*1.16 -> 0
A9: =PREMISAS!C15 -> 0 | C9: ='F08 INGRESOS'!M13 -> 0 | D9: ='F08 INGRESOS'!N13 -> 0 | E9: ='F08 INGRESOS'!O13 -> 0 | F9: ='F08 INGRESOS'!P13 -> 0 | G9: ='F08 INGRESOS'!Q13 -> 0 | H9: ='F08 INGRESOS'!R13 -> 0 | I9: ='F08 INGRESOS'!S13 -> 0 | J9: ='F08 INGRESOS'!T13 -> 0 | ... P9: ='F08 INGRESOS'!Z13 -> 0 | R9: =SUM(C9:P9) -> 0 | T9: =R9*1.16 -> 0 | V9: =+R9/$E$37 -> 0 | X9: =V9*1.16 -> 0
A11: Ingresos Totales (MN) | C11: =SUM(C6:C10) -> 0 | D11: =SUM(D6:D10) -> 0 | E11: =SUM(E6:E10) -> 0 | F11: =SUM(F6:F10) -> 0 | G11: =SUM(G6:G10) -> 0 | H11: =SUM(H6:H10) -> 0 | I11: =SUM(I6:I10) -> 0 | J11: =SUM(J6:J10) -> 0 | ... P11: =SUM(P6:P10) -> 0 | R11: =SUM(C11:P11) -> 0
A13: Ingresos Totales (MN) IVA | C13: =+C11*1.16 -> 0 | D13: =+D11*1.16 -> 0 | E13: =+E11*1.16 -> 0 | F13: =+F11*1.16 -> 0 | G13: =+G11*1.16 -> 0 | H13: =+H11*1.16 -> 0 | I13: =+I11*1.16 -> 0 | J13: =+J11*1.16 -> 0 | ... P13: =+P11*1.16 -> 0 | R13: =SUM(C13:P13) -> 0
A15: Egresos (MX)
A16: OPEX | C16: =EGRESOS!D37 -> 0 | D16: =EGRESOS!E37 -> 94460.018 | E16: =EGRESOS!F37 -> 93260.018 | F16: =EGRESOS!G37 -> 92810.018 | G16: =EGRESOS!H37 -> 95060.018 | H16: =EGRESOS!I37 -> 98142.518 | I16: =EGRESOS!J37 -> 94663.018 | J16: =EGRESOS!K37 -> 92810.018 | ... P16: =EGRESOS!Q37 -> 97810.018 | R16: =SUM(C16:P16) -> 1238047 | V16: =+R16/$E$37 -> 61902.349 | X16: =+V16*1.16 -> 71806.725
A17: FINANCIAMIENTO
A18: CAPEX | C18: =EGRESOS!D35 -> 0 | D18: =EGRESOS!E35 -> 0 | E18: =EGRESOS!F35 -> 31800 | F18: =EGRESOS!G35 -> 0 | G18: =EGRESOS!H35 -> 0 | H18: =EGRESOS!I35 -> 0 | I18: =EGRESOS!J35 -> 0 | J18: =EGRESOS!K35 -> 0 | ... P18: =EGRESOS!Q35 -> 0 | R18: =SUM(C18:P18) -> 31800 | V18: =+R18/$E$37 -> 1590 | X18: =+V18*1.16 -> 1844.4
A20: Egresos Totales (MN) | C20: =SUM(C16:C19) -> 0 | D20: =SUM(D16:D19) -> 94460.018 | E20: =SUM(E16:E19) -> 125060.02 | F20: =SUM(F16:F19) -> 92810.018 | G20: =SUM(G16:G19) -> 95060.018 | H20: =SUM(H16:H19) -> 98142.518 | I20: =SUM(I16:I19) -> 94663.018 | J20: =SUM(J16:J19) -> 92810.018 | ... P20: =SUM(P16:P19) -> 97810.018 | R20: =SUM(C20:P20) -> 1269847 | T20: =+R20*1.16 -> 1473022.5 | V20: =+R20/$E$37 -> 63492.349 | X20: =+V20*1.16 -> 73651.125
A22: Egresos Totales (MN) IVA | C22: =+C20*1.16 -> 0 | D22: =+D20*1.16 -> 109573.62 | E22: =+E20*1.16 -> 145069.62 | F22: =+F20*1.16 -> 107659.62 | G22: =+G20*1.16 -> 110269.62 | H22: =+H20*1.16 -> 113845.32 | I22: =+I20*1.16 -> 109809.1 | J22: =+J20*1.16 -> 107659.62 | ... P22: =+P20*1.16 -> 113459.62 | R22: =SUM(C22:P22) -> 1473022.5 | T22: =+R22*1.16 -> 1708706.1 | V22: =+R22/$E$37 -> 73651.125 | X22: =+V22*1.16 -> 85435.305
A24: FLUJO EFECTIVO | C24: =C11-C20 -> 0 | D24: =D11-D20 -> -94460.018 | E24: =E11-E20 -> -125060.02 | F24: =F11-F20 -> -92810.018 | G24: =G11-G20 -> -95060.018 | H24: =H11-H20 -> -98142.518 | I24: =I11-I20 -> -94663.018 | J24: =J11-J20 -> -92810.018 | ... P24: =P11-P20 -> -97810.018
A26: FLUJO EFECTIVO IVA | C26: =+C24*1.16 -> 0 | D26: =+D24*1.16 -> -109573.62 | E26: =+E24*1.16 -> -145069.62 | F26: =+F24*1.16 -> -107659.62 | G26: =+G24*1.16 -> -110269.62 | H26: =+H24*1.16 -> -113845.32 | I26: =+I24*1.16 -> -109809.1 | J26: =+J24*1.16 -> -107659.62 | ... P26: =+P24*1.16 -> -113459.62
A28: FLUJO ACUMULADO | C28: =+C24 -> 0 | D28: =+D24+C28 -> -94460.018 | E28: =+E24+D28 -> -219520.04 | F28: =+F24+E28 -> -312330.05 | G28: =+G24+F28 -> -407390.07 | H28: =+H24+G28 -> -505532.59 | I28: =+I24+H28 -> -600195.61 | J28: =+J24+I28 -> -693005.63 | K28: =+K24+J28 -> -785815.64 | ... P28: =+P24+O28 -> -1269847
A30: FLUJO ACUMULADO IVA | C30: =+C28*1.16 -> 0 | D30: =+D28*1.16 -> -109573.62 | E30: =+E28*1.16 -> -254643.24 | F30: =+F28*1.16 -> -362302.86 | G30: =+G28*1.16 -> -472572.48 | H30: =+H28*1.16 -> -586417.81 | I30: =+I28*1.16 -> -696226.91 | J30: =+J28*1.16 -> -803886.53 | ... P30: =+P28*1.16 -> -1473022.5
C32: OPEX Promedio | D32: =AVERAGE(C16:P16) -> 88431.928
C33: CAPEX | D33: =SUM(C18:G18) -> 31800
C34: Opex Total | D34: =SUM(C16:P16) -> 1238047
C36: FACTORES DE SENSIBILIDAD | G36: RESULTADOS (MMMN)
C37: Tipo de Cambio | E37: =PREMISAS!I23 -> 20 | I37: Total Ingresos | J37: =SUM(R11)/1000000 -> 0
F38: USD | I38: Total Egresos | J38: =SUM(R20)/1000000 -> 1.269847
F39: USD
C40: Equipo sup. | F40: USD
C41: Instalación | F41: USD
C42: Gas lp | F42: (USD/L)
C43: Desinstalación | F43: USD
C44: Telemetría | F44: USD
C46: Préstamo | F46: USD | G46: EBTDA Acumulado | H46: =(R11-R20)/1000000 -> -1.269847 | I46: EBTDA Anual | J46: =H46/E50 -> -0.84656466
C47: Capital de trabajo | E47: =MIN(C30:P30) -> -1473022.5 | G47: VPN | H47: =(NPV(E48/18,D24:P24))/1000000 -> -1.2130659 | I47: VPN Anual | J47: =H47/E50 -> -0.80871058
C48: Tasa de VPN y VPI Anual | E48: 0.12 | G48: VPI | H48: =(NPV(E48/18,D18:P18))/1000000 -> 0.031380203
C49: Meses de Préstamo | G49: Punto de Equilibrio | I49: meses
C50: Años del proyecto | E50: 1.5 | G50: TIR | H50: =XIRR(D24:P24,D4:P4) -> #VALUE! | I50: %
G51: Utilidades | H51: =+H46/J37 -> #DIV/0!
C52: OPEX mensual (MMMN) | E52: =((AVERAGE(C16:P16)/1000000)) -> 0.088431928
C53: CAPEX total (MMMN) | E53: =R18/1000000 -> 0.0318 | G53: VPN/VPI | H53: =H47/H48 -> -38.657044

Sheet EGRESOS
A2: REFERENCIA EGRESO - JD EDWARDS
D4: Instalación | E4: Instalación | F4: Mes 1 | G4: Mes 2 | H4: Mes 3 | I4: Mes 4 | J4: Mes 5 | K4: Mes 6 | L4: Mes 7 | M4: Mes 8 | N4: Mes 9 | O4: Mes 10 | P4: Mes 11 | Q4: Mes 12
D5: JUN | E5: JUL | F5: AGO | G5: SEP | H5: OCT | I5: NOV | J5: DIC | K5: ENE | L5: FEB | M5: MAR | N5: ABR | O5: MAY | P5: JUN | Q5: JUL | R5: TOTAL PROYECTO (MXN) | T5: TOTAL PROYECTO (USD)
D6: 31 | E6: 30 | F6: 31 | G6: 30 | H6: 31 | I6: 30 | J6: 31 | K6: 31 | L6: 28 | M6: 31 | N6: 30 | O6: 31 | P6: 30 | Q6: 31
A8: INVERSIÓN | D8: ='F00 INVERSIÓN'!L40 -> 0 | E8: ='F00 INVERSIÓN'!M40 -> 0 | F8: ='F00 INVERSIÓN'!N40 -> 31800 | G8: ='F00 INVERSIÓN'!O40 -> 0 | H8: ='F00 INVERSIÓN'!P40 -> 0 | I8: ='F00 INVERSIÓN'!Q40 -> 0 | J8: ='F00 INVERSIÓN'!R40 -> 0 | K8: ='F00 INVERSIÓN'!S40 -> 0 | ... Q8: ='F00 INVERSIÓN'!Y40 -> 0 | R8: =SUM(D8:Q8) -> 31800 | T8: =R8/$E$42 -> 1590 | V8: ='F00 INVERSIÓN'!L42 -> 31800 | W8: =SERVICIO!B13 -> 31800 | X8: =V8-R8 -> 0 | Y8: =V8-W8 -> 0
B9: ACTIVOS
A10: NOMINA Y ADICIONALES | D10: =NOMINA!V19+'F01 EPP'!M19+'F01 UNIFORMES'!M12 -> 0 | E10: =NOMINA!W19+'F01 EPP'!N19+'F01 UNIFORMES'!N12 -> 16653.273 | F10: =NOMINA!X19+'F01 EPP'!O19+'F01 UNIFORMES'!O12 -> 16653.273 | G10: =NOMINA!Y19+'F01 EPP'!P19+'F01 UNIFORMES'!P12 -> 16653.273 | H10: =NOMINA!Z19+'F01 EPP'!Q19+'F01 UNIFORMES'!Q12 -> 16653.273 | I10: =NOMINA!AA19+'F01 EPP'!R19+'F01 UNIFORMES'!R12 -> 21985.773 | J10: =NOMINA!AB19+'F01 EPP'!S19+'F01 UNIFORMES'!S12 -> 16653.273 | K10: =NOMINA!AC19+'F01 EPP'!T19+'F01 UNIFORMES'!T12 -> 16653.273 | ... Q10: =NOMINA!AI19+'F01 EPP'!Z19+'F01 UNIFORMES'!Z12 -> 16653.273 | R10: =SUM(D10:Q10) -> 235156.29 | T10: =R10/$E$42 -> 11757.815 | V10: =+NOMINA!V21+'F01 EPP'!M21+'F01 UNIFORMES'!M14 -> 235156.29 | W10: =SERVICIO!B80+SERVICIO!B25+SERVICIO!B154 -> 235156.29 | X10: =V10-R10 -> 0 | Y10: =V10-W10 -> 0
B11: NÓMINA + EPP + UNIFORMES
A12: INMUEBLES Y SERVICIOS | D12: ='F02 INMUEBLES Y S'!M19 -> 0 | E12: ='F02 INMUEBLES Y S'!N19 -> 2020 | F12: ='F02 INMUEBLES Y S'!O19 -> 2020 | G12: ='F02 INMUEBLES Y S'!P19 -> 2020 | H12: ='F02 INMUEBLES Y S'!Q19 -> 2020 | I12: ='F02 INMUEBLES Y S'!R19 -> 2020 | J12: ='F02 INMUEBLES Y S'!S19 -> 2020 | K12: ='F02 INMUEBLES Y S'!T19 -> 2020 | ... Q12: ='F02 INMUEBLES Y S'!Z19 -> 2020 | R12: =SUM(D12:Q12) -> 26260 | T12: =R12/$E$42 -> 1313 | V12: ='F02 INMUEBLES Y S'!M21 -> 26260 | W12: =SERVICIO!B23 -> 26260 | X12: =V12-R12 -> 0 | Y12: =V12-W12 -> 0
B13: INMUEBLES
A14: TELEFONIA Y COMUNICACIÓN | D14: ='F03 COM Y EQ COM'!L35 -> 0 | E14: ='F03 COM Y EQ COM'!M35 -> 75 | F14: ='F03 COM Y EQ COM'!N35 -> 75 | G14: ='F03 COM Y EQ COM'!O35 -> 75 | H14: ='F03 COM Y EQ COM'!P35 -> 75 | I14: ='F03 COM Y EQ COM'!Q35 -> 75 | J14: ='F03 COM Y EQ COM'!R35 -> 75 | K14: ='F03 COM Y EQ COM'!S35 -> 75 | ... Q14: ='F03 COM Y EQ COM'!Y35 -> 75 | R14: =SUM(D14:Q14) -> 975 | T14: =R14/$E$42 -> 48.75 | V14: ='F03 COM Y EQ COM'!L37 -> 975 | W14: =SERVICIO!B84 -> 975 | X14: =V14-R14 -> 0 | Y14: =V14-W14 -> 0
B15: COM Y EQ COM
A16: VEHICULOS Y COMBUSTIBLE | D16: ='F04 VEHÍCULOS Y COMB. '!R30 -> 0 | E16: ='F04 VEHÍCULOS Y COMB. '!S30 -> 1386 | F16: ='F04 VEHÍCULOS Y COMB. '!T30 -> 1386 | G16: ='F04 VEHÍCULOS Y COMB. '!U30 -> 1386 | H16: ='F04 VEHÍCULOS Y COMB. '!V30 -> 1386 | I16: ='F04 VEHÍCULOS Y COMB. '!W30 -> 1386 | J16: ='F04 VEHÍCULOS Y COMB. '!X30 -> 1386 | K16: ='F04 VEHÍCULOS Y COMB. '!Y30 -> 1386 | ... Q16: ='F04 VEHÍCULOS Y COMB. '!AE30 -> 1386 | R16: =SUM(D16:Q16) -> 18018 | T16: =R16/$E$42 -> 900.9 | V16: ='F04 VEHÍCULOS Y COMB. '!R32 -> 18018 | W16: =SERVICIO!B157 -> 18018 | X16: =V16-R16 -> 0 | Y16: =V16-W16 -> 0
B17: VEHÍCULOS Y COMB
A18: VIATICOS | D18: ='F05 VIÁTICOS'!K27 -> 0 | E18: ='F05 VIÁTICOS'!L27 -> 450 | F18: ='F05 VIÁTICOS'!M27 -> 450 | G18: ='F05 VIÁTICOS'!N27 -> 450 | H18: ='F05 VIÁTICOS'!O27 -> 450 | I18: ='F05 VIÁTICOS'!P27 -> 450 | J18: ='F05 VIÁTICOS'!Q27 -> 450 | K18: ='F05 VIÁTICOS'!R27 -> 450 | ... Q18: ='F05 VIÁTICOS'!X27 -> 450 | R18: =SUM(D18:Q18) -> 5850 | T18: =R18/$E$42 -> 292.5 | V18: ='F05 VIÁTICOS'!K29 -> 5850 | W18: =SERVICIO!B165 -> 5850 | X18: =V18-R18 -> 0 | Y18: =V18-W18 -> 0
B19: VIATICOS CAJA CHICA Y REEMBOLSO
A20: MAT, SERV & EQUIPO | D20: ='F06 (MAT,SERV & EQUIPO)'!L43 -> 0 | E20: ='F06 (MAT,SERV & EQUIPO)'!M43 -> 2760 | F20: ='F06 (MAT,SERV & EQUIPO)'!N43 -> 1260 | G20: ='F06 (MAT,SERV & EQUIPO)'!O43 -> 1260 | H20: ='F06 (MAT,SERV & EQUIPO)'!P43 -> 3510 | I20: ='F06 (MAT,SERV & EQUIPO)'!Q43 -> 1260 | J20: ='F06 (MAT,SERV & EQUIPO)'!R43 -> 2963 | K20: ='F06 (MAT,SERV & EQUIPO)'!S43 -> 1260 | ... Q20: ='F06 (MAT,SERV & EQUIPO)'!Y43 -> 1260 | R20: =SUM(D20:Q20) -> 23333 | T20: =R20/$E$42 -> 1166.65 | V20: ='F06 (MAT,SERV & EQUIPO)'!L45 -> 23333 | W20: =SERVICIO!B76 -> 23333 | X20: =V20-R20 -> 0 | Y20: =V20-W20 -> 0
B21: MAT,SERV & EQUIPO
A22: SERVICIOS | D22: ='F07 OPERAC. (MAT,SERV & EQUIPO)'!L116 -> 0 | E22: ='F07 OPERAC. (MAT,SERV & EQUIPO)'!M116 -> 70537.5 | F22: ='F07 OPERAC. (MAT,SERV & EQUIPO)'!N116 -> 70837.5 | G22: ='F07 OPERAC. (MAT,SERV & EQUIPO)'!O116 -> 70387.5 | H22: ='F07 OPERAC. (MAT,SERV & EQUIPO)'!P116 -> 70387.5 | I22: ='F07 OPERAC. (MAT,SERV & EQUIPO)'!Q116 -> 70387.5 | J22: ='F07 OPERAC. (MAT,SERV & EQUIPO)'!R116 -> 70537.5 | K22: ='F07 OPERAC. (MAT,SERV & EQUIPO)'!S116 -> 70387.5 | ... Q22: ='F07 OPERAC. (MAT,SERV & EQUIPO)'!Y116 -> 75387.5 | R22: =SUM(D22:Q22) -> 920937.5 | T22: =R22/$E$42 -> 46046.875 | V22: ='F07 OPERAC. (MAT,SERV & EQUIPO)'!L118 -> 920937.5 | W22: =SERVICIO!B148 -> 920937.5 | X22: =V22-R22 -> 0 | Y22: =V22-W22 -> 0
B23: MAT,SERV & EQUIPO (CONSTRUCCION)
A24: ACTIVOS (CONSTRUCCION) | D24: ='F07 OPERAC. (MAT,SERV & EQUIPO)'!L21 -> 0 | E24: ='F07 OPERAC. (MAT,SERV & EQUIPO)'!M21 -> 82.5 | F24: ='F07 OPERAC. (MAT,SERV & EQUIPO)'!N21 -> 82.5 | G24: ='F07 OPERAC. (MAT,SERV & EQUIPO)'!O21 -> 82.5 | H24: ='F07 OPERAC. (MAT,SERV & EQUIPO)'!P21 -> 82.5 | I24: ='F07 OPERAC. (MAT,SERV & EQUIPO)'!Q21 -> 82.5 | J24: ='F07 OPERAC. (MAT,SERV & EQUIPO)'!R21 -> 82.5 | K24: ='F07 OPERAC. (MAT,SERV & EQUIPO)'!S21 -> 82.5 | ... Q24: ='F07 OPERAC. (MAT,SERV & EQUIPO)'!Y21 -> 82.5 | R24: =SUM(D24:Q24) -> 1072.5 | T24: =R24/$E$42 -> 53.625 | V24: ='F07 OPERAC. (MAT,SERV & EQUIPO)'!L23 -> 1072.5 | W24: =SERVICIO!B30 -> 1072.5 | X24: =V24-R24 -> 0 | Y24: =V24-W24 -> 0
B25: ENSERES MENORES DIVERSOS
A26: MATERIALES (OPERACION) | D26: ='F07 OPERAC. (MAT,SERV & EQUIPO)'!L43 -> 0 | E26: ='F07 OPERAC. (MAT,SERV & EQUIPO)'!M43 -> 57.7115 | F26: ='F07 OPERAC. (MAT,SERV & EQUIPO)'!N43 -> 57.7115 | G26: ='F07 OPERAC. (MAT,SERV & EQUIPO)'!O43 -> 57.7115 | H26: ='F07 OPERAC. (MAT,SERV & EQUIPO)'!P43 -> 57.7115 | I26: ='F07 OPERAC. (MAT,SERV & EQUIPO)'!Q43 -> 57.7115 | J26: ='F07 OPERAC. (MAT,SERV & EQUIPO)'!R43 -> 57.7115 | K26: ='F07 OPERAC. (MAT,SERV & EQUIPO)'!S43 -> 57.7115 | ... Q26: ='F07 OPERAC. (MAT,SERV & EQUIPO)'!Y43 -> 57.7115 | R26: =SUM(D26:Q26) -> 750.2495 | T26: =R26/$E$42 -> 37.512475 | V26: ='F07 OPERAC. (MAT,SERV & EQUIPO)'!L45 -> 750.2495 | W26: =SERVICIO!B32 -> 750.2495 | X26: =V26-R26 -> 0 | Y26: =V26-W26 -> 0
B27: INSUMOS AGRICOLAS
A28: SERVICIOS (OPERACION) | D28: ='F07 OPERAC. (MAT,SERV & EQUIPO)'!L193 -> 0 | E28: ='F07 OPERAC. (MAT,SERV & EQUIPO)'!M193 -> 438.034 | F28: ='F07 OPERAC. (MAT,SERV & EQUIPO)'!N193 -> 438.034 | G28: ='F07 OPERAC. (MAT,SERV & EQUIPO)'!O193 -> 438.034 | H28: ='F07 OPERAC. (MAT,SERV & EQUIPO)'!P193 -> 438.034 | I28: ='F07 OPERAC. (MAT,SERV & EQUIPO)'!Q193 -> 438.034 | J28: ='F07 OPERAC. (MAT,SERV & EQUIPO)'!R193 -> 438.034 | K28: ='F07 OPERAC. (MAT,SERV & EQUIPO)'!S193 -> 438.034 | ... Q28: ='F07 OPERAC. (MAT,SERV & EQUIPO)'!Y193 -> 438.034 | R28: =SUM(D28:Q28) -> 5694.442 | T28: =R28/$E$42 -> 284.7221 | V28: ='F07 OPERAC. (MAT,SERV & EQUIPO)'!L195 -> 5694.442 | W28: =SERVICIO!B37+SERVICIO!B40+SERVICIO!B78+SERVICIO!B150+SERVICIO!B152 -> 5694.442 | X28: =V28-R28 -> 0 | Y28: =V28-W28 -> 0
B29: " SERVICIOS DE SALUD / SERVICIOS DE CAPACITACION / MATERIALES DE SALUD / MARKETING / INSUMOS DE OFICINA
A30: ACTIVOS (OPERACION) (Computadoras) | D30: ='F03 COM Y EQ COM'!L50 -> 0 | E30: ='F03 COM Y EQ COM'!M50 -> 0 | F30: ='F03 COM Y EQ COM'!N50 -> 0 | G30: ='F03 COM Y EQ COM'!O50 -> 0 | H30: ='F03 COM Y EQ COM'!P50 -> 0 | I30: ='F03 COM Y EQ COM'!Q50 -> 0 | J30: ='F03 COM Y EQ COM'!R50 -> 0 | K30: ='F03 COM Y EQ COM'!S50 -> 0 | ... Q30: ='F03 COM Y EQ COM'!Y50 -> 0 | R30: =SUM(D30:Q30) -> 0 | T30: =R30/$E$42 -> 0 | V30: ='F03 COM Y EQ COM'!L52 -> 0 | W30: =SERVICIO!B28 -> 0 | X30: =V30-R30 -> 0 | Y30: =V30-W30 -> 0
B31: EQUIPO DE COMPUTO Y ARRENDAMIENTO DE EQ. COMPUTO
A33: EGRESO TOTAL MENSUAL | D33: =SUM(D8:D30) -> 0 | E33: =SUM(E8:E30) -> 94460.018 | F33: =SUM(F8:F30) -> 125060.02 | G33: =SUM(G8:G30) -> 92810.018 | H33: =SUM(H8:H30) -> 95060.018 | I33: =SUM(I8:I30) -> 98142.518 | J33: =SUM(J8:J30) -> 94663.018 | K33: =SUM(K8:K30) -> 92810.018 | ... Q33: =SUM(Q8:Q30) -> 97810.018 | R33: =SUM(D33:Q33) -> 1269847 | T33: =R33/$E$42 -> 63492.349 | V33: =SERVICIO!B166 -> 1269847 | X33: =V33-R33 -> 0
A35: CAPEX TOTAL MENSUAL | D35: =D8 -> 0 | E35: =E8 -> 0 | F35: =F8 -> 31800 | G35: =G8 -> 0 | H35: =H8 -> 0 | I35: =I8 -> 0 | J35: =J8 -> 0 | K35: =K8 -> 0 | ... Q35: =Q8 -> 0 | R35: =SUM(D35:Q35) -> 31800 | T35: =R35/$E$42 -> 1590
A37: OPEX TOTAL MENSUAL | D37: =+D33-D35 -> 0 | E37: =+E33-E35 -> 94460.018 | F37: =+F33-F35 -> 93260.018 | G37: =+G33-G35 -> 92810.018 | H37: =+H33-H35 -> 95060.018 | I37: =+I33-I35 -> 98142.518 | J37: =+J33-J35 -> 94663.018 | K37: =+K33-K35 -> 92810.018 | ... Q37: =+Q33-Q35 -> 97810.018 | R37: =SUM(D37:Q37) -> 1238047 | T37: =R37/$E$42 -> 61902.349
A39: OPEX TOTAL MENSUAL REAL | R39: =SUM(D39:Q39) -> 0 | T39: =+R39*PREMISAS!$I$23 -> 0
D41: PREMISAS
D42: PARIDAD | E42: =PREMISAS!I23 -> 20
D43: MES | E43: =PREMISAS!I24 -> 30.4
D44: CRÉDITO | E44: =PREMISAS!I25 -> 45
D45: GAS LP | E45: =PREMISAS!I26 -> 10.5
D46: GASOLINA | E46: =PREMISAS!I27 -> 22
D47: DIESEL | E47: =PREMISAS!I28 -> 23
D48: https://www.google.com/search?client=firefox-b-d&q=precio+del+dolar+hoy

Sheet PREMISAS
B2: PREMISAS
B4: PARTIDAS | C4: DESCRIPCIÓN | D4: UNIDAD | E4: CANTIDAD | F4: PU [USD] | G4: TOTAL [USD] | H4: PU [MN] | I4: TOTAL [MN] | K4: Instalación | L4: M1 | M4: M2 | N4: M3 | O4: M4 | P4: M5 | Q4: M6 | R4: M7 | S4: M8 | T4: M9 | U4: M10 | V4: M11 | W4: M12 | X4: M13
K5: - | L5: ENE | M5: FEB | N5: MAR | O5: ABR | P5: MAY | Q5: JUN | R5: JUL | S5: AGO | T5: SEP | U5: OCT | V5: NOV | W5: DIC | X5: ENE
K6: - | L6: 31 | M6: 28 | N6: 31 | O6: 30 | P6: 31 | Q6: 30 | R6: 31 | S6: 31 | T6: 30 | U6: 31 | V6: 30 | W6: 31 | X6: 31
B8: - | C8: NOMBRE Y OBJETIVO DEL SRVICIO | D8: TIPO
B9: 1 | C9: Patín con bomba electrocentrifuga horizontal con gasto de 10,000-20,000 BPD incluye la operación continua. | D9: Día | E9: 0 | F9: 602.496 | G9: =F9*E9 -> 0 | H9: =F9*$I$23 -> 12049.92 | I9: =E9*H9 -> 0 | K9: 0 | L9: =$G$9*L6 -> 0 | M9: =$G$9*M6 -> 0 | N9: =$G$9*N6 -> 0 | O9: =$G$9*O6 -> 0 | P9: =$G$9*P6 -> 0 | Q9: =$G$9*Q6 -> 0 | R9: =$G$9*R6 -> 0 | S9: =$G$9*S6 -> 0 | ... X9: =$G$9*X6 -> 0
B10: 2 | C10: Patín con bomba electrocentrifuga horizontal con gasto de 20,000-30,000 BPD incluye la operación continua. | D10: Día | E10: 0 | F10: 470.01 | G10: =F10*E10 -> 0 | H10: =F10*$I$23 -> 9400.2 | I10: =E10*H10 -> 0 | K10: 0 | L10: =$G$10*L6 -> 0 | M10: =$G$10*M6 -> 0 | N10: =$G$10*N6 -> 0 | O10: =$G$10*O6 -> 0 | P10: =$G$10*P6 -> 0 | Q10: =$G$10*Q6 -> 0 | R10: =$G$10*R6 -> 0 | S10: =$G$10*S6 -> 0 | ... X10: =$G$10*X6 -> 0
B11: 3 | C11: Generador de energía a gas de 300 KW/375 KVA. | D11: Día | E11: 4 | F11: 1662.32 | G11: =F11*E11 -> 6649.28 | H11: =F11*$I$23 -> 33246.4 | I11: =E11*H11 -> 132985.6 | K11: 0 | L11: =$G$11*L6 -> 206127.68 | M11: =$G$11*M6 -> 186179.84 | N11: =$G$11*N6 -> 206127.68 | O11: =$G$11*O6 -> 199478.4 | P11: =$G$11*P6 -> 206127.68 | Q11: =$G$11*Q6 -> 199478.4 | R11: =$G$11*R6 -> 206127.68 | S11: =$G$11*S6 -> 206127.68 | ... X11: =$G$11*X6 -> 206127.68
B12: 4 | C12: Generador de energía a gas de 300 KW/375 KVA a disposición. | D12: Día | E12: 0 | F12: 1079.64 | G12: =F12*E12 -> 0 | H12: =F12*$I$23 -> 21592.8 | I12: =E12*H12 -> 0 | K12: 0 | L12: =$G$12*L6 -> 0 | M12: =$G$12*M6 -> 0 | N12: =$G$12*N6 -> 0 | O12: =$G$12*O6 -> 0 | P12: =$G$12*P6 -> 0 | Q12: =$G$12*Q6 -> 0 | R12: =$G$12*R6 -> 0 | S12: =$G$12*S6 -> 0 | ... X12: =$G$12*X6 -> 0
B13: 5 | C13: Variador de frecuencia para 300 KW/375 KVA. | D13: Día | E13: 0 | F13: 227.38 | G13: =F13*E13 -> 0 | H13: =F13*$I$23 -> 4547.6 | I13: =E13*H13 -> 0 | K13: 0 | L13: =$G$13*L6 -> 0 | M13: =$G$13*M6 -> 0 | N13: =$G$13*N6 -> 0 | O13: =$G$13*O6 -> 0 | P13: =$G$13*P6 -> 0 | Q13: =$G$13*Q6 -> 0 | R13: =$G$13*R6 -> 0 | S13: =$G$13*S6 -> 0 | ... X13: =$G$13*X6 -> 0
B14: 6 | E14: 0 | F14: 0 | G14: =F14*E14 -> 0 | H14: =F14*$I$23 -> 0 | I14: =E14*H14 -> 0 | K14: 0 | L14: 0 | M14: 0 | N14: 0 | O14: 0 | P14: 0 | Q14: 0 | R14: 0 | S14: 0 | T14: 0 | U14: 0 | V14: 0 | W14: 0 | X14: 0
B15: 7 | K15: 0 | L15: =$G$15*L6 -> 0 | M15: =$G$15*M6 -> 0 | N15: =$G$15*N6 -> 0 | O15: =$G$15*O6 -> 0 | P15: =$G$15*P6 -> 0 | Q15: =$G$15*Q6 -> 0 | R15: =$G$15*R6 -> 0 | S15: =$G$15*S6 -> 0 | ... X15: =$G$15*X6 -> 0
H17: TOTAL MENSUAL [USD] | K17: =SUM(K9:K15) -> 0 | L17: =SUM(L9:L15) -> 206127.68 | M17: =SUM(M9:M15) -> 186179.84 | N17: =SUM(N9:N15) -> 206127.68 | O17: =SUM(O9:O15) -> 199478.4 | P17: =SUM(P9:P15) -> 206127.68 | Q17: =SUM(Q9:Q15) -> 199478.4 | R17: =SUM(R9:R15) -> 206127.68 | ... X17: =SUM(X9:X15) -> 206127.68
H18: TOTAL MENSUAL [MN] | K18: =K17/$I$23 -> 0 | L18: =L17*$I$23 -> 4122553.6 | M18: =M17*$I$23 -> 3723596.8 | N18: =N17*$I$23 -> 4122553.6 | O18: =O17*$I$23 -> 3989568 | P18: =P17*$I$23 -> 4122553.6 | Q18: =Q17*$I$23 -> 3989568 | R18: =R17*$I$23 -> 4122553.6 | S18: =S17*$I$23 -> 4122553.6 | ... X18: =X17*$I$23 -> 4122553.6
H19: TOTAL [USD] | K19: =SUM(K17:X17) -> 2633114.9
H20: TOTAL [MN] | K20: =SUM(K18:X18) -> 52662298
H22: PREMISAS
H23: PARIDAD | I23: 20
H24: MES | I24: 30.4
H25: CRÉDITO | I25: 45
H26: GAS LP | I26: 10.5
H27: GASOLINA | I27: 22
H28: DIESEL | I28: 23
H29: https://www.google.com/search?client=firefox-b-d&q=precio+del+dolar+hoy
H31: Descuento MB2
B115: 64373.77

Sheet F08 INGRESOS
B2: INGRESOS
B4: RESUMEN | C4: PARTIDA | D4: CONCEPTO | E4: UNIDAD | F4: CANTIDAD | G4: PU [USD] | H4: TOTAL [USD] | I4: PU [MN] | J4: TOTAL [MN] | K4: TOTAL [MN] | M4: Instalación | N4: M1 | O4: M2 | P4: M3 | Q4: M4 | R4: M5 | S4: M6 | T4: M7 | U4: M8 | V4: M9 | W4: M10 | X4: M11 | Y4: M12 | Z4: M13
H5: TOTAL [USD] | I5: PU [MN] | J5: TOTAL [MN] | M5: - | N5: ENE | O5: FEB | P5: MAR | Q5: ABR | R5: MAY | S5: JUN | T5: JUL | U5: AGO | V5: SEP | W5: OCT | X5: NOV | Y5: DIC | Z5: ENE
H6: [USD] | I6: [MN] | J6: [MN] | K6: C / IVA | M6: - | N6: 31 | O6: 28 | P6: 31 | Q6: 30 | R6: 31 | S6: 30 | T6: 31 | U6: 31 | V6: 30 | W6: 31 | X6: 30 | Y6: 31 | Z6: 31
B7: FACTURACION | C7: 1 | D7: =PREMISAS!C9 -> Patín con bomba electrocentrifuga horizontal con gasto de 10,000-20,000 BPD incluye la operación continua. | E7: =PREMISAS!D9 -> Día | F7: =PREMISAS!E9 -> 0 | G7: =PREMISAS!F9 -> 602.496 | H7: =PREMISAS!G9 -> 0 | I7: =PREMISAS!H9 -> 12049.92 | J7: =PREMISAS!I9 -> 0 | K7: =J7*1.16 -> 0 | M7: =PREMISAS!K9 -> 0 | N7: =PREMISAS!L9 -> 0 | O7: =PREMISAS!M9 -> 0 | P7: =PREMISAS!N9 -> 0 | Q7: =PREMISAS!O9 -> 0 | R7: =PREMISAS!P9 -> 0 | S7: =PREMISAS!Q9 -> 0 | T7: =PREMISAS!R9 -> 0 | ... Z7: =PREMISAS!X9 -> 0
B8: FACTURACION | C8: 2 | D8: =PREMISAS!C10 -> Patín con bomba electrocentrifuga horizontal con gasto de 20,000-30,000 BPD incluye la operación continua. | E8: =PREMISAS!D10 -> Día | F8: =PREMISAS!E10 -> 0 | G8: =PREMISAS!F10 -> 470.01 | H8: =PREMISAS!G10 -> 0 | I8: =PREMISAS!H10 -> 9400.2 | J8: =PREMISAS!I10 -> 0 | K8: =J8*1.16 -> 0 | M8: =PREMISAS!K10 -> 0 | N8: =PREMISAS!L10 -> 0 | O8: =PREMISAS!M10 -> 0 | P8: =PREMISAS!N10 -> 0 | Q8: =PREMISAS!O10 -> 0 | R8: =PREMISAS!P10 -> 0 | S8: =PREMISAS!Q10 -> 0 | T8: =PREMISAS!R10 -> 0 | ... Z8: =PREMISAS!X10 -> 0
B9: FACTURACION | C9: 3 | D9: =PREMISAS!C11 -> Generador de energía a gas de 300 KW/375 KVA. | E9: =PREMISAS!D11 -> Día | F9: =PREMISAS!E11 -> 4 | G9: =PREMISAS!F11 -> 1662.32 | H9: =PREMISAS!G11 -> 6649.28 | I9: =PREMISAS!H11 -> 33246.4 | J9: =PREMISAS!I11 -> 132985.6 | K9: =J9*1.16 -> 154263.3 | M9: =PREMISAS!K11 -> 0 | N9: =PREMISAS!L11 -> 206127.68 | O9: =PREMISAS!M11 -> 186179.84 | P9: =PREMISAS!N11 -> 206127.68 | Q9: =PREMISAS!O11 -> 199478.4 | R9: =PREMISAS!P11 -> 206127.68 | S9: =PREMISAS!Q11 -> 199478.4 | T9: =PREMISAS!R11 -> 206127.68 | ... Z9: =PREMISAS!X11 -> 206127.68
B10: FACTURACION | C10: 4 | D10: =PREMISAS!C12 -> Generador de energía a gas de 300 KW/375 KVA a disposición. | E10: =PREMISAS!D12 -> Día | F10: =PREMISAS!E12 -> 0 | G10: =PREMISAS!F12 -> 1079.64 | H10: =PREMISAS!G12 -> 0 | I10: =PREMISAS!H12 -> 21592.8 | J10: =PREMISAS!I12 -> 0 | K10: =J10*1.16 -> 0 | M10: =PREMISAS!K12 -> 0 | N10: =PREMISAS!L12 -> 0 | O10: =PREMISAS!M12 -> 0 | P10: =PREMISAS!N12 -> 0 | Q10: =PREMISAS!O12 -> 0 | R10: =PREMISAS!P12 -> 0 | S10: =PREMISAS!Q12 -> 0 | T10: =PREMISAS!R12 -> 0 | ... Z10: =PREMISAS!X12 -> 0
B11: FACTURACION | C11: 5 | D11: =PREMISAS!C13 -> Variador de frecuencia para 300 KW/375 KVA. | E11: =PREMISAS!D13 -> Día | F11: =PREMISAS!E13 -> 0 | G11: =PREMISAS!F13 -> 227.38 | H11: =PREMISAS!G13 -> 0 | I11: =PREMISAS!H13 -> 4547.6 | J11: =PREMISAS!I13 -> 0 | K11: =J11*1.16 -> 0 | M11: =PREMISAS!K13 -> 0 | N11: =PREMISAS!L13 -> 0 | O11: =PREMISAS!M13 -> 0 | P11: =PREMISAS!N13 -> 0 | Q11: =PREMISAS!O13 -> 0 | R11: =PREMISAS!P13 -> 0 | S11: =PREMISAS!Q13 -> 0 | T11: =PREMISAS!R13 -> 0 | ... Z11: =PREMISAS!X13 -> 0
B12: FACTURACION | C12: 6 | E12: =PREMISAS!D14 -> 0 | F12: =PREMISAS!E14 -> 0 | G12: =PREMISAS!F14 -> 0 | H12: =PREMISAS!G14 -> 0 | I12: =PREMISAS!H14 -> 0 | J12: =PREMISAS!I14 -> 0 | K12: =J12*1.16 -> 0 | M12: =PREMISAS!K14 -> 0 | N12: =PREMISAS!L14 -> 0 | O12: =PREMISAS!M14 -> 0 | P12: =PREMISAS!N14 -> 0 | Q12: =PREMISAS!O14 -> 0 | R12: =PREMISAS!P14 -> 0 | S12: =PREMISAS!Q14 -> 0 | T12: =PREMISAS!R14 -> 0 | ... Z12: =PREMISAS!X14 -> 0
B13: FACTURACION | C13: 7
J15: TOTAL MENSUAL [USD] | M15: =SUM(M7:M13) -> 0 | N15: =SUM(N7:N13) -> 206127.68 | O15: =SUM(O7:O13) -> 186179.84 | P15: =SUM(P7:P13) -> 206127.68 | Q15: =SUM(Q7:Q13) -> 199478.4 | R15: =SUM(R7:R13) -> 206127.68 | S15: =SUM(S7:S13) -> 199478.4 | T15: =SUM(T7:T13) -> 206127.68 | ... Z15: =SUM(Z7:Z13) -> 206127.68
J16: TOTAL MENSUAL [MN] | M16: =M15/$K$21 -> 0 | N16: =N15*$K$21 -> 4122553.6 | O16: =O15*$K$21 -> 3723596.8 | P16: =P15*$K$21 -> 4122553.6 | Q16: =Q15*$K$21 -> 3989568 | R16: =R15*$K$21 -> 4122553.6 | S16: =S15*$K$21 -> 3989568 | T16: =T15*$K$21 -> 4122553.6 | U16: =U15*$K$21 -> 4122553.6 | ... Z16: =Z15*$K$21 -> 4122553.6
J17: TOTAL [USD] | M17: =SUM(M15:Z15) -> 2633114.9
J18: TOTAL [MN] | M18: =SUM(M16:Z16) -> 52662298
J20: =PREMISAS!H22 -> PREMISAS
J21: =PREMISAS!H23 -> PARIDAD | K21: =PREMISAS!I23 -> 20
J22: =PREMISAS!H24 -> MES | K22: =PREMISAS!I24 -> 30.4
J23: =PREMISAS!H25 -> CRÉDITO | K23: =PREMISAS!I25 -> 45
J24: =PREMISAS!H26 -> GAS LP | K24: =PREMISAS!I26 -> 10.5
J25: =PREMISAS!H27 -> GASOLINA | K25: =PREMISAS!I27 -> 22
J26: =PREMISAS!H28 -> DIESEL | K26: =PREMISAS!I28 -> 23
J27: https://www.google.com/search?client=firefox-b-d&q=precio+del+dolar+hoy

Sheet F00 INVERSIÓN
B2: INVERSIÓN
B4: RESUMEN | C4: DESCRIPCIÓN 1 | D4: UNIDAD | E4: CANTIDAD | F4: PU [USD] | G4: TOTAL [USD] | H4: PU [MN] | I4: TOTAL [MN] | J4: TOTAL [MN] | L4: Instalación | M4: M1 | N4: M2 | O4: M3 | P4: M4 | Q4: M5 | R4: M6 | S4: M7 | T4: M8 | U4: M9 | V4: M10 | W4: M11 | X4: M12 | Y4: M13
G5: TOTAL [USD] | H5: PU [MN] | I5: TOTAL [MN] | L5: - | M5: ENE | N5: FEB | O5: MAR | P5: ABR | Q5: MAY | R5: JUN | S5: JUL | T5: AGO | U5: SEP | V5: OCT | W5: NOV | X5: DIC | Y5: ENE
G6: [USD] | H6: [MN] | I6: [MN] | J6: C / IVA | L6: - | M6: 31 | N6: 28 | O6: 31 | P6: 30 | Q6: 31 | R6: 30 | S6: 31 | T6: 31 | U6: 30 | V6: 31 | W6: 30 | X6: 31 | Y6: 31
B7: EQUIPO DE TRANSPORTE | C7: Repuesto unidad 31 | E7: 1 | F7: 31800 | G7: =E7*F7 -> 31800 | H7: =F7*$J$46 -> 636000 | I7: =E7*H7 -> 636000 | J7: =I7*1.16 -> 737760 | L7: 0 | M7: 0 | N7: =G7 -> 31800 | O7: 0 | P7: 0 | Q7: =K7 -> 0 | R7: 0 | S7: 0 | T7: 0 | U7: 0 | V7: 0 | W7: 0 | X7: 0 | Y7: 0
B8: EQUIPO DE TRANSPORTE | E8: 0 | F8: 0 | G8: =E8*F8 -> 0 | H8: =F8*$J$46 -> 0 | I8: =E8*H8 -> 0 | J8: =I8*1.16 -> 0 | L8: 0 | M8: 0 | N8: =H8 -> 0 | O8: 0 | P8: 0 | Q8: 0 | R8: =L8 -> 0 | S8: 0 | T8: 0 | U8: 0 | V8: 0 | W8: 0 | X8: 0 | Y8: 0
B9: EQUIPO DE TRANSPORTE | E9: 0 | F9: 0 | G9: =E9*F9 -> 0 | H9: =F9*$J$46 -> 0 | I9: =E9*H9 -> 0 | J9: =I9*1.16 -> 0 | L9: 0 | M9: 0 | N9: 0 | O9: =H9 -> 0 | P9: 0 | Q9: 0 | R9: 0 | S9: =L9 -> 0 | T9: 0 | U9: 0 | V9: 0 | W9: 0 | X9: 0 | Y9: 0
B10: EQUIPO DE TRANSPORTE | E10: 0 | F10: 0 | G10: =E10*F10 -> 0 | H10: =F10*$J$46 -> 0 | I10: =E10*H10 -> 0 | J10: =I10*1.16 -> 0 | L10: 0 | M10: 0 | N10: 0 | O10: 0 | P10: =H10 -> 0 | Q10: 0 | R10: 0 | S10: 0 | T10: =L10 -> 0 | U10: 0 | V10: 0 | W10: 0 | X10: 0 | Y10: 0
L11: =SUM(L7:L10) -> 0 | M11: =SUM(M7:M10) -> 0 | N11: =SUM(N7:N10) -> 31800 | O11: =SUM(O7:O10) -> 0 | P11: =SUM(P7:P10) -> 0 | Q11: =SUM(Q7:Q10) -> 0 | R11: =SUM(R7:R10) -> 0 | S11: =SUM(S7:S10) -> 0 | ... Y11: =SUM(Y7:Y10) -> 0
B13: EQUIPO DE MOBILIARIO | E13: 1 | F13: 0 | G13: =E13*F13 -> 0 | H13: =F13*$J$46 -> 0 | I13: =E13*H13 -> 0 | J13: =I13*1.16 -> 0 | L13: 0 | M13: =G13 -> 0 | N13: 0 | O13: 0 | P13: 0 | Q13: =K13 -> 0 | R13: 0 | S13: 0 | T13: 0 | U13: 0 | V13: 0 | W13: 0 | X13: 0 | Y13: 0
B14: EQUIPO DE MOBILIARIO | E14: 2 | F14: 0 | G14: =E14*F14 -> 0 | H14: =F14*$J$46 -> 0 | I14: =E14*H14 -> 0 | J14: =I14*1.16 -> 0 | L14: 0 | M14: 0 | N14: =H14 -> 0 | O14: 0 | P14: 0 | Q14: 0 | R14: =L14 -> 0 | S14: 0 | T14: 0 | U14: 0 | V14: 0 | W14: 0 | X14: 0 | Y14: 0
B15: EQUIPO DE MOBILIARIO | E15: 3 | F15: 0 | G15: =E15*F15 -> 0 | H15: =F15*$J$46 -> 0 | I15: =E15*H15 -> 0 | J15: =I15*1.16 -> 0 | L15: 0 | M15: 0 | N15: 0 | O15: =H15 -> 0 | P15: 0 | Q15: 0 | R15: 0 | S15: =L15 -> 0 | T15: 0 | U15: 0 | V15: 0 | W15: 0 | X15: 0 | Y15: 0
B16: EQUIPO DE MOBILIARIO | E16: 4 | F16: 0 | G16: =E16*F16 -> 0 | H16: =F16*$J$46 -> 0 | I16: =E16*H16 -> 0 | J16: =I16*1.16 -> 0 | L16: 0 | M16: 0 | N16: 0 | O16: 0 | P16: =H16 -> 0 | Q16: 0 | R16: 0 | S16: 0 | T16: =L16 -> 0 | U16: 0 | V16: 0 | W16: 0 | X16: 0 | Y16: 0
L17: =SUM(L13:L16) -> 0 | M17: =SUM(M13:M16) -> 0 | N17: =SUM(N13:N16) -> 0 | O17: =SUM(O13:O16) -> 0 | P17: =SUM(P13:P16) -> 0 | Q17: =SUM(Q13:Q16) -> 0 | R17: =SUM(R13:R16) -> 0 | S17: =SUM(S13:S16) -> 0 | ... Y17: =SUM(Y13:Y16) -> 0
B19: MAQUINARIA Y EQUIPO 1 | E19: 1 | F19: 0 | G19: =E19*F19 -> 0 | H19: =F19*$J$46 -> 0 | I19: =E19*H19 -> 0 | J19: =I19*1.16 -> 0 | L19: 0 | M19: =G19 -> 0 | N19: 0 | O19: 0 | P19: 0 | Q19: 0 | R19: 0 | S19: 0 | T19: 0 | U19: 0 | V19: 0 | W19: 0 | X19: 0 | Y19: 0
B20: MAQUINARIA Y EQUIPO 2 | E20: 2 | F20: 0 | G20: =E20*F20 -> 0 | H20: =F20*$J$46 -> 0 | I20: =E20*H20 -> 0 | J20: =I20*1.16 -> 0 | L20: 0 | M20: 0 | N20: =H20 -> 0 | O20: 0 | P20: 0 | Q20: 0 | R20: 0 | S20: 0 | T20: 0 | U20: 0 | V20: 0 | W20: 0 | X20: 0 | Y20: 0
B21: MAQUINARIA Y EQUIPO 3 | E21: 3 | F21: 0 | G21: =E21*F21 -> 0 | H21: =F21*$J$46 -> 0 | I21: =E21*H21 -> 0 | J21: =I21*1.16 -> 0 | L21: 0 | M21: 0 | N21: 0 | O21: =H21 -> 0 | P21: 0 | Q21: 0 | R21: 0 | S21: 0 | T21: 0 | U21: 0 | V21: 0 | W21: 0 | X21: 0 | Y21: 0
B22: MAQUINARIA Y EQUIPO 4 | E22: 4 | F22: 0 | G22: =E22*F22 -> 0 | H22: =F22*$J$46 -> 0 | I22: =E22*H22 -> 0 | J22: =I22*1.16 -> 0 | L22: 0 | M22: 0 | N22: 0 | O22: 0 | P22: =H22 -> 0 | Q22: 0 | R22: 0 | S22: 0 | T22: 0 | U22: 0 | V22: 0 | W22: 0 | X22: 0 | Y22: 0
B23: MAQUINARIA Y EQUIPO 5 | E23: 5 | F23: 0 | G23: =E23*F23 -> 0 | H23: =F23*$J$46 -> 0 | I23: =E23*H23 -> 0 | J23: =I23*1.16 -> 0 | L23: 0 | M23: 0 | N23: 0 | O23: 0 | P23: 0 | Q23: =H23 -> 0 | R23: 0 | S23: 0 | T23: 0 | U23: 0 | V23: 0 | W23: 0 | X23: 0 | Y23: 0
B24: MAQUINARIA Y EQUIPO 6 | E24: 6 | F24: 0 | G24: =E24*F24 -> 0 | H24: =F24*$J$46 -> 0 | I24: =E24*H24 -> 0 | J24: =I24*1.16 -> 0 | L24: 0 | M24: 0 | N24: 0 | O24: 0 | P24: 0 | Q24: 0 | R24: =H24 -> 0 | S24: 0 | T24: 0 | U24: 0 | V24: 0 | W24: 0 | X24: 0 | Y24: 0
B25: MAQUINARIA Y EQUIPO 8 | E25: 7 | F25: 0 | G25: =E25*F25 -> 0 | H25: =F25*$J$46 -> 0 | I25: =E25*H25 -> 0 | J25: =I25*1.16 -> 0 | L25: 0 | M25: 0 | N25: 0 | O25: 0 | P25: 0 | Q25: 0 | R25: 0 | S25: =H25 -> 0 | T25: 0 | U25: 0 | V25: 0 | W25: 0 | X25: 0 | Y25: 0
L26: =SUM(L19:L25) -> 0 | M26: =SUM(M19:M25) -> 0 | N26: =SUM(N19:N25) -> 0 | O26: =SUM(O19:O25) -> 0 | P26: =SUM(P19:P25) -> 0 | Q26: =SUM(Q19:Q25) -> 0 | R26: =SUM(R19:R25) -> 0 | S26: =SUM(S19:S25) -> 0 | ... Y26: =SUM(Y19:Y25) -> 0
B28: OTROS ACTIVOS | E28: 1 | F28: 0 | G28: =E28*F28 -> 0 | H28: =F28*$J$46 -> 0 | I28: =E28*H28 -> 0 | J28: =I28*1.16 -> 0 | L28: 0 | M28: =G28 -> 0 | N28: 0 | O28: 0 | P28: 0 | Q28: 0 | R28: 0 | S28: 0 | T28: 0 | U28: 0 | V28: 0 | W28: 0 | X28: 0 | Y28: 0
B29: OTROS ACTIVOS | E29: 2 | F29: 0 | G29: =E29*F29 -> 0 | H29: =F29*$J$46 -> 0 | I29: =E29*H29 -> 0 | J29: =I29*1.16 -> 0 | L29: 0 | M29: 0 | N29: =H29 -> 0 | O29: 0 | P29: 0 | Q29: 0 | R29: 0 | S29: 0 | T29: 0 | U29: 0 | V29: 0 | W29: 0 | X29: 0 | Y29: 0
B30: OTROS ACTIVOS | E30: 3 | F30: 0 | G30: =E30*F30 -> 0 | H30: =F30*$J$46 -> 0 | I30: =E30*H30 -> 0 | J30: =I30*1.16 -> 0 | L30: 0 | M30: 0 | N30: 0 | O30: =H30 -> 0 | P30: 0 | Q30: 0 | R30: 0 | S30: 0 | T30: 0 | U30: 0 | V30: 0 | W30: 0 | X30: 0 | Y30: 0
B31: OTROS ACTIVOS | E31: 4 | F31: 0 | G31: =E31*F31 -> 0 | H31: =F31*$J$46 -> 0 | I31: =E31*H31 -> 0 | J31: =I31*1.16 -> 0 | L31: 0 | M31: 0 | N31: 0 | O31: 0 | P31: =H31 -> 0 | Q31: 0 | R31: 0 | S31: 0 | T31: 0 | U31: 0 | V31: 0 | W31: 0 | X31: 0 | Y31: 0
L32: =SUM(L28:L31) -> 0 | M32: =SUM(M28:M31) -> 0 | N32: =SUM(N28:N31) -> 0 | O32: =SUM(O28:O31) -> 0 | P32: =SUM(P28:P31) -> 0 | Q32: =SUM(Q28:Q31) -> 0 | R32: =SUM(R28:R31) -> 0 | S32: =SUM(S28:S31) -> 0 | ... Y32: =SUM(Y28:Y31) -> 0
B34: SOFTWARE Y LICICENCIAS | E34: 1 | F34: 0 | G34: =E34*F34 -> 0 | H34: =F34*$J$46 -> 0 | I34: =E34*H34 -> 0 | J34: =I34*1.16 -> 0 | L34: 0 | M34: =G34 -> 0 | N34: 0 | O34: 0 | P34: 0 | Q34: 0 | R34: 0 | S34: 0 | T34: 0 | U34: 0 | V34: 0 | W34: 0 | X34: 0 | Y34: 0
B35: SOFTWARE Y LICICENCIAS | E35: 2 | F35: 0 | G35: =E35*F35 -> 0 | H35: =F35*$J$46 -> 0 | I35: =E35*H35 -> 0 | J35: =I35*1.16 -> 0 | L35: 0 | M35: 0 | N35: =H35 -> 0 | O35: 0 | P35: 0 | Q35: 0 | R35: 0 | S35: 0 | T35: 0 | U35: 0 | V35: 0 | W35: 0 | X35: 0 | Y35: 0
B36: SOFTWARE Y LICICENCIAS | E36: 3 | F36: 0 | G36: =E36*F36 -> 0 | H36: =F36*$J$46 -> 0 | I36: =E36*H36 -> 0 | J36: =I36*1.16 -> 0 | L36: 0 | M36: 0 | N36: 0 | O36: =H36 -> 0 | P36: 0 | Q36: 0 | R36: 0 | S36: 0 | T36: 0 | U36: 0 | V36: 0 | W36: 0 | X36: 0 | Y36: 0
B37: SOFTWARE Y LICICENCIAS | E37: 4 | F37: 0 | G37: =E37*F37 -> 0 | H37: =F37*$J$46 -> 0 | I37: =E37*H37 -> 0 | J37: =I37*1.16 -> 0 | L37: 0 | M37: 0 | N37: 0 | O37: 0 | P37: =H37 -> 0 | Q37: 0 | R37: 0 | S37: 0 | T37: 0 | U37: 0 | V37: 0 | W37: 0 | X37: 0 | Y37: 0
L38: =SUM(L34:L37) -> 0 | M38: =SUM(M34:M37) -> 0 | N38: =SUM(N34:N37) -> 0 | O38: =SUM(O34:O37) -> 0 | P38: =SUM(P34:P37) -> 0 | Q38: =SUM(Q34:Q37) -> 0 | R38: =SUM(R34:R37) -> 0 | S38: =SUM(S34:S37) -> 0 | ... Y38: =SUM(Y34:Y37) -> 0
I40: TOTAL MENSUAL [USD] | L40: =SUM(L34:L38) -> 0 | M40: =+M38+M32+M26+M17+M11 -> 0 | N40: =+N38+N32+N26+N17+N11 -> 31800 | O40: =+O38+O32+O26+O17+O11 -> 0 | P40: =+P38+P32+P26+P17+P11 -> 0 | Q40: =+Q38+Q32+Q26+Q17+Q11 -> 0 | R40: =+R38+R32+R26+R17+R11 -> 0 | S40: =+S38+S32+S26+S17+S11 -> 0 | T40: =+T38+T32+T26+T17+T11 -> 0 | ... Y40: =+Y38+Y32+Y26+Y17+Y11 -> 0
I41: TOTAL MENSUAL [MN] | L41: =L40*$K$19 -> 0 | M41: =M40*$J$46 -> 0 | N41: =N40*$J$46 -> 636000 | O41: =O40*$J$46 -> 0 | P41: =P40*$J$46 -> 0 | Q41: =Q40*$J$46 -> 0 | R41: =R40*$J$46 -> 0 | S41: =S40*$J$46 -> 0 | T41: =T40*$J$46 -> 0 | ... Y41: =Y40*$J$46 -> 0
I42: TOTAL [USD] | L42: =SUM(L40:Y40) -> 31800
I43: TOTAL [MN] | L43: =SUM(L41:Y41) -> 636000
I45: ='F08 INGRESOS'!J20 -> PREMISAS
I46: ='F08 INGRESOS'!J21 -> PARIDAD | J46: ='F08 INGRESOS'!K21 -> 20
I47: ='F08 INGRESOS'!J22 -> MES | J47: ='F08 INGRESOS'!K22 -> 30.4
I48: ='F08 INGRESOS'!J23 -> CRÉDITO | J48: ='F08 INGRESOS'!K23 -> 45
I49: ='F08 INGRESOS'!J24 -> GAS LP | J49: ='F08 INGRESOS'!K24 -> 10.5
I50: ='F08 INGRESOS'!J25 -> GASOLINA | J50: ='F08 INGRESOS'!K25 -> 22
I51: ='F08 INGRESOS'!J26 -> DIESEL | J51: ='F08 INGRESOS'!K26 -> 23
I52: https://www.google.com/search?client=firefox-b-d&q=precio+del+dolar+hoy

Sheet NOMINA
B2: NÓMINA
B4: RESUMEN | C4: NOMBRE | D4: PUESTO | E4: UNIDAD | F4: CANTIDAD | G4: SALARIO | H4: IMPUESTOS | I4: COSTO REAL C/IMP. | K4: AGUINALDO | L4: FONDO DE AHORRO | M4: UTILIDADES | N4: APOYOS | O4: VACACIONES | P4: PU [USD] | Q4: TOTAL [USD] | R4: PU [MN] | S4: TOTAL [MN] | T4: TOTAL [MN] | V4: Instalación | W4: M1 | X4: M2 | Y4: M3 | Z4: M4 | AA4: M5 | AB4: M6 | AC4: M7 | AD4: M8 | AE4: M9 | AF4: M10 | AG4: M11 | AH4: M12 | AI4: M13
Q5: TOTAL [USD] | R5: PU [MN] | S5: TOTAL [MN] | V5: - | W5: ENE | X5: FEB | Y5: MAR | Z5: ABR | AA5: MAY | AB5: JUN | AC5: JUL | AD5: AGO | AE5: SEP | AF5: OCT | AG5: NOV | AH5: DIC | AI5: ENE
Q6: [USD] | R6: [MN] | S6: [MN] | T6: C / IVA | V6: - | W6: 31 | X6: 28 | Y6: 31 | Z6: 30 | AA6: 31 | AB6: 30 | AC6: 31 | AD6: 31 | AE6: 30 | AF6: 31 | AG6: 30 | AH6: 31 | AI6: 31
B7: NOMINA Y ADICIONALES | C7: HUMBERTO LECHUGA | D7: SUPERVISOR PROY. | F7: 1 | G7: 33000 | H7: =$T$33 -> 0.8 | I7: =G7*(1+H7) -> 59400 | K7: =G7 -> 33000 | L7: =K7/4 -> 8250 | M7: =G7/2 -> 16500 | N7: 0 | O7: =(G7/30.4)*12 -> 13026.316 | P7: =S7/$T$25 -> 3024.2763 | Q7: =P7*F7 -> 3024.2763 | R7: =I7+N7+(O7/12) -> 60485.526 | S7: =R7*F7 -> 60485.526 | T7: =S7*1.16 -> 70163.211 | V7: 0 | W7: =$Q$7 -> 3024.2763 | X7: =$Q$7 -> 3024.2763 | Y7: =$Q$7 -> 3024.2763 | Z7: =$Q$7 -> 3024.2763 | AA7: =$Q$7+(M7/$T$25) -> 3849.2763 | AB7: =$Q$7 -> 3024.2763 | AC7: =$Q$7 -> 3024.2763 | AD7: =$Q$7 -> 3024.2763 | AE7: =$Q$7 -> 3024.2763 | AF7: =$Q$7 -> 3024.2763 | AG7: =$Q$7 -> 3024.2763 | AH7: =$Q$7+((K7+L7)/$T$25) -> 5086.7763 | AI7: =$Q$7 -> 3024.2763
B8: NOMINA Y ADICIONALES | C8: ROCIO RODRIGUEZ | F8: 1 | G8: 30000 | H8: =$T$33 -> 0.8 | I8: =G8*(1+H8) -> 54000 | K8: =G8 -> 30000 | L8: =K8/4 -> 7500 | M8: =G8/2 -> 15000 | N8: 0 | O8: =(G8/30.4)*12 -> 11842.105 | P8: =S8/$T$25 -> 2749.3421 | Q8: =P8*F8 -> 2749.3421 | R8: =I8+N8+(O8/12) -> 54986.842 | S8: =R8*F8 -> 54986.842 | T8: =S8*1.16 -> 63784.737 | V8: 0 | W8: =$Q$8 -> 2749.3421 | X8: =$Q$8 -> 2749.3421 | Y8: =$Q$8 -> 2749.3421 | Z8: =$Q$8 -> 2749.3421 | AA8: =$Q$8+(M8/$T$25) -> 3499.3421 | AB8: =$Q$8 -> 2749.3421 | AC8: =$Q$8 -> 2749.3421 | AD8: =$Q$8 -> 2749.3421 | AE8: =$Q$8 -> 2749.3421 | AF8: =$Q$8 -> 2749.3421 | AG8: =$Q$8 -> 2749.3421 | AH8: =$Q$8+((K8+L8)/$T$25) -> 4624.3421 | AI8: =$Q$8 -> 2749.3421
B9: NOMINA Y ADICIONALES | F9: 1 | G9: 20898.214 | H9: =$T$33 -> 0.8 | I9: =G9*(1+H9) -> 37616.786 | K9: =G9 -> 20898.214 | L9: =K9/4 -> 5224.5536 | M9: =G9/2 -> 10449.107 | N9: 0 | O9: =(G9/30.4)*12 -> 8249.2951 | P9: =S9/$T$25 -> 1915.2113 | Q9: =P9*F9 -> 1915.2113 | R9: =I9+N9+(O9/12) -> 38304.227 | S9: =R9*F9 -> 38304.227 | T9: =S9*1.16 -> 44432.903 | V9: 0 | W9: =$Q$9 -> 1915.2113 | X9: =$Q$9 -> 1915.2113 | Y9: =$Q$9 -> 1915.2113 | Z9: =$Q$9 -> 1915.2113 | AA9: =$Q$9+(M9/$T$25) -> 2437.6667 | AB9: =$Q$9 -> 1915.2113 | AC9: =$Q$9 -> 1915.2113 | AD9: =$Q$9 -> 1915.2113 | AE9: =$Q$9 -> 1915.2113 | AF9: =$Q$9 -> 1915.2113 | AG9: =$Q$9 -> 1915.2113 | AH9: =$Q$9+((K9+L9)/$T$25) -> 3221.3497 | AI9: =$Q$9 -> 1915.2113
B10: NOMINA Y ADICIONALES | F10: 1 | G10: 20898.214 | H10: =$T$33 -> 0.8 | I10: =G10*(1+H10) -> 37616.786 | K10: =G10 -> 20898.214 | L10: =K10/4 -> 5224.5536 | M10: =G10/2 -> 10449.107 | N10: 0 | O10: =(G10/30.4)*12 -> 8249.2951 | P10: =S10/$T$25 -> 1915.2113 | Q10: =P10*F10 -> 1915.2113 | R10: =I10+N10+(O10/12) -> 38304.227 | S10: =R10*F10 -> 38304.227 | T10: =S10*1.16 -> 44432.903 | V10: 0 | W10: =$Q$10 -> 1915.2113 | X10: =$Q$10 -> 1915.2113 | Y10: =$Q$10 -> 1915.2113 | Z10: =$Q$10 -> 1915.2113 | AA10: =$Q$10+(M10/$T$25) -> 2437.6667 | AB10: =$Q$10 -> 1915.2113 | AC10: =$Q$10 -> 1915.2113 | AD10: =$Q$10 -> 1915.2113 | AE10: =$Q$10 -> 1915.2113 | AF10: =$Q$10 -> 1915.2113 | AG10: =$Q$10 -> 1915.2113 | AH10: =$Q$10+((K10+L10)/$T$25) -> 3221.3497 | AI10: =$Q$10 -> 1915.2113
B11: NOMINA Y ADICIONALES | F11: 1 | G11: 16676.79 | H11: =$T$33 -> 0.8 | I11: =G11*(1+H11) -> 30018.222 | K11: =G11 -> 16676.79 | L11: =K11/4 -> 4169.1975 | M11: =G11/2 -> 8338.395 | N11: 0 | O11: =(G11/30.4)*12 -> 6582.9434 | P11: =S11/$T$25 -> 1528.34 | Q11: =P11*F11 -> 1528.34 | R11: =I11+N11+(O11/12) -> 30566.801 | S11: =R11*F11 -> 30566.801 | T11: =S11*1.16 -> 35457.489 | V11: 0 | W11: =$Q$11 -> 1528.34 | X11: =$Q$11 -> 1528.34 | Y11: =$Q$11 -> 1528.34 | Z11: =$Q$11 -> 1528.34 | AA11: =$Q$11+(M11/$T$25) -> 1945.2598 | AB11: =$Q$11 -> 1528.34 | AC11: =$Q$11 -> 1528.34 | AD11: =$Q$11 -> 1528.34 | AE11: =$Q$11 -> 1528.34 | AF11: =$Q$11 -> 1528.34 | AG11: =$Q$11 -> 1528.34 | AH11: =$Q$11+((K11+L11)/$T$25) -> 2570.6394 | AI11: =$Q$11 -> 1528.34
B12: NOMINA Y ADICIONALES | F12: 1 | G12: 16676.79 | H12: =$T$33 -> 0.8 | I12: =G12*(1+H12) -> 30018.222 | K12: =G12 -> 16676.79 | L12: =K12/4 -> 4169.1975 | M12: =G12/2 -> 8338.395 | N12: 0 | O12: =(G12/30.4)*12 -> 6582.9434 | P12: =S12/$T$25 -> 1528.34 | Q12: =P12*F12 -> 1528.34 | R12: =I12+N12+(O12/12) -> 30566.801 | S12: =R12*F12 -> 30566.801 | T12: =S12*1.16 -> 35457.489 | V12: 0 | W12: =$Q$12 -> 1528.34 | X12: =$Q$12 -> 1528.34 | Y12: =$Q$12 -> 1528.34 | Z12: =$Q$12 -> 1528.34 | AA12: =$Q$12+(M12/$T$25) -> 1945.2598 | AB12: =$Q$12 -> 1528.34 | AC12: =$Q$12 -> 1528.34 | AD12: =$Q$12 -> 1528.34 | AE12: =$Q$12 -> 1528.34 | AF12: =$Q$12 -> 1528.34 | AG12: =$Q$12 -> 1528.34 | AH12: =$Q$12+((K12+L12)/$T$25) -> 2570.6394 | AI12: =$Q$12 -> 1528.34
B13: NOMINA Y ADICIONALES | F13: 1 | G13: 16676.79 | H13: =$T$33 -> 0.8 | I13: =G13*(1+H13) -> 30018.222 | K13: =G13 -> 16676.79 | L13: =K13/4 -> 4169.1975 | M13: =G13/2 -> 8338.395 | N13: 0 | O13: =(G13/30.4)*12 -> 6582.9434 | P13: =S13/$T$25 -> 1528.34 | Q13: =P13*F13 -> 1528.34 | R13: =I13+N13+(O13/12) -> 30566.801 | S13: =R13*F13 -> 30566.801 | T13: =S13*1.16 -> 35457.489 | V13: 0 | W13: =$Q$13 -> 1528.34 | X13: =$Q$13 -> 1528.34 | Y13: =$Q$13 -> 1528.34 | Z13: =$Q$13 -> 1528.34 | AA13: =$Q$13+(M13/$T$25) -> 1945.2598 | AB13: =$Q$13 -> 1528.34 | AC13: =$Q$13 -> 1528.34 | AD13: =$Q$13 -> 1528.34 | AE13: =$Q$13 -> 1528.34 | AF13: =$Q$13 -> 1528.34 | AG13: =$Q$13 -> 1528.34 | AH13: =$Q$13+((K13+L13)/$T$25) -> 2570.6394 | AI13: =$Q$13 -> 1528.34
B14: NOMINA Y ADICIONALES | F14: 1 | G14: 20898.214 | H14: =$T$33 -> 0.8 | I14: =G14*(1+H14) -> 37616.786 | K14: =G14 -> 20898.214 | L14: =K14/4 -> 5224.5536 | M14: =G14/2 -> 10449.107 | N14: 0 | O14: =(G14/30.4)*12 -> 8249.2951 | P14: =S14/$T$25 -> 1915.2113 | Q14: =P14*F14 -> 1915.2113 | R14: =I14+N14+(O14/12) -> 38304.227 | S14: =R14*F14 -> 38304.227 | T14: =S14*1.16 -> 44432.903 | V14: 0 | W14: =$Q$14 -> 1915.2113 | X14: =$Q$14 -> 1915.2113 | Y14: =$Q$14 -> 1915.2113 | Z14: =$Q$14 -> 1915.2113 | AA14: =$Q$14+(M14/$T$25) -> 2437.6667 | AB14: =$Q$14 -> 1915.2113 | AC14: =$Q$14 -> 1915.2113 | AD14: =$Q$14 -> 1915.2113 | AE14: =$Q$14 -> 1915.2113 | AF14: =$Q$14 -> 1915.2113 | AG14: =$Q$14 -> 1915.2113 | AH14: =$Q$14+((K14+L14)/$T$25) -> 3221.3497 | AI14: =$Q$14 -> 1915.2113
B15: NOMINA Y ADICIONALES | F15: 0 | G15: 20898.21 | H15: =$T$33 -> 0.8 | I15: =G15*(1+H15) -> 37616.778 | K15: =G15 -> 20898.21 | L15: =K15/4 -> 5224.5525 | M15: =G15/2 -> 10449.105 | N15: 0 | O15: =(G15/30.4)*12 -> 8249.2934 | P15: =S15/$T$25 -> 0 | Q15: =P15*F15 -> 0 | R15: =I15+N15+(O15/12) -> 38304.219 | S15: =R15*F15 -> 0 | T15: =S15*1.16 -> 0 | V15: 0 | W15: =$Q$15 -> 0 | X15: =$Q$15 -> 0 | Y15: =$Q$15 -> 0 | Z15: =$Q$15 -> 0 | AA15: =$Q$15+(M15/$T$25) -> 522.45525 | AB15: =$Q$15 -> 0 | AC15: =$Q$15 -> 0 | AD15: =$Q$15 -> 0 | AE15: =$Q$15 -> 0 | AF15: =$Q$15 -> 0 | AG15: =$Q$15 -> 0 | AH15: =$Q$15+((K15+L15)/$T$25) -> 1306.1381 | AI15: =$Q$15 -> 0
B16: NOMINA Y ADICIONALES | F16: 0 | G16: 16676.79 | H16: =$T$33 -> 0.8 | I16: =G16*(1+H16) -> 30018.222 | K16: =G16 -> 16676.79 | L16: =K16/4 -> 4169.1975 | M16: =G16/2 -> 8338.395 | N16: 0 | O16: =(G16/30.4)*12 -> 6582.9434 | P16: =S16/$T$25 -> 0 | Q16: =P16*F16 -> 0 | R16: =I16+N16+(O16/12) -> 30566.801 | S16: =R16*F16 -> 0 | T16: =S16*1.16 -> 0 | V16: 0 | W16: =$Q$16 -> 0 | X16: =$Q$16 -> 0 | Y16: =$Q$16 -> 0 | Z16: =$Q$16 -> 0 | AA16: =$Q$16+(M16/$T$25) -> 416.91975 | AB16: =$Q$16 -> 0 | AC16: =$Q$16 -> 0 | AD16: =$Q$16 -> 0 | AE16: =$Q$16 -> 0 | AF16: =$Q$16 -> 0 | AG16: =$Q$16 -> 0 | AH16: =$Q$16+((K16+L16)/$T$25) -> 1042.2994 | AI16: =$Q$16 -> 0
B17: NOMINA Y ADICIONALES | F17: 0 | G17: 0 | H17: =$T$33 -> 0.8 | I17: =G17*(1+H17) -> 0 | K17: =G17 -> 0 | L17: =K17/4 -> 0 | M17: =G17/2 -> 0 | N17: 0 | O17: =(G17/30.4)*12 -> 0 | P17: =S17/$T$25 -> 0 | Q17: =P17*F17 -> 0 | R17: =I17+N17+(O17/12) -> 0 | S17: =R17*F17 -> 0 | T17: =S17*1.16 -> 0 | V17: 0 | W17: =$Q$17 -> 0 | X17: =$Q$17 -> 0 | Y17: =$Q$17 -> 0 | Z17: =$Q$17 -> 0 | AA17: =$Q$17+(M17/$T$25) -> 0 | AB17: =$Q$17 -> 0 | AC17: =$Q$17 -> 0 | AD17: =$Q$17 -> 0 | AE17: =$Q$17 -> 0 | AF17: =$Q$17 -> 0 | AG17: =$Q$17 -> 0 | AH17: =$Q$17+((K17+L17)/$T$25) -> 0 | AI17: =$Q$17 -> 0
B19: PERSONAL OPERATIVO (TERRESTRE) | S19: TOTAL MENSUAL [USD] | V19: =SUM(V13:V17) -> 0 | W19: =SUM(W7:W17) -> 16104.273 | X19: =SUM(X7:X17) -> 16104.273 | Y19: =SUM(Y7:Y17) -> 16104.273 | Z19: =SUM(Z7:Z17) -> 16104.273 | AA19: =SUM(AA7:AA17) -> 21436.773 | AB19: =SUM(AB7:AB17) -> 16104.273 | AC19: =SUM(AC7:AC17) -> 16104.273 | AD19: =SUM(AD7:AD17) -> 16104.273 | ... AI19: =SUM(AI7:AI17) -> 16104.273
B20: Categoría | C20: Base | D20: Bono de campo | F20: Salario integrado | S20: TOTAL MENSUAL [MN] | V20: =V19*$T$25 -> 0 | W20: =W19*$T$25 -> 322085.45 | X20: =X19*$T$25 -> 322085.45 | Y20: =Y19*$T$25 -> 322085.45 | Z20: =Z19*$T$25 -> 322085.45 | AA20: =AA19*$T$25 -> 428735.46 | AB20: =AB19*$T$25 -> 322085.45 | AC20: =AC19*$T$25 -> 322085.45 | ... AI20: =AI19*$T$25 -> 322085.45
D21: dia | E21: Mes | S21: TOTAL [USD] | V21: =SUM(V19:AI19) -> 228019.29
B22: Operador Terrestre A | C22: 17000 | D22: 325 | E22: =D22*20.5 -> 6662.5 | F22: =((C22/28)*30.4)+E22 -> 25119.643 | S22: TOTAL [MN] | V22: =SUM(V20:AI20) -> 4560385.9
B23: Operador Terrestre B | C23: 15000 | D23: 225 | E23: =D23*20.5 -> 4612.5 | F23: =((C23/28)*30.4)+E23 -> 20898.214
B24: Operador Terrestre C | C24: 13000 | D24: 125 | E24: =D24*20.5 -> 2562.5 | F24: =((C24/28)*30.4)+E24 -> 16676.786 | S24: ='F00 INVERSIÓN'!I45 -> PREMISAS
B25: Operador Terrestre D | C25: 11200 | D25: 125 | E25: =D25*20.5 -> 2562.5 | F25: =((C25/28)*30.4)+E25 -> 14722.5 | S25: ='F00 INVERSIÓN'!I46 -> PARIDAD | T25: ='F00 INVERSIÓN'!J46 -> 20
E26: =D26*20.5 -> 0 | F26: =((C26/28)*30.4)+E26 -> 0 | S26: ='F00 INVERSIÓN'!I47 -> MES | T26: ='F00 INVERSIÓN'!J47 -> 30.4
B27: Técnico Especialista A | C27: 21000 | D27: 500 | E27: =D27*21.7 -> 10850 | F27: =((C27/28)*30.4)+E27 -> 33650 | S27: ='F00 INVERSIÓN'!I48 -> CRÉDITO | T27: ='F00 INVERSIÓN'!J48 -> 45
B28: Técnico Especialista B | C28: 20000 | D28: 450 | E28: =D28*21.7 -> 9765 | F28: =((C28/28)*30.4)+E28 -> 31479.286 | S28: ='F00 INVERSIÓN'!I49 -> GAS LP | T28: ='F00 INVERSIÓN'!J49 -> 10.5
B29: Técnico Especialista C | C29: 19000 | D29: 400 | E29: =D29*21.7 -> 8680 | F29: =((C29/28)*30.4)+E29 -> 29308.571 | S29: ='F00 INVERSIÓN'!I50 -> GASOLINA | T29: ='F00 INVERSIÓN'!J50 -> 22
S30: ='F00 INVERSIÓN'!I51 -> DIESEL | T30: ='F00 INVERSIÓN'!J51 -> 23
S31: https://www.google.com/search?client=firefox-b-d&q=precio+del+dolar+hoy
S33: Nómina | T33: 0.8
S34: Aguinaldo
S35: Utilidades

Sheet F01 EPP
B2: EPP
B4: RESUMEN | C4: NOMBRE | D4: PUESTO | E4: UNIDAD | F4: CANTIDAD | G4: PU [USD] | H4: TOTAL [USD] | I4: PU [MN] | J4: TOTAL [MN] | K4: TOTAL [MN] | M4: Instalación | N4: M1 | O4: M2 | P4: M3 | Q4: M4 | R4: M5 | S4: M6 | T4: M7 | U4: M8 | V4: M9 | W4: M10 | X4: M11 | Y4: M12 | Z4: M13
H5: TOTAL [USD] | I5: PU [MN] | J5: TOTAL [MN] | M5: - | N5: ENE | O5: FEB | P5: MAR | Q5: ABR | R5: MAY | S5: JUN | T5: JUL | U5: AGO | V5: SEP | W5: OCT | X5: NOV | Y5: DIC | Z5: ENE
H6: [USD] | I6: [MN] | J6: [MN] | K6: C / IVA | M6: - | N6: 31 | O6: 28 | P6: 31 | Q6: 30 | R6: 31 | S6: 30 | T6: 31 | U6: 31 | V6: 30 | W6: 31 | X6: 30 | Y6: 31 | Z6: 31
B7: ROPA Y ARTICULOS DE PROTECCION | F7: 1 | G7: =J7/$K$25 -> 30 | H7: =F7*G7 -> 30 | I7: 600 | J7: =I7*F7 -> 600 | K7: =J7*1.16 -> 696 | M7: 0 | N7: =$H$7 -> 30 | O7: =$H$7 -> 30 | P7: =$H$7 -> 30 | Q7: =$H$7 -> 30 | R7: =$H$7 -> 30 | S7: =$H$7 -> 30 | T7: =$H$7 -> 30 | U7: =$H$7 -> 30 | ... Z7: =$H$7 -> 30
B8: ROPA Y ARTICULOS DE PROTECCION | F8: 1 | G8: =J8/$K$25 -> 30 | H8: =F8*G8 -> 30 | I8: 600 | J8: =I8*F8 -> 600 | K8: =J8*1.16 -> 696 | M8: 0 | N8: =$H$8 -> 30 | O8: =$H$8 -> 30 | P8: =$H$8 -> 30 | Q8: =$H$8 -> 30 | R8: =$H$8 -> 30 | S8: =$H$8 -> 30 | T8: =$H$8 -> 30 | U8: =$H$8 -> 30 | ... Z8: =$H$8 -> 30
B9: ROPA Y ARTICULOS DE PROTECCION | F9: 1 | G9: =J9/$K$25 -> 45 | H9: =F9*G9 -> 45 | I9: 900 | J9: =I9*F9 -> 900 | K9: =J9*1.16 -> 1044 | M9: 0 | N9: =$H$9 -> 45 | O9: =$H$9 -> 45 | P9: =$H$9 -> 45 | Q9: =$H$9 -> 45 | R9: =$H$9 -> 45 | S9: =$H$9 -> 45 | T9: =$H$9 -> 45 | U9: =$H$9 -> 45 | ... Z9: =$H$9 -> 45
B10: ROPA Y ARTICULOS DE PROTECCION | F10: 1 | G10: =J10/$K$25 -> 45 | H10: =F10*G10 -> 45 | I10: 900 | J10: =I10*F10 -> 900 | K10: =J10*1.16 -> 1044 | M10: 0 | N10: =$H$10 -> 45 | O10: =$H$10 -> 45 | P10: =$H$10 -> 45 | Q10: =$H$10 -> 45 | R10: =$H$10 -> 45 | S10: =$H$10 -> 45 | T10: =$H$10 -> 45 | U10: =$H$10 -> 45 | ... Z10: =$H$10 -> 45
B11: ROPA Y ARTICULOS DE PROTECCION | F11: 1 | G11: =J11/$K$25 -> 45 | H11: =F11*G11 -> 45 | I11: 900 | J11: =I11*F11 -> 900 | K11: =J11*1.16 -> 1044 | M11: 0 | N11: =$H$11 -> 45 | O11: =$H$11 -> 45 | P11: =$H$11 -> 45 | Q11: =$H$11 -> 45 | R11: =$H$11 -> 45 | S11: =$H$11 -> 45 | T11: =$H$11 -> 45 | U11: =$H$11 -> 45 | ... Z11: =$H$11 -> 45
B12: ROPA Y ARTICULOS DE PROTECCION | F12: 1 | G12: =J12/$K$25 -> 45 | H12: =F12*G12 -> 45 | I12: 900 | J12: =I12*F12 -> 900 | K12: =J12*1.16 -> 1044 | M12: 0 | N12: =$H$12 -> 45 | O12: =$H$12 -> 45 | P12: =$H$12 -> 45 | Q12: =$H$12 -> 45 | R12: =$H$12 -> 45 | S12: =$H$12 -> 45 | T12: =$H$12 -> 45 | U12: =$H$12 -> 45 | ... Z12: =$H$12 -> 45
B13: ROPA Y ARTICULOS DE PROTECCION | F13: 1 | G13: =J13/$K$25 -> 45 | H13: =F13*G13 -> 45 | I13: 900 | J13: =I13*F13 -> 900 | K13: =J13*1.16 -> 1044 | M13: 0 | N13: =$H$13 -> 45 | O13: =$H$13 -> 45 | P13: =$H$13 -> 45 | Q13: =$H$13 -> 45 | R13: =$H$13 -> 45 | S13: =$H$13 -> 45 | T13: =$H$13 -> 45 | U13: =$H$13 -> 45 | ... Z13: =$H$13 -> 45
B14: ROPA Y ARTICULOS DE PROTECCION | F14: 1 | G14: =J14/$K$25 -> 45 | H14: =F14*G14 -> 45 | I14: 900 | J14: =I14*F14 -> 900 | K14: =J14*1.16 -> 1044 | M14: 0 | N14: =$H$14 -> 45 | O14: =$H$14 -> 45 | P14: =$H$14 -> 45 | Q14: =$H$14 -> 45 | R14: =$H$14 -> 45 | S14: =$H$14 -> 45 | T14: =$H$14 -> 45 | U14: =$H$14 -> 45 | ... Z14: =$H$14 -> 45
B15: ROPA Y ARTICULOS DE PROTECCION | F15: 1 | G15: =J15/$K$25 -> 45 | H15: =F15*G15 -> 45 | I15: 900 | J15: =I15*F15 -> 900 | K15: =J15*1.16 -> 1044 | M15: 0 | N15: =$H$15 -> 45 | O15: =$H$15 -> 45 | P15: =$H$15 -> 45 | Q15: =$H$15 -> 45 | R15: =$H$15 -> 45 | S15: =$H$15 -> 45 | T15: =$H$15 -> 45 | U15: =$H$15 -> 45 | ... Z15: =$H$15 -> 45
B16: ROPA Y ARTICULOS DE PROTECCION | F16: 1 | G16: =J16/$K$25 -> 30 | H16: =F16*G16 -> 30 | I16: 600 | J16: =I16*F16 -> 600 | K16: =J16*1.16 -> 696 | M16: 0 | N16: =$H$16 -> 30 | O16: =$H$16 -> 30 | P16: =$H$16 -> 30 | Q16: =$H$16 -> 30 | R16: =$H$16 -> 30 | S16: =$H$16 -> 30 | T16: =$H$16 -> 30 | U16: =$H$16 -> 30 | ... Z16: =$H$16 -> 30
B17: ROPA Y ARTICULOS DE PROTECCION | F17: 0 | G17: =J17/$K$25 -> 0 | H17: =F17*G17 -> 0 | I17: 850 | J17: =I17*F17 -> 0 | K17: =J17*1.16 -> 0 | M17: 0 | N17: =$H$17 -> 0 | O17: =$H$17 -> 0 | P17: =$H$17 -> 0 | Q17: =$H$17 -> 0 | R17: =$H$17 -> 0 | S17: =$H$17 -> 0 | T17: =$H$17 -> 0 | U17: =$H$17 -> 0 | ... Z17: =$H$17 -> 0
J19: TOTAL MENSUAL [USD] | M19: =SUM(M7:M17) -> 0 | N19: =SUM(N7:N17) -> 405 | O19: =SUM(O7:O17) -> 405 | P19: =SUM(P7:P17) -> 405 | Q19: =SUM(Q7:Q17) -> 405 | R19: =SUM(R7:R17) -> 405 | S19: =SUM(S7:S17) -> 405 | T19: =SUM(T7:T17) -> 405 | ... Z19: =SUM(Z7:Z17) -> 405
J20: TOTAL MENSUAL [MN] | M20: =M19*$K$25 -> 0 | N20: =N19*$K$25 -> 8100 | O20: =O19*$K$25 -> 8100 | P20: =P19*$K$25 -> 8100 | Q20: =Q19*$K$25 -> 8100 | R20: =R19*$K$25 -> 8100 | S20: =S19*$K$25 -> 8100 | T20: =T19*$K$25 -> 8100 | ... Z20: =Z19*$K$25 -> 8100
J21: TOTAL [USD] | M21: =SUM(M19:Z19) -> 5265
J22: TOTAL [MN] | M22: =SUM(M20:Z20) -> 105300
J24: =NOMINA!S24 -> PREMISAS
J25: =NOMINA!S25 -> PARIDAD | K25: =NOMINA!T25 -> 20
J26: =NOMINA!S26 -> MES | K26: =NOMINA!T26 -> 30.4
J27: =NOMINA!S27 -> CRÉDITO | K27: =NOMINA!T27 -> 45
J28: =NOMINA!S28 -> GAS LP | K28: =NOMINA!T28 -> 10.5
J29: =NOMINA!S29 -> GASOLINA | K29: =NOMINA!T29 -> 22
J30: =NOMINA!S30 -> DIESEL | K30: =NOMINA!T30 -> 23
J31: https://www.google.com/search?client=firefox-b-d&q=precio+del+dolar+hoy

Sheet F01 UNIFORMES
B2: UNIFORMES
B4: RESUMEN | C4: NOMBRE | D4: PUESTO | E4: UNIDAD | F4: CANTIDAD | G4: PU [USD] | H4: TOTAL [USD] | I4: PU [MN] | J4: TOTAL [MN] | K4: TOTAL [MN] | M4: Instalación | N4: M1 | O4: M2 | P4: M3 | Q4: M4 | R4: M5 | S4: M6 | T4: M7 | U4: M8 | V4: M9 | W4: M10 | X4: M11 | Y4: M12 | Z4: M13
H5: TOTAL [USD] | I5: PU [MN] | J5: TOTAL [MN] | M5: - | N5: ENE | O5: FEB | P5: MAR | Q5: ABR | R5: MAY | S5: JUN | T5: JUL | U5: AGO | V5: SEP | W5: OCT | X5: NOV | Y5: DIC | Z5: ENE
H6: [USD] | I6: [MN] | J6: [MN] | K6: C / IVA | M6: - | N6: 31 | O6: 28 | P6: 31 | Q6: 30 | R6: 31 | S6: 30 | T6: 31 | U6: 31 | V6: 30 | W6: 31 | X6: 30 | Y6: 31 | Z6: 31
B7: UNIFORMES | F7: 4 | G7: =J7/$K$18 -> 12 | H7: =F7*G7 -> 48 | I7: 60 | J7: =I7*F7 -> 240 | K7: =J7*1.16 -> 278.4 | M7: 0 | N7: =$H$7 -> 48 | O7: =$H$7 -> 48 | P7: =$H$7 -> 48 | Q7: =$H$7 -> 48 | R7: =$H$7 -> 48 | S7: =$H$7 -> 48 | T7: =$H$7 -> 48 | U7: =$H$7 -> 48 | ... Z7: =$H$7 -> 48
B8: UNIFORMES | F8: 4 | G8: =J8/$K$18 -> 12 | H8: =F8*G8 -> 48 | I8: 60 | J8: =I8*F8 -> 240 | K8: =J8*1.16 -> 278.4 | M8: 0 | N8: =$H$8 -> 48 | O8: =$H$8 -> 48 | P8: =$H$8 -> 48 | Q8: =$H$8 -> 48 | R8: =$H$8 -> 48 | S8: =$H$8 -> 48 | T8: =$H$8 -> 48 | U8: =$H$8 -> 48 | ... Z8: =$H$8 -> 48
B9: UNIFORMES | F9: 4 | G9: =J9/$K$18 -> 12 | H9: =F9*G9 -> 48 | I9: 60 | J9: =I9*F9 -> 240 | K9: =J9*1.16 -> 278.4 | M9: 0 | N9: =$H$9 -> 48 | O9: =$H$9 -> 48 | P9: =$H$9 -> 48 | Q9: =$H$9 -> 48 | R9: =$H$9 -> 48 | S9: =$H$9 -> 48 | T9: =$H$9 -> 48 | U9: =$H$9 -> 48 | ... Z9: =$H$9 -> 48
B10: UNIFORMES | F10: 0 | G10: 0 | H10: 0 | I10: 0 | J10: =I10*F10 -> 0 | K10: =J10*1.16 -> 0 | M10: 0 | N10: =$H$10 -> 0 | O10: =$H$10 -> 0 | P10: =$H$10 -> 0 | Q10: =$H$10 -> 0 | R10: =$H$10 -> 0 | S10: =$H$10 -> 0 | T10: =$H$10 -> 0 | U10: =$H$10 -> 0 | ... Z10: =$H$10 -> 0
J12: TOTAL MENSUAL [USD] | M12: =SUM(M7:M10) -> 0 | N12: =SUM(N7:N10) -> 144 | O12: =SUM(O7:O10) -> 144 | P12: =SUM(P7:P10) -> 144 | Q12: =SUM(Q7:Q10) -> 144 | R12: =SUM(R7:R10) -> 144 | S12: =SUM(S7:S10) -> 144 | T12: =SUM(T7:T10) -> 144 | ... Z12: =SUM(Z7:Z10) -> 144
J13: TOTAL MENSUAL [MN] | M13: =M12*$T$18 -> 0 | N13: =N12*$K$18 -> 2880 | O13: =O12*$K$18 -> 2880 | P13: =P12*$K$18 -> 2880 | Q13: =Q12*$K$18 -> 2880 | R13: =R12*$K$18 -> 2880 | S13: =S12*$K$18 -> 2880 | T13: =T12*$K$18 -> 2880 | U13: =U12*$K$18 -> 2880 | ... Z13: =Z12*$K$18 -> 2880
J14: TOTAL [USD] | M14: =SUM(M12:Z12) -> 1872
J15: TOTAL [MN] | M15: =SUM(M13:Z13) -> 37440
J17: =NOMINA!S24 -> PREMISAS
J18: =NOMINA!S25 -> PARIDAD | K18: =NOMINA!T25 -> 20
J19: =NOMINA!S26 -> MES | K19: =NOMINA!T26 -> 30.4
J20: =NOMINA!S27 -> CRÉDITO | K20: =NOMINA!T27 -> 45
J21: =NOMINA!S28 -> GAS LP | K21: =NOMINA!T28 -> 10.5
J22: =NOMINA!S29 -> GASOLINA | K22: =NOMINA!T29 -> 22
J23: =NOMINA!S30 -> DIESEL | K23: =NOMINA!T30 -> 23
J24: https://www.google.com/search?client=firefox-b-d&q=precio+del+dolar+hoy

Sheet F02 INMUEBLES Y S
B2: INMUEBLES Y SERVICIOS
B4: RESUMEN | C4: NOMBRE | D4: UNIDAD | E4: CANTIDAD | F4: PU [USD] | G4: TOTAL [USD] | H4: PU [MN] | I4: TOTAL [MN] | J4: TOTAL [MN] | K4: GASTO POR TRABAJADOR C/IVA | M4: Instalación | N4: M1 | O4: M2 | P4: M3 | Q4: M4 | R4: M5 | S4: M6 | T4: M7 | U4: M8 | V4: M9 | W4: M10 | X4: M11 | Y4: M12 | Z4: M13
G5: TOTAL [USD] | H5: PU [MN] | I5: TOTAL [MN] | M5: - | N5: ENE | O5: FEB | P5: MAR | Q5: ABR | R5: MAY | S5: JUN | T5: JUL | U5: AGO | V5: SEP | W5: OCT | X5: NOV | Y5: DIC | Z5: ENE
G6: [USD] | H6: [MN] | I6: [MN] | J6: C / IVA | M6: - | N6: 31 | O6: 28 | P6: 31 | Q6: 30 | R6: 31 | S6: 30 | T6: 31 | U6: 31 | V6: 30 | W6: 31 | X6: 30 | Y6: 31 | Z6: 31
B7: ARRENDAMIENTO DE INMUEBLES | C7: Casa staff cardenas | E7: 0 | F7: =I7/$K$25 -> 0 | G7: =E7*F7 -> 0 | H7: 16000 | I7: =H7*E7 -> 0 | J7: =I7*1.16 -> 0 | K7: =J7/10 -> 0 | M7: 0 | N7: =$G$7 -> 0 | O7: =$G$7 -> 0 | P7: =$G$7 -> 0 | Q7: =$G$7 -> 0 | R7: =$G$7 -> 0 | S7: =$G$7 -> 0 | T7: =$G$7 -> 0 | U7: =$G$7 -> 0 | ... Z7: =$G$7 -> 0
B8: ENERGIA ELECTRICA | C8: Casa staff cardenas | E8: 0 | F8: =I8/$K$25 -> 0 | G8: =E8*F8 -> 0 | H8: 6500 | I8: =H8*E8 -> 0 | J8: =I8*1.16 -> 0 | K8: =J8/10 -> 0 | M8: 0 | N8: =$G$8 -> 0 | O8: =$G$8 -> 0 | P8: =$G$8 -> 0 | Q8: =$G$8 -> 0 | R8: =$G$8 -> 0 | S8: =$G$8 -> 0 | T8: =$G$8 -> 0 | U8: =$G$8 -> 0 | ... Z8: =$G$8 -> 0
B9: RENTA DE CASAS NO DEDUCIBLE | E9: 0 | F9: =I9/$K$25 -> 0 | G9: =E9*F9 -> 0 | H9: 0 | I9: =H9*E9 -> 0 | J9: =I9*1.16 -> 0 | K9: =J9/10 -> 0 | M9: 0 | N9: =$G$9 -> 0 | O9: =$G$9 -> 0 | P9: =$G$9 -> 0 | Q9: =$G$9 -> 0 | R9: =$G$9 -> 0 | S9: =$G$9 -> 0 | T9: =$G$9 -> 0 | U9: =$G$9 -> 0 | ... Z9: =$G$9 -> 0
B10: SERVICIOS DE LIMPIEZA | E10: 0 | F10: =I10/$K$25 -> 0 | G10: =E10*F10 -> 0 | H10: 0 | I10: =H10*E10 -> 0 | J10: =I10*1.16 -> 0 | K10: =J10/10 -> 0 | M10: 0 | N10: =$G$10 -> 0 | O10: =$G$10 -> 0 | P10: =$G$10 -> 0 | Q10: =$G$10 -> 0 | R10: =$G$10 -> 0 | S10: =$G$10 -> 0 | T10: =$G$10 -> 0 | U10: =$G$10 -> 0 | ... Z10: =$G$10 -> 0
B11: SERVICIOS DE VIGILANCIA | E11: 0 | F11: =I11/$K$25 -> 0 | G11: =E11*F11 -> 0 | H11: 0 | I11: =H11*E11 -> 0 | J11: =I11*1.16 -> 0 | K11: =J11/10 -> 0 | M11: 0 | N11: =$G$11 -> 0 | O11: =$G$11 -> 0 | P11: =$G$11 -> 0 | Q11: =$G$11 -> 0 | R11: =$G$11 -> 0 | S11: =$G$11 -> 0 | T11: =$G$11 -> 0 | U11: =$G$11 -> 0 | ... Z11: =$G$11 -> 0
B12: SERVICIOS DE FUMIGACION | E12: 0 | F12: =I12/$K$25 -> 0 | G12: =E12*F12 -> 0 | H12: 0 | I12: =H12*E12 -> 0 | J12: =I12*1.16 -> 0 | K12: =J12/10 -> 0 | M12: 0 | N12: =$G$12 -> 0 | O12: =$G$12 -> 0 | P12: =$G$12 -> 0 | Q12: =$G$12 -> 0 | R12: =$G$12 -> 0 | S12: =$G$12 -> 0 | T12: =$G$12 -> 0 | U12: =$G$12 -> 0 | ... Z12: =$G$12 -> 0
B13: TELEFONIA FIJA | C13: Internet casa staff | E13: 0 | F13: =I13/$K$25 -> 0 | G13: =E13*F13 -> 0 | H13: 650 | I13: =H13*E13 -> 0 | J13: =I13*1.16 -> 0 | K13: =J13/10 -> 0 | M13: 0 | N13: =$G$13 -> 0 | O13: =$G$13 -> 0 | P13: =$G$13 -> 0 | Q13: =$G$13 -> 0 | R13: =$G$13 -> 0 | S13: =$G$13 -> 0 | T13: =$G$13 -> 0 | U13: =$G$13 -> 0 | ... Z13: =$G$13 -> 0
B14: AGUA Y ALCANTARILLADO | C14: Succion de fosas | E14: 1 | F14: =I14/$K$25 -> 870 | G14: =E14*F14 -> 870 | H14: 17400 | I14: =H14*E14 -> 17400 | J14: =I14*1.16 -> 20184 | K14: =J14/10 -> 2018.4 | M14: 0 | N14: =$G$14 -> 870 | O14: =$G$14 -> 870 | P14: =$G$14 -> 870 | Q14: =$G$14 -> 870 | R14: =$G$14 -> 870 | S14: =$G$14 -> 870 | T14: =$G$14 -> 870 | U14: =$G$14 -> 870 | ... Z14: =$G$14 -> 870
B15: ARRENDAMIENTO DE OF. MOVILES | C15: Camper operativo | E15: 1 | F15: =I15/$K$25 -> 1150 | G15: =E15*F15 -> 1150 | H15: 23000 | I15: =H15*E15 -> 23000 | J15: =I15*1.16 -> 26680 | K15: =J15/10 -> 2668 | M15: 0 | N15: =$G$15 -> 1150 | O15: =$G$15 -> 1150 | P15: =$G$15 -> 1150 | Q15: =$G$15 -> 1150 | R15: =$G$15 -> 1150 | S15: =$G$15 -> 1150 | T15: =$G$15 -> 1150 | U15: =$G$15 -> 1150 | ... Z15: =$G$15 -> 1150
N16: =$H$16 -> 0 | O16: =$H$16 -> 0 | P16: =$H$16 -> 0 | Q16: =$H$16 -> 0 | R16: =$H$16 -> 0 | S16: =$H$16 -> 0 | T16: =$H$16 -> 0 | U16: =$H$16 -> 0 | ... Z16: =$H$16 -> 0
N17: =$H$17 -> 0 | O17: =$H$17 -> 0 | P17: =$H$17 -> 0 | Q17: =$H$17 -> 0 | R17: =$H$17 -> 0 | S17: =$H$17 -> 0 | T17: =$H$17 -> 0 | U17: =$H$17 -> 0 | ... Z17: =$H$17 -> 0
J19: TOTAL MENSUAL [USD] | M19: =SUM(M7:M17) -> 0 | N19: =SUM(N7:N17) -> 2020 | O19: =SUM(O7:O17) -> 2020 | P19: =SUM(P7:P17) -> 2020 | Q19: =SUM(Q7:Q17) -> 2020 | R19: =SUM(R7:R17) -> 2020 | S19: =SUM(S7:S17) -> 2020 | T19: =SUM(T7:T17) -> 2020 | ... Z19: =SUM(Z7:Z17) -> 2020
J20: TOTAL MENSUAL [MN] | M20: =M19*$T$25 -> 0 | N20: =N19*$K$25 -> 40400 | O20: =O19*$K$25 -> 40400 | P20: =P19*$K$25 -> 40400 | Q20: =Q19*$K$25 -> 40400 | R20: =R19*$K$25 -> 40400 | S20: =S19*$K$25 -> 40400 | T20: =T19*$K$25 -> 40400 | U20: =U19*$K$25 -> 40400 | ... Z20: =Z19*$K$25 -> 40400
J21: TOTAL [USD] | M21: =SUM(M19:Z19) -> 26260
J22: TOTAL [MN] | M22: =SUM(M20:Z20) -> 525200
J24: PREMISAS
J25: {='F01 UNIFORMES'!J18:K18} -> PARIDAD | K25: 20
J26: {='F01 UNIFORMES'!J19:K19} -> MES | K26: 30.4
J27: {='F01 UNIFORMES'!J20:K20} -> CRÉDITO | K27: 45
J28: {='F01 UNIFORMES'!J21:K21} -> GAS LP | K28: 10.5
J29: {='F01 UNIFORMES'!J22:K22} -> GASOLINA | K29: 22
J30: {='F01 UNIFORMES'!J23:K23} -> DIESEL | K30: 23
J31: https://www.google.com/search?client=firefox-b-d&q=precio+del+dolar+hoy

Sheet F03 COM Y EQ COM
B2: COMUNICACIÓN Y EQUIPO DE COMPUTO
B4: RESUMEN | C4: NOMBRE | D4: UNIDAD | E4: CANTIDAD | F4: PU [USD] | G4: TOTAL [USD] | H4: PU [MN] | I4: TOTAL [MN] | J4: TOTAL [MN] | L4: Instalación | M4: M1 | N4: M2 | O4: M3 | P4: M4 | Q4: M5 | R4: M6 | S4: M7 | T4: M8 | U4: M9 | V4: M10 | W4: M11 | X4: M12 | Y4: M13
G5: TOTAL [USD] | H5: PU [MN] | I5: TOTAL [MN] | L5: - | M5: ENE | N5: FEB | O5: MAR | P5: ABR | Q5: MAY | R5: JUN | S5: JUL | T5: AGO | U5: SEP | V5: OCT | W5: NOV | X5: DIC | Y5: ENE
G6: [USD] | H6: [MN] | I6: [MN] | J6: C / IVA | L6: - | M6: 31 | N6: 28 | O6: 31 | P6: 30 | Q6: 31 | R6: 30 | S6: 31 | T6: 31 | U6: 30 | V6: 31 | W6: 30 | X6: 31 | Y6: 31
B7: SERV TELEFONIA CELULAR | C7: Salvador Alcazar Trinidad | E7: 0 | F7: =I7/$J$57 -> 0 | G7: =E7*F7 -> 0 | H7: 257.76 | I7: =H7*E7 -> 0 | J7: =I7*1.16 -> 0 | L7: 0 | M7: =$G$7 -> 0 | N7: =$G$7 -> 0 | O7: =$G$7 -> 0 | P7: =$G$7 -> 0 | Q7: =$G$7 -> 0 | R7: =$G$7 -> 0 | S7: =$G$7 -> 0 | T7: =$G$7 -> 0 | ... Y7: =$G$7 -> 0
B8: SERV TELEFONIA CELULAR | C8: German Vargas Ramirez | E8: 0 | F8: =I8/$J$57 -> 0 | G8: =E8*F8 -> 0 | H8: 731.9 | I8: =H8*E8 -> 0 | J8: =I8*1.16 -> 0 | L8: 0 | M8: =$G$8 -> 0 | N8: =$G$8 -> 0 | O8: =$G$8 -> 0 | P8: =$G$8 -> 0 | Q8: =$G$8 -> 0 | R8: =$G$8 -> 0 | S8: =$G$8 -> 0 | T8: =$G$8 -> 0 | ... Y8: =$G$8 -> 0
B9: SERV TELEFONIA CELULAR | C9: Jose Luis Luria Nuñez | E9: 0 | F9: =I9/$J$57 -> 0 | G9: =E9*F9 -> 0 | H9: 283.62 | I9: =H9*E9 -> 0 | J9: =I9*1.16 -> 0 | L9: 0 | M9: =$G$9 -> 0 | N9: =$G$9 -> 0 | O9: =$G$9 -> 0 | P9: =$G$9 -> 0 | Q9: =$G$9 -> 0 | R9: =$G$9 -> 0 | S9: =$G$9 -> 0 | T9: =$G$9 -> 0 | ... Y9: =$G$9 -> 0
I11: TOTAL MENSUAL [USD] | L11: =SUM(L7:L9) -> 0 | M11: =SUM(M7:M9) -> 0 | N11: =SUM(N7:N9) -> 0 | O11: =SUM(O7:O9) -> 0 | P11: =SUM(P7:P9) -> 0 | Q11: =SUM(Q7:Q9) -> 0 | R11: =SUM(R7:R9) -> 0 | S11: =SUM(S7:S9) -> 0 | ... Y11: =SUM(Y7:Y9) -> 0
I12: TOTAL MENSUAL [MN] | L12: =L11*$T$25 -> 0 | M12: =M11*$J$57 -> 0 | N12: =N11*$J$57 -> 0 | O12: =O11*$J$57 -> 0 | P12: =P11*$J$57 -> 0 | Q12: =Q11*$J$57 -> 0 | R12: =R11*$J$57 -> 0 | S12: =S11*$J$57 -> 0 | T12: =T11*$J$57 -> 0 | ... Y12: =Y11*$J$57 -> 0
I13: TOTAL [USD] | L13: =SUM(L11:Y11) -> 0
I14: TOTAL [MN] | L14: =SUM(L12:Y12) -> 0
B16: SERVICIO DE BANDA ANCHA | C16: Star Link camper operativo | E16: 1 | F16: =I16/$J$57 -> 75 | G16: =E16*F16 -> 75 | H16: 1500 | I16: =H16*E16 -> 1500 | J16: =I16*1.16 -> 1740 | L16: 0 | M16: =$G$16 -> 75 | N16: =$G$16 -> 75 | O16: =$G$16 -> 75 | P16: =$G$16 -> 75 | Q16: =$G$16 -> 75 | R16: =$G$16 -> 75 | S16: =$G$16 -> 75 | T16: =$G$16 -> 75 | ... Y16: =$G$16 -> 75
B17: SERVICIO DE BANDA ANCHA | E17: 0 | F17: =I17/$J$57 -> 0 | G17: =E17*F17 -> 0 | H17: 0 | I17: =H17*E17 -> 0 | J17: =I17*1.16 -> 0 | L17: 0 | M17: =$G$17 -> 0 | N17: =$G$17 -> 0 | O17: =$G$17 -> 0 | P17: =$G$17 -> 0 | Q17: =$G$17 -> 0 | R17: =$G$17 -> 0 | S17: =$G$17 -> 0 | T17: =$G$17 -> 0 | ... Y17: =$G$17 -> 0
B18: SERVICIO DE BANDA ANCHA | E18: 0 | F18: =I18/$J$57 -> 0 | G18: =E18*F18 -> 0 | H18: 0 | I18: =H18*E18 -> 0 | J18: =I18*1.16 -> 0 | L18: 0 | M18: =$G$18 -> 0 | N18: =$G$18 -> 0 | O18: =$G$18 -> 0 | P18: =$G$18 -> 0 | Q18: =$G$18 -> 0 | R18: =$G$18 -> 0 | S18: =$G$18 -> 0 | T18: =$G$18 -> 0 | ... Y18: =$G$18 -> 0
I20: TOTAL MENSUAL [USD] | L20: =SUM(L16:L18) -> 0 | M20: =SUM(M16:M18) -> 75 | N20: =SUM(N16:N18) -> 75 | O20: =SUM(O16:O18) -> 75 | P20: =SUM(P16:P18) -> 75 | Q20: =SUM(Q16:Q18) -> 75 | R20: =SUM(R16:R18) -> 75 | S20: =SUM(S16:S18) -> 75 | ... Y20: =SUM(Y16:Y18) -> 75
I21: TOTAL MENSUAL [MN] | L21: =L20*$T$25 -> 0 | M21: =M20*$J$57 -> 1500 | N21: =N20*$J$57 -> 1500 | O21: =O20*$J$57 -> 1500 | P21: =P20*$J$57 -> 1500 | Q21: =Q20*$J$57 -> 1500 | R21: =R20*$J$57 -> 1500 | S21: =S20*$J$57 -> 1500 | T21: =T20*$J$57 -> 1500 | ... Y21: =Y20*$J$57 -> 1500
I22: TOTAL [USD] | L22: =SUM(L20:Y20) -> 975
I23: TOTAL [MN] | L23: =SUM(L21:Y21) -> 19500
B25: SERVICIO DE RADIOCOMUNICACION | C25: Transmision de telemetría | E25: 0 | F25: =I25/$J$57 -> 0 | G25: =E25*F25 -> 0 | H25: 11600 | I25: =H25*E25 -> 0 | J25: =I25*1.16 -> 0 | L25: 0 | M25: =$G$25 -> 0 | N25: =$G$25 -> 0 | O25: =$G$25 -> 0 | P25: =$G$25 -> 0 | Q25: =$G$25 -> 0 | R25: =$G$25 -> 0 | S25: =$G$25 -> 0 | T25: =$G$25 -> 0 | ... Y25: =$G$25 -> 0
B26: SERVICIO DE RADIOCOMUNICACION | C26: Radiofrecuencia | E26: 0 | F26: =I26/$J$57 -> 0 | G26: =E26*F26 -> 0 | H26: 0 | I26: =H26*E26 -> 0 | J26: =I26*1.16 -> 0 | L26: 0 | M26: =$G$26 -> 0 | N26: =$G$26 -> 0 | O26: =$G$26 -> 0 | P26: =$G$26 -> 0 | Q26: =$G$26 -> 0 | R26: =$G$26 -> 0 | S26: =$G$26 -> 0 | T26: =$G$26 -> 0 | ... Y26: =$G$26 -> 0
B27: SERVICIO DE RADIOCOMUNICACION | E27: 0 | F27: =I27/$J$57 -> 0 | G27: =E27*F27 -> 0 | H27: 0 | I27: =H27*E27 -> 0 | J27: =I27*1.16 -> 0 | L27: 0 | M27: =$G$27 -> 0 | N27: =$G$27 -> 0 | O27: =$G$27 -> 0 | P27: =$G$27 -> 0 | Q27: =$G$27 -> 0 | R27: =$G$27 -> 0 | S27: =$G$27 -> 0 | T27: =$G$27 -> 0 | ... Y27: =$G$27 -> 0
I29: TOTAL MENSUAL [USD] | L29: =SUM(L25:L27) -> 0 | M29: =SUM(M25:M27) -> 0 | N29: =SUM(N25:N27) -> 0 | O29: =SUM(O25:O27) -> 0 | P29: =SUM(P25:P27) -> 0 | Q29: =SUM(Q25:Q27) -> 0 | R29: =SUM(R25:R27) -> 0 | S29: =SUM(S25:S27) -> 0 | ... Y29: =SUM(Y25:Y27) -> 0
I30: TOTAL MENSUAL [MN] | L30: =L29*$T$25 -> 0 | M30: =M29*$J$57 -> 0 | N30: =N29*$J$57 -> 0 | O30: =O29*$J$57 -> 0 | P30: =P29*$J$57 -> 0 | Q30: =Q29*$J$57 -> 0 | R30: =R29*$J$57 -> 0 | S30: =S29*$J$57 -> 0 | T30: =T29*$J$57 -> 0 | ... Y30: =Y29*$J$57 -> 0
I31: TOTAL [USD] | L31: =SUM(L29:Y29) -> 0
I32: TOTAL [MN] | L32: =SUM(L30:Y30) -> 0
I35: TOTAL MENSUAL [USD] | L35: =+L29+L20+L11 -> 0 | M35: =+M29+M20+M11 -> 75 | N35: =+N29+N20+N11 -> 75 | O35: =+O29+O20+O11 -> 75 | P35: =+P29+P20+P11 -> 75 | Q35: =+Q29+Q20+Q11 -> 75 | R35: =+R29+R20+R11 -> 75 | S35: =+S29+S20+S11 -> 75 | ... Y35: =+Y29+Y20+Y11 -> 75
I36: TOTAL MENSUAL [MN] | L36: =L35*$J$57 -> 0 | M36: =M35*$J$57 -> 1500 | N36: =N35*$J$57 -> 1500 | O36: =O35*$J$57 -> 1500 | P36: =P35*$J$57 -> 1500 | Q36: =Q35*$J$57 -> 1500 | R36: =R35*$J$57 -> 1500 | S36: =S35*$J$57 -> 1500 | ... Y36: =Y35*$J$57 -> 1500
I37: TOTAL [USD] | L37: =SUM(L35:Y35) -> 975
I38: TOTAL [MN] | L38: =SUM(L36:Y36) -> 19500
B42: "EQUIPO DE COMPUTO "
B44: RESUMEN | C44: NOMBRE | D44: UNIDAD | E44: CANTIDAD | F44: PU [USD] | G44: TOTAL [USD] | H44: PU [MN] | I44: TOTAL [MN] | J44: TOTAL [MN] | L44: Instalación | M44: M1 | N44: M2 | O44: M3 | P44: M4 | Q44: M5 | R44: M6 | S44: M7 | T44: M8 | U44: M9 | V44: M10 | W44: M11 | X44: M12 | Y44: M13
G45: TOTAL [USD] | H45: PU [MN] | I45: TOTAL [MN] | L45: - | M45: ENE | N45: FEB | O45: MAR | P45: ABR | Q45: MAY | R45: JUN | S45: JUL | T45: AGO | U45: SEP | V45: OCT | W45: NOV | X45: DIC | Y45: ENE
G46: [USD] | H46: [MN] | I46: [MN] | J46: C / IVA | L46: - | M46: 31 | N46: 28 | O46: 31 | P46: 30 | Q46: 31 | R46: 30 | S46: 31 | T46: 31 | U46: 30 | V46: 31 | W46: 30 | X46: 31 | Y46: 31
B47: EQUIPO DE COMPUTO (Adquisición) | E47: 0 | F47: =I47/$J$57 -> 0 | G47: =E47*F47 -> 0 | H47: 0 | I47: =H47*E47 -> 0 | J47: =I47*1.16 -> 0 | L47: 0 | M47: =$G$47 -> 0 | N47: =$G$47 -> 0 | O47: =$G$47 -> 0 | P47: =$G$47 -> 0 | Q47: =$G$47 -> 0 | R47: =$G$47 -> 0 | S47: =$G$47 -> 0 | T47: =$G$47 -> 0 | ... Y47: =$G$47 -> 0
B48: ARRENDAMIENTO DE EQ. COMPUTO | E48: 0 | F48: =I48/$J$57 -> 0 | G48: =E48*F48 -> 0 | H48: 0 | I48: =H48*E48 -> 0 | J48: =I48*1.16 -> 0 | L48: 0 | M48: =$G$48 -> 0 | N48: =$G$48 -> 0 | O48: =$G$48 -> 0 | P48: =$G$48 -> 0 | Q48: =$G$48 -> 0 | R48: =$G$48 -> 0 | S48: =$G$48 -> 0 | T48: =$G$48 -> 0 | ... Y48: =$G$48 -> 0
I50: TOTAL MENSUAL [USD] | L50: =SUM(L47:L48) -> 0 | M50: =SUM(M47:M48) -> 0 | N50: =SUM(N47:N48) -> 0 | O50: =SUM(O47:O48) -> 0 | P50: =SUM(P47:P48) -> 0 | Q50: =SUM(Q47:Q48) -> 0 | R50: =SUM(R47:R48) -> 0 | S50: =SUM(S47:S48) -> 0 | ... Y50: =SUM(Y47:Y48) -> 0
I51: TOTAL MENSUAL [MN] | L51: =L50*$J$57 -> 0 | M51: =M50*$J$57 -> 0 | N51: =N50*$J$57 -> 0 | O51: =O50*$J$57 -> 0 | P51: =P50*$J$57 -> 0 | Q51: =Q50*$J$57 -> 0 | R51: =R50*$J$57 -> 0 | S51: =S50*$J$57 -> 0 | ... Y51: =Y50*$J$57 -> 0
I52: TOTAL [USD] | L52: =SUM(L50:Y50) -> 0
I53: TOTAL [MN] | L53: =SUM(L51:Y51) -> 0
I56: {='F02 INMUEBLES Y S'!J24:K24} -> PREMISAS | J56: 0
I57: {=_xlfn.ANCHORARRAY('F02 INMUEBLES Y S'!J25)} -> PARIDAD | J57: 20
I58: {=_xlfn.ANCHORARRAY('F02 INMUEBLES Y S'!J26)} -> MES | J58: 30.4
I59: {=_xlfn.ANCHORARRAY('F02 INMUEBLES Y S'!J27)} -> CRÉDITO | J59: 45
I60: {=_xlfn.ANCHORARRAY('F02 INMUEBLES Y S'!J28)} -> GAS LP | J60: 10.5
I61: {=_xlfn.ANCHORARRAY('F02 INMUEBLES Y S'!J29)} -> GASOLINA | J61: 22
I62: {=_xlfn.ANCHORARRAY('F02 INMUEBLES Y S'!J30)} -> DIESEL | J62: 23
I63: https://www.google.com/search?client=firefox-b-d&q=precio+del+dolar+hoy

Sheet F04 VEHÍCULOS Y COMB. 
B2: VEHICULOS Y COMBUSTIBLE
B4: NOMBRE | C4: RENTA | D4: VERIFICACIÓN | E4: SINIESTROS | F4: TENENCIA | G4: MANTTO (10,000 KM) | H4: LLANTAS | I4: GPS | J4: SEGURO | L4: PU [USD] | M4: TOTAL [USD] | N4: PU [MN] | O4: TOTAL [MN] | P4: TOTAL [MN] | R4: Instalación | S4: M1 | T4: M2 | U4: M3 | V4: M4 | W4: M5 | X4: M6 | Y4: M7 | Z4: M8 | AA4: M9 | AB4: M10 | AC4: M11 | AD4: M12 | AE4: M13
M5: TOTAL [USD] | N5: PU [MN] | O5: TOTAL [MN] | R5: - | S5: ENE | T5: FEB | U5: MAR | V5: ABR | W5: MAY | X5: JUN | Y5: JUL | Z5: AGO | AA5: SEP | AB5: OCT | AC5: NOV | AD5: DIC | AE5: ENE
M6: [USD] | N6: [MN] | O6: [MN] | P6: C / IVA | R6: - | S6: 31 | T6: 28 | U6: 31 | V6: 30 | W6: 31 | X6: 30 | Y6: 31 | Z6: 31 | AA6: 30 | AB6: 31 | AC6: 30 | AD6: 31 | AE6: 31
B7: Unidad 18 | C7: 0 | D7: 0 | E7: 0 | F7: 0 | G7: 0 | H7: 0 | I7: 0 | J7: 0 | L7: =+O7/$P$36 -> 0 | M7: =L7 -> 0 | N7: =SUM(C7:J7)/12 -> 0 | O7: =+N7 -> 0 | P7: =+O7*1.16 -> 0 | R7: 0 | S7: =$M$7 -> 0 | T7: =$M$7 -> 0 | U7: =$M$7 -> 0 | V7: =$M$7 -> 0 | W7: =$M$7 -> 0 | X7: =$M$7 -> 0 | Y7: =$M$7 -> 0 | Z7: =$M$7 -> 0 | ... AE7: =$M$7 -> 0
B8: Unidad van | C8: 0 | D8: 0 | E8: 0 | F8: 0 | G8: 0 | H8: 0 | I8: 0 | J8: 0 | L8: =+O8/$P$36 -> 0 | M8: =L8 -> 0 | N8: =SUM(C8:J8)/12 -> 0 | O8: =+N8 -> 0 | P8: =+O8*1.16 -> 0 | R8: 0 | S8: =$M$8 -> 0 | T8: =$M$8 -> 0 | U8: =$M$8 -> 0 | V8: =$M$8 -> 0 | W8: =$M$8 -> 0 | X8: =$M$8 -> 0 | Y8: =$M$8 -> 0 | Z8: =$M$8 -> 0 | ... AE8: =$M$8 -> 0
B9: SUPERVISOR | C9: 0 | D9: 0 | E9: 0 | F9: 0 | G9: 0 | H9: 0 | I9: 0 | J9: 0 | L9: =+O9/$P$36 -> 0 | M9: =L9 -> 0 | N9: =SUM(C9:J9)/12 -> 0 | O9: =+N9 -> 0 | P9: =+O9*1.16 -> 0 | R9: 0 | S9: =$M$9 -> 0 | T9: =$M$9 -> 0 | U9: =$M$9 -> 0 | V9: =$M$9 -> 0 | W9: =$M$9 -> 0 | X9: =$M$9 -> 0 | Y9: =$M$9 -> 0 | Z9: =$M$9 -> 0 | ... AE9: =$M$9 -> 0
O11: TOTAL MENSUAL [USD] | R11: =SUM(R7:R10) -> 0 | S11: =SUM(S7:S10) -> 0 | T11: =SUM(T7:T10) -> 0 | U11: =SUM(U7:U10) -> 0 | V11: =SUM(V7:V10) -> 0 | W11: =SUM(W7:W10) -> 0 | X11: =SUM(X7:X10) -> 0 | Y11: =SUM(Y7:Y10) -> 0 | ... AE11: =SUM(AE7:AE10) -> 0
O12: TOTAL MENSUAL [MN] | R12: =R11*$P$36 -> 0 | S12: =S11*$P$36 -> 0 | T12: =T11*$P$36 -> 0 | U12: =U11*$P$36 -> 0 | V12: =V11*$P$36 -> 0 | W12: =W11*$P$36 -> 0 | X12: =X11*$P$36 -> 0 | Y12: =Y11*$P$36 -> 0 | ... AE12: =AE11*$P$36 -> 0
O13: TOTAL [USD] | R13: =SUM(R11:AE11) -> 0
O14: TOTAL [MN] | R14: =SUM(R12:AE12) -> 0
B18: TIPO DE COMBUSTIBLE | C18: PRECIO X LITRO | D18: LITROS / DIARIOS | E18: LITROS / SEMANA | F18: LITROS / MES | L18: PU [USD] | M18: TOTAL [USD] | N18: PU [MN] | O18: TOTAL [MN] | P18: TOTAL [MN]
M19: TOTAL [USD] | N19: PU [MN] | O19: TOTAL [MN]
M20: [USD] | N20: [MN] | O20: [MN] | P20: C / IVA
B21: MAGNA | C21: 22 | D21: 20 | E21: =D21*7 -> 140 | F21: =E21*4 -> 560 | L21: =+O21/$P$36 -> 616 | M21: =L21 -> 616 | N21: =+F21*C21 -> 12320 | O21: =N21 -> 12320 | P21: =O21*1.16 -> 14291.2 | R21: 0 | S21: =$M$21 -> 616 | T21: =$M$21 -> 616 | U21: =$M$21 -> 616 | V21: =$M$21 -> 616 | W21: =$M$21 -> 616 | X21: =$M$21 -> 616 | Y21: =$M$21 -> 616 | Z21: =$M$21 -> 616 | ... AE21: =$M$21 -> 616
B22: MAGNA | C22: 22 | D22: 20 | E22: =D22*7 -> 140 | F22: =E22*4 -> 560 | L22: 770 | M22: =L22 -> 770 | N22: =+F22*C22 -> 12320 | O22: =N22 -> 12320 | P22: =O22*1.16 -> 14291.2 | R22: 0 | S22: =$M$22 -> 770 | T22: =$M$22 -> 770 | U22: =$M$22 -> 770 | V22: =$M$22 -> 770 | W22: =$M$22 -> 770 | X22: =$M$22 -> 770 | Y22: =$M$22 -> 770 | Z22: =$M$22 -> 770 | ... AE22: =$M$22 -> 770
B23: MAGNA | C23: 0 | D23: 0 | E23: 0 | F23: =E23*4 -> 0 | L23: =+O23/$P$36 -> 0 | M23: =L23 -> 0 | N23: =+F23*C23 -> 0 | O23: =N23 -> 0 | P23: =O23*1.16 -> 0 | R23: 0 | S23: =$M$23 -> 0 | T23: =$M$23 -> 0 | U23: =$M$23 -> 0 | V23: =$M$23 -> 0 | W23: =$M$23 -> 0 | X23: =$M$23 -> 0 | Y23: =$M$23 -> 0 | Z23: =$M$23 -> 0 | ... AE23: =$M$23 -> 0
O25: TOTAL MENSUAL [USD] | R25: =SUM(R21:R24) -> 0 | S25: =SUM(S21:S24) -> 1386 | T25: =SUM(T21:T24) -> 1386 | U25: =SUM(U21:U24) -> 1386 | V25: =SUM(V21:V24) -> 1386 | W25: =SUM(W21:W24) -> 1386 | X25: =SUM(X21:X24) -> 1386 | Y25: =SUM(Y21:Y24) -> 1386 | ... AE25: =SUM(AE21:AE24) -> 1386
O26: TOTAL MENSUAL [MN] | R26: =R25*$P$36 -> 0 | S26: =S25*$P$36 -> 27720 | T26: =T25*$P$36 -> 27720 | U26: =U25*$P$36 -> 27720 | V26: =V25*$P$36 -> 27720 | W26: =W25*$P$36 -> 27720 | X26: =X25*$P$36 -> 27720 | Y26: =Y25*$P$36 -> 27720 | ... AE26: =AE25*$P$36 -> 27720
O27: TOTAL [USD] | R27: =SUM(R25:AE25) -> 18018
O28: TOTAL [MN] | R28: =SUM(R26:AE26) -> 360360
O30: TOTAL MENSUAL [USD] | R30: =+R25+R11 -> 0 | S30: =+S25+S11 -> 1386 | T30: =+T25+T11 -> 1386 | U30: =+U25+U11 -> 1386 | V30: =+V25+V11 -> 1386 | W30: =+W25+W11 -> 1386 | X30: =+X25+X11 -> 1386 | Y30: =+Y25+Y11 -> 1386 | ... AE30: =+AE25+AE11 -> 1386
O31: TOTAL MENSUAL [MN] | R31: =R30*$P$36 -> 0 | S31: =S30*$P$36 -> 27720 | T31: =T30*$P$36 -> 27720 | U31: =U30*$P$36 -> 27720 | V31: =V30*$P$36 -> 27720 | W31: =W30*$P$36 -> 27720 | X31: =X30*$P$36 -> 27720 | Y31: =Y30*$P$36 -> 27720 | ... AE31: =AE30*$P$36 -> 27720
O32: TOTAL [USD] | R32: =SUM(R30:AE30) -> 18018
O33: TOTAL [MN] | R33: =SUM(R31:AE31) -> 360360
O36: ='F03 COM Y EQ COM'!I57 -> PARIDAD | P36: ='F03 COM Y EQ COM'!J57 -> 20
O37: ='F03 COM Y EQ COM'!I58 -> MES | P37: ='F03 COM Y EQ COM'!J58 -> 30.4
O38: ='F03 COM Y EQ COM'!I59 -> CRÉDITO | P38: ='F03 COM Y EQ COM'!J59 -> 45
C39: - | O39: ='F03 COM Y EQ COM'!I60 -> GAS LP | P39: ='F03 COM Y EQ COM'!J60 -> 10.5
O40: ='F03 COM Y EQ COM'!I61 -> GASOLINA | P40: ='F03 COM Y EQ COM'!J61 -> 22
O41: ='F03 COM Y EQ COM'!I62 -> DIESEL | P41: ='F03 COM Y EQ COM'!J62 -> 23
O42: https://www.google.com/search?client=firefox-b-d&q=precio+del+dolar+hoy

Sheet F05 VIÁTICOS
B2: VIATICOS
B4: RESUMEN | C4: UNIDAD | D4: CANTIDAD | E4: PU [USD] | F4: TOTAL [USD] | G4: PU [MN] | H4: TOTAL [MN] | I4: TOTAL [MN] | K4: Instalación | L4: M1 | M4: M2 | N4: M3 | O4: M4 | P4: M5 | Q4: M6 | R4: M7 | S4: M8 | T4: M9 | U4: M10 | V4: M11 | W4: M12 | X4: M13
F5: TOTAL [USD] | G5: PU [MN] | H5: TOTAL [MN] | K5: - | L5: ENE | M5: FEB | N5: MAR | O5: ABR | P5: MAY | Q5: JUN | R5: JUL | S5: AGO | T5: SEP | U5: OCT | V5: NOV | W5: DIC | X5: ENE
F6: [USD] | G6: [MN] | H6: [MN] | I6: C / IVA | K6: - | L6: 31 | M6: 28 | N6: 31 | O6: 30 | P6: 31 | Q6: 30 | R6: 31 | S6: 31 | T6: 30 | U6: 31 | V6: 30 | W6: 31 | X6: 31
B7: ALIMENTACION | D7: 2 | E7: =+G7/$I$33 -> 50 | F7: =E7 -> 50 | G7: 1000 | H7: =(D7*G7) -> 2000 | I7: =H7*1.16 -> 2320 | K7: 0 | L7: =$F$7 -> 50 | M7: =$F$7 -> 50 | N7: =$F$7 -> 50 | O7: =$F$7 -> 50 | P7: =$F$7 -> 50 | Q7: =$F$7 -> 50 | R7: =$F$7 -> 50 | S7: =$F$7 -> 50 | ... X7: =$F$7 -> 50
B8: CASETAS PUENTES Y PEAJES | D8: 2 | E8: =+G8/$I$33 -> 50 | F8: =E8 -> 50 | G8: 1000 | H8: =(D8*G8) -> 2000 | I8: =H8*1.16 -> 2320 | K8: 0 | L8: =$F$8 -> 50 | M8: =$F$8 -> 50 | N8: =$F$8 -> 50 | O8: =$F$8 -> 50 | P8: =$F$8 -> 50 | Q8: =$F$8 -> 50 | R8: =$F$8 -> 50 | S8: =$F$8 -> 50 | ... X8: =$F$8 -> 50
B9: SERV DE TRANSPORTAC AEREA | D9: 2 | E9: =+G9/$I$33 -> 150 | F9: =E9 -> 150 | G9: 3000 | H9: =(D9*G9) -> 6000 | I9: =H9*1.16 -> 6960 | K9: 0 | L9: =$F$9 -> 150 | M9: =$F$9 -> 150 | N9: =$F$9 -> 150 | O9: =$F$9 -> 150 | P9: =$F$9 -> 150 | Q9: =$F$9 -> 150 | R9: =$F$9 -> 150 | S9: =$F$9 -> 150 | ... X9: =$F$9 -> 150
B10: SERV DE TRANSPORTAC TERRESTRE | D10: 2 | E10: =+G10/$I$33 -> 100 | F10: =E10 -> 100 | G10: 2000 | H10: =(D10*G10) -> 4000 | I10: =H10*1.16 -> 4640 | K10: 0 | L10: =$F$10 -> 100 | M10: =$F$10 -> 100 | N10: =$F$10 -> 100 | O10: =$F$10 -> 100 | P10: =$F$10 -> 100 | Q10: =$F$10 -> 100 | R10: =$F$10 -> 100 | S10: =$F$10 -> 100 | ... X10: =$F$10 -> 100
B11: SERVICIOS DE HOSPEDAJE | D11: 2 | E11: =+G11/$I$33 -> 100 | F11: =E11 -> 100 | G11: 2000 | H11: =(D11*G11) -> 4000 | I11: =H11*1.16 -> 4640 | K11: 0 | L11: =$F$11 -> 100 | M11: =$F$11 -> 100 | N11: =$F$11 -> 100 | O11: =$F$11 -> 100 | P11: =$F$11 -> 100 | Q11: =$F$11 -> 100 | R11: =$F$11 -> 100 | S11: =$F$11 -> 100 | ... X11: =$F$11 -> 100
H13: TOTAL MENSUAL [USD] | K13: =SUM(K7:K11) -> 0 | L13: =SUM(L7:L11) -> 450 | M13: =SUM(M7:M11) -> 450 | N13: =SUM(N7:N11) -> 450 | O13: =SUM(O7:O11) -> 450 | P13: =SUM(P7:P11) -> 450 | Q13: =SUM(Q7:Q11) -> 450 | R13: =SUM(R7:R11) -> 450 | ... X13: =SUM(X7:X11) -> 450
H14: TOTAL MENSUAL [MN] | K14: =K13*$I$33 -> 0 | L14: =L13*$I$33 -> 9000 | M14: =M13*$I$33 -> 9000 | N14: =N13*$I$33 -> 9000 | O14: =O13*$I$33 -> 9000 | P14: =P13*$I$33 -> 9000 | Q14: =Q13*$I$33 -> 9000 | R14: =R13*$I$33 -> 9000 | ... X14: =X13*$I$33 -> 9000
H15: TOTAL [USD] | K15: =SUM(K13:X13) -> 5850
H16: TOTAL [MN] | K16: =SUM(K14:X14) -> 117000
B19: CAJA CHICA | D19: 1 | E19: =+G19/$I$33 -> 0 | F19: =E19 -> 0 | G19: 0 | H19: =(D19*G19) -> 0 | I19: =H19*1.16 -> 0 | K19: 0 | L19: =$F$19 -> 0 | M19: =$F$19 -> 0 | N19: =$F$19 -> 0 | O19: =$F$19 -> 0 | P19: =$F$19 -> 0 | Q19: =$F$19 -> 0 | R19: =$F$19 -> 0 | S19: =$F$19 -> 0 | ... X19: =$F$19 -> 0
B20: REEMBOLSOS | D20: 1 | E20: =+G20/$I$33 -> 0 | F20: =E20 -> 0 | G20: 0 | H20: =(D20*G20) -> 0 | I20: =H20*1.16 -> 0 | K20: 0 | L20: =$F$20 -> 0 | M20: =$F$20 -> 0 | N20: =$F$20 -> 0 | O20: =$F$20 -> 0 | P20: =$F$20 -> 0 | Q20: =$F$20 -> 0 | R20: =$F$20 -> 0 | S20: =$F$20 -> 0 | ... X20: =$F$20 -> 0
H22: TOTAL MENSUAL [USD] | K22: =SUM(K19:K20) -> 0 | L22: =SUM(L19:L20) -> 0 | M22: =SUM(M19:M20) -> 0 | N22: =SUM(N19:N20) -> 0 | O22: =SUM(O19:O20) -> 0 | P22: =SUM(P19:P20) -> 0 | Q22: =SUM(Q19:Q20) -> 0 | R22: =SUM(R19:R20) -> 0 | ... X22: =SUM(X19:X20) -> 0
H23: TOTAL MENSUAL [MN] | K23: =K22*$I$33 -> 0 | L23: =L22*$I$33 -> 0 | M23: =M22*$I$33 -> 0 | N23: =N22*$I$33 -> 0 | O23: =O22*$I$33 -> 0 | P23: =P22*$I$33 -> 0 | Q23: =Q22*$I$33 -> 0 | R23: =R22*$I$33 -> 0 | ... X23: =X22*$I$33 -> 0
H24: TOTAL [USD] | K24: =SUM(K22:X22) -> 0
H25: TOTAL [MN] | K25: =SUM(K23:X23) -> 0
H27: TOTAL MENSUAL [USD] | K27: =+K13+K22 -> 0 | L27: =+L13+L22 -> 450 | M27: =+M13+M22 -> 450 | N27: =+N13+N22 -> 450 | O27: =+O13+O22 -> 450 | P27: =+P13+P22 -> 450 | Q27: =+Q13+Q22 -> 450 | R27: =+R13+R22 -> 450 | ... X27: =+X13+X22 -> 450
H28: TOTAL MENSUAL [MN] | K28: =K27*$I$33 -> 0 | L28: =L27*$I$33 -> 9000 | M28: =M27*$I$33 -> 9000 | N28: =N27*$I$33 -> 9000 | O28: =O27*$I$33 -> 9000 | P28: =P27*$I$33 -> 9000 | Q28: =Q27*$I$33 -> 9000 | R28: =R27*$I$33 -> 9000 | ... X28: =X27*$I$33 -> 9000
H29: TOTAL [USD] | K29: =SUM(K27:X27) -> 5850
H30: TOTAL [MN] | K30: =SUM(K28:X28) -> 117000
H33: ='F02 INMUEBLES Y S'!J25 -> PARIDAD | I33: ='F02 INMUEBLES Y S'!K25 -> 20
H34: ='F02 INMUEBLES Y S'!J26 -> MES | I34: ='F02 INMUEBLES Y S'!K26 -> 30.4
H35: ='F02 INMUEBLES Y S'!J27 -> CRÉDITO | I35: ='F02 INMUEBLES Y S'!K27 -> 45
H36: ='F02 INMUEBLES Y S'!J28 -> GAS LP | I36: ='F02 INMUEBLES Y S'!K28 -> 10.5
H37: ='F02 INMUEBLES Y S'!J29 -> GASOLINA | I37: ='F02 INMUEBLES Y S'!K29 -> 22
H38: ='F02 INMUEBLES Y S'!J30 -> DIESEL | I38: ='F02 INMUEBLES Y S'!K30 -> 23
H39: https://www.google.com/search?client=firefox-b-d&q=precio+del+dolar+hoy

Sheet F06 (MAT,SERV & EQUIPO)
B2: MATERIALES, SERVICIOS Y EQUIPO DE CONSTRUCCION
B4: RESUMEN 1 | C4: RESUMEN 2 | D4: UNIDAD | E4: CANTIDAD | F4: PU [USD] | G4: TOTAL [USD] | H4: PU [MN] | I4: TOTAL [MN] | J4: TOTAL [MN] | L4: Instalación | M4: M1 | N4: M2 | O4: M3 | P4: M4 | Q4: M5 | R4: M6 | S4: M7 | T4: M8 | U4: M9 | V4: M10 | W4: M11 | X4: M12 | Y4: M13
E5: CANTIDAD | G5: TOTAL [USD] | H5: PU [MN] | I5: TOTAL [MN] | L5: - | M5: ENE | N5: FEB | O5: MAR | P5: ABR | Q5: MAY | R5: JUN | S5: JUL | T5: AGO | U5: SEP | V5: OCT | W5: NOV | X5: DIC | Y5: ENE
G6: [USD] | H6: [MN] | I6: [MN] | J6: C / IVA | L6: - | M6: 31 | N6: 28 | O6: 31 | P6: 30 | Q6: 31 | R6: 30 | S6: 31 | T6: 31 | U6: 30 | V6: 31 | W6: 30 | X6: 31 | Y6: 31
B7: ABRASIVOS (THINER/DESENGRASANTE/W40) | C7: Desengrasante | E7: 1 | F7: =+H7/$J$49 -> 100 | G7: =F7 -> 100 | H7: 2000 | I7: =(E7*H7) -> 2000 | J7: =I7*1.16 -> 2320 | K7: =G7 -> 100 | L7: 0 | M7: =+$G$7 -> 100 | N7: =+$G$7 -> 100 | O7: =+$G$7 -> 100 | P7: =+$G$7 -> 100 | Q7: =+$G$7 -> 100 | R7: =+$G$7 -> 100 | S7: =+$G$7 -> 100 | T7: =+$G$7 -> 100 | ... Y7: =+$G$7 -> 100
B8: ACEITE LUBRICANTE P/MAQUINARIA (100+120) | C8: Camara de empuje | E8: 1 | F8: =+H8/$J$49 -> 0 | G8: =F8 -> 0 | H8: 0 | I8: =(E8*H8) -> 0 | J8: =I8*1.16 -> 0 | K8: =G8 -> 0 | L8: 0 | M8: =+$G$8 -> 0 | N8: 0 | O8: 0 | P8: 0 | Q8: 0 | R8: 0 | S8: =+$G$8 -> 0 | T8: 0 | U8: 0 | V8: 0 | W8: 0 | X8: 0 | Y8: =+$G$8 -> 0
B9: ACEITES Y LUBRICANTES | C9: Sello mecanico | E9: 1 | F9: =+H9/$J$49 -> 0 | G9: =F9 -> 0 | H9: 0 | I9: =(E9*H9) -> 0 | J9: =I9*1.16 -> 0 | K9: =G9 -> 0 | L9: 0 | M9: =+$G$9 -> 0 | N9: 0 | O9: 0 | P9: =+$G$9 -> 0 | Q9: 0 | R9: 0 | S9: =+$G$9 -> 0 | T9: 0 | U9: 0 | V9: =+$G$9 -> 0 | W9: 0 | X9: 0 | Y9: =+$G$9 -> 0
B10: AISLANTES IMPERM REFRA | E10: 1 | F10: =+H10/$J$49 -> 0 | G10: =F10 -> 0 | H10: 0 | I10: =(E10*H10) -> 0 | J10: =I10*1.16 -> 0 | K10: =G10 -> 0 | L10: 0 | M10: =+$G$10 -> 0 | N10: =+$G$10 -> 0 | O10: =+$G$10 -> 0 | P10: =+$G$10 -> 0 | Q10: =+$G$10 -> 0 | R10: =+$G$10 -> 0 | S10: =+$G$10 -> 0 | T10: =+$G$10 -> 0 | ... Y10: =+$G$10 -> 0
B11: BANDA CADEN TRANS COPL | E11: 1 | F11: =+H11/$J$49 -> 0 | G11: =F11 -> 0 | H11: 0 | I11: =(E11*H11) -> 0 | J11: =I11*1.16 -> 0 | K11: =G11 -> 0 | L11: 0 | M11: =+$G$11 -> 0 | N11: =+$G$11 -> 0 | O11: =+$G$11 -> 0 | P11: =+$G$11 -> 0 | Q11: =+$G$11 -> 0 | R11: =+$G$11 -> 0 | S11: =+$G$11 -> 0 | T11: =+$G$11 -> 0 | ... Y11: =+$G$11 -> 0
B12: CONEXIONES PARA TUBERIA | C12: Flexitalics | E12: 1 | F12: =+H12/$J$49 -> 0 | G12: =F12 -> 0 | H12: 0 | I12: =(E12*H12) -> 0 | J12: =I12*1.16 -> 0 | K12: =G12 -> 0 | L12: 0 | M12: =+$G$12 -> 0 | N12: =+$G$12 -> 0 | O12: =+$G$12 -> 0 | P12: =+$G$12 -> 0 | Q12: =+$G$12 -> 0 | R12: =+$G$12 -> 0 | S12: =+$G$12 -> 0 | T12: =+$G$12 -> 0 | ... Y12: =+$G$12 -> 0
B13: EMPAQUETAD JTAS Y SELLOS | C13: Garloc | E13: 1 | F13: =+H13/$J$49 -> 0 | G13: =F13 -> 0 | H13: 0 | I13: =(E13*H13) -> 0 | J13: =I13*1.16 -> 0 | K13: =G13 -> 0 | L13: 0 | M13: =+$G$13 -> 0 | N13: 0 | O13: =+$G$13 -> 0 | P13: 0 | Q13: =+$G$13 -> 0 | R13: 0 | S13: =+$G$13 -> 0 | T13: 0 | U13: =+$G$13 -> 0 | V13: 0 | W13: =+$G$13 -> 0 | X13: 0 | Y13: =+$G$13 -> 0
B14: ENVASES | C14: Garrafas | E14: 1 | F14: =+H14/$J$49 -> 0 | G14: =F14 -> 0 | H14: 0 | I14: =(E14*H14) -> 0 | J14: =I14*1.16 -> 0 | K14: =G14 -> 0 | L14: 0 | M14: =+$G$14 -> 0 | N14: =+$G$14 -> 0 | O14: =+$G$14 -> 0 | P14: =+$G$14 -> 0 | Q14: =+$G$14 -> 0 | R14: =+$G$14 -> 0 | S14: =+$G$14 -> 0 | T14: =+$G$14 -> 0 | ... Y14: =+$G$14 -> 0
B15: FIBRAS HILOS Y TELAS | E15: 0 | F15: =+H15/$J$49 -> 0 | G15: =F15 -> 0 | H15: 0 | I15: =(E15*H15) -> 0 | J15: =I15*1.16 -> 0 | K15: =G15 -> 0 | L15: 0 | M15: =+$G$15 -> 0 | N15: =+$G$15 -> 0 | O15: =+$G$15 -> 0 | P15: =+$G$15 -> 0 | Q15: =+$G$15 -> 0 | R15: =+$G$15 -> 0 | S15: =+$G$15 -> 0 | T15: =+$G$15 -> 0 | ... Y15: =+$G$15 -> 0
B16: GRASAS | C16: Polirex | E16: 1 | F16: =+H16/$J$49 -> 0 | G16: =F16 -> 0 | H16: 0 | I16: =(E16*H16) -> 0 | J16: =I16*1.16 -> 0 | K16: =G16 -> 0 | L16: 0 | M16: =+$G$16 -> 0 | N16: 0 | O16: 0 | P16: 0 | Q16: 0 | R16: =+$G$16 -> 0 | S16: 0 | T16: 0 | U16: 0 | V16: 0 | W16: 0 | X16: =+$G$16 -> 0 | Y16: =+$G$16 -> 0
B17: HERRAMIENTAS MANUALES | E17: 1 | F17: =+H17/$J$49 -> 0 | G17: =F17 -> 0 | H17: 0 | I17: =(E17*H17) -> 0 | J17: =I17*1.16 -> 0 | K17: =G17 -> 0 | L17: 0 | M17: =+$G$17 -> 0 | N17: =+$G$17 -> 0 | O17: =+$G$17 -> 0 | P17: =+$G$17 -> 0 | Q17: =+$G$17 -> 0 | R17: =+$G$17 -> 0 | S17: =+$G$17 -> 0 | T17: =+$G$17 -> 0 | ... Y17: =+$G$17 -> 0
B18: INSTRUM DE MEDICION Y CONTROL | C18: Termometro fluke | E18: 1 | F18: =+H18/$J$49 -> 203 | G18: =F18 -> 203 | H18: 4060 | I18: =(E18*H18) -> 4060 | J18: =I18*1.16 -> 4709.6 | K18: =G18 -> 203 | L18: 0 | M18: 0 | N18: 0 | O18: 0 | P18: 0 | Q18: 0 | R18: =+$G$18 -> 203 | S18: 0 | T18: 0 | U18: 0 | V18: 0 | W18: 0 | X18: 0 | Y18: 0
B19: LLANTAS, CAMARAS Y ACCESORIOS | C19: Reparaciones | E19: 1 | F19: =+H19/$J$49 -> 10 | G19: =F19 -> 10 | H19: 200 | I19: =(E19*H19) -> 200 | J19: =I19*1.16 -> 232 | K19: =G19 -> 10 | L19: 0 | M19: =+$G$19 -> 10 | N19: =+$G$19 -> 10 | O19: =+$G$19 -> 10 | P19: =+$G$19 -> 10 | Q19: =+$G$19 -> 10 | R19: =+$G$19 -> 10 | S19: =+$G$19 -> 10 | T19: =+$G$19 -> 10 | ... Y19: =+$G$19 -> 10
B20: MANGUERAS, CONEXIONES | E20: 1 | F20: =+H20/$J$49 -> 0 | G20: =F20 -> 0 | H20: 0 | I20: =(E20*H20) -> 0 | J20: =I20*1.16 -> 0 | K20: =G20 -> 0 | L20: 0 | M20: =+$G$20 -> 0 | N20: =+$G$20 -> 0 | O20: =+$G$20 -> 0 | P20: =+$G$20 -> 0 | Q20: =+$G$20 -> 0 | R20: =+$G$20 -> 0 | S20: =+$G$20 -> 0 | T20: =+$G$20 -> 0 | ... Y20: =+$G$20 -> 0
B21: MATERIAL ELECTRICO | C21: Mantenimeinto electrico | E21: 1 | F21: =+H21/$J$49 -> 1500 | G21: =F21 -> 1500 | H21: 30000 | I21: =(E21*H21) -> 30000 | J21: =I21*1.16 -> 34800 | K21: =G21 -> 1500 | L21: 0 | M21: =+$G$21 -> 1500 | N21: 0 | O21: 0 | P21: 0 | Q21: 0 | R21: =+$G$21 -> 1500 | S21: 0 | T21: 0 | U21: 0 | V21: 0 | W21: 0 | X21: =+$G$21 -> 1500 | Y21: 0
B22: MATERIAL PARA LA CONSTRUCCION | E22: 1 | F22: =+H22/$J$49 -> 0 | G22: =F22 -> 0 | H22: 0 | I22: =(E22*H22) -> 0 | J22: =I22*1.16 -> 0 | K22: =G22 -> 0 | L22: 0 | M22: =+$G$22 -> 0 | N22: =+$G$22 -> 0 | O22: =+$G$22 -> 0 | P22: =+$G$22 -> 0 | Q22: =+$G$22 -> 0 | R22: =+$G$22 -> 0 | S22: =+$G$22 -> 0 | T22: =+$G$22 -> 0 | ... Y22: =+$G$22 -> 0
B23: MATERIALES Y ART P/MANTENIMIENTO | C23: Mantenimiento | E23: 1 | F23: =+H23/$J$49 -> 0 | G23: =F23 -> 0 | H23: 0 | I23: =(E23*H23) -> 0 | J23: =I23*1.16 -> 0 | K23: =G23 -> 0 | L23: 0 | M23: =+$G$23 -> 0 | N23: =+$G$23 -> 0 | O23: =+$G$23 -> 0 | P23: =+$G$23 -> 0 | Q23: =+$G$23 -> 0 | R23: =+$G$23 -> 0 | S23: =+$G$23 -> 0 | T23: =+$G$23 -> 0 | ... Y23: =+$G$23 -> 0
B24: METALES | E24: 1 | F24: =+H24/$J$49 -> 250 | G24: =F24 -> 250 | H24: 5000 | I24: =(E24*H24) -> 5000 | J24: =I24*1.16 -> 5800 | K24: =G24 -> 250 | L24: 0 | M24: =+$G$24 -> 250 | N24: =+$G$24 -> 250 | O24: =+$G$24 -> 250 | P24: =+$G$24 -> 250 | Q24: =+$G$24 -> 250 | R24: =+$G$24 -> 250 | S24: =+$G$24 -> 250 | T24: =+$G$24 -> 250 | ... Y24: =+$G$24 -> 250
B25: PART REP ACCES Y PROD P/VEHIC | E25: 1 | F25: =+H25/$J$49 -> 0 | G25: =F25 -> 0 | H25: 0 | I25: =(E25*H25) -> 0 | J25: =I25*1.16 -> 0 | K25: =G25 -> 0 | L25: 0 | M25: =+$G$25 -> 0 | N25: =+$G$25 -> 0 | O25: =+$G$25 -> 0 | P25: =+$G$25 -> 0 | Q25: =+$G$25 -> 0 | R25: =+$G$25 -> 0 | S25: =+$G$25 -> 0 | T25: =+$G$25 -> 0 | ... Y25: =+$G$25 -> 0
B26: PARTES ACCES Y MAT P/LABORATORIO | E26: 1 | F26: =+H26/$J$49 -> 0 | G26: =F26 -> 0 | H26: 0 | I26: =(E26*H26) -> 0 | J26: =I26*1.16 -> 0 | K26: =G26 -> 0 | L26: 0 | M26: =+$G$26 -> 0 | N26: =+$G$26 -> 0 | O26: =+$G$26 -> 0 | P26: =+$G$26 -> 0 | Q26: =+$G$26 -> 0 | R26: =+$G$26 -> 0 | S26: =+$G$26 -> 0 | T26: =+$G$26 -> 0 | ... Y26: =+$G$26 -> 0
B27: PARTES ACCES Y REFAC P/ LUBRICANTES | E27: 1 | F27: =+H27/$J$49 -> 0 | G27: =F27 -> 0 | H27: 0 | I27: =(E27*H27) -> 0 | J27: =I27*1.16 -> 0 | K27: =G27 -> 0 | L27: 0 | M27: =+$G$27 -> 0 | N27: =+$G$27 -> 0 | O27: =+$G$27 -> 0 | P27: =+$G$27 -> 0 | Q27: =+$G$27 -> 0 | R27: =+$G$27 -> 0 | S27: =+$G$27 -> 0 | T27: =+$G$27 -> 0 | ... Y27: =+$G$27 -> 0
B28: PARTES ELECT, ACCES Y REFACC | E28: 1 | F28: =+H28/$J$49 -> 0 | G28: =F28 -> 0 | H28: 0 | I28: =(E28*H28) -> 0 | J28: =I28*1.16 -> 0 | K28: =G28 -> 0 | L28: 0 | M28: =+$G$28 -> 0 | N28: =+$G$28 -> 0 | O28: =+$G$28 -> 0 | P28: =+$G$28 -> 0 | Q28: =+$G$28 -> 0 | R28: =+$G$28 -> 0 | S28: =+$G$28 -> 0 | T28: =+$G$28 -> 0 | ... Y28: =+$G$28 -> 0
B29: PARTES Y REFAC TELECOM Y VIDEO (TELEMETRÍA) | C29: Telemetría | E29: 1 | F29: =+H29/$J$49 -> 900 | G29: =F29 -> 900 | H29: 18000 | I29: =(E29*H29) -> 18000 | J29: =I29*1.16 -> 20880 | K29: =G29 -> 900 | L29: 0 | M29: =+$G$29 -> 900 | N29: =+$G$29 -> 900 | O29: =+$G$29 -> 900 | P29: =+$G$29 -> 900 | Q29: =+$G$29 -> 900 | R29: =+$G$29 -> 900 | S29: =+$G$29 -> 900 | T29: =+$G$29 -> 900 | ... Y29: =+$G$29 -> 900
B30: PARTES Y REFACCION C/INCENDIO | E30: 0 | F30: =+H30/$J$49 -> 0 | G30: =F30 -> 0 | H30: 0 | I30: =(E30*H30) -> 0 | J30: =I30*1.16 -> 0 | K30: =G30 -> 0 | L30: 0 | M30: =+$G$30 -> 0 | N30: =+$G$30 -> 0 | O30: =+$G$30 -> 0 | P30: =+$G$30 -> 0 | Q30: =+$G$30 -> 0 | R30: =+$G$30 -> 0 | S30: =+$G$30 -> 0 | T30: =+$G$30 -> 0 | ... Y30: =+$G$30 -> 0
B31: PASTA PEGAMENTO OTRO COMPUESTO | E31: 0 | F31: =+H31/$J$49 -> 0 | G31: =F31 -> 0 | H31: 0 | I31: =(E31*H31) -> 0 | J31: =I31*1.16 -> 0 | K31: =G31 -> 0 | L31: 0 | M31: =+$G$31 -> 0 | N31: =+$G$31 -> 0 | O31: =+$G$31 -> 0 | P31: =+$G$31 -> 0 | Q31: =+$G$31 -> 0 | R31: =+$G$31 -> 0 | S31: =+$G$31 -> 0 | T31: =+$G$31 -> 0 | ... Y31: =+$G$31 -> 0
B32: PINTURA Y OTROS RECUBRIMIENTOS | C32: Retoque pintura | E32: 1 | F32: =+H32/$J$49 -> 2250 | G32: =F32 -> 2250 | H32: 45000 | I32: =(E32*H32) -> 45000 | J32: =I32*1.16 -> 52200 | K32: =G32 -> 2250 | L32: 0 | M32: 0 | N32: 0 | O32: 0 | P32: =+$G$32 -> 2250 | Q32: 0 | R32: 0 | S32: 0 | T32: 0 | U32: 0 | V32: 0 | W32: 0 | X32: 0 | Y32: 0
B33: REFAC P/INSTRUM DE MED Y CONTROL | E33: 1 | F33: =+H33/$J$49 -> 0 | G33: =F33 -> 0 | H33: 0 | I33: =(E33*H33) -> 0 | J33: =I33*1.16 -> 0 | K33: =G33 -> 0 | L33: 0 | M33: =+$G$33 -> 0 | N33: =+$G$33 -> 0 | O33: =+$G$33 -> 0 | P33: =+$G$33 -> 0 | Q33: =+$G$33 -> 0 | R33: =+$G$33 -> 0 | S33: =+$G$33 -> 0 | T33: =+$G$33 -> 0 | ... Y33: =+$G$33 -> 0
B34: REFACC Y ACCES PARA VALVULAS | C34: Grasa sellante | E34: 1 | F34: =+H34/$J$49 -> 0 | G34: =F34 -> 0 | H34: 0 | I34: =(E34*H34) -> 0 | J34: =I34*1.16 -> 0 | K34: =G34 -> 0 | L34: 0 | M34: 0 | N34: 0 | O34: 0 | P34: 0 | Q34: 0 | R34: 0 | S34: 0 | T34: =+$G$34 -> 0 | U34: 0 | V34: 0 | W34: 0 | X34: 0 | Y34: 0
B35: REFACC Y ACCESORIO PARA HERRAMIENTA | C35: Housing y BJ | E35: 1 | F35: =+H35/$J$49 -> 0 | G35: =F35 -> 0 | H35: 0 | I35: =(E35*H35) -> 0 | J35: =I35*1.16 -> 0 | K35: =G35 -> 0 | L35: 0 | M35: =+$G$35 -> 0 | N35: =+$G$35 -> 0 | O35: =+$G$35 -> 0 | P35: =+$G$35 -> 0 | Q35: =+$G$35 -> 0 | R35: =+$G$35 -> 0 | S35: =+$G$35 -> 0 | T35: =+$G$35 -> 0 | ... Y35: =+$G$35 -> 0
B36: REFACCIONES P/MAQUINARIA | C36: Refaccionamiento MB | E36: 1 | F36: =+H36/$J$49 -> 0 | G36: =F36 -> 0 | H36: 0 | I36: =(E36*H36) -> 0 | J36: =I36*1.16 -> 0 | K36: =G36 -> 0 | L36: 0 | M36: =+$G$36 -> 0 | N36: =+$G$36 -> 0 | O36: =+$G$36 -> 0 | P36: =+$G$36 -> 0 | Q36: =+$G$36 -> 0 | R36: =+$G$36 -> 0 | S36: =+$G$36 -> 0 | T36: =+$G$36 -> 0 | ... Y36: =+$G$36 -> 0
B37: RODAM ACCES Y SELLOS P/ ACEITE | E37: 1 | F37: =+H37/$J$49 -> 0 | G37: =F37 -> 0 | H37: 0 | I37: =(E37*H37) -> 0 | J37: =I37*1.16 -> 0 | K37: =G37 -> 0 | L37: 0 | M37: =+$G$37 -> 0 | N37: =+$G$37 -> 0 | O37: =+$G$37 -> 0 | P37: =+$G$37 -> 0 | Q37: =+$G$37 -> 0 | R37: =+$G$37 -> 0 | S37: =+$G$37 -> 0 | T37: =+$G$37 -> 0 | ... Y37: =+$G$37 -> 0
B38: SUSTANCIAS QUIMICAS | E38: 1 | F38: =+H38/$J$49 -> 0 | G38: =F38 -> 0 | H38: 0 | I38: =(E38*H38) -> 0 | J38: =I38*1.16 -> 0 | K38: =G38 -> 0 | L38: 0 | M38: =+$G$38 -> 0 | N38: =+$G$38 -> 0 | O38: =+$G$38 -> 0 | P38: =+$G$38 -> 0 | Q38: =+$G$38 -> 0 | R38: =+$G$38 -> 0 | S38: =+$G$38 -> 0 | T38: =+$G$38 -> 0 | ... Y38: =+$G$38 -> 0
B39: TORNILLERIA Y ARTICULO | E39: 1 | F39: =+H39/$J$49 -> 0 | G39: =F39 -> 0 | H39: 0 | I39: =(E39*H39) -> 0 | J39: =I39*1.16 -> 0 | K39: =G39 -> 0 | L39: 0 | M39: =+$G$39 -> 0 | N39: =+$G$39 -> 0 | O39: =+$G$39 -> 0 | P39: =+$G$39 -> 0 | Q39: =+$G$39 -> 0 | R39: =+$G$39 -> 0 | S39: =+$G$39 -> 0 | T39: =+$G$39 -> 0 | ... Y39: =+$G$39 -> 0
B40: TUBERIAS | E40: 1 | F40: =+H40/$J$49 -> 0 | G40: =F40 -> 0 | H40: 0 | I40: =(E40*H40) -> 0 | J40: =I40*1.16 -> 0 | K40: =G40 -> 0 | L40: 0 | M40: =+$G$40 -> 0 | N40: =+$G$40 -> 0 | O40: =+$G$40 -> 0 | P40: =+$G$40 -> 0 | Q40: =+$G$40 -> 0 | R40: =+$G$40 -> 0 | S40: =+$G$40 -> 0 | T40: =+$G$40 -> 0 | ... Y40: =+$G$40 -> 0
B41: VALVULAS | E41: 1 | F41: =+H41/$J$49 -> 0 | G41: =F41 -> 0 | H41: 0 | I41: =(E41*H41) -> 0 | J41: =I41*1.16 -> 0 | K41: =G41 -> 0 | L41: 0 | M41: =+$G$41 -> 0 | N41: =+$G$41 -> 0 | O41: =+$G$41 -> 0 | P41: =+$G$41 -> 0 | Q41: =+$G$41 -> 0 | R41: =+$G$41 -> 0 | S41: =+$G$41 -> 0 | T41: =+$G$41 -> 0 | ... Y41: =+$G$41 -> 0
I43: TOTAL MENSUAL [USD] | L43: =SUM(L7:L41) -> 0 | M43: =SUM(M7:M41) -> 2760 | N43: =SUM(N7:N41) -> 1260 | O43: =SUM(O7:O41) -> 1260 | P43: =SUM(P7:P41) -> 3510 | Q43: =SUM(Q7:Q41) -> 1260 | R43: =SUM(R7:R41) -> 2963 | S43: =SUM(S7:S41) -> 1260 | ... Y43: =SUM(Y7:Y41) -> 1260
I44: TOTAL MENSUAL [MN] | L44: =L43*$J$49 -> 0 | M44: =M43*$J$49 -> 55200 | N44: =N43*$J$49 -> 25200 | O44: =O43*$J$49 -> 25200 | P44: =P43*$J$49 -> 70200 | Q44: =Q43*$J$49 -> 25200 | R44: =R43*$J$49 -> 59260 | S44: =S43*$J$49 -> 25200 | ... Y44: =Y43*$J$49 -> 25200
I45: TOTAL [USD] | L45: =SUM(L43:Y43) -> 23333
I46: TOTAL [MN] | L46: =SUM(L44:Y44) -> 466660
I49: ='F05 VIÁTICOS'!H33 -> PARIDAD | J49: ='F05 VIÁTICOS'!I33 -> 20
I50: ='F05 VIÁTICOS'!H34 -> MES | J50: ='F05 VIÁTICOS'!I34 -> 30.4
I51: ='F05 VIÁTICOS'!H35 -> CRÉDITO | J51: ='F05 VIÁTICOS'!I35 -> 45
I52: ='F05 VIÁTICOS'!H36 -> GAS LP | J52: ='F05 VIÁTICOS'!I36 -> 10.5
I53: ='F05 VIÁTICOS'!H37 -> GASOLINA | J53: ='F05 VIÁTICOS'!I37 -> 22
I54: ='F05 VIÁTICOS'!H38 -> DIESEL | J54: ='F05 VIÁTICOS'!I38 -> 23
I55: https://www.google.com/search?client=firefox-b-d&q=precio+del+dolar+hoy

Sheet F07 OPERAC. (MAT,SERV & EQUIPO)
B2: MATERIALES, SERVICIOS Y EQUIPO DE OPERACIÓN
B4: RESUMEN 1 | C4: RESUMEN 2 | D4: UNIDAD | E4: CANTIDAD | F4: PU [USD] | G4: TOTAL [USD] | H4: PU [MN] | I4: TOTAL [MN] | J4: TOTAL [MN] | L4: Instalación | M4: M1 | N4: M2 | O4: M3 | P4: M4 | Q4: M5 | R4: M6 | S4: M7 | T4: M8 | U4: M9 | V4: M10 | W4: M11 | X4: M12 | Y4: M13
E5: CANTIDAD | G5: TOTAL [USD] | H5: PU [MN] | I5: TOTAL [MN] | L5: - | M5: ENE | N5: FEB | O5: MAR | P5: ABR | Q5: MAY | R5: JUN | S5: JUL | T5: AGO | U5: SEP | V5: OCT | W5: NOV | X5: DIC | Y5: ENE
G6: [USD] | H6: [MN] | I6: [MN] | J6: C / IVA | L6: - | M6: 31 | N6: 28 | O6: 31 | P6: 30 | Q6: 31 | R6: 30 | S6: 31 | T6: 31 | U6: 30 | V6: 31 | W6: 30 | X6: 31 | Y6: 31
B7: ENSERES MENORES DIVERSOS (Acondicionamiento de casas) | C7: Escoba y Trapeador | E7: 1 | F7: =+H7/$J$199 -> 15 | G7: =F7 -> 15 | H7: 300 | I7: =(E7*H7) -> 300 | J7: =I7*1.16 -> 348 | L7: 0 | M7: =+$G$7 -> 15 | N7: =+$G$7 -> 15 | O7: =+$G$7 -> 15 | P7: =+$G$7 -> 15 | Q7: =+$G$7 -> 15 | R7: =+$G$7 -> 15 | S7: =+$G$7 -> 15 | T7: =+$G$7 -> 15 | ... Y7: =+$G$7 -> 15
B8: ENSERES MENORES DIVERSOS (Acondicionamiento de casas) | C8: Bolsas de basura | E8: 1 | F8: =+H8/$J$199 -> 10 | G8: =F8 -> 10 | H8: 200 | I8: =(E8*H8) -> 200 | J8: =I8*1.16 -> 232 | L8: 0 | M8: =+$G$8 -> 10 | N8: =+$G$8 -> 10 | O8: =+$G$8 -> 10 | P8: =+$G$8 -> 10 | Q8: =+$G$8 -> 10 | R8: =+$G$8 -> 10 | S8: =+$G$8 -> 10 | T8: =+$G$8 -> 10 | ... Y8: =+$G$8 -> 10
B9: ENSERES MENORES DIVERSOS (Acondicionamiento de casas) | C9: Bote de basura | E9: 4 | F9: =+H9/$J$199 -> 0 | G9: =F9 -> 0 | H9: 0 | I9: =(E9*H9) -> 0 | J9: =I9*1.16 -> 0 | L9: 0 | M9: =+$G$9 -> 0 | N9: =+$G$9 -> 0 | O9: =+$G$9 -> 0 | P9: =+$G$9 -> 0 | Q9: =+$G$9 -> 0 | R9: =+$G$9 -> 0 | S9: =+$G$9 -> 0 | T9: =+$G$9 -> 0 | ... Y9: =+$G$9 -> 0
B10: ENSERES MENORES DIVERSOS (Acondicionamiento de casas) | C10: Kit de limpieza de baño | E10: 2 | F10: =+H10/$J$199 -> 10 | G10: =F10 -> 10 | H10: 200 | I10: =(E10*H10) -> 400 | J10: =I10*1.16 -> 464 | L10: 0 | M10: =+$G$7 -> 15 | N10: =+$G$7 -> 15 | O10: =+$G$7 -> 15 | P10: =+$G$7 -> 15 | Q10: =+$G$7 -> 15 | R10: =+$G$7 -> 15 | S10: =+$G$7 -> 15 | T10: =+$G$7 -> 15 | ... Y10: =+$G$7 -> 15
B11: ENSERES MENORES DIVERSOS (Acondicionamiento de casas) | C11: Cubeta | E11: 6 | F11: =+H11/$J$199 -> 5 | G11: =F11 -> 5 | H11: 100 | I11: =(E11*H11) -> 600 | J11: =I11*1.16 -> 696 | L11: 0 | M11: =+$G$11 -> 5 | N11: =+$G$11 -> 5 | O11: =+$G$11 -> 5 | P11: =+$G$11 -> 5 | Q11: =+$G$11 -> 5 | R11: =+$G$11 -> 5 | S11: =+$G$11 -> 5 | T11: =+$G$11 -> 5 | ... Y11: =+$G$11 -> 5
B12: ENSERES MENORES DIVERSOS (Acondicionamiento de casas) | C12: Cloro | E12: 3 | F12: =+H12/$J$199 -> 15 | G12: =F12 -> 15 | H12: 300 | I12: =(E12*H12) -> 900 | J12: =I12*1.16 -> 1044 | L12: 0 | M12: =+$G$12 -> 15 | N12: =+$G$12 -> 15 | O12: =+$G$12 -> 15 | P12: =+$G$12 -> 15 | Q12: =+$G$12 -> 15 | R12: =+$G$12 -> 15 | S12: =+$G$12 -> 15 | T12: =+$G$12 -> 15 | ... Y12: =+$G$12 -> 15
B13: ENSERES MENORES DIVERSOS (Acondicionamiento de casas) | C13: Jabon | E13: 3 | F13: =+H13/$J$199 -> 7.5 | G13: =F13 -> 7.5 | H13: 150 | I13: =(E13*H13) -> 450 | J13: =I13*1.16 -> 522 | L13: 0 | M13: =+$G$13 -> 7.5 | N13: =+$G$13 -> 7.5 | O13: =+$G$13 -> 7.5 | P13: =+$G$13 -> 7.5 | Q13: =+$G$13 -> 7.5 | R13: =+$G$13 -> 7.5 | S13: =+$G$13 -> 7.5 | T13: =+$G$13 -> 7.5 | ... Y13: =+$G$13 -> 7.5
B14: ENSERES MENORES DIVERSOS (Acondicionamiento de casas) | C14: Fabuloso o Pino | E14: 3 | F14: =+H14/$J$199 -> 15 | G14: =F14 -> 15 | H14: 300 | I14: =(E14*H14) -> 900 | J14: =I14*1.16 -> 1044 | L14: 0 | M14: =+$G$14 -> 15 | N14: =+$G$14 -> 15 | O14: =+$G$14 -> 15 | P14: =+$G$14 -> 15 | Q14: =+$G$14 -> 15 | R14: =+$G$14 -> 15 | S14: =+$G$14 -> 15 | T14: =+$G$14 -> 15 | ... Y14: =+$G$14 -> 15
I16: TOTAL MENSUAL [USD] | L16: =SUM(L7:L14) -> 0 | M16: =SUM(M7:M14) -> 82.5 | N16: =SUM(N7:N14) -> 82.5 | O16: =SUM(O7:O14) -> 82.5 | P16: =SUM(P7:P14) -> 82.5 | Q16: =SUM(Q7:Q14) -> 82.5 | R16: =SUM(R7:R14) -> 82.5 | S16: =SUM(S7:S14) -> 82.5 | ... Y16: =SUM(Y7:Y14) -> 82.5
I17: TOTAL MENSUAL [MN] | L17: =L16*$J$199 -> 0 | M17: =M16*$J$199 -> 1650 | N17: =N16*$J$199 -> 1650 | O17: =O16*$J$199 -> 1650 | P17: =P16*$J$199 -> 1650 | Q17: =Q16*$J$199 -> 1650 | R17: =R16*$J$199 -> 1650 | S17: =S16*$J$199 -> 1650 | ... Y17: =Y16*$J$199 -> 1650
I18: TOTAL [USD] | L18: =SUM(L16:Y16) -> 1072.5
I19: TOTAL [MN] | L19: =SUM(L17:Y17) -> 21450
F21: =EGRESOS!R26 -> 750.2495 | G21: MATERIALES (OPERACION) | I21: TOTAL MENSUAL [USD] | L21: =L16 -> 0 | M21: =M16 -> 82.5 | N21: =N16 -> 82.5 | O21: =O16 -> 82.5 | P21: =P16 -> 82.5 | Q21: =Q16 -> 82.5 | R21: =R16 -> 82.5 | S21: =S16 -> 82.5 | ... Y21: =Y16 -> 82.5
I22: TOTAL MENSUAL [MN] | L22: =L21*$J$199 -> 0 | M22: =M21*$J$199 -> 1650 | N22: =N21*$J$199 -> 1650 | O22: =O21*$J$199 -> 1650 | P22: =P21*$J$199 -> 1650 | Q22: =Q21*$J$199 -> 1650 | R22: =R21*$J$199 -> 1650 | S22: =S21*$J$199 -> 1650 | ... Y22: =Y21*$J$199 -> 1650
I23: TOTAL [USD] | L23: =SUM(L21:Y21) -> 1072.5
I24: TOTAL [MN] | L24: =SUM(L22:Y22) -> 21450
B27: INSUMOS AGRICOLAS
B28: RESUMEN 1 | C28: RESUMEN 2 | D28: UNIDAD | E28: CANTIDAD | F28: PU [USD] | G28: TOTAL [USD] | H28: PU [MN] | I28: TOTAL [MN] | J28: TOTAL [MN] | L28: Instalación | M28: M1 | N28: M2 | O28: M3 | P28: M4 | Q28: M5 | R28: M6 | S28: M7 | T28: M8 | U28: M9 | V28: M10 | W28: M11 | X28: M12 | Y28: M13
E29: CANTIDAD | G29: TOTAL [USD] | H29: PU [MN] | I29: TOTAL [MN] | L29: - | M29: ENE | N29: FEB | O29: MAR | P29: ABR | Q29: MAY | R29: JUN | S29: JUL | T29: AGO | U29: SEP | V29: OCT | W29: NOV | X29: DIC | Y29: ENE
G30: [USD] | H30: [MN] | I30: [MN] | J30: C / IVA | L30: - | M30: 31 | N30: 28 | O30: 31 | P30: 30 | Q30: 31 | R30: 30 | S30: 31 | T30: 31 | U30: 30 | V30: 31 | W30: 30 | X30: 31 | Y30: 31
B31: INSUMOS AGRICOLAS | C31: Hilo para desbrosadora | E31: 1 | F31: =+H31/$J$199 -> 26.2565 | G31: =F31 -> 26.2565 | H31: 525.13 | I31: =(E31*H31) -> 525.13 | J31: =I31*1.16 -> 609.1508 | L31: 0 | M31: =+$G$31 -> 26.2565 | N31: =+$G$31 -> 26.2565 | O31: =+$G$31 -> 26.2565 | P31: =+$G$31 -> 26.2565 | Q31: =+$G$31 -> 26.2565 | R31: =+$G$31 -> 26.2565 | S31: =+$G$31 -> 26.2565 | T31: =+$G$31 -> 26.2565 | ... Y31: =+$G$31 -> 26.2565
B32: INSUMOS AGRICOLAS | C32: Aceite para desbrosadora | E32: 1 | F32: =+H32/$J$199 -> 6.455 | G32: =F32 -> 6.455 | H32: 129.1 | I32: =(E32*H32) -> 129.1 | J32: =I32*1.16 -> 149.756 | L32: 0 | M32: =+$G$32 -> 6.455 | N32: =+$G$32 -> 6.455 | O32: =+$G$32 -> 6.455 | P32: =+$G$32 -> 6.455 | Q32: =+$G$32 -> 6.455 | R32: =+$G$32 -> 6.455 | S32: =+$G$32 -> 6.455 | T32: =+$G$32 -> 6.455 | ... Y32: =+$G$32 -> 6.455
B33: INSUMOS AGRICOLAS | C33: Mtto. Para desbrosadora | E33: 1 | F33: =+H33/$J$199 -> 25 | G33: =F33 -> 25 | H33: 500 | I33: =(E33*H33) -> 500 | J33: =I33*1.16 -> 580 | L33: 0 | M33: =+$G$33 -> 25 | N33: =+$G$33 -> 25 | O33: =+$G$33 -> 25 | P33: =+$G$33 -> 25 | Q33: =+$G$33 -> 25 | R33: =+$G$33 -> 25 | S33: =+$G$33 -> 25 | T33: =+$G$33 -> 25 | ... Y33: =+$G$33 -> 25
B34: INSUMOS AGRICOLAS | E34: 1 | F34: =+H34/$J$199 -> 0 | G34: =F34 -> 0 | H34: 0 | I34: =(E34*H34) -> 0 | J34: =I34*1.16 -> 0 | L34: 0 | M34: =+$G$34 -> 0 | N34: =+$G$34 -> 0 | O34: =+$G$34 -> 0 | P34: =+$G$34 -> 0 | Q34: =+$G$34 -> 0 | R34: =+$G$34 -> 0 | S34: =+$G$34 -> 0 | T34: =+$G$34 -> 0 | ... Y34: =+$G$34 -> 0
B35: INSUMOS AGRICOLAS | E35: 1 | F35: =+H35/$J$199 -> 0 | G35: =F35 -> 0 | H35: 0 | I35: =(E35*H35) -> 0 | J35: =I35*1.16 -> 0 | L35: 0 | M35: =+$G$35 -> 0 | N35: =+$G$35 -> 0 | O35: =+$G$35 -> 0 | P35: =+$G$35 -> 0 | Q35: =+$G$35 -> 0 | R35: =+$G$35 -> 0 | S35: =+$G$35 -> 0 | T35: =+$G$35 -> 0 | ... Y35: =+$G$35 -> 0
B36: INSUMOS AGRICOLAS | E36: 1 | F36: =+H36/$J$199 -> 0 | G36: =F36 -> 0 | H36: 0 | I36: =(E36*H36) -> 0 | J36: =I36*1.16 -> 0 | L36: 0 | M36: =+$G$36 -> 0 | N36: =+$G$36 -> 0 | O36: =+$G$36 -> 0 | P36: =+$G$36 -> 0 | Q36: =+$G$36 -> 0 | R36: =+$G$36 -> 0 | S36: =+$G$36 -> 0 | T36: =+$G$36 -> 0 | ... Y36: =+$G$36 -> 0
I38: TOTAL MENSUAL [USD] | L38: =SUM(L31:L36) -> 0 | M38: =SUM(M31:M36) -> 57.7115 | N38: =SUM(N31:N36) -> 57.7115 | O38: =SUM(O31:O36) -> 57.7115 | P38: =SUM(P31:P36) -> 57.7115 | Q38: =SUM(Q31:Q36) -> 57.7115 | R38: =SUM(R31:R36) -> 57.7115 | S38: =SUM(S31:S36) -> 57.7115 | ... Y38: =SUM(Y31:Y36) -> 57.7115
I39: TOTAL MENSUAL [MN] | L39: =L38*$J$199 -> 0 | M39: =M38*$J$199 -> 1154.23 | N39: =N38*$J$199 -> 1154.23 | O39: =O38*$J$199 -> 1154.23 | P39: =P38*$J$199 -> 1154.23 | Q39: =Q38*$J$199 -> 1154.23 | R39: =R38*$J$199 -> 1154.23 | S39: =S38*$J$199 -> 1154.23 | ... Y39: =Y38*$J$199 -> 1154.23
I40: TOTAL [USD] | L40: =SUM(L38:Y38) -> 750.2495
I41: TOTAL [MN] | L41: =SUM(L39:Y39) -> 15004.99
F43: =SERVICIO!B32 -> 750.2495 | G43: MATERIALES (OPERACION) | I43: TOTAL MENSUAL [USD] | L43: =L38 -> 0 | M43: =M38 -> 57.7115 | N43: =N38 -> 57.7115 | O43: =O38 -> 57.7115 | P43: =P38 -> 57.7115 | Q43: =Q38 -> 57.7115 | R43: =R38 -> 57.7115 | S43: =S38 -> 57.7115 | ... Y43: =Y38 -> 57.7115
I44: TOTAL MENSUAL [MN] | L44: =L43*$J$199 -> 0 | M44: =M43*$J$199 -> 1154.23 | N44: =N43*$J$199 -> 1154.23 | O44: =O43*$J$199 -> 1154.23 | P44: =P43*$J$199 -> 1154.23 | Q44: =Q43*$J$199 -> 1154.23 | R44: =R43*$J$199 -> 1154.23 | S44: =S43*$J$199 -> 1154.23 | ... Y44: =Y43*$J$199 -> 1154.23
I45: TOTAL [USD] | L45: =SUM(L43:Y43) -> 750.2495
I46: TOTAL [MN] | L46: =SUM(L44:Y44) -> 15004.99
B48: SERVICIOS
B49: RESUMEN 1 | C49: RESUMEN 2 | D49: UNIDAD | E49: CANTIDAD | F49: PU [USD] | G49: TOTAL [USD] | H49: PU [MN] | I49: TOTAL [MN] | J49: TOTAL [MN] | L49: Instalación | M49: M1 | N49: M2 | O49: M3 | P49: M4 | Q49: M5 | R49: M6 | S49: M7 | T49: M8 | U49: M9 | V49: M10 | W49: M11 | X49: M12 | Y49: M13
E50: CANTIDAD | G50: TOTAL [USD] | H50: PU [MN] | I50: TOTAL [MN] | L50: - | M50: ENE | N50: FEB | O50: MAR | P50: ABR | Q50: MAY | R50: JUN | S50: JUL | T50: AGO | U50: SEP | V50: OCT | W50: NOV | X50: DIC | Y50: ENE
G51: [USD] | H51: [MN] | I51: [MN] | J51: C / IVA | L51: - | M51: 31 | N51: 28 | O51: 31 | P51: 30 | Q51: 31 | R51: 30 | S51: 31 | T51: 31 | U51: 30 | V51: 31 | W51: 30 | X51: 31 | Y51: 31
B52: ACONDICION DE CASA HABITACION | C52: Casa staff moviliario | E52: 1 | F52: =+H52/$J$199 -> 0 | G52: =F52 -> 0 | H52: 0 | I52: =(E52*H52) -> 0 | J52: =I52*1.16 -> 0 | L52: 0 | M52: =+$G$52 -> 0 | N52: =+$G$52 -> 0 | O52: =+$G$52 -> 0 | P52: =+$G$52 -> 0 | Q52: =+$G$52 -> 0 | R52: =+$G$52 -> 0 | S52: =+$G$52 -> 0 | T52: =+$G$52 -> 0 | ... Y52: =+$G$52 -> 0
B53: ADICION Y MODIFIC DE MATERIAL | E53: 1 | F53: =+H53/$J$199 -> 0 | G53: =F53 -> 0 | H53: 0 | I53: =(E53*H53) -> 0 | J53: =I53*1.16 -> 0 | L53: 0 | M53: =+$G$53 -> 0 | N53: =+$G$53 -> 0 | O53: =+$G$53 -> 0 | P53: =+$G$53 -> 0 | Q53: =+$G$53 -> 0 | R53: =+$G$53 -> 0 | S53: =+$G$53 -> 0 | T53: =+$G$53 -> 0 | ... Y53: =+$G$53 -> 0
B54: ADQUISICION TARJET COMBUSTIBLE | E54: 1 | F54: =+H54/$J$199 -> 0 | G54: =F54 -> 0 | H54: 0 | I54: =(E54*H54) -> 0 | J54: =I54*1.16 -> 0 | L54: 0 | M54: =+$G$54 -> 0 | N54: =+$G$54 -> 0 | O54: =+$G$54 -> 0 | P54: =+$G$54 -> 0 | Q54: =+$G$54 -> 0 | R54: =+$G$54 -> 0 | S54: =+$G$54 -> 0 | T54: =+$G$54 -> 0 | ... Y54: =+$G$54 -> 0
B55: ANALISIS CAUSA RAIZ | C55: ANALISIS CAUSA RAIZ | E55: 1 | F55: =+H55/$J$199 -> 125 | G55: =F55 -> 125 | H55: 2500 | I55: =(E55*H55) -> 2500 | J55: =I55*1.16 -> 2900 | L55: 0 | M55: =+$G$55 -> 125 | N55: =+$G$55 -> 125 | O55: =+$G$55 -> 125 | P55: =+$G$55 -> 125 | Q55: =+$G$55 -> 125 | R55: =+$G$55 -> 125 | S55: =+$G$55 -> 125 | T55: =+$G$55 -> 125 | ... Y55: =+$G$55 -> 125
B56: ANALISIS DE RIESGO | C56: Anális de Riesgo y Plan de Respuesta de Emergencia | E56: 1 | F56: =+H56/$J$199 -> 0 | G56: =F56 -> 0 | H56: 0 | I56: =(E56*H56) -> 0 | J56: =I56*1.16 -> 0 | L56: 0 | M56: =+$G$56 -> 0 | N56: =+$G$56 -> 0 | O56: =+$G$56 -> 0 | P56: =+$G$56 -> 0 | Q56: =+$G$56 -> 0 | R56: =+$G$56 -> 0 | S56: =+$G$56 -> 0 | T56: =+$G$56 -> 0 | ... Y56: =+$G$56 -> 0
B57: ANALISIS DE VIBRACION | C57: ANALISIS DE VIBRACION | E57: 1 | F57: =+H57/$J$199 -> 0 | G57: =F57 -> 0 | H57: 0 | I57: =(E57*H57) -> 0 | J57: =I57*1.16 -> 0 | L57: 0 | M57: =+$G$57 -> 0 | N57: =+$G$57 -> 0 | O57: =+$G$57 -> 0 | P57: =+$G$57 -> 0 | Q57: =+$G$57 -> 0 | R57: =+$G$57 -> 0 | S57: =+$G$57 -> 0 | T57: =+$G$57 -> 0 | ... Y57: =+$G$57 -> 0
B58: BASES LICITACION Y CONCURSOS | E58: 1 | F58: =+H58/$J$199 -> 0 | G58: =F58 -> 0 | H58: 0 | I58: =(E58*H58) -> 0 | J58: =I58*1.16 -> 0 | L58: 0 | M58: =+$G$58 -> 0 | N58: =+$G$58 -> 0 | O58: =+$G$58 -> 0 | P58: =+$G$58 -> 0 | Q58: =+$G$58 -> 0 | R58: =+$G$58 -> 0 | S58: =+$G$58 -> 0 | T58: =+$G$58 -> 0 | ... Y58: =+$G$58 -> 0
B59: CARGOS EXTRAORDINARIOS | E59: 1 | F59: =+H59/$J$199 -> 0 | G59: =F59 -> 0 | H59: 0 | I59: =(E59*H59) -> 0 | J59: =I59*1.16 -> 0 | L59: 0 | M59: =+$G$59 -> 0 | N59: =+$G$59 -> 0 | O59: =+$G$59 -> 0 | P59: =+$G$59 -> 0 | Q59: =+$G$59 -> 0 | R59: =+$G$59 -> 0 | S59: =+$G$59 -> 0 | T59: =+$G$59 -> 0 | ... Y59: =+$G$59 -> 0
B60: CERTIFICACION | E60: 1 | F60: =+H60/$J$199 -> 0 | G60: =F60 -> 0 | H60: 0 | I60: =(E60*H60) -> 0 | J60: =I60*1.16 -> 0 | L60: 0 | M60: =+$G$60 -> 0 | N60: =+$G$60 -> 0 | O60: =+$G$60 -> 0 | P60: =+$G$60 -> 0 | Q60: =+$G$60 -> 0 | R60: =+$G$60 -> 0 | S60: =+$G$60 -> 0 | T60: =+$G$60 -> 0 | ... Y60: =+$G$60 -> 0
B61: COLOCACION DE PILOTE | E61: 1 | F61: =+H61/$J$199 -> 0 | G61: =F61 -> 0 | H61: 0 | I61: =(E61*H61) -> 0 | J61: =I61*1.16 -> 0 | L61: 0 | M61: =+$G$61 -> 0 | N61: =+$G$61 -> 0 | O61: =+$G$61 -> 0 | P61: =+$G$61 -> 0 | Q61: =+$G$61 -> 0 | R61: =+$G$61 -> 0 | S61: =+$G$61 -> 0 | T61: =+$G$61 -> 0 | ... Y61: =+$G$61 -> 0
B62: CORREOS Y MENSAJERIAS | E62: 1 | F62: =+H62/$J$199 -> 0 | G62: =F62 -> 0 | H62: 0 | I62: =(E62*H62) -> 0 | J62: =I62*1.16 -> 0 | L62: 0 | M62: =+$G$62 -> 0 | N62: =+$G$62 -> 0 | O62: =+$G$62 -> 0 | P62: =+$G$62 -> 0 | Q62: =+$G$62 -> 0 | R62: =+$G$62 -> 0 | S62: =+$G$62 -> 0 | T62: =+$G$62 -> 0 | ... Y62: =+$G$62 -> 0
B63: CUOTAS Y SUSCRIPCIONES | E63: 1 | F63: =+H63/$J$199 -> 0 | G63: =F63 -> 0 | H63: 0 | I63: =(E63*H63) -> 0 | J63: =I63*1.16 -> 0 | L63: 0 | M63: =+$G$63 -> 0 | N63: =+$G$63 -> 0 | O63: =+$G$63 -> 0 | P63: =+$G$63 -> 0 | Q63: =+$G$63 -> 0 | R63: =+$G$63 -> 0 | S63: =+$G$63 -> 0 | T63: =+$G$63 -> 0 | ... Y63: =+$G$63 -> 0
B64: DEDUCIBLE POR SINIESTRO | E64: 1 | F64: =+H64/$J$199 -> 0 | G64: =F64 -> 0 | H64: 0 | I64: =(E64*H64) -> 0 | J64: =I64*1.16 -> 0 | L64: 0 | M64: =+$G$64 -> 0 | N64: =+$G$64 -> 0 | O64: =+$G$64 -> 0 | P64: =+$G$64 -> 0 | Q64: =+$G$64 -> 0 | R64: =+$G$64 -> 0 | S64: =+$G$64 -> 0 | T64: =+$G$64 -> 0 | ... Y64: =+$G$64 -> 0
B65: DESARROLLO DE SOFTWARE | E65: 1 | F65: =+H65/$J$199 -> 0 | G65: =F65 -> 0 | H65: 0 | I65: =(E65*H65) -> 0 | J65: =I65*1.16 -> 0 | L65: 0 | M65: =+$G$65 -> 0 | N65: =+$G$65 -> 0 | O65: =+$G$65 -> 0 | P65: =+$G$65 -> 0 | Q65: =+$G$65 -> 0 | R65: =+$G$65 -> 0 | S65: =+$G$65 -> 0 | T65: =+$G$65 -> 0 | ... Y65: =+$G$65 -> 0
B66: FIANZAS | E66: 1 | F66: =+H66/$J$199 -> 0 | G66: =F66 -> 0 | H66: 0 | I66: =(E66*H66) -> 0 | J66: =I66*1.16 -> 0 | L66: 0 | M66: =$G$66 -> 0 | N66: =$G$66 -> 0 | O66: =$G$66 -> 0 | P66: =$G$66 -> 0 | Q66: =$G$66 -> 0 | R66: =$G$66 -> 0 | S66: =$G$66 -> 0 | T66: =$G$66 -> 0 | ... Y66: =$G$66 -> 0
B67: FLETES EXTRANJEROS | C67: Frontera - Geolis - Sitio | E67: 1 | F67: =+H67/$J$199 -> 0 | G67: =F67 -> 0 | H67: 0 | I67: =(E67*H67) -> 0 | J67: =I67*1.16 -> 0 | L67: 0 | M67: =$G$67 -> 0 | N67: =$G$67 -> 0 | O67: =$G$67 -> 0 | P67: =$G$67 -> 0 | Q67: =$G$67 -> 0 | R67: =$G$67 -> 0 | S67: =$G$67 -> 0 | T67: =$G$67 -> 0 | ... Y67: =$G$67 -> 0
B68: FLETES NACIONALES | C68: Frontera - Geolis - Sitio | E68: 1 | F68: =+H68/$J$199 -> 0 | G68: =F68 -> 0 | H68: 0 | I68: =(E68*H68) -> 0 | J68: =I68*1.16 -> 0 | L68: 0 | M68: =$G$68 -> 0 | N68: =$G$68 -> 0 | O68: =$G$68 -> 0 | P68: =$G$68 -> 0 | Q68: =$G$68 -> 0 | R68: =$G$68 -> 0 | S68: =$G$68 -> 0 | T68: =$G$68 -> 0 | ... Y68: =$G$68 -> 0
B69: GASTOS DE IMPORTACION | E69: 1 | F69: =+H69/$J$199 -> 0 | G69: =F69 -> 0 | H69: 0 | I69: =(E69*H69) -> 0 | J69: =I69*1.16 -> 0 | L69: 0 | M69: =$G$69 -> 0 | N69: =$G$69 -> 0 | O69: =$G$69 -> 0 | P69: =$G$69 -> 0 | Q69: =$G$69 -> 0 | R69: =$G$69 -> 0 | S69: =$G$69 -> 0 | T69: =$G$69 -> 0 | ... Y69: =$G$69 -> 0
B70: GTO EXPED DE SEG/TRAMITE | C70: Tarifa de agilización de entrega | E70: 1 | F70: =+H70/$J$199 -> 0 | G70: =F70 -> 0 | H70: 0 | I70: =(E70*H70) -> 0 | J70: =I70*1.16 -> 0 | L70: 0 | M70: =$G$70 -> 0 | N70: =$G$70 -> 0 | O70: =$G$70 -> 0 | P70: =$G$70 -> 0 | Q70: =$G$70 -> 0 | R70: =$G$70 -> 0 | S70: =$G$70 -> 0 | T70: =$G$70 -> 0 | ... Y70: =$G$70 -> 0
B71: HIELO Y AGUA | E71: 1 | F71: =+H71/$J$199 -> 25 | G71: =F71 -> 25 | H71: 500 | I71: =(E71*H71) -> 500 | J71: =I71*1.16 -> 580 | L71: 0 | M71: =$G$71 -> 25 | N71: =$G$71 -> 25 | O71: =$G$71 -> 25 | P71: =$G$71 -> 25 | Q71: =$G$71 -> 25 | R71: =$G$71 -> 25 | S71: =$G$71 -> 25 | T71: =$G$71 -> 25 | ... Y71: =$G$71 -> 25
B72: HONORARIOS A PERSONA FISICA | E72: 1 | F72: =+H72/$J$199 -> 0 | G72: =F72 -> 0 | H72: 0 | I72: =(E72*H72) -> 0 | J72: =I72*1.16 -> 0 | L72: 0 | M72: =$G$72 -> 0 | N72: =$G$72 -> 0 | O72: =$G$72 -> 0 | P72: =$G$72 -> 0 | Q72: =$G$72 -> 0 | R72: =$G$72 -> 0 | S72: =$G$72 -> 0 | T72: =$G$72 -> 0 | ... Y72: =$G$72 -> 0
B73: IMPUESTOS Y DERECHOS | E73: 1 | F73: =+H73/$J$199 -> 0 | G73: =F73 -> 0 | H73: 0 | I73: =(E73*H73) -> 0 | J73: =I73*1.16 -> 0 | L73: 0 | M73: =$G$73 -> 0 | N73: =$G$73 -> 0 | O73: =$G$73 -> 0 | P73: =$G$73 -> 0 | Q73: =$G$73 -> 0 | R73: =$G$73 -> 0 | S73: =$G$73 -> 0 | T73: =$G$73 -> 0 | ... Y73: =$G$73 -> 0
B74: INTERNET Y DATOS | E74: 1 | F74: =+H74/$J$199 -> 0 | G74: =F74 -> 0 | H74: 0 | I74: =(E74*H74) -> 0 | J74: =I74*1.16 -> 0 | L74: 0 | M74: =$G$74 -> 0 | N74: =$G$74 -> 0 | O74: =$G$74 -> 0 | P74: =$G$74 -> 0 | Q74: =$G$74 -> 0 | R74: =$G$74 -> 0 | S74: =$G$74 -> 0 | T74: =$G$74 -> 0 | ... Y74: =$G$74 -> 0
B75: MANIOBRAS | E75: 1 | F75: =+H75/$J$199 -> 0 | G75: =F75 -> 0 | H75: 0 | I75: =(E75*H75) -> 0 | J75: =I75*1.16 -> 0 | L75: 0 | M75: =$G$75 -> 0 | N75: =$G$75 -> 0 | O75: =$G$75 -> 0 | P75: =$G$75 -> 0 | Q75: =$G$75 -> 0 | R75: =$G$75 -> 0 | S75: =$G$75 -> 0 | T75: =$G$75 -> 0 | ... Y75: =$G$75 -> 0
B76: MANTENIMIENTO A VEHICULOS | E76: 1 | F76: =+H76/$J$199 -> 0 | G76: =F76 -> 0 | H76: 0 | I76: =(E76*H76) -> 0 | J76: =I76*1.16 -> 0 | L76: 0 | M76: =$G$76 -> 0 | N76: =$G$76 -> 0 | O76: =$G$76 -> 0 | P76: =$G$76 -> 0 | Q76: =$G$76 -> 0 | R76: =$G$76 -> 0 | S76: =$G$76 -> 0 | T76: =$G$76 -> 0 | ... Y76: =$G$76 -> 0
B77: MANTTO A EQUIPOS DE SEGURIDAD | C77: Certificación de Extintores y Detector de Gas | E77: 1 | F77: =+H77/$J$199 -> 125 | G77: =F77 -> 125 | H77: 2500 | I77: =(E77*H77) -> 2500 | J77: =I77*1.16 -> 2900 | L77: 0 | M77: =$G$77 -> 125 | N77: =$G$77 -> 125 | O77: =$G$77 -> 125 | P77: =$G$77 -> 125 | Q77: =$G$77 -> 125 | R77: =$G$77 -> 125 | S77: =$G$77 -> 125 | T77: =$G$77 -> 125 | ... Y77: =$G$77 -> 125
B78: MANTTO DE MOBILIARIO Y EQUIPO | E78: 1 | F78: =+H78/$J$199 -> 0 | G78: =F78 -> 0 | H78: 0 | I78: =(E78*H78) -> 0 | J78: =I78*1.16 -> 0 | L78: 0 | M78: =$G$78 -> 0 | N78: =$G$78 -> 0 | O78: =$G$78 -> 0 | P78: =$G$78 -> 0 | Q78: =$G$78 -> 0 | R78: =$G$78 -> 0 | S78: =$G$78 -> 0 | T78: =$G$78 -> 0 | ... Y78: =$G$78 -> 0
B79: MANTTO PREV A EQUIPOS DE MEDICION | E79: 1 | F79: =+H79/$J$199 -> 0 | G79: =F79 -> 0 | H79: 0 | I79: =(E79*H79) -> 0 | J79: =I79*1.16 -> 0 | L79: 0 | M79: =$G$79 -> 0 | N79: =$G$79 -> 0 | O79: =$G$79 -> 0 | P79: =$G$79 -> 0 | Q79: =$G$79 -> 0 | R79: =$G$79 -> 0 | S79: =$G$79 -> 0 | T79: =$G$79 -> 0 | ... Y79: =$G$79 -> 0
B80: MANTTO Y ACONDICION DE CAMPER | E80: 1 | F80: =+H80/$J$199 -> 150 | G80: =F80 -> 150 | H80: 3000 | I80: =(E80*H80) -> 3000 | J80: =I80*1.16 -> 3480 | L80: 0 | M80: =$G$80 -> 150 | N80: 0 | O80: 0 | P80: 0 | Q80: 0 | R80: =$G$80 -> 150 | S80: 0 | T80: 0 | U80: 0 | V80: 0 | W80: 0 | X80: =$G$80 -> 150 | Y80: 0
B81: MECANICA DE SUELOS | E81: 1 | F81: =+H81/$J$199 -> 0 | G81: =F81 -> 0 | H81: 0 | I81: =(E81*H81) -> 0 | J81: =I81*1.16 -> 0 | L81: 0 | M81: =$G$81 -> 0 | N81: =$G$81 -> 0 | O81: =$G$81 -> 0 | P81: =$G$81 -> 0 | Q81: =$G$81 -> 0 | R81: =$G$81 -> 0 | S81: =$G$81 -> 0 | T81: =$G$81 -> 0 | ... Y81: =$G$81 -> 0
B82: OTROS DERECHOS | E82: 1 | F82: =+H82/$J$199 -> 0 | G82: =F82 -> 0 | H82: 0 | I82: =(E82*H82) -> 0 | J82: =I82*1.16 -> 0 | L82: 0 | M82: =$G$82 -> 0 | N82: =$G$82 -> 0 | O82: =$G$82 -> 0 | P82: =$G$82 -> 0 | Q82: =$G$82 -> 0 | R82: =$G$82 -> 0 | S82: =$G$82 -> 0 | T82: =$G$82 -> 0 | ... Y82: =$G$82 -> 0
B83: PACMA PEMEX EXPLORACION | E83: 1 | F83: =+H83/$J$199 -> 0 | G83: =F83 -> 0 | H83: 0 | I83: =(E83*H83) -> 0 | J83: =I83*1.16 -> 0 | L83: 0 | M83: =$G$83 -> 0 | N83: =$G$83 -> 0 | O83: =$G$83 -> 0 | P83: =$G$83 -> 0 | Q83: =$G$83 -> 0 | R83: =$G$83 -> 0 | S83: =$G$83 -> 0 | T83: =$G$83 -> 0 | ... Y83: =$G$83 -> 0
B84: PAGO DE RECARGOS | E84: 1 | F84: =+H84/$J$199 -> 0 | G84: =F84 -> 0 | H84: 0 | I84: =(E84*H84) -> 0 | J84: =I84*1.16 -> 0 | L84: 0 | M84: =$G$84 -> 0 | N84: =$G$84 -> 0 | O84: =$G$84 -> 0 | P84: =$G$84 -> 0 | Q84: =$G$84 -> 0 | R84: =$G$84 -> 0 | S84: =$G$84 -> 0 | T84: =$G$84 -> 0 | ... Y84: =$G$84 -> 0
B85: RECARGA DE GASES INDUSTRIALES | E85: 1 | F85: =+H85/$J$199 -> 0 | G85: =F85 -> 0 | H85: 0 | I85: =(E85*H85) -> 0 | J85: =I85*1.16 -> 0 | L85: 0 | M85: =$G$85 -> 0 | N85: =$G$85 -> 0 | O85: =$G$85 -> 0 | P85: =$G$85 -> 0 | Q85: =$G$85 -> 0 | R85: =$G$85 -> 0 | S85: =$G$85 -> 0 | T85: =$G$85 -> 0 | ... Y85: =$G$85 -> 0
B86: RENTA DE MAQUINARIA Y EQUIPO | C86: Generación | E86: 1 | F86: =+H86/$J$199 -> 63915 | G86: =F86 -> 63915 | H86: 1278300 | I86: =(E86*H86) -> 1278300 | J86: =I86*1.16 -> 1482828 | L86: 0 | M86: =$G$86 -> 63915 | N86: =$G$86 -> 63915 | O86: =$G$86 -> 63915 | P86: =$G$86 -> 63915 | Q86: =$G$86 -> 63915 | R86: =$G$86 -> 63915 | S86: =$G$86 -> 63915 | T86: =$G$86 -> 63915 | ... Y86: =$G$86 -> 63915
B87: RENTA DE SANITARIOS | C87: Sanitarios + Fosa + Recolección | E87: 1 | F87: =+H87/$J$199 -> 0 | G87: =F87 -> 0 | H87: 0 | I87: =(E87*H87) -> 0 | J87: =I87*1.16 -> 0 | L87: 0 | M87: =$G$87 -> 0 | N87: =$G$87 -> 0 | O87: =$G$87 -> 0 | P87: =$G$87 -> 0 | Q87: =$G$87 -> 0 | R87: =$G$87 -> 0 | S87: =$G$87 -> 0 | T87: =$G$87 -> 0 | ... Y87: =$G$87 -> 0
B88: REPARACIONES | E88: 1 | F88: =+H88/$J$199 -> 0 | G88: =F88 -> 0 | H88: 0 | I88: =(E88*H88) -> 0 | J88: =I88*1.16 -> 0 | L88: 0 | M88: =$G$88 -> 0 | N88: =$G$88 -> 0 | O88: =$G$88 -> 0 | P88: =$G$88 -> 0 | Q88: =$G$88 -> 0 | R88: =$G$88 -> 0 | S88: =$G$88 -> 0 | T88: =$G$88 -> 0 | ... Y88: =$G$88 -> 0
B89: SEGUROS | E89: 1 | F89: =+H89/$J$199 -> 0 | G89: =F89 -> 0 | H89: 0 | I89: =(E89*H89) -> 0 | J89: =I89*1.16 -> 0 | L89: 0 | M89: =$G$89 -> 0 | N89: =$G$89 -> 0 | O89: =$G$89 -> 0 | P89: =$G$89 -> 0 | Q89: =$G$89 -> 0 | R89: =$G$89 -> 0 | S89: =$G$89 -> 0 | T89: =$G$89 -> 0 | ... Y89: =$G$89 -> 0
B90: SERV DE DISEÑO Y ROTULACION | C90: Rotulación | E90: 1 | F90: =+H90/$J$199 -> 450 | G90: =F90 -> 450 | H90: 9000 | I90: =(E90*H90) -> 9000 | J90: =I90*1.16 -> 10440 | L90: 0 | M90: 0 | N90: =$G$90 -> 450 | O90: 0 | P90: 0 | Q90: 0 | R90: 0 | S90: 0 | T90: 0 | U90: 0 | V90: 0 | W90: 0 | X90: 0 | Y90: 0
B91: SERV DE DISPOS DE RESIDUOS | C91: Recolección de residuos | E91: 1 | F91: =+H91/$J$199 -> 250 | G91: =F91 -> 250 | H91: =60000/12 -> 5000 | I91: =(E91*H91) -> 5000 | J91: =I91*1.16 -> 5800 | L91: 0 | M91: =$G$91 -> 250 | N91: =$G$91 -> 250 | O91: =$G$91 -> 250 | P91: =$G$91 -> 250 | Q91: =$G$91 -> 250 | R91: =$G$91 -> 250 | S91: =$G$91 -> 250 | T91: =$G$91 -> 250 | ... Y91: =$G$91 -> 250
B92: SERV DE MANTO A INSTALACIONES (INSTALACIÓN | E92: 1 | F92: =+H92/$J$199 -> 0 | G92: =F92 -> 0 | H92: 0 | I92: =(E92*H92) -> 0 | J92: =I92*1.16 -> 0 | L92: 0 | M92: =$G$92 -> 0 | N92: =$G$92 -> 0 | O92: =$G$92 -> 0 | P92: =$G$92 -> 0 | Q92: =$G$92 -> 0 | R92: =$G$92 -> 0 | S92: =$G$92 -> 0 | T92: =$G$92 -> 0 | ... Y92: =$G$92 -> 0
B93: SERV DE RECARGA DE EXTINTORES | E93: 1 | F93: =+H93/$J$199 -> 12.5 | G93: =F93 -> 12.5 | H93: 250 | I93: =(E93*H93) -> 250 | J93: =I93*1.16 -> 290 | L93: 0 | M93: =$G$93 -> 12.5 | N93: =$G$93 -> 12.5 | O93: =$G$93 -> 12.5 | P93: =$G$93 -> 12.5 | Q93: =$G$93 -> 12.5 | R93: =$G$93 -> 12.5 | S93: =$G$93 -> 12.5 | T93: =$G$93 -> 12.5 | ... Y93: =$G$93 -> 12.5
B94: SERV DE TRANSMISION DE DATOS | C94: Telemetría por tercero | E94: 1 | F94: =+H94/$J$199 -> 0 | G94: =F94 -> 0 | H94: 0 | I94: =(E94*H94) -> 0 | J94: =I94*1.16 -> 0 | L94: 0 | M94: =$G$94 -> 0 | N94: =$G$94 -> 0 | O94: =$G$94 -> 0 | P94: =$G$94 -> 0 | Q94: =$G$94 -> 0 | R94: =$G$94 -> 0 | S94: =$G$94 -> 0 | T94: =$G$94 -> 0 | ... Y94: =$G$94 -> 0
B95: SERV PROFES DE PERSONA MORAL | E95: 1 | F95: =+H95/$J$199 -> 0 | G95: =F95 -> 0 | H95: 0 | I95: =(E95*H95) -> 0 | J95: =I95*1.16 -> 0 | L95: 0 | M95: =$G$95 -> 0 | N95: =$G$95 -> 0 | O95: =$G$95 -> 0 | P95: =$G$95 -> 0 | Q95: =$G$95 -> 0 | R95: =$G$95 -> 0 | S95: =$G$95 -> 0 | T95: =$G$95 -> 0 | ... Y95: =$G$95 -> 0
B96: SERV Y MANTTO A EQ INFORMATICO | E96: 1 | F96: =+H96/$J$199 -> 0 | G96: =F96 -> 0 | H96: 0 | I96: =(E96*H96) -> 0 | J96: =I96*1.16 -> 0 | L96: 0 | M96: =$G$96 -> 0 | N96: =$G$96 -> 0 | O96: =$G$96 -> 0 | P96: =$G$96 -> 0 | Q96: =$G$96 -> 0 | R96: =$G$96 -> 0 | S96: =$G$96 -> 0 | T96: =$G$96 -> 0 | ... Y96: =$G$96 -> 0
B97: SERVICIO DE AUTOLAVADO | C97: Unidad vehicular | E97: 1 | F97: =+H97/$J$199 -> 20 | G97: =F97 -> 20 | H97: 400 | I97: =(E97*H97) -> 400 | J97: =I97*1.16 -> 464 | L97: 0 | M97: =$G$97 -> 20 | N97: =$G$97 -> 20 | O97: =$G$97 -> 20 | P97: =$G$97 -> 20 | Q97: =$G$97 -> 20 | R97: =$G$97 -> 20 | S97: =$G$97 -> 20 | T97: =$G$97 -> 20 | ... Y97: =$G$97 -> 20
B98: SERVICIO DE EQPO Y MAQUINARIA | E98: 1 | F98: =+H98/$J$199 -> 0 | G98: =F98 -> 0 | H98: 0 | I98: =(E98*H98) -> 0 | J98: =I98*1.16 -> 0 | L98: 0 | M98: =$G$98 -> 0 | N98: =$G$98 -> 0 | O98: =$G$98 -> 0 | P98: =$G$98 -> 0 | Q98: =$G$98 -> 0 | R98: =$G$98 -> 0 | S98: =$G$98 -> 0 | T98: =$G$98 -> 0 | ... Y98: =$G$98 -> 0
B99: SERVICIO REPRESENTACION LEGAL | E99: 1 | F99: =+H99/$J$199 -> 0 | G99: =F99 -> 0 | H99: 0 | I99: =(E99*H99) -> 0 | J99: =I99*1.16 -> 0 | L99: 0 | M99: =$G$99 -> 0 | N99: =$G$99 -> 0 | O99: =$G$99 -> 0 | P99: =$G$99 -> 0 | Q99: =$G$99 -> 0 | R99: =$G$99 -> 0 | S99: =$G$99 -> 0 | T99: =$G$99 -> 0 | ... Y99: =$G$99 -> 0
B100: SERVICIOS DE BANQUETERIA | E100: 1 | F100: =+H100/$J$199 -> 0 | G100: =F100 -> 0 | H100: 0 | I100: =(E100*H100) -> 0 | J100: =I100*1.16 -> 0 | L100: 0 | M100: =$G$100 -> 0 | N100: =$G$100 -> 0 | O100: =$G$100 -> 0 | P100: =$G$100 -> 0 | Q100: =$G$100 -> 0 | R100: =$G$100 -> 0 | S100: =$G$100 -> 0 | T100: =$G$100 -> 0 | ... Y100: =$G$100 -> 0
B101: SERVICIOS DE COPIADO | E101: 1 | F101: =+H101/$J$199 -> 0 | G101: =F101 -> 0 | H101: 0 | I101: =(E101*H101) -> 0 | J101: =I101*1.16 -> 0 | L101: 0 | M101: =$G$101 -> 0 | N101: =$G$101 -> 0 | O101: =$G$101 -> 0 | P101: =$G$101 -> 0 | Q101: =$G$101 -> 0 | R101: =$G$101 -> 0 | S101: =$G$101 -> 0 | T101: =$G$101 -> 0 | ... Y101: =$G$101 -> 0
B102: SERVICIOS DE TAXI | E102: 1 | F102: =+H102/$J$199 -> 0 | G102: =F102 -> 0 | H102: 0 | I102: =(E102*H102) -> 0 | J102: =I102*1.16 -> 0 | L102: 0 | M102: =$G$102 -> 0 | N102: =$G$102 -> 0 | O102: =$G$102 -> 0 | P102: =$G$102 -> 0 | Q102: =$G$102 -> 0 | R102: =$G$102 -> 0 | S102: =$G$102 -> 0 | T102: =$G$102 -> 0 | ... Y102: =$G$102 -> 0
B103: SERVICIOS PREOPERATIVOS | E103: 1 | F103: =+H103/$J$199 -> 0 | G103: =F103 -> 0 | H103: 0 | I103: =(E103*H103) -> 0 | J103: =I103*1.16 -> 0 | L103: 0 | M103: =$G$103 -> 0 | N103: =$G$103 -> 0 | O103: =$G$103 -> 0 | P103: =$G$103 -> 0 | Q103: =$G$103 -> 0 | R103: =$G$103 -> 0 | S103: =$G$103 -> 0 | T103: =$G$103 -> 0 | ... Y103: =$G$103 -> 0
B104: SERVICIOS RADIOGRAFICOS | E104: 1 | F104: =+H104/$J$199 -> 0 | G104: =F104 -> 0 | H104: 0 | I104: =(E104*H104) -> 0 | J104: =I104*1.16 -> 0 | L104: 0 | M104: =$G$104 -> 0 | N104: =$G$104 -> 0 | O104: =$G$104 -> 0 | P104: =$G$104 -> 0 | Q104: =$G$104 -> 0 | R104: =$G$104 -> 0 | S104: =$G$104 -> 0 | T104: =$G$104 -> 0 | ... Y104: =$G$104 -> 0
B105: TENENCIA | E105: 1 | F105: =+H105/$J$199 -> 0 | G105: =F105 -> 0 | H105: 0 | I105: =(E105*H105) -> 0 | J105: =I105*1.16 -> 0 | L105: 0 | M105: =$G$105 -> 0 | N105: =$G$105 -> 0 | O105: =$G$105 -> 0 | P105: =$G$105 -> 0 | Q105: =$G$105 -> 0 | R105: =$G$105 -> 0 | S105: =$G$105 -> 0 | T105: =$G$105 -> 0 | ... Y105: =$G$105 -> 0
B106: TOPOGRAFIA | E106: 1 | F106: =+H106/$J$199 -> 0 | G106: =F106 -> 0 | H106: 0 | I106: =(E106*H106) -> 0 | J106: =I106*1.16 -> 0 | L106: 0 | M106: =$G$106 -> 0 | N106: =$G$106 -> 0 | O106: =$G$106 -> 0 | P106: =$G$106 -> 0 | Q106: =$G$106 -> 0 | R106: =$G$106 -> 0 | S106: =$G$106 -> 0 | T106: =$G$106 -> 0 | ... Y106: =$G$106 -> 0
B107: VERIFICACIONES | E107: 1 | F107: =+H107/$J$199 -> 0 | G107: =F107 -> 0 | H107: 0 | I107: =(E107*H107) -> 0 | J107: =I107*1.16 -> 0 | L107: 0 | M107: =$G$107 -> 0 | N107: =$G$107 -> 0 | O107: =$G$107 -> 0 | P107: =$G$107 -> 0 | Q107: =$G$107 -> 0 | R107: =$G$107 -> 0 | S107: =$G$107 -> 0 | T107: =$G$107 -> 0 | ... Y107: =$G$107 -> 0
B108: ASESORIA ESPECIAL INTERNA | C108: Acesoria | E108: 1 | F108: =+H108/$J$199 -> 5000 | G108: =F108 -> 5000 | H108: 100000 | I108: =(E108*H108) -> 100000 | J108: =I108*1.16 -> 116000 | L108: 0 | M108: =$G$108 -> 5000 | N108: =$G$108 -> 5000 | O108: =$G$108 -> 5000 | P108: =$G$108 -> 5000 | Q108: =$G$108 -> 5000 | R108: =$G$108 -> 5000 | S108: =$G$108 -> 5000 | T108: =$G$108 -> 5000 | ... Y108: =$G$108 -> 5000
B109: ASESORIA ESPECIAL OPERATIVA | C109: Sindicato | E109: 1 | F109: =+H109/$J$199 -> 900 | G109: =F109 -> 900 | H109: 18000 | I109: =(E109*H109) -> 18000 | J109: =I109*1.16 -> 20880 | L109: 0 | M109: =$G$109 -> 900 | N109: =$G$109 -> 900 | O109: =$G$109 -> 900 | P109: =$G$109 -> 900 | Q109: =$G$109 -> 900 | R109: =$G$109 -> 900 | S109: =$G$109 -> 900 | T109: =$G$109 -> 900 | ... Y109: =$G$109 -> 900
...

Sheet Hoja1

Sheet Hoja2
