Workbook
Name Departamentos: '[1]BD Competencias'!$F$14:$F$41
Name Departamentos: '[2]BD Competencias'!$F$14:$F$41
Name Display_Week: [3]ProjectSchedule!$I$3
Name Project_Start: [3]ProjectSchedule!$I$2

Sheet SERVICIO
A1: GEOLIS SA DE CV
A2: Proyecto: Cambio de servicio Perdiz - Papan
A3: INGRESOS 2022 MXN | E3: M 1 | F3: M 2 | G3: M 3 | H3: M 4 | I3: M 5 | J3: M 6 | K3: M 7 | L3: M 8 | M3: M 9 | N3: M 10 | O3: M 11 | P3: M 12
A4: Descripcion | B4: Total Presupuestado | C4: Instalación | D4: Instalación | E4: Enero | F4: Febrero | G4: Marzo | H4: Abril | I4: Mayo | J4: Junio | K4: Julio | L4: Agosto | M4: Septiembre | N4: Octubre | O4: Noviembre | P4: Diciembre | Q4: Meses
A5: FACTURACION | B5: =SUM(C5:P5) -> 75320045 | C5: ='F08 INGRESOS'!M16 -> 17783233 | D5: ='F08 INGRESOS'!N16 -> 57536812 | E5: ='F08 INGRESOS'!O16 -> 0 | F5: ='F08 INGRESOS'!P16 -> 0 | G5: ='F08 INGRESOS'!Q16 -> 0 | H5: ='F08 INGRESOS'!R16 -> 0 | I5: ='F08 INGRESOS'!S16 -> 0 | J5: ='F08 INGRESOS'!T16 -> 0 | ... P5: ='F08 INGRESOS'!Z16 -> 0 | Q5: =COUNTA(E4:P4) -> 12
A6: EGRESOS 2024
A7: Descripcion | B7: Total Presupuestado | C7: - | D7: - | E7: Enero | F7: Febrero | G7: Marzo | H7: Abril | I7: Mayo | J7: Junio | K7: Julio | L7: Agosto | M7: Septiembre | N7: Octubre | O7: Noviembre | P7: Diciembre
A8: EQUIPO DE TRANSPORTE | B8: =SUM(C8:P8) -> 0 | C8: ='F00 INVERSIÓN'!L12 -> 0 | D8: ='F00 INVERSIÓN'!M12 -> 0 | E8: ='F00 INVERSIÓN'!N12 -> 0 | F8: ='F00 INVERSIÓN'!O12 -> 0 | G8: ='F00 INVERSIÓN'!P12 -> 0 | H8: ='F00 INVERSIÓN'!Q12 -> 0 | I8: ='F00 INVERSIÓN'!R12 -> 0 | J8: ='F00 INVERSIÓN'!S12 -> 0 | ... P8: ='F00 INVERSIÓN'!Y12 -> 0 | Q8: =B8/$B$162 -> 0
A9: EQUIPO DE MOBILIARIO | B9: =SUM(C9:P9) -> 0 | C9: ='F00 INVERSIÓN'!L18 -> 0 | D9: ='F00 INVERSIÓN'!M18 -> 0 | E9: ='F00 INVERSIÓN'!N18 -> 0 | F9: ='F00 INVERSIÓN'!O18 -> 0 | G9: ='F00 INVERSIÓN'!P18 -> 0 | H9: ='F00 INVERSIÓN'!Q18 -> 0 | I9: ='F00 INVERSIÓN'!R18 -> 0 | J9: ='F00 INVERSIÓN'!S18 -> 0 | ... P9: ='F00 INVERSIÓN'!Y18 -> 0 | Q9: =B9/$B$162 -> 0
A10: MAQUINARIA Y EQUIPO | B10: =SUM(C10:P10) -> 0 | C10: ='F00 INVERSIÓN'!L28 -> 0 | D10: ='F00 INVERSIÓN'!M28 -> 0 | E10: ='F00 INVERSIÓN'!N28 -> 0 | F10: ='F00 INVERSIÓN'!O28 -> 0 | G10: ='F00 INVERSIÓN'!P28 -> 0 | H10: ='F00 INVERSIÓN'!Q28 -> 0 | I10: ='F00 INVERSIÓN'!R28 -> 0 | J10: ='F00 INVERSIÓN'!S28 -> 0 | ... P10: ='F00 INVERSIÓN'!Y28 -> 0 | Q10: =B10/$B$162 -> 0
A11: OTROS ACTIVOS | B11: =SUM(C11:P11) -> 16714398 | C11: ='F00 INVERSIÓN'!L35 -> 16714398 | D11: ='F00 INVERSIÓN'!M35 -> 0 | E11: ='F00 INVERSIÓN'!N35 -> 0 | F11: ='F00 INVERSIÓN'!O35 -> 0 | G11: ='F00 INVERSIÓN'!P35 -> 0 | H11: ='F00 INVERSIÓN'!Q35 -> 0 | I11: ='F00 INVERSIÓN'!R35 -> 0 | J11: ='F00 INVERSIÓN'!S35 -> 0 | ... P11: ='F00 INVERSIÓN'!Y35 -> 0 | Q11: =B11/$B$162 -> 0.71848475
A12: SOFTWARE Y LICICENCIAS | B12: =SUM(C12:P12) -> 0 | C12: ='F00 INVERSIÓN'!L41 -> 0 | D12: ='F00 INVERSIÓN'!M41 -> 0 | E12: ='F00 INVERSIÓN'!N41 -> 0 | F12: ='F00 INVERSIÓN'!O41 -> 0 | G12: ='F00 INVERSIÓN'!P41 -> 0 | H12: ='F00 INVERSIÓN'!Q41 -> 0 | I12: ='F00 INVERSIÓN'!R41 -> 0 | J12: ='F00 INVERSIÓN'!S41 -> 0 | ... P12: ='F00 INVERSIÓN'!Y41 -> 0 | Q12: =B12/$B$162 -> 0
A13: ACTIVOS | B13: =SUM(B8:B12) -> 16714398 | C13: =SUM(C8:C12) -> 16714398 | D13: =SUM(D8:D12) -> 0 | E13: =SUM(E8:E12) -> 0 | F13: =SUM(F8:F12) -> 0 | G13: =SUM(G8:G12) -> 0 | H13: =SUM(H8:H12) -> 0 | I13: =SUM(I8:I12) -> 0 | ... P13: =SUM(P8:P12) -> 0 | Q13: =B13/$B$162 -> 0.71848475
A14: ARRENDAMIENTO DE INMUEBLES | B14: =SUM(C14:P14) -> 0 | C14: ='F02 INMUEBLES Y S'!N8 -> 0 | D14: ='F02 INMUEBLES Y S'!O8 -> 0 | E14: ='F02 INMUEBLES Y S'!P8 -> 0 | F14: ='F02 INMUEBLES Y S'!Q8 -> 0 | G14: ='F02 INMUEBLES Y S'!R8 -> 0 | H14: ='F02 INMUEBLES Y S'!S8 -> 0 | I14: ='F02 INMUEBLES Y S'!T8 -> 0 | J14: ='F02 INMUEBLES Y S'!U8 -> 0 | ... P14: ='F02 INMUEBLES Y S'!AA8 -> 0 | Q14: =B14/$B$162 -> 0
A15: ENERGIA ELECTRICA | B15: =SUM(C15:P15) -> 0 | C15: ='F02 INMUEBLES Y S'!N9 -> 0 | D15: ='F02 INMUEBLES Y S'!O9 -> 0 | E15: ='F02 INMUEBLES Y S'!P9 -> 0 | F15: ='F02 INMUEBLES Y S'!Q9 -> 0 | G15: ='F02 INMUEBLES Y S'!R9 -> 0 | H15: ='F02 INMUEBLES Y S'!S9 -> 0 | I15: ='F02 INMUEBLES Y S'!T9 -> 0 | J15: ='F02 INMUEBLES Y S'!U9 -> 0 | ... P15: ='F02 INMUEBLES Y S'!AA9 -> 0 | Q15: =B15/$B$162 -> 0
A16: RENTA DE CASAS NO DEDUCIBLE | B16: =SUM(C16:P16) -> 0 | C16: ='F02 INMUEBLES Y S'!N10 -> 0 | D16: ='F02 INMUEBLES Y S'!O10 -> 0 | E16: ='F02 INMUEBLES Y S'!P10 -> 0 | F16: ='F02 INMUEBLES Y S'!Q10 -> 0 | G16: ='F02 INMUEBLES Y S'!R10 -> 0 | H16: ='F02 INMUEBLES Y S'!S10 -> 0 | I16: ='F02 INMUEBLES Y S'!T10 -> 0 | J16: ='F02 INMUEBLES Y S'!U10 -> 0 | ... P16: ='F02 INMUEBLES Y S'!AA10 -> 0 | Q16: =B16/$B$162 -> 0
A17: SERVICIOS DE LIMPIEZA | B17: =SUM(C17:P17) -> 0 | C17: ='F02 INMUEBLES Y S'!N11 -> 0 | D17: ='F02 INMUEBLES Y S'!O11 -> 0 | E17: ='F02 INMUEBLES Y S'!P11 -> 0 | F17: ='F02 INMUEBLES Y S'!Q11 -> 0 | G17: ='F02 INMUEBLES Y S'!R11 -> 0 | H17: ='F02 INMUEBLES Y S'!S11 -> 0 | I17: ='F02 INMUEBLES Y S'!T11 -> 0 | J17: ='F02 INMUEBLES Y S'!U11 -> 0 | ... P17: ='F02 INMUEBLES Y S'!AA11 -> 0 | Q17: =B17/$B$162 -> 0
A18: SERVICIOS DE VIGILANCIA | B18: =SUM(C18:P18) -> 0 | C18: ='F02 INMUEBLES Y S'!N12 -> 0 | D18: ='F02 INMUEBLES Y S'!O12 -> 0 | E18: ='F02 INMUEBLES Y S'!P12 -> 0 | F18: ='F02 INMUEBLES Y S'!Q12 -> 0 | G18: ='F02 INMUEBLES Y S'!R12 -> 0 | H18: ='F02 INMUEBLES Y S'!S12 -> 0 | I18: ='F02 INMUEBLES Y S'!T12 -> 0 | J18: ='F02 INMUEBLES Y S'!U12 -> 0 | ... P18: ='F02 INMUEBLES Y S'!AA12 -> 0 | Q18: =B18/$B$162 -> 0
A19: SERVICIOS DE FUMIGACION | B19: =SUM(C19:P19) -> 0 | C19: ='F02 INMUEBLES Y S'!N13 -> 0 | D19: ='F02 INMUEBLES Y S'!O13 -> 0 | E19: ='F02 INMUEBLES Y S'!P13 -> 0 | F19: ='F02 INMUEBLES Y S'!Q13 -> 0 | G19: ='F02 INMUEBLES Y S'!R13 -> 0 | H19: ='F02 INMUEBLES Y S'!S13 -> 0 | I19: ='F02 INMUEBLES Y S'!T13 -> 0 | J19: ='F02 INMUEBLES Y S'!U13 -> 0 | ... P19: ='F02 INMUEBLES Y S'!AA13 -> 0 | Q19: =B19/$B$162 -> 0
A20: TELEFONIA FIJA | B20: =SUM(C20:P20) -> 0 | C20: ='F02 INMUEBLES Y S'!N14 -> 0 | D20: ='F02 INMUEBLES Y S'!O14 -> 0 | E20: ='F02 INMUEBLES Y S'!P14 -> 0 | F20: ='F02 INMUEBLES Y S'!Q14 -> 0 | G20: ='F02 INMUEBLES Y S'!R14 -> 0 | H20: ='F02 INMUEBLES Y S'!S14 -> 0 | I20: ='F02 INMUEBLES Y S'!T14 -> 0 | J20: ='F02 INMUEBLES Y S'!U14 -> 0 | ... P20: ='F02 INMUEBLES Y S'!AA14 -> 0 | Q20: =B20/$B$162 -> 0
A21: AGUA Y ALCANTARILLADO | B21: =SUM(C21:P21) -> 0 | C21: ='F02 INMUEBLES Y S'!N15 -> 0 | D21: ='F02 INMUEBLES Y S'!O15 -> 0 | E21: ='F02 INMUEBLES Y S'!P15 -> 0 | F21: ='F02 INMUEBLES Y S'!Q15 -> 0 | G21: ='F02 INMUEBLES Y S'!R15 -> 0 | H21: ='F02 INMUEBLES Y S'!S15 -> 0 | I21: ='F02 INMUEBLES Y S'!T15 -> 0 | J21: ='F02 INMUEBLES Y S'!U15 -> 0 | ... P21: ='F02 INMUEBLES Y S'!AA15 -> 0 | Q21: =B21/$B$162 -> 0
A22: ARRENDAMIENTO DE OF. MOVILES | B22: =SUM(C22:P22) -> 0 | C22: ='F02 INMUEBLES Y S'!N16 -> 0 | D22: ='F02 INMUEBLES Y S'!O16 -> 0 | E22: ='F02 INMUEBLES Y S'!P16 -> 0 | F22: ='F02 INMUEBLES Y S'!Q16 -> 0 | G22: ='F02 INMUEBLES Y S'!R16 -> 0 | H22: ='F02 INMUEBLES Y S'!S16 -> 0 | I22: ='F02 INMUEBLES Y S'!T16 -> 0 | J22: ='F02 INMUEBLES Y S'!U16 -> 0 | ... P22: ='F02 INMUEBLES Y S'!AA16 -> 0 | Q22: =B22/$B$162 -> 0
A23: ARRENDA DE INMUEBLES Y SERV | B23: =SUM(B14:B22) -> 0 | C23: =SUM(C14:C22) -> 0 | D23: =SUM(D14:D22) -> 0 | E23: =SUM(E14:E22) -> 0 | F23: =SUM(F14:F22) -> 0 | G23: =SUM(G14:G22) -> 0 | H23: =SUM(H14:H22) -> 0 | I23: =SUM(I14:I22) -> 0 | ... P23: =SUM(P14:P22) -> 0 | Q23: =B23/$B$162 -> 0
A24: ROPA Y ARTICULOS DE PROTECCION | B24: =SUM(C24:P24) -> 233794.18 | C24: ='F01 EPP'!M19 -> 233794.18 | D24: ='F01 EPP'!N19 -> 0 | E24: ='F01 EPP'!O19 -> 0 | F24: ='F01 EPP'!P19 -> 0 | G24: ='F01 EPP'!Q19 -> 0 | H24: ='F01 EPP'!R19 -> 0 | I24: ='F01 EPP'!S19 -> 0 | J24: ='F01 EPP'!T19 -> 0 | ... P24: ='F01 EPP'!Z19 -> 0 | Q24: =B24/$B$162 -> 0.010049872
A25: ARTICULOS DE SEGURIDAD | B25: =B24 -> 233794.18 | C25: =C24 -> 233794.18 | D25: =D24 -> 0 | E25: =E24 -> 0 | F25: =F24 -> 0 | G25: =G24 -> 0 | H25: =H24 -> 0 | I25: =I24 -> 0 | ... P25: =P24 -> 0 | Q25: =B25/$B$162 -> 0.010049872
A26: EQUIPO DE COMPUTO (Adquisición) | B26: =SUM(C26:P26) -> 32526 | C26: ='F03 COM Y EQ COM'!L45 -> 0 | D26: ='F03 COM Y EQ COM'!M45 -> 32526 | E26: ='F03 COM Y EQ COM'!N45 -> 0 | F26: ='F03 COM Y EQ COM'!O45 -> 0 | G26: ='F03 COM Y EQ COM'!P45 -> 0 | H26: ='F03 COM Y EQ COM'!Q45 -> 0 | I26: ='F03 COM Y EQ COM'!R45 -> 0 | J26: ='F03 COM Y EQ COM'!S45 -> 0 | ... P26: ='F03 COM Y EQ COM'!Y45 -> 0 | Q26: =B26/$B$162 -> 0.001398162
A27: ARRENDAMIENTO DE EQ. COMPUTO | B27: =SUM(C27:P27) -> 0 | C27: ='F03 COM Y EQ COM'!L46 -> 0 | D27: ='F03 COM Y EQ COM'!M46 -> 0 | E27: ='F03 COM Y EQ COM'!N46 -> 0 | F27: ='F03 COM Y EQ COM'!O46 -> 0 | G27: ='F03 COM Y EQ COM'!P46 -> 0 | H27: ='F03 COM Y EQ COM'!Q46 -> 0 | I27: ='F03 COM Y EQ COM'!R46 -> 0 | J27: ='F03 COM Y EQ COM'!S46 -> 0 | ... P27: ='F03 COM Y EQ COM'!Y46 -> 0 | Q27: =B27/$B$162 -> 0
A28: EQUIPO DE COMPUTO | B28: =SUM(B26:B27) -> 32526 | C28: =SUM(C26:C27) -> 0 | D28: =SUM(D26:D27) -> 32526 | E28: =SUM(E26:E27) -> 0 | F28: =SUM(F26:F27) -> 0 | G28: =SUM(G26:G27) -> 0 | H28: =SUM(H26:H27) -> 0 | I28: =SUM(I26:I27) -> 0 | ... P28: =SUM(P26:P27) -> 0 | Q28: =B28/$B$162 -> 0.001398162
A29: ENSERES MENORES DIVERSOS (Acondicionamiento de casas) | B29: =SUM(C29:P29) -> 10057.52 | C29: ='F07 OPERAC. (MAT,SERV & EQUIPO)'!L17 -> 5028.76 | D29: ='F07 OPERAC. (MAT,SERV & EQUIPO)'!M17 -> 5028.76 | E29: ='F07 OPERAC. (MAT,SERV & EQUIPO)'!N17 -> 0 | F29: ='F07 OPERAC. (MAT,SERV & EQUIPO)'!O17 -> 0 | G29: ='F07 OPERAC. (MAT,SERV & EQUIPO)'!P17 -> 0 | H29: ='F07 OPERAC. (MAT,SERV & EQUIPO)'!Q17 -> 0 | I29: ='F07 OPERAC. (MAT,SERV & EQUIPO)'!R17 -> 0 | J29: ='F07 OPERAC. (MAT,SERV & EQUIPO)'!S17 -> 0 | ... P29: ='F07 OPERAC. (MAT,SERV & EQUIPO)'!Y17 -> 0 | Q29: =B29/$B$162 -> 0.00043233235
A30: EQUIPOS Y ENSERES | B30: =B29 -> 10057.52 | C30: =C29 -> 5028.76 | D30: =D29 -> 5028.76 | E30: =E29 -> 0 | F30: =F29 -> 0 | G30: =G29 -> 0 | H30: =H29 -> 0 | I30: =I29 -> 0 | ... P30: =P29 -> 0 | Q30: =B30/$B$162 -> 0.00043233235
A31: INSUMOS AGRICOLAS | B31: =SUM(C31:P31) -> 0 | C31: ='F07 OPERAC. (MAT,SERV & EQUIPO)'!L39 -> 0 | D31: ='F07 OPERAC. (MAT,SERV & EQUIPO)'!M39 -> 0 | E31: ='F07 OPERAC. (MAT,SERV & EQUIPO)'!N39 -> 0 | F31: ='F07 OPERAC. (MAT,SERV & EQUIPO)'!O39 -> 0 | G31: ='F07 OPERAC. (MAT,SERV & EQUIPO)'!P39 -> 0 | H31: ='F07 OPERAC. (MAT,SERV & EQUIPO)'!Q39 -> 0 | I31: ='F07 OPERAC. (MAT,SERV & EQUIPO)'!R39 -> 0 | J31: ='F07 OPERAC. (MAT,SERV & EQUIPO)'!S39 -> 0 | ... P31: ='F07 OPERAC. (MAT,SERV & EQUIPO)'!Y39 -> 0 | Q31: =B31/$B$162 -> 0
A32: PAPELERIA Y UTILES DE OFICINA | B32: =SUM(C32:P32) -> 0 | C32: ='F07 OPERAC. (MAT,SERV & EQUIPO)'!L126 -> 0 | D32: ='F07 OPERAC. (MAT,SERV & EQUIPO)'!M126 -> 0 | E32: ='F07 OPERAC. (MAT,SERV & EQUIPO)'!N126 -> 0 | F32: ='F07 OPERAC. (MAT,SERV & EQUIPO)'!O126 -> 0 | G32: ='F07 OPERAC. (MAT,SERV & EQUIPO)'!P126 -> 0 | H32: ='F07 OPERAC. (MAT,SERV & EQUIPO)'!Q126 -> 0 | I32: ='F07 OPERAC. (MAT,SERV & EQUIPO)'!R126 -> 0 | J32: ='F07 OPERAC. (MAT,SERV & EQUIPO)'!S126 -> 0 | ... P32: ='F07 OPERAC. (MAT,SERV & EQUIPO)'!Y126 -> 0 | Q32: =B32/$B$162 -> 0
A33: ARTICULOS DE ASEO Y SANITARIOS | B33: =SUM(C33:P33) -> 0 | C33: ='F07 OPERAC. (MAT,SERV & EQUIPO)'!L127 -> 0 | D33: ='F07 OPERAC. (MAT,SERV & EQUIPO)'!M127 -> 0 | E33: ='F07 OPERAC. (MAT,SERV & EQUIPO)'!N127 -> 0 | F33: ='F07 OPERAC. (MAT,SERV & EQUIPO)'!O127 -> 0 | G33: ='F07 OPERAC. (MAT,SERV & EQUIPO)'!P127 -> 0 | H33: ='F07 OPERAC. (MAT,SERV & EQUIPO)'!Q127 -> 0 | I33: ='F07 OPERAC. (MAT,SERV & EQUIPO)'!R127 -> 0 | J33: ='F07 OPERAC. (MAT,SERV & EQUIPO)'!S127 -> 0 | ... P33: ='F07 OPERAC. (MAT,SERV & EQUIPO)'!Y127 -> 0 | Q33: =B33/$B$162 -> 0
A34: ARTICULOS DE CAFETERIA | B34: =SUM(C34:P34) -> 0 | C34: ='F07 OPERAC. (MAT,SERV & EQUIPO)'!L128 -> 0 | D34: ='F07 OPERAC. (MAT,SERV & EQUIPO)'!M128 -> 0 | E34: ='F07 OPERAC. (MAT,SERV & EQUIPO)'!N128 -> 0 | F34: ='F07 OPERAC. (MAT,SERV & EQUIPO)'!O128 -> 0 | G34: ='F07 OPERAC. (MAT,SERV & EQUIPO)'!P128 -> 0 | H34: ='F07 OPERAC. (MAT,SERV & EQUIPO)'!Q128 -> 0 | I34: ='F07 OPERAC. (MAT,SERV & EQUIPO)'!R128 -> 0 | J34: ='F07 OPERAC. (MAT,SERV & EQUIPO)'!S128 -> 0 | ... P34: ='F07 OPERAC. (MAT,SERV & EQUIPO)'!Y128 -> 0 | Q34: =B34/$B$162 -> 0
A35: ARTICULOS DIGITALES Y DE COMPUTO | B35: =SUM(C35:P35) -> 0 | C35: ='F07 OPERAC. (MAT,SERV & EQUIPO)'!L129 -> 0 | D35: ='F07 OPERAC. (MAT,SERV & EQUIPO)'!M129 -> 0 | E35: ='F07 OPERAC. (MAT,SERV & EQUIPO)'!N129 -> 0 | F35: ='F07 OPERAC. (MAT,SERV & EQUIPO)'!O129 -> 0 | G35: ='F07 OPERAC. (MAT,SERV & EQUIPO)'!P129 -> 0 | H35: ='F07 OPERAC. (MAT,SERV & EQUIPO)'!Q129 -> 0 | I35: ='F07 OPERAC. (MAT,SERV & EQUIPO)'!R129 -> 0 | J35: ='F07 OPERAC. (MAT,SERV & EQUIPO)'!S129 -> 0 | ... P35: ='F07 OPERAC. (MAT,SERV & EQUIPO)'!Y129 -> 0 | Q35: =B35/$B$162 -> 0
A36: INSUMOS DE OFICINA | B36: =SUM(B32:B35) -> 0 | C36: =SUM(C32:C35) -> 0 | D36: =SUM(D32:D35) -> 0 | E36: =SUM(E32:E35) -> 0 | F36: =SUM(F32:F35) -> 0 | G36: =SUM(G32:G35) -> 0 | H36: =SUM(H32:H35) -> 0 | I36: =SUM(I32:I35) -> 0 | ... P36: =SUM(P32:P35) -> 0 | Q36: =B36/$B$162 -> 0
A37: SERVICIOS DE MERCADOTECNIA | B37: =SUM(C37:P37) -> 0 | C37: ='F07 OPERAC. (MAT,SERV & EQUIPO)'!L140 -> 0 | D37: ='F07 OPERAC. (MAT,SERV & EQUIPO)'!M140 -> 0 | E37: ='F07 OPERAC. (MAT,SERV & EQUIPO)'!N140 -> 0 | F37: ='F07 OPERAC. (MAT,SERV & EQUIPO)'!O140 -> 0 | G37: ='F07 OPERAC. (MAT,SERV & EQUIPO)'!P140 -> 0 | H37: ='F07 OPERAC. (MAT,SERV & EQUIPO)'!Q140 -> 0 | I37: ='F07 OPERAC. (MAT,SERV & EQUIPO)'!R140 -> 0 | J37: ='F07 OPERAC. (MAT,SERV & EQUIPO)'!S140 -> 0 | ... P37: ='F07 OPERAC. (MAT,SERV & EQUIPO)'!Y140 -> 0 | Q37: =B37/$B$162 -> 0
A38: PUBLICIDAD Y PROPAGANDA | B38: =SUM(C38:P38) -> 0 | C38: ='F07 OPERAC. (MAT,SERV & EQUIPO)'!L141 -> 0 | D38: ='F07 OPERAC. (MAT,SERV & EQUIPO)'!M141 -> 0 | E38: ='F07 OPERAC. (MAT,SERV & EQUIPO)'!N141 -> 0 | F38: ='F07 OPERAC. (MAT,SERV & EQUIPO)'!O141 -> 0 | G38: ='F07 OPERAC. (MAT,SERV & EQUIPO)'!P141 -> 0 | H38: ='F07 OPERAC. (MAT,SERV & EQUIPO)'!Q141 -> 0 | I38: ='F07 OPERAC. (MAT,SERV & EQUIPO)'!R141 -> 0 | J38: ='F07 OPERAC. (MAT,SERV & EQUIPO)'!S141 -> 0 | ... P38: ='F07 OPERAC. (MAT,SERV & EQUIPO)'!Y141 -> 0 | Q38: =B38/$B$162 -> 0
A39: MARKETING | B39: =SUM(B37:B38) -> 0 | C39: =SUM(C37:C38) -> 0 | D39: =SUM(D37:D38) -> 0 | E39: =SUM(E37:E38) -> 0 | F39: =SUM(F37:F38) -> 0 | G39: =SUM(G37:G38) -> 0 | H39: =SUM(H37:H38) -> 0 | I39: =SUM(I37:I38) -> 0 | ... P39: =SUM(P37:P38) -> 0 | Q39: =B39/$B$162 -> 0
A40: ABRASIVOS | B40: =SUM(C40:P40) -> 20997.34 | C40: ='F06 (MAT,SERV & EQUIPO)'!M8 -> 10498.67 | D40: ='F06 (MAT,SERV & EQUIPO)'!N8 -> 10498.67 | E40: ='F06 (MAT,SERV & EQUIPO)'!O8 -> 0 | F40: ='F06 (MAT,SERV & EQUIPO)'!P8 -> 0 | G40: ='F06 (MAT,SERV & EQUIPO)'!Q8 -> 0 | H40: ='F06 (MAT,SERV & EQUIPO)'!R8 -> 0 | I40: ='F06 (MAT,SERV & EQUIPO)'!S8 -> 0 | J40: ='F06 (MAT,SERV & EQUIPO)'!T8 -> 0 | ... P40: ='F06 (MAT,SERV & EQUIPO)'!Z8 -> 0 | Q40: =B40/$B$162 -> 0.00090259122
A41: ACEITE LUBRICANTE P/MAQUINARIA | B41: =SUM(C41:P41) -> 0 | C41: ='F06 (MAT,SERV & EQUIPO)'!M9 -> 0 | D41: ='F06 (MAT,SERV & EQUIPO)'!N9 -> 0 | E41: ='F06 (MAT,SERV & EQUIPO)'!O9 -> 0 | F41: ='F06 (MAT,SERV & EQUIPO)'!P9 -> 0 | G41: ='F06 (MAT,SERV & EQUIPO)'!Q9 -> 0 | H41: ='F06 (MAT,SERV & EQUIPO)'!R9 -> 0 | I41: ='F06 (MAT,SERV & EQUIPO)'!S9 -> 0 | J41: ='F06 (MAT,SERV & EQUIPO)'!T9 -> 0 | ... P41: ='F06 (MAT,SERV & EQUIPO)'!Z9 -> 0 | Q41: =B41/$B$162 -> 0
A42: ACEITES Y LUBRICANTES | B42: =SUM(C42:P42) -> 0 | C42: ='F06 (MAT,SERV & EQUIPO)'!M10 -> 0 | D42: ='F06 (MAT,SERV & EQUIPO)'!N10 -> 0 | E42: ='F06 (MAT,SERV & EQUIPO)'!O10 -> 0 | F42: ='F06 (MAT,SERV & EQUIPO)'!P10 -> 0 | G42: ='F06 (MAT,SERV & EQUIPO)'!Q10 -> 0 | H42: ='F06 (MAT,SERV & EQUIPO)'!R10 -> 0 | I42: ='F06 (MAT,SERV & EQUIPO)'!S10 -> 0 | J42: ='F06 (MAT,SERV & EQUIPO)'!T10 -> 0 | ... P42: ='F06 (MAT,SERV & EQUIPO)'!Z10 -> 0 | Q42: =B42/$B$162 -> 0
A43: AISLANTES IMPERM REFRA | B43: =SUM(C43:P43) -> 0 | C43: ='F06 (MAT,SERV & EQUIPO)'!M11 -> 0 | D43: ='F06 (MAT,SERV & EQUIPO)'!N11 -> 0 | E43: ='F06 (MAT,SERV & EQUIPO)'!O11 -> 0 | F43: ='F06 (MAT,SERV & EQUIPO)'!P11 -> 0 | G43: ='F06 (MAT,SERV & EQUIPO)'!Q11 -> 0 | H43: ='F06 (MAT,SERV & EQUIPO)'!R11 -> 0 | I43: ='F06 (MAT,SERV & EQUIPO)'!S11 -> 0 | J43: ='F06 (MAT,SERV & EQUIPO)'!T11 -> 0 | ... P43: ='F06 (MAT,SERV & EQUIPO)'!Z11 -> 0 | Q43: =B43/$B$162 -> 0
A44: BANDA CADEN TRANS COPL | B44: =SUM(C44:P44) -> 0 | C44: ='F06 (MAT,SERV & EQUIPO)'!M12 -> 0 | D44: ='F06 (MAT,SERV & EQUIPO)'!N12 -> 0 | E44: ='F06 (MAT,SERV & EQUIPO)'!O12 -> 0 | F44: ='F06 (MAT,SERV & EQUIPO)'!P12 -> 0 | G44: ='F06 (MAT,SERV & EQUIPO)'!Q12 -> 0 | H44: ='F06 (MAT,SERV & EQUIPO)'!R12 -> 0 | I44: ='F06 (MAT,SERV & EQUIPO)'!S12 -> 0 | J44: ='F06 (MAT,SERV & EQUIPO)'!T12 -> 0 | ... P44: ='F06 (MAT,SERV & EQUIPO)'!Z12 -> 0 | Q44: =B44/$B$162 -> 0
A45: CONEXIONES PARA TUBERIA | B45: =SUM(C45:P45) -> 0 | C45: ='F06 (MAT,SERV & EQUIPO)'!M13 -> 0 | D45: ='F06 (MAT,SERV & EQUIPO)'!N13 -> 0 | E45: ='F06 (MAT,SERV & EQUIPO)'!O13 -> 0 | F45: ='F06 (MAT,SERV & EQUIPO)'!P13 -> 0 | G45: ='F06 (MAT,SERV & EQUIPO)'!Q13 -> 0 | H45: ='F06 (MAT,SERV & EQUIPO)'!R13 -> 0 | I45: ='F06 (MAT,SERV & EQUIPO)'!S13 -> 0 | J45: ='F06 (MAT,SERV & EQUIPO)'!T13 -> 0 | ... P45: ='F06 (MAT,SERV & EQUIPO)'!Z13 -> 0 | Q45: =B45/$B$162 -> 0
A46: EMPAQUETAD JTAS Y SELLOS | B46: =SUM(C46:P46) -> 0 | C46: ='F06 (MAT,SERV & EQUIPO)'!M14 -> 0 | D46: ='F06 (MAT,SERV & EQUIPO)'!N14 -> 0 | E46: ='F06 (MAT,SERV & EQUIPO)'!O14 -> 0 | F46: ='F06 (MAT,SERV & EQUIPO)'!P14 -> 0 | G46: ='F06 (MAT,SERV & EQUIPO)'!Q14 -> 0 | H46: ='F06 (MAT,SERV & EQUIPO)'!R14 -> 0 | I46: ='F06 (MAT,SERV & EQUIPO)'!S14 -> 0 | J46: ='F06 (MAT,SERV & EQUIPO)'!T14 -> 0 | ... P46: ='F06 (MAT,SERV & EQUIPO)'!Z14 -> 0 | Q46: =B46/$B$162 -> 0
A47: ENVASES | B47: =SUM(C47:P47) -> 0 | C47: ='F06 (MAT,SERV & EQUIPO)'!M15 -> 0 | D47: ='F06 (MAT,SERV & EQUIPO)'!N15 -> 0 | E47: ='F06 (MAT,SERV & EQUIPO)'!O15 -> 0 | F47: ='F06 (MAT,SERV & EQUIPO)'!P15 -> 0 | G47: ='F06 (MAT,SERV & EQUIPO)'!Q15 -> 0 | H47: ='F06 (MAT,SERV & EQUIPO)'!R15 -> 0 | I47: ='F06 (MAT,SERV & EQUIPO)'!S15 -> 0 | J47: ='F06 (MAT,SERV & EQUIPO)'!T15 -> 0 | ... P47: ='F06 (MAT,SERV & EQUIPO)'!Z15 -> 0 | Q47: =B47/$B$162 -> 0
A48: FIBRAS HILOS Y TELAS | B48: =SUM(C48:P48) -> 0 | C48: ='F06 (MAT,SERV & EQUIPO)'!M16 -> 0 | D48: ='F06 (MAT,SERV & EQUIPO)'!N16 -> 0 | E48: ='F06 (MAT,SERV & EQUIPO)'!O16 -> 0 | F48: ='F06 (MAT,SERV & EQUIPO)'!P16 -> 0 | G48: ='F06 (MAT,SERV & EQUIPO)'!Q16 -> 0 | H48: ='F06 (MAT,SERV & EQUIPO)'!R16 -> 0 | I48: ='F06 (MAT,SERV & EQUIPO)'!S16 -> 0 | J48: ='F06 (MAT,SERV & EQUIPO)'!T16 -> 0 | ... P48: ='F06 (MAT,SERV & EQUIPO)'!Z16 -> 0 | Q48: =B48/$B$162 -> 0
A49: GRASAS | B49: =SUM(C49:P49) -> 0 | C49: ='F06 (MAT,SERV & EQUIPO)'!M17 -> 0 | D49: ='F06 (MAT,SERV & EQUIPO)'!N17 -> 0 | E49: ='F06 (MAT,SERV & EQUIPO)'!O17 -> 0 | F49: ='F06 (MAT,SERV & EQUIPO)'!P17 -> 0 | G49: ='F06 (MAT,SERV & EQUIPO)'!Q17 -> 0 | H49: ='F06 (MAT,SERV & EQUIPO)'!R17 -> 0 | I49: ='F06 (MAT,SERV & EQUIPO)'!S17 -> 0 | J49: ='F06 (MAT,SERV & EQUIPO)'!T17 -> 0 | ... P49: ='F06 (MAT,SERV & EQUIPO)'!Z17 -> 0 | Q49: =B49/$B$162 -> 0
A50: HERRAMIENTAS MANUALES | B50: =SUM(C50:P50) -> 0 | C50: ='F06 (MAT,SERV & EQUIPO)'!M18 -> 0 | D50: ='F06 (MAT,SERV & EQUIPO)'!N18 -> 0 | E50: ='F06 (MAT,SERV & EQUIPO)'!O18 -> 0 | F50: ='F06 (MAT,SERV & EQUIPO)'!P18 -> 0 | G50: ='F06 (MAT,SERV & EQUIPO)'!Q18 -> 0 | H50: ='F06 (MAT,SERV & EQUIPO)'!R18 -> 0 | I50: ='F06 (MAT,SERV & EQUIPO)'!S18 -> 0 | J50: ='F06 (MAT,SERV & EQUIPO)'!T18 -> 0 | ... P50: ='F06 (MAT,SERV & EQUIPO)'!Z18 -> 0 | Q50: =B50/$B$162 -> 0
A51: INSTRUM DE MEDICION Y CONTROL | B51: =SUM(C51:P51) -> 0 | C51: ='F06 (MAT,SERV & EQUIPO)'!M19 -> 0 | D51: ='F06 (MAT,SERV & EQUIPO)'!N19 -> 0 | E51: ='F06 (MAT,SERV & EQUIPO)'!O19 -> 0 | F51: ='F06 (MAT,SERV & EQUIPO)'!P19 -> 0 | G51: ='F06 (MAT,SERV & EQUIPO)'!Q19 -> 0 | H51: ='F06 (MAT,SERV & EQUIPO)'!R19 -> 0 | I51: ='F06 (MAT,SERV & EQUIPO)'!S19 -> 0 | J51: ='F06 (MAT,SERV & EQUIPO)'!T19 -> 0 | ... P51: ='F06 (MAT,SERV & EQUIPO)'!Z19 -> 0 | Q51: =B51/$B$162 -> 0
... A74: VALVULAS | B74: =SUM(C74:P74) -> 0 | C74: ='F06 (MAT,SERV & EQUIPO)'!M42 -> 0 | D74: ='F06 (MAT,SERV & EQUIPO)'!N42 -> 0 | E74: ='F06 (MAT,SERV & EQUIPO)'!O42 -> 0 | F74: ='F06 (MAT,SERV & EQUIPO)'!P42 -> 0 | G74: ='F06 (MAT,SERV & EQUIPO)'!Q42 -> 0 | H74: ='F06 (MAT,SERV & EQUIPO)'!R42 -> 0 | I74: ='F06 (MAT,SERV & EQUIPO)'!S42 -> 0 | J74: ='F06 (MAT,SERV & EQUIPO)'!T42 -> 0 | ... P74: ='F06 (MAT,SERV & EQUIPO)'!Z42 -> 0 | Q74: =B74/$B$162 -> 0
A75: MATERIALES | B75: =SUM(B40:B74) -> 20997.34 | C75: =SUM(C40:C74) -> 10498.67 | D75: =SUM(D40:D74) -> 10498.67 | E75: =SUM(E40:E74) -> 0 | F75: =SUM(F40:F74) -> 0 | G75: =SUM(G40:G74) -> 0 | H75: =SUM(H40:H74) -> 0 | I75: =SUM(I40:I74) -> 0 | ... P75: =SUM(P40:P74) -> 0 | Q75: =B75/$B$162 -> 0.00090259122
A76: MATERIAL PRIMEROS AUXILIOS | B76: =SUM(C76:P76) -> 0 | C76: ='F07 OPERAC. (MAT,SERV & EQUIPO)'!L163 -> 0 | D76: ='F07 OPERAC. (MAT,SERV & EQUIPO)'!M163 -> 0 | E76: ='F07 OPERAC. (MAT,SERV & EQUIPO)'!N163 -> 0 | F76: ='F07 OPERAC. (MAT,SERV & EQUIPO)'!O163 -> 0 | G76: ='F07 OPERAC. (MAT,SERV & EQUIPO)'!P163 -> 0 | H76: ='F07 OPERAC. (MAT,SERV & EQUIPO)'!Q163 -> 0 | I76: ='F07 OPERAC. (MAT,SERV & EQUIPO)'!R163 -> 0 | J76: ='F07 OPERAC. (MAT,SERV & EQUIPO)'!S163 -> 0 | ... P76: ='F07 OPERAC. (MAT,SERV & EQUIPO)'!Y163 -> 0 | Q76: =B76/$B$162 -> 0
A77: MATERIALES DE SALUD | B77: =SUM(C77:P77) -> 0 | C77: =C76 -> 0 | D77: =D76 -> 0 | E77: =E76 -> 0 | F77: =F76 -> 0 | G77: =G76 -> 0 | H77: =H76 -> 0 | I77: =I76 -> 0 | J77: =J76 -> 0 | ... P77: =P76 -> 0 | Q77: =B77/$B$162 -> 0
A78: NOMINA Y ADICIONALES | B78: =SUM(C78:P78) -> 1095939.1 | C78: ='F01 NÓMINA'!X20 -> 417404.61 | D78: ='F01 NÓMINA'!Y20 -> 678534.54 | E78: ='F01 NÓMINA'!Z20 -> 0 | F78: ='F01 NÓMINA'!AA20 -> 0 | G78: ='F01 NÓMINA'!AB20 -> 0 | H78: ='F01 NÓMINA'!AC20 -> 0 | I78: ='F01 NÓMINA'!AD20 -> 0 | J78: ='F01 NÓMINA'!AE20 -> 0 | ... P78: ='F01 NÓMINA'!AK20 -> 0 | Q78: =B78/$B$162 -> 0.047110017
A79: SERV TELEFONIA CELULAR | B79: =SUM(C79:P79) -> 0 | C79: ='F03 COM Y EQ COM'!L12 -> 0 | D79: ='F03 COM Y EQ COM'!M12 -> 0 | E79: ='F03 COM Y EQ COM'!N12 -> 0 | F79: ='F03 COM Y EQ COM'!O12 -> 0 | G79: ='F03 COM Y EQ COM'!P12 -> 0 | H79: ='F03 COM Y EQ COM'!Q12 -> 0 | I79: ='F03 COM Y EQ COM'!R12 -> 0 | J79: ='F03 COM Y EQ COM'!S12 -> 0 | ... P79: ='F03 COM Y EQ COM'!Y12 -> 0 | Q79: =B79/$B$162 -> 0
A80: SERVICIO DE BANDA ANCHA | B80: =SUM(C80:P80) -> 0 | C80: ='F03 COM Y EQ COM'!L21 -> 0 | D80: ='F03 COM Y EQ COM'!M21 -> 0 | E80: ='F03 COM Y EQ COM'!N21 -> 0 | F80: ='F03 COM Y EQ COM'!O21 -> 0 | G80: ='F03 COM Y EQ COM'!P21 -> 0 | H80: ='F03 COM Y EQ COM'!Q21 -> 0 | I80: ='F03 COM Y EQ COM'!R21 -> 0 | J80: ='F03 COM Y EQ COM'!S21 -> 0 | ... P80: ='F03 COM Y EQ COM'!Y21 -> 0 | Q80: =B80/$B$162 -> 0
A81: SERVICIO DE RADIOCOMUNICACION | B81: =SUM(C81:P81) -> 0 | C81: ='F03 COM Y EQ COM'!L30 -> 0 | D81: ='F03 COM Y EQ COM'!M30 -> 0 | E81: ='F03 COM Y EQ COM'!N30 -> 0 | F81: ='F03 COM Y EQ COM'!O30 -> 0 | G81: ='F03 COM Y EQ COM'!P30 -> 0 | H81: ='F03 COM Y EQ COM'!Q30 -> 0 | I81: ='F03 COM Y EQ COM'!R30 -> 0 | J81: ='F03 COM Y EQ COM'!S30 -> 0 | ... P81: ='F03 COM Y EQ COM'!Y30 -> 0 | Q81: =B81/$B$162 -> 0
A82: SERV TELEFONIA CELULAR Y RADIO | B82: =SUM(B79:B81) -> 0 | C82: =SUM(C79:C81) -> 0 | D82: =SUM(D79:D81) -> 0 | E82: =SUM(E79:E81) -> 0 | F82: =SUM(F79:F81) -> 0 | G82: =SUM(G79:G81) -> 0 | H82: =SUM(H79:H81) -> 0 | I82: =SUM(I79:I81) -> 0 | ... P82: =SUM(P79:P81) -> 0 | Q82: =B82/$B$162 -> 0
A83: ACONDICION DE CASA HABITACION | B83: =SUM(C83:P83) -> 0 | C83: ='F07 OPERAC. (MAT,SERV & EQUIPO)'!L53 -> 0 | D83: ='F07 OPERAC. (MAT,SERV & EQUIPO)'!M53 -> 0 | E83: ='F07 OPERAC. (MAT,SERV & EQUIPO)'!N53 -> 0 | F83: ='F07 OPERAC. (MAT,SERV & EQUIPO)'!O53 -> 0 | G83: ='F07 OPERAC. (MAT,SERV & EQUIPO)'!P53 -> 0 | H83: ='F07 OPERAC. (MAT,SERV & EQUIPO)'!Q53 -> 0 | I83: ='F07 OPERAC. (MAT,SERV & EQUIPO)'!R53 -> 0 | J83: ='F07 OPERAC. (MAT,SERV & EQUIPO)'!S53 -> 0 | ... P83: ='F07 OPERAC. (MAT,SERV & EQUIPO)'!Y53 -> 0 | Q83: =B83/$B$162 -> 0
A84: ADICION Y MODIFIC DE MATERIAL | B84: =SUM(C84:P84) -> 0 | C84: ='F07 OPERAC. (MAT,SERV & EQUIPO)'!L54 -> 0 | D84: ='F07 OPERAC. (MAT,SERV & EQUIPO)'!M54 -> 0 | E84: ='F07 OPERAC. (MAT,SERV & EQUIPO)'!N54 -> 0 | F84: ='F07 OPERAC. (MAT,SERV & EQUIPO)'!O54 -> 0 | G84: ='F07 OPERAC. (MAT,SERV & EQUIPO)'!P54 -> 0 | H84: ='F07 OPERAC. (MAT,SERV & EQUIPO)'!Q54 -> 0 | I84: ='F07 OPERAC. (MAT,SERV & EQUIPO)'!R54 -> 0 | J84: ='F07 OPERAC. (MAT,SERV & EQUIPO)'!S54 -> 0 | ... P84: ='F07 OPERAC. (MAT,SERV & EQUIPO)'!Y54 -> 0 | Q84: =B84/$B$162 -> 0
A85: ADQUISICION TARJET COMBUSTIBLE | B85: =SUM(C85:P85) -> 903.5 | C85: ='F07 OPERAC. (MAT,SERV & EQUIPO)'!L55 -> 903.5 | D85: ='F07 OPERAC. (MAT,SERV & EQUIPO)'!M55 -> 0 | E85: ='F07 OPERAC. (MAT,SERV & EQUIPO)'!N55 -> 0 | F85: ='F07 OPERAC. (MAT,SERV & EQUIPO)'!O55 -> 0 | G85: ='F07 OPERAC. (MAT,SERV & EQUIPO)'!P55 -> 0 | H85: ='F07 OPERAC. (MAT,SERV & EQUIPO)'!Q55 -> 0 | I85: ='F07 OPERAC. (MAT,SERV & EQUIPO)'!R55 -> 0 | J85: ='F07 OPERAC. (MAT,SERV & EQUIPO)'!S55 -> 0 | ... P85: ='F07 OPERAC. (MAT,SERV & EQUIPO)'!Y55 -> 0 | Q85: =B85/$B$162 -> 3.8837832e-05
A86: ANALISIS CAUSA RAIZ | B86: =SUM(C86:P86) -> 0 | C86: ='F07 OPERAC. (MAT,SERV & EQUIPO)'!L56 -> 0 | D86: ='F07 OPERAC. (MAT,SERV & EQUIPO)'!M56 -> 0 | E86: ='F07 OPERAC. (MAT,SERV & EQUIPO)'!N56 -> 0 | F86: ='F07 OPERAC. (MAT,SERV & EQUIPO)'!O56 -> 0 | G86: ='F07 OPERAC. (MAT,SERV & EQUIPO)'!P56 -> 0 | H86: ='F07 OPERAC. (MAT,SERV & EQUIPO)'!Q56 -> 0 | I86: ='F07 OPERAC. (MAT,SERV & EQUIPO)'!R56 -> 0 | J86: ='F07 OPERAC. (MAT,SERV & EQUIPO)'!S56 -> 0 | ... P86: ='F07 OPERAC. (MAT,SERV & EQUIPO)'!Y56 -> 0 | Q86: =B86/$B$162 -> 0
A87: ANALISIS DE RIESGO | B87: =SUM(C87:P87) -> 0 | C87: ='F07 OPERAC. (MAT,SERV & EQUIPO)'!L57 -> 0 | D87: ='F07 OPERAC. (MAT,SERV & EQUIPO)'!M57 -> 0 | E87: ='F07 OPERAC. (MAT,SERV & EQUIPO)'!N57 -> 0 | F87: ='F07 OPERAC. (MAT,SERV & EQUIPO)'!O57 -> 0 | G87: ='F07 OPERAC. (MAT,SERV & EQUIPO)'!P57 -> 0 | H87: ='F07 OPERAC. (MAT,SERV & EQUIPO)'!Q57 -> 0 | I87: ='F07 OPERAC. (MAT,SERV & EQUIPO)'!R57 -> 0 | J87: ='F07 OPERAC. (MAT,SERV & EQUIPO)'!S57 -> 0 | ... P87: ='F07 OPERAC. (MAT,SERV & EQUIPO)'!Y57 -> 0 | Q87: =B87/$B$162 -> 0
A88: ANALISIS DE VIBRACION | B88: =SUM(C88:P88) -> 0 | C88: ='F07 OPERAC. (MAT,SERV & EQUIPO)'!L58 -> 0 | D88: ='F07 OPERAC. (MAT,SERV & EQUIPO)'!M58 -> 0 | E88: ='F07 OPERAC. (MAT,SERV & EQUIPO)'!N58 -> 0 | F88: ='F07 OPERAC. (MAT,SERV & EQUIPO)'!O58 -> 0 | G88: ='F07 OPERAC. (MAT,SERV & EQUIPO)'!P58 -> 0 | H88: ='F07 OPERAC. (MAT,SERV & EQUIPO)'!Q58 -> 0 | I88: ='F07 OPERAC. (MAT,SERV & EQUIPO)'!R58 -> 0 | J88: ='F07 OPERAC. (MAT,SERV & EQUIPO)'!S58 -> 0 | ... P88: ='F07 OPERAC. (MAT,SERV & EQUIPO)'!Y58 -> 0 | Q88: =B88/$B$162 -> 0
A89: BASES LICITACION Y CONCURSOS | B89: =SUM(C89:P89) -> 0 | C89: ='F07 OPERAC. (MAT,SERV & EQUIPO)'!L59 -> 0 | D89: ='F07 OPERAC. (MAT,SERV & EQUIPO)'!M59 -> 0 | E89: ='F07 OPERAC. (MAT,SERV & EQUIPO)'!N59 -> 0 | F89: ='F07 OPERAC. (MAT,SERV & EQUIPO)'!O59 -> 0 | G89: ='F07 OPERAC. (MAT,SERV & EQUIPO)'!P59 -> 0 | H89: ='F07 OPERAC. (MAT,SERV & EQUIPO)'!Q59 -> 0 | I89: ='F07 OPERAC. (MAT,SERV & EQUIPO)'!R59 -> 0 | J89: ='F07 OPERAC. (MAT,SERV & EQUIPO)'!S59 -> 0 | ... P89: ='F07 OPERAC. (MAT,SERV & EQUIPO)'!Y59 -> 0 | Q89: =B89/$B$162 -> 0
A90: CARGOS EXTRAORDINARIOS | B90: =SUM(C90:P90) -> 0 | C90: ='F07 OPERAC. (MAT,SERV & EQUIPO)'!L60 -> 0 | D90: ='F07 OPERAC. (MAT,SERV & EQUIPO)'!M60 -> 0 | E90: ='F07 OPERAC. (MAT,SERV & EQUIPO)'!N60 -> 0 | F90: ='F07 OPERAC. (MAT,SERV & EQUIPO)'!O60 -> 0 | G90: ='F07 OPERAC. (MAT,SERV & EQUIPO)'!P60 -> 0 | H90: ='F07 OPERAC. (MAT,SERV & EQUIPO)'!Q60 -> 0 | I90: ='F07 OPERAC. (MAT,SERV & EQUIPO)'!R60 -> 0 | J90: ='F07 OPERAC. (MAT,SERV & EQUIPO)'!S60 -> 0 | ... P90: ='F07 OPERAC. (MAT,SERV & EQUIPO)'!Y60 -> 0 | Q90: =B90/$B$162 -> 0
A91: CERTIFICACION | B91: =SUM(C91:P91) -> 0 | C91: ='F07 OPERAC. (MAT,SERV & EQUIPO)'!L61 -> 0 | D91: ='F07 OPERAC. (MAT,SERV & EQUIPO)'!M61 -> 0 | E91: ='F07 OPERAC. (MAT,SERV & EQUIPO)'!N61 -> 0 | F91: ='F07 OPERAC. (MAT,SERV & EQUIPO)'!O61 -> 0 | G91: ='F07 OPERAC. (MAT,SERV & EQUIPO)'!P61 -> 0 | H91: ='F07 OPERAC. (MAT,SERV & EQUIPO)'!Q61 -> 0 | I91: ='F07 OPERAC. (MAT,SERV & EQUIPO)'!R61 -> 0 | J91: ='F07 OPERAC. (MAT,SERV & EQUIPO)'!S61 -> 0 | ... P91: ='F07 OPERAC. (MAT,SERV & EQUIPO)'!Y61 -> 0 | Q91: =B91/$B$162 -> 0
A92: COLOCACION DE PILOTE | B92: =SUM(C92:P92) -> 0 | C92: ='F07 OPERAC. (MAT,SERV & EQUIPO)'!L62 -> 0 | D92: ='F07 OPERAC. (MAT,SERV & EQUIPO)'!M62 -> 0 | E92: ='F07 OPERAC. (MAT,SERV & EQUIPO)'!N62 -> 0 | F92: ='F07 OPERAC. (MAT,SERV & EQUIPO)'!O62 -> 0 | G92: ='F07 OPERAC. (MAT,SERV & EQUIPO)'!P62 -> 0 | H92: ='F07 OPERAC. (MAT,SERV & EQUIPO)'!Q62 -> 0 | I92: ='F07 OPERAC. (MAT,SERV & EQUIPO)'!R62 -> 0 | J92: ='F07 OPERAC. (MAT,SERV & EQUIPO)'!S62 -> 0 | ... P92: ='F07 OPERAC. (MAT,SERV & EQUIPO)'!Y62 -> 0 | Q92: =B92/$B$162 -> 0
A93: CORREOS Y MENSAJERIAS | B93: =SUM(C93:P93) -> 0 | C93: ='F07 OPERAC. (MAT,SERV & EQUIPO)'!L63 -> 0 | D93: ='F07 OPERAC. (MAT,SERV & EQUIPO)'!M63 -> 0 | E93: ='F07 OPERAC. (MAT,SERV & EQUIPO)'!N63 -> 0 | F93: ='F07 OPERAC. (MAT,SERV & EQUIPO)'!O63 -> 0 | G93: ='F07 OPERAC. (MAT,SERV & EQUIPO)'!P63 -> 0 | H93: ='F07 OPERAC. (MAT,SERV & EQUIPO)'!Q63 -> 0 | I93: ='F07 OPERAC. (MAT,SERV & EQUIPO)'!R63 -> 0 | J93: ='F07 OPERAC. (MAT,SERV & EQUIPO)'!S63 -> 0 | ... P93: ='F07 OPERAC. (MAT,SERV & EQUIPO)'!Y63 -> 0 | Q93: =B93/$B$162 -> 0
A94: CUOTAS Y SUSCRIPCIONES | B94: =SUM(C94:P94) -> 0 | C94: ='F07 OPERAC. (MAT,SERV & EQUIPO)'!L64 -> 0 | D94: ='F07 OPERAC. (MAT,SERV & EQUIPO)'!M64 -> 0 | E94: ='F07 OPERAC. (MAT,SERV & EQUIPO)'!N64 -> 0 | F94: ='F07 OPERAC. (MAT,SERV & EQUIPO)'!O64 -> 0 | G94: ='F07 OPERAC. (MAT,SERV & EQUIPO)'!P64 -> 0 | H94: ='F07 OPERAC. (MAT,SERV & EQUIPO)'!Q64 -> 0 | I94: ='F07 OPERAC. (MAT,SERV & EQUIPO)'!R64 -> 0 | J94: ='F07 OPERAC. (MAT,SERV & EQUIPO)'!S64 -> 0 | ... P94: ='F07 OPERAC. (MAT,SERV & EQUIPO)'!Y64 -> 0 | Q94: =B94/$B$162 -> 0
... A145: PAGO DE MULTAS | B145: =SUM(C145:P145) -> 0 | C145: ='F07 OPERAC. (MAT,SERV & EQUIPO)'!L115 -> 0 | D145: ='F07 OPERAC. (MAT,SERV & EQUIPO)'!M115 -> 0 | E145: ='F07 OPERAC. (MAT,SERV & EQUIPO)'!N115 -> 0 | F145: ='F07 OPERAC. (MAT,SERV & EQUIPO)'!O115 -> 0 | G145: ='F07 OPERAC. (MAT,SERV & EQUIPO)'!P115 -> 0 | H145: ='F07 OPERAC. (MAT,SERV & EQUIPO)'!Q115 -> 0 | I145: ='F07 OPERAC. (MAT,SERV & EQUIPO)'!R115 -> 0 | J145: ='F07 OPERAC. (MAT,SERV & EQUIPO)'!S115 -> 0 | ... P145: ='F07 OPERAC. (MAT,SERV & EQUIPO)'!Y115 -> 0 | Q145: =B145/$B$162 -> 0
A146: SERVICIOS | B146: =SUM(B83:B145) -> 3241593.3 | C146: =SUM(C83:C145) -> 1959720.8 | D146: =SUM(D83:D145) -> 1281872.5 | E146: =SUM(E83:E145) -> 0 | F146: =SUM(F83:F145) -> 0 | G146: =SUM(G83:G145) -> 0 | H146: =SUM(H83:H145) -> 0 | I146: =SUM(I83:I145) -> 0 | ... P146: =SUM(P83:P145) -> 0 | Q146: =B146/$B$162 -> 0.13934306
A147: SERVICIOS DE CAPACITACION | B147: =SUM(C147:P147) -> 0 | C147: ='F07 OPERAC. (MAT,SERV & EQUIPO)'!L176 -> 0 | D147: ='F07 OPERAC. (MAT,SERV & EQUIPO)'!M176 -> 0 | E147: ='F07 OPERAC. (MAT,SERV & EQUIPO)'!N176 -> 0 | F147: ='F07 OPERAC. (MAT,SERV & EQUIPO)'!O176 -> 0 | G147: ='F07 OPERAC. (MAT,SERV & EQUIPO)'!P176 -> 0 | H147: ='F07 OPERAC. (MAT,SERV & EQUIPO)'!Q176 -> 0 | I147: ='F07 OPERAC. (MAT,SERV & EQUIPO)'!R176 -> 0 | J147: ='F07 OPERAC. (MAT,SERV & EQUIPO)'!S176 -> 0 | ... P147: ='F07 OPERAC. (MAT,SERV & EQUIPO)'!Y176 -> 0 | Q147: =B147/$B$162 -> 0
A148: SERVICIOS MEDICOS | B148: =SUM(C148:P148) -> 0 | C148: ='F07 OPERAC. (MAT,SERV & EQUIPO)'!L189 -> 0 | D148: ='F07 OPERAC. (MAT,SERV & EQUIPO)'!M189 -> 0 | E148: ='F07 OPERAC. (MAT,SERV & EQUIPO)'!N189 -> 0 | F148: ='F07 OPERAC. (MAT,SERV & EQUIPO)'!O189 -> 0 | G148: ='F07 OPERAC. (MAT,SERV & EQUIPO)'!P189 -> 0 | H148: ='F07 OPERAC. (MAT,SERV & EQUIPO)'!Q189 -> 0 | I148: ='F07 OPERAC. (MAT,SERV & EQUIPO)'!R189 -> 0 | J148: ='F07 OPERAC. (MAT,SERV & EQUIPO)'!S189 -> 0 | ... P148: ='F07 OPERAC. (MAT,SERV & EQUIPO)'!Y189 -> 0 | Q148: =B148/$B$162 -> 0
A149: SERVICIOS DE SALUD | B149: =SUM(B148) -> 0 | C149: =SUM(C148) -> 0 | D149: =SUM(D148) -> 0 | E149: =SUM(E148) -> 0 | F149: =SUM(F148) -> 0 | G149: =SUM(G148) -> 0 | H149: =SUM(H148) -> 0 | I149: =SUM(I148) -> 0 | ... P149: =SUM(P148) -> 0 | Q149: =B149/$B$162 -> 0
A150: UNIFORMES | B150: =SUM(C150:P150) -> 0 | C150: ='F01 UNIFORMES'!M15 -> 0 | D150: ='F01 UNIFORMES'!N15 -> 0 | E150: ='F01 UNIFORMES'!O15 -> 0 | F150: ='F01 UNIFORMES'!P15 -> 0 | G150: ='F01 UNIFORMES'!Q15 -> 0 | H150: ='F01 UNIFORMES'!R15 -> 0 | I150: ='F01 UNIFORMES'!S15 -> 0 | J150: ='F01 UNIFORMES'!T15 -> 0 | ... P150: ='F01 UNIFORMES'!Z15 -> 0 | Q150: =B150/$B$162 -> 0
A151: ARRENDAMIENTO DE VEHIC | B151: =SUM(C151:P151) -> 0 | C151: ='F04 VEHÍCULOS Y COMB. '!V20 -> 0 | D151: ='F04 VEHÍCULOS Y COMB. '!W20 -> 0 | E151: ='F04 VEHÍCULOS Y COMB. '!X20 -> 0 | F151: ='F04 VEHÍCULOS Y COMB. '!Y20 -> 0 | G151: ='F04 VEHÍCULOS Y COMB. '!Z20 -> 0 | H151: ='F04 VEHÍCULOS Y COMB. '!AA20 -> 0 | I151: ='F04 VEHÍCULOS Y COMB. '!AB20 -> 0 | J151: ='F04 VEHÍCULOS Y COMB. '!AC20 -> 0 | ... P151: ='F04 VEHÍCULOS Y COMB. '!AI20 -> 0 | Q151: =B151/$B$162 -> 0
A152: COMBUSTIBLES | B152: =SUM(C152:P152) -> 300800 | C152: ='F04 VEHÍCULOS Y COMB. '!V22 -> 150400 | D152: ='F04 VEHÍCULOS Y COMB. '!W22 -> 150400 | E152: ='F04 VEHÍCULOS Y COMB. '!X22 -> 0 | F152: ='F04 VEHÍCULOS Y COMB. '!Y22 -> 0 | G152: ='F04 VEHÍCULOS Y COMB. '!Z22 -> 0 | H152: ='F04 VEHÍCULOS Y COMB. '!AA22 -> 0 | I152: ='F04 VEHÍCULOS Y COMB. '!AB22 -> 0 | J152: ='F04 VEHÍCULOS Y COMB. '!AC22 -> 0 | ... P152: ='F04 VEHÍCULOS Y COMB. '!AI22 -> 0 | Q152: =B152/$B$162 -> 0.012930183
A153: VEHICULOS Y COMBUSTIBLE | B153: =SUM(B151:B152) -> 300800 | C153: =SUM(C151:C152) -> 150400 | D153: =SUM(D151:D152) -> 150400 | E153: =SUM(E151:E152) -> 0 | F153: =SUM(F151:F152) -> 0 | G153: =SUM(G151:G152) -> 0 | H153: =SUM(H151:H152) -> 0 | I153: =SUM(I151:I152) -> 0 | ... P153: =SUM(P151:P152) -> 0 | Q153: =B153/$B$162 -> 0.012930183
A154: ALIMENTACION | B154: =SUM(C154:P154) -> 677625 | C154: ='F05 VIÁTICOS'!K8 -> 338812.5 | D154: ='F05 VIÁTICOS'!L8 -> 338812.5 | E154: ='F05 VIÁTICOS'!M8 -> 0 | F154: ='F05 VIÁTICOS'!N8 -> 0 | G154: ='F05 VIÁTICOS'!O8 -> 0 | H154: ='F05 VIÁTICOS'!P8 -> 0 | I154: ='F05 VIÁTICOS'!Q8 -> 0 | J154: ='F05 VIÁTICOS'!R8 -> 0 | ... P154: ='F05 VIÁTICOS'!X8 -> 0 | Q154: =B154/$B$162 -> 0.029128374
A155: CASETAS PUENTES Y PEAJES | B155: =SUM(C155:P155) -> 18719.797 | C155: ='F05 VIÁTICOS'!K9 -> 9359.8986 | D155: ='F05 VIÁTICOS'!L9 -> 9359.8986 | E155: ='F05 VIÁTICOS'!M9 -> 0 | F155: ='F05 VIÁTICOS'!N9 -> 0 | G155: ='F05 VIÁTICOS'!O9 -> 0 | H155: ='F05 VIÁTICOS'!P9 -> 0 | I155: ='F05 VIÁTICOS'!Q9 -> 0 | J155: ='F05 VIÁTICOS'!R9 -> 0 | ... P155: ='F05 VIÁTICOS'!X9 -> 0 | Q155: =B155/$B$162 -> 0.00080468881
A156: SERV DE TRANSPORTAC AEREA | B156: =SUM(C156:P156) -> 0 | C156: ='F05 VIÁTICOS'!K10 -> 0 | D156: ='F05 VIÁTICOS'!L10 -> 0 | E156: ='F05 VIÁTICOS'!M10 -> 0 | F156: ='F05 VIÁTICOS'!N10 -> 0 | G156: ='F05 VIÁTICOS'!O10 -> 0 | H156: ='F05 VIÁTICOS'!P10 -> 0 | I156: ='F05 VIÁTICOS'!Q10 -> 0 | J156: ='F05 VIÁTICOS'!R10 -> 0 | ... P156: ='F05 VIÁTICOS'!X10 -> 0 | Q156: =B156/$B$162 -> 0
A157: SERV DE TRANSPORTAC TERRESTRE | B157: =SUM(C157:P157) -> 0 | C157: ='F05 VIÁTICOS'!K11 -> 0 | D157: ='F05 VIÁTICOS'!L11 -> 0 | E157: ='F05 VIÁTICOS'!M11 -> 0 | F157: ='F05 VIÁTICOS'!N11 -> 0 | G157: ='F05 VIÁTICOS'!O11 -> 0 | H157: ='F05 VIÁTICOS'!P11 -> 0 | I157: ='F05 VIÁTICOS'!Q11 -> 0 | J157: ='F05 VIÁTICOS'!R11 -> 0 | ... P157: ='F05 VIÁTICOS'!X11 -> 0 | Q157: =B157/$B$162 -> 0
A158: SERVICIOS DE HOSPEDAJE | B158: =SUM(C158:P158) -> 902493.5 | C158: ='F05 VIÁTICOS'!K12 -> 451246.75 | D158: ='F05 VIÁTICOS'!L12 -> 451246.75 | E158: ='F05 VIÁTICOS'!M12 -> 0 | F158: ='F05 VIÁTICOS'!N12 -> 0 | G158: ='F05 VIÁTICOS'!O12 -> 0 | H158: ='F05 VIÁTICOS'!P12 -> 0 | I158: ='F05 VIÁTICOS'!Q12 -> 0 | J158: ='F05 VIÁTICOS'!R12 -> 0 | ... P158: ='F05 VIÁTICOS'!X12 -> 0 | Q158: =B158/$B$162 -> 0.038794567
A159: ='F05 VIÁTICOS'!B20 -> CAJA CHICA | B159: =SUM(C159:P159) -> 0 | C159: ='F05 VIÁTICOS'!K20 -> 0 | D159: ='F05 VIÁTICOS'!L20 -> 0 | E159: ='F05 VIÁTICOS'!M20 -> 0 | F159: ='F05 VIÁTICOS'!N20 -> 0 | G159: ='F05 VIÁTICOS'!O20 -> 0 | H159: ='F05 VIÁTICOS'!P20 -> 0 | I159: ='F05 VIÁTICOS'!Q20 -> 0 | J159: ='F05 VIÁTICOS'!R20 -> 0 | ... P159: ='F05 VIÁTICOS'!X20 -> 0 | Q159: =B159/$B$162 -> 0
A160: ='F05 VIÁTICOS'!B21 -> REEMBOLSOS | B160: =SUM(C160:P160) -> 14456 | C160: ='F05 VIÁTICOS'!K21 -> 7228 | D160: ='F05 VIÁTICOS'!L21 -> 7228 | E160: ='F05 VIÁTICOS'!M21 -> 0 | F160: ='F05 VIÁTICOS'!N21 -> 0 | G160: ='F05 VIÁTICOS'!O21 -> 0 | H160: ='F05 VIÁTICOS'!P21 -> 0 | I160: ='F05 VIÁTICOS'!Q21 -> 0 | J160: ='F05 VIÁTICOS'!R21 -> 0 | ... P160: ='F05 VIÁTICOS'!X21 -> 0 | Q160: =B160/$B$162 -> 0.00062140532
A161: VIATICOS | B161: =SUM(B154:B160) -> 1613294.3 | C161: =SUM(C154:C160) -> 806647.15 | D161: =SUM(D154:D160) -> 806647.15 | E161: =SUM(E154:E160) -> 0 | F161: =SUM(F154:F160) -> 0 | G161: =SUM(G154:G160) -> 0 | H161: =SUM(H154:H160) -> 0 | I161: =SUM(I154:I160) -> 0 | ... P161: =SUM(P154:P160) -> 0 | Q161: =B161/$B$162 -> 0.069349035
A162: TOTAL | B162: =SUM(B161,B153,B150,B149,B147,B146,B82,B78,B77,B75,B39,B36,B31,B30,B28,B25,B23,B13) -> 23263399 | C162: =C13+C23+C25+C28+C30+C31+C36+C39+C75+C77+C78+C82+C146+C147+C149+C150+C153+C161 -> 20297892 | D162: =D13+D23+D25+D28+D30+D31+D36+D39+D75+D77+D78+D82+D146+D147+D149+D150+D153+D161 -> 2965507.6 | E162: =E13+E23+E25+E28+E30+E31+E36+E39+E75+E77+E78+E82+E146+E147+E149+E150+E153+E161 -> 0 | F162: =F13+F23+F25+F28+F30+F31+F36+F39+F75+F77+F78+F82+F146+F147+F149+F150+F153+F161 -> 0 | G162: =G13+G23+G25+G28+G30+G31+G36+G39+G75+G77+G78+G82+G146+G147+G149+G150+G153+G161 -> 0 | H162: =H13+H23+H25+H28+H30+H31+H36+H39+H75+H77+H78+H82+H146+H147+H149+H150+H153+H161 -> 0 | I162: =I13+I23+I25+I28+I30+I31+I36+I39+I75+I77+I78+I82+I146+I147+I149+I150+I153+I161 -> 0 | J162: =J13+J23+J25+J28+J30+J31+J36+J39+J75+J77+J78+J82+J146+J147+J149+J150+J153+J161 -> 0 | ... P162: =P13+P23+P25+P28+P30+P31+P36+P39+P75+P77+P78+P82+P146+P147+P149+P150+P153+P161 -> 0
A163: OPEX | B163: =SUM(B161,B153,B150,B149,B147,B146,B82,B78,B77,B75,B39,B36,B31,B30,B28,B25,B23) -> 6549001.8 | C163: =SUM(C161,C153,C150,C149,C147,C146,C82,C78,C77,C75,C39,C36,C31,C30,C28,C25,C23) -> 3583494.2 | D163: =SUM(D161,D153,D150,D149,D147,D146,D82,D78,D77,D75,D39,D36,D31,D30,D28,D25,D23) -> 2965507.6 | E163: =SUM(E161,E153,E150,E149,E147,E146,E82,E78,E77,E75,E39,E36,E31,E30,E28,E25,E23) -> 0 | F163: =SUM(F161,F153,F150,F149,F147,F146,F82,F78,F77,F75,F39,F36,F31,F30,F28,F25,F23) -> 0 | G163: =SUM(G161,G153,G150,G149,G147,G146,G82,G78,G77,G75,G39,G36,G31,G30,G28,G25,G23) -> 0 | H163: =SUM(H161,H153,H150,H149,H147,H146,H82,H78,H77,H75,H39,H36,H31,H30,H28,H25,H23) -> 0 | I163: =SUM(I161,I153,I150,I149,I147,I146,I82,I78,I77,I75,I39,I36,I31,I30,I28,I25,I23) -> 0 | ... P163: =SUM(P161,P153,P150,P149,P147,P146,P82,P78,P77,P75,P39,P36,P31,P30,P28,P25,P23) -> 0
A164: ACUMULADO | B164: =B5-B162 -> 52056645 | C164: =C163 -> 3583494.2 | D164: =C164+D163 -> 6549001.8 | E164: =D164+E163 -> 6549001.8 | F164: =E164+F163 -> 6549001.8 | G164: =F164+G163 -> 6549001.8 | H164: =G164+H163 -> 6549001.8 | I164: =H164+I163 -> 6549001.8 | J164: =I164+J163 -> 6549001.8 | K164: =J164+K163 -> 6549001.8 | ... P164: =O164+P163 -> 6549001.8 | Q164: =B162/$B$162 -> 1
B165: =1-(B162/B5) -> 0.69113933
A167: INGRESOS 2022 USD
A168: Descripcion | B168: Total Presupuestado | C168: Instalación | D168: Instalación | E168: Enero | F168: Febrero | G168: Marzo | H168: Abril | I168: Mayo | J168: Junio | K168: Julio | L168: Agosto | M168: Septiembre | N168: Octubre | O168: Noviembre | P168: Diciembre
A169: FACTURACION | B169: =SUM(C169:P169) -> 4168237.1 | C169: ='F08 INGRESOS'!M17 -> 984130.19 | D169: ='F08 INGRESOS'!N17 -> 3184106.9 | E169: ='F08 INGRESOS'!O17 -> 0 | F169: ='F08 INGRESOS'!P17 -> 0 | G169: ='F08 INGRESOS'!Q17 -> 0 | H169: ='F08 INGRESOS'!R17 -> 0 | I169: ='F08 INGRESOS'!S17 -> 0 | J169: ='F08 INGRESOS'!T17 -> 0 | ... P169: ='F08 INGRESOS'!Z17 -> 0
A171: EGRESOS 2024
A172: Descripcion | B172: Total Presupuestado | C172: Instalación | D172: Instalación | E172: Enero | F172: Febrero | G172: Marzo | H172: Abril | I172: Mayo | J172: Junio | K172: Julio | L172: Agosto | M172: Septiembre | N172: Octubre | O172: Noviembre | P172: Diciembre
A173: ACTIVOS | B173: =SUM(C173:P173) -> 924980.5 | C173: =C13/$B$196 -> 924980.5 | D173: =D13/$B$196 -> 0 | E173: =E13/$B$196 -> 0 | F173: =F13/$B$196 -> 0 | G173: =G13/$B$196 -> 0 | H173: =H13/$B$196 -> 0 | I173: =I13/$B$196 -> 0 | J173: =J13/$B$196 -> 0 | ... P173: =P13/$B$196 -> 0
A174: ARRENDA DE INMUEBLES Y SERV | B174: =SUM(C174:P174) -> 0 | C174: =C23/$B$196 -> 0 | D174: =D23/$B$196 -> 0 | E174: =E23/$B$196 -> 0 | F174: =F23/$B$196 -> 0 | G174: =G23/$B$196 -> 0 | H174: =H23/$B$196 -> 0 | I174: =I23/$B$196 -> 0 | J174: =J23/$B$196 -> 0 | ... P174: =P23/$B$196 -> 0
...

Sheet Comparativa Anexo C
B2: RESUMEN ORDINARIAS
B3: No. | C3: DISCIPLINA | D3: MONTO [USD] | E3: GEOLIS
B4: 9 | C4: OBRA CIVIL | D4: 104077.7 | E4: =D4*0.7 -> 72854.39
B5: 2 | C5: OBRA ELÉCTRICA | D5: 1149249 | E5: =D5*0.7 -> 804474.31
B6: 83 | C6: OBRA MECÁNICA | D6: 880052.49 | E6: =D6*0.7 -> 616036.74
B8: TOTAL | D8: =SUM(D4:D7) -> 2133379.2 | E8: =D8*0.7 -> 1493365.4
B10: RESUMEN
B11: No. | C11: DISCIPLINA | D11: MONTO [USD] | E11: GEOLIS
B12: 49 | C12: INTERCONEXIÓN DE TBBA-04 (SUCCIÓN, DESCARGA, DRENAJE Y GAS COMBUSTIBLE) | D12: 228790.08 | E12: =D12*0.7 -> 160153.06
B13: 37 | C13: OBRA ELÉCTRICA | D13: 1790079 | E13: =D13*0.7 -> 1253055.3
B14: 2 | C14: INGENIERIA | D14: 15988.8 | E14: =D14*0.7 -> 11192.16
E15: =D15*0.7 -> 0
E16: =D16*0.7 -> 0
B17: TOTAL | D17: =SUM(D12:D16) -> 2034857.9 | E17: =D17*0.7 -> 1424400.5

Sheet GRÁFICA

Sheet GRÁFICA II
B32: OPEX | C32: Mes 0 | D32: Instalación | E32: Mes 2 | F32: Mes 3 | G32: Mes 4 | H32: Mes 5 | I32: Mes 6 | J32: Mes 7 | K32: Mes 8 | L32: Mes 9 | M32: Mes 10 | N32: Mes 11 | O32: Mes 12 | P32: Mes 13 | Q32: Mes 14 | R32: Total
A33: 1 | B33: =SERVICIO!A23 -> ARRENDA DE INMUEBLES Y SERV | C33: =SERVICIO!C23 -> 0 | D33: =SERVICIO!D23 -> 0 | E33: =SERVICIO!E23 -> 0 | F33: =SERVICIO!F23 -> 0 | G33: =SERVICIO!G23 -> 0 | H33: =SERVICIO!H23 -> 0 | I33: =SERVICIO!I23 -> 0 | J33: =SERVICIO!J23 -> 0 | ... P33: =SERVICIO!P23 -> 0 | Q33: =SERVICIO!#REF! -> #REF! | R33: =SERVICIO!B23 -> 0
A34: 2 | B34: =SERVICIO!A25 -> ARTICULOS DE SEGURIDAD | C34: =SERVICIO!C25 -> 233794.18 | D34: =SERVICIO!D25 -> 0 | E34: =SERVICIO!E25 -> 0 | F34: =SERVICIO!F25 -> 0 | G34: =SERVICIO!G25 -> 0 | H34: =SERVICIO!H25 -> 0 | I34: =SERVICIO!I25 -> 0 | J34: =SERVICIO!J25 -> 0 | ... P34: =SERVICIO!P25 -> 0 | Q34: =SERVICIO!#REF! -> #REF! | R34: =SERVICIO!B25 -> 233794.18
A35: 3 | B35: =SERVICIO!A28 -> EQUIPO DE COMPUTO | C35: =SERVICIO!C28 -> 0 | D35: =SERVICIO!D28 -> 32526 | E35: =SERVICIO!E28 -> 0 | F35: =SERVICIO!F28 -> 0 | G35: =SERVICIO!G28 -> 0 | H35: =SERVICIO!H28 -> 0 | I35: =SERVICIO!I28 -> 0 | J35: =SERVICIO!J28 -> 0 | ... P35: =SERVICIO!P28 -> 0 | Q35: =SERVICIO!#REF! -> #REF! | R35: =SERVICIO!B28 -> 32526
A36: 4 | B36: =SERVICIO!A30 -> EQUIPOS Y ENSERES | C36: =SERVICIO!C30 -> 5028.76 | D36: =SERVICIO!D30 -> 5028.76 | E36: =SERVICIO!E30 -> 0 | F36: =SERVICIO!F30 -> 0 | G36: =SERVICIO!G30 -> 0 | H36: =SERVICIO!H30 -> 0 | I36: =SERVICIO!I30 -> 0 | J36: =SERVICIO!J30 -> 0 | ... P36: =SERVICIO!P30 -> 0 | Q36: =SERVICIO!#REF! -> #REF! | R36: =SERVICIO!B30 -> 10057.52
A37: 5 | B37: =SERVICIO!A31 -> INSUMOS AGRICOLAS | C37: =SERVICIO!C31 -> 0 | D37: =SERVICIO!D31 -> 0 | E37: =SERVICIO!E31 -> 0 | F37: =SERVICIO!F31 -> 0 | G37: =SERVICIO!G31 -> 0 | H37: =SERVICIO!H31 -> 0 | I37: =SERVICIO!I31 -> 0 | J37: =SERVICIO!J31 -> 0 | ... P37: =SERVICIO!P31 -> 0 | Q37: =SERVICIO!#REF! -> #REF! | R37: =SERVICIO!B31 -> 0
A38: 6 | B38: =SERVICIO!A36 -> INSUMOS DE OFICINA | C38: =SERVICIO!C36 -> 0 | D38: =SERVICIO!D36 -> 0 | E38: =SERVICIO!E36 -> 0 | F38: =SERVICIO!F36 -> 0 | G38: =SERVICIO!G36 -> 0 | H38: =SERVICIO!H36 -> 0 | I38: =SERVICIO!I36 -> 0 | J38: =SERVICIO!J36 -> 0 | ... P38: =SERVICIO!P36 -> 0 | Q38: =SERVICIO!#REF! -> #REF! | R38: =SERVICIO!B36 -> 0
A39: 7 | B39: =SERVICIO!A39 -> MARKETING | C39: =SERVICIO!C39 -> 0 | D39: =SERVICIO!D39 -> 0 | E39: =SERVICIO!E39 -> 0 | F39: =SERVICIO!F39 -> 0 | G39: =SERVICIO!G39 -> 0 | H39: =SERVICIO!H39 -> 0 | I39: =SERVICIO!I39 -> 0 | J39: =SERVICIO!J39 -> 0 | ... P39: =SERVICIO!P39 -> 0 | Q39: =SERVICIO!#REF! -> #REF! | R39: =SERVICIO!B39 -> 0
A40: 8 | B40: =SERVICIO!A75 -> MATERIALES | C40: =SERVICIO!C75 -> 10498.67 | D40: =SERVICIO!D75 -> 10498.67 | E40: =SERVICIO!E75 -> 0 | F40: =SERVICIO!F75 -> 0 | G40: =SERVICIO!G75 -> 0 | H40: =SERVICIO!H75 -> 0 | I40: =SERVICIO!I75 -> 0 | J40: =SERVICIO!J75 -> 0 | ... P40: =SERVICIO!P75 -> 0 | Q40: =SERVICIO!#REF! -> #REF! | R40: =SERVICIO!B75 -> 20997.34
A41: 9 | B41: =SERVICIO!A77 -> MATERIALES DE SALUD | C41: =SERVICIO!C77 -> 0 | D41: =SERVICIO!D77 -> 0 | E41: =SERVICIO!E77 -> 0 | F41: =SERVICIO!F77 -> 0 | G41: =SERVICIO!G77 -> 0 | H41: =SERVICIO!H77 -> 0 | I41: =SERVICIO!I77 -> 0 | J41: =SERVICIO!J77 -> 0 | ... P41: =SERVICIO!P77 -> 0 | Q41: =SERVICIO!#REF! -> #REF! | R41: =SERVICIO!B77 -> 0
A42: 10 | B42: =SERVICIO!A78 -> NOMINA Y ADICIONALES | C42: =SERVICIO!C78 -> 417404.61 | D42: =SERVICIO!D78 -> 678534.54 | E42: =SERVICIO!E78 -> 0 | F42: =SERVICIO!F78 -> 0 | G42: =SERVICIO!G78 -> 0 | H42: =SERVICIO!H78 -> 0 | I42: =SERVICIO!I78 -> 0 | J42: =SERVICIO!J78 -> 0 | ... P42: =SERVICIO!P78 -> 0 | Q42: =SERVICIO!#REF! -> #REF! | R42: =SERVICIO!B78 -> 1095939.1
A43: 11 | B43: =SERVICIO!A82 -> SERV TELEFONIA CELULAR Y RADIO | C43: =SERVICIO!C82 -> 0 | D43: =SERVICIO!D82 -> 0 | E43: =SERVICIO!E82 -> 0 | F43: =SERVICIO!F82 -> 0 | G43: =SERVICIO!G82 -> 0 | H43: =SERVICIO!H82 -> 0 | I43: =SERVICIO!I82 -> 0 | J43: =SERVICIO!J82 -> 0 | ... P43: =SERVICIO!P82 -> 0 | Q43: =SERVICIO!#REF! -> #REF! | R43: =SERVICIO!B82 -> 0
A44: 12 | B44: =SERVICIO!A146 -> SERVICIOS | C44: =SERVICIO!C146 -> 1959720.8 | D44: =SERVICIO!D146 -> 1281872.5 | E44: =SERVICIO!E146 -> 0 | F44: =SERVICIO!F146 -> 0 | G44: =SERVICIO!G146 -> 0 | H44: =SERVICIO!H146 -> 0 | I44: =SERVICIO!I146 -> 0 | J44: =SERVICIO!J146 -> 0 | ... P44: =SERVICIO!P146 -> 0 | Q44: =SERVICIO!#REF! -> #REF! | R44: =SERVICIO!B146 -> 3241593.3
A45: 13 | B45: =SERVICIO!A147 -> SERVICIOS DE CAPACITACION | C45: =SERVICIO!C147 -> 0 | D45: =SERVICIO!D147 -> 0 | E45: =SERVICIO!E147 -> 0 | F45: =SERVICIO!F147 -> 0 | G45: =SERVICIO!G147 -> 0 | H45: =SERVICIO!H147 -> 0 | I45: =SERVICIO!I147 -> 0 | J45: =SERVICIO!J147 -> 0 | ... P45: =SERVICIO!P147 -> 0 | Q45: =SERVICIO!#REF! -> #REF! | R45: =SERVICIO!B147 -> 0
A46: 14 | B46: =SERVICIO!A149 -> SERVICIOS DE SALUD | C46: =SERVICIO!C149 -> 0 | D46: =SERVICIO!D149 -> 0 | E46: =SERVICIO!E149 -> 0 | F46: =SERVICIO!F149 -> 0 | G46: =SERVICIO!G149 -> 0 | H46: =SERVICIO!H149 -> 0 | I46: =SERVICIO!I149 -> 0 | J46: =SERVICIO!J149 -> 0 | ... P46: =SERVICIO!P149 -> 0 | Q46: =SERVICIO!#REF! -> #REF! | R46: =SERVICIO!B149 -> 0
A47: 15 | B47: =SERVICIO!A150 -> UNIFORMES | C47: =SERVICIO!C150 -> 0 | D47: =SERVICIO!D150 -> 0 | E47: =SERVICIO!E150 -> 0 | F47: =SERVICIO!F150 -> 0 | G47: =SERVICIO!G150 -> 0 | H47: =SERVICIO!H150 -> 0 | I47: =SERVICIO!I150 -> 0 | J47: =SERVICIO!J150 -> 0 | ... P47: =SERVICIO!P150 -> 0 | Q47: =SERVICIO!#REF! -> #REF! | R47: =SERVICIO!B150 -> 0
A48: 16 | B48: =SERVICIO!A153 -> VEHICULOS Y COMBUSTIBLE | C48: =SERVICIO!C153 -> 150400 | D48: =SERVICIO!D153 -> 150400 | E48: =SERVICIO!E153 -> 0 | F48: =SERVICIO!F153 -> 0 | G48: =SERVICIO!G153 -> 0 | H48: =SERVICIO!H153 -> 0 | I48: =SERVICIO!I153 -> 0 | J48: =SERVICIO!J153 -> 0 | ... P48: =SERVICIO!P153 -> 0 | Q48: =SERVICIO!#REF! -> #REF! | R48: =SERVICIO!B153 -> 300800
A49: 17 | B49: =SERVICIO!A161 -> VIATICOS | C49: =SERVICIO!C161 -> 806647.15 | D49: =SERVICIO!D161 -> 806647.15 | E49: =SERVICIO!E161 -> 0 | F49: =SERVICIO!F161 -> 0 | G49: =SERVICIO!G161 -> 0 | H49: =SERVICIO!H161 -> 0 | I49: =SERVICIO!I161 -> 0 | J49: =SERVICIO!J161 -> 0 | ... P49: =SERVICIO!P161 -> 0 | Q49: =SERVICIO!#REF! -> #REF! | R49: =SERVICIO!B161 -> 1613294.3
R50: =SUM(R33:R49) -> 6549001.8

Sheet PREMISAS
M3: Instalación | N3: Instalación | O3: Mes 1 | P3: Mes 2 | Q3: Mes 3 | R3: Mes 4 | S3: Mes 5 | T3: Mes 6 | U3: Mes 7 | V3: Mes 8 | W3: Mes 9 | X3: Mes 10 | Y3: Mes 11 | Z3: Mes 12
O4: ENE | P4: FEB | Q4: MAR | R4: ABR | S4: MAY | T4: JUN | U4: JUL | V4: AGO | W4: SEP | X4: OCT | Y4: NOV | Z4: DIC
B5: PARTIDAS | C5: DESCRIPCIÓN | F5: UNIDAD | G5: CANTIDAD | H5: PU [USD] | I5: PU [MN] | J5: TOTAL [USD] | K5: TOTAL [MN] | O5: 31 | P5: 29 | Q5: 31 | R5: 30 | S5: 30 | T5: 31 | U5: 31 | V5: 31 | W5: 30 | X5: 31 | Y5: 30 | Z5: 31
B6: BEH
B7: 1 | C7: ='Comparativa Anexo C'!C4 -> OBRA CIVIL | F7: Servicio | G7: 1 | H7: ='Comparativa Anexo C'!D4 -> 104077.7 | I7: =H7*$D$18 -> 1880684 | J7: =H7*G7 -> 104077.7 | K7: =G7*I7 -> 1880684 | M7: =K7 -> 1880684 | N7: 0 | O7: 0 | P7: 0 | Q7: 0 | R7: 0 | S7: 0 | T7: 0 | U7: 0 | V7: 0 | W7: 0 | X7: 0 | Y7: 0 | Z7: 0
B8: 2 | C8: ='Comparativa Anexo C'!C5 -> OBRA ELÉCTRICA | F8: Día | G8: 1 | H8: ='Comparativa Anexo C'!D5 -> 1149249 | I8: =H8*$D$18 -> 20766930 | J8: =H8*G8 -> 1149249 | K8: =G8*I8 -> 20766930 | N8: =K8 -> 20766930 | O8: 0 | P8: 0 | Q8: 0 | R8: 0 | S8: 0 | T8: 0 | U8: 0 | V8: 0 | W8: 0 | X8: 0 | Y8: 0 | Z8: 0
B9: 3 | C9: ='Comparativa Anexo C'!C6 -> OBRA MECÁNICA | F9: Día | G9: 1 | H9: ='Comparativa Anexo C'!D6 -> 880052.49 | I9: =H9*$D$18 -> 15902548 | J9: =H9*G9 -> 880052.49 | K9: =G9*I9 -> 15902548 | M9: =K9 -> 15902548 | O9: 0 | P9: 0 | Q9: 0 | R9: 0 | S9: 0 | T9: 0 | U9: 0 | V9: 0 | W9: 0 | X9: 0 | Y9: 0 | Z9: 0
B10: 4 | C10: - | F10: Día | G10: 1 | H10: ='Comparativa Anexo C'!E7 -> 0 | I10: =H10*$D$18 -> 0 | J10: =H10*G10 -> 0 | K10: =G10*I10 -> 0 | M10: =K10 -> 0 | N10: 0 | O10: 0 | P10: 0 | Q10: 0 | R10: 0 | S10: 0 | T10: 0 | U10: 0 | V10: 0 | W10: 0 | X10: 0 | Y10: 0 | Z10: 0
B11: 5 | C11: - | F11: Día | G11: 0 | H11: 0 | I11: =H11*$D$18 -> 0 | J11: =H11*G11 -> 0 | K11: =G11*I11 -> 0 | M11: 0 | N11: 0 | O11: 0 | P11: 0 | Q11: 0 | R11: 0 | S11: 0 | T11: 0 | U11: 0 | V11: 0 | W11: 0 | X11: 0 | Y11: 0 | Z11: 0
B12: 6 | C12: Conceptos extraordinarios | F12: Día | G12: 1 | H12: ='Comparativa Anexo C'!D17 -> 2034857.9 | I12: =H12*$D$18 -> 36769882 | J12: =H12*G12 -> 2034857.9 | K12: =G12*I12 -> 36769882 | M12: 0 | N12: =K12 -> 36769882 | O12: 0 | P12: 0 | Q12: 0 | R12: 0 | S12: 0 | T12: 0 | U12: 0 | V12: 0 | W12: 0 | X12: 0 | Y12: 0 | Z12: 0
B14: Costo día Gen Op. + Resp. | D14: 4540.18 | E14: =D14*D18 -> 82041.053 | J14: Total Mensual [MN] | M14: =SUM(M7:M12) -> 17783233 | N14: =SUM(N7:N12) -> 57536812 | O14: =SUM(O7:O12) -> 0 | P14: =SUM(P7:P12) -> 0 | Q14: =SUM(Q7:Q12) -> 0 | R14: =SUM(R7:R12) -> 0 | S14: =SUM(S7:S12) -> 0 | T14: =SUM(T7:T12) -> 0 | ... Z14: =SUM(Z7:Z12) -> 0
B15: Costo día 2 Gen Op. | D15: 5141.2 | E15: =D15*D18 -> 92901.484 | J15: Total Mensual [USD] | M15: =M14/$D$18 -> 984130.19 | N15: =N14/$D$18 -> 3184106.9 | O15: =O14/$D$18 -> 0 | P15: =P14/$D$18 -> 0 | Q15: =Q14/$D$18 -> 0 | R15: =R14/$D$18 -> 0 | S15: =S14/$D$18 -> 0 | T15: =T14/$D$18 -> 0 | ... Z15: =Z14/$D$18 -> 0
J16: Total [MN] | M16: =SUM(M14:Z14) -> 75320045
C17: Premisas | J17: Total [USD] | M17: =SUM(M15:Z15) -> 4168237.1
C18: Paridad | D18: 18.07
C19: Mes | D19: 30.4 | I19: Ingresos sin IVA (MXN) | K19: =M16 -> 75320045
C20: Periodo Pago (días) | D20: 30 | I20: Ingresos IVA (MXN) | K20: =K19*1.16 -> 87371252
C21: Gas lp | D21: 0 | I21: Ingresos IVA (USD) | K21: =M17 -> 4168237.1
C22: Gasolina Magna | D22: 22 | I22: Ingresos sin IVA (USD) | K22: =K21*1.16 -> 4835155.1
C23: Diesel | D23: 23
C24: https://www.google.com/search?client=firefox-b-d&q=precio+del+dolar+hoy
B81: 64373.77
O124: ENE | P124: FEB
C125: ='F08 INGRESOS'!M17 -> 984130.19 | D125: ='F08 INGRESOS'!N17 -> 3184106.9 | E125: ='F08 INGRESOS'!O17 -> 0 | F125: ='F08 INGRESOS'!P17 -> 0 | G125: ='F08 INGRESOS'!Q17 -> 0 | H125: ='F08 INGRESOS'!R17 -> 0 | I125: ='F08 INGRESOS'!S17 -> 0 | J125: ='F08 INGRESOS'!T17 -> 0 | ... P125: ='F08 INGRESOS'!Z17 -> 0
B129: =SUM(C129:P129) -> #DIV/0! | D129: =D13/$B$152 -> #DIV/0!
B130: =SUM(C130:P130) -> #DIV/0! | D130: =D23/$B$152 -> #DIV/0!
B131: =SUM(C131:P131) -> 0
B132: =SUM(C132:P132) -> 0
B133: =SUM(C133:P133) -> #REF! | D133: =#REF!/$B$152 -> #REF!
B134: =SUM(C134:P134) -> 0
B135: =SUM(C135:P135) -> 0
B136: =SUM(C136:P136) -> 0
B137: =SUM(C137:P137) -> 0
B138: =SUM(C138:P138) -> 0
B139: =SUM(C139:P139) -> 0
B140: =SUM(C140:P140) -> 0
B141: =SUM(C141:P141) -> #DIV/0! | G141: =G102/$B$152 -> #DIV/0!
B142: =SUM(C142:P142) -> 0
B143: =SUM(C143:P143) -> 0
B144: =SUM(C144:P144) -> 0
B145: =SUM(C145:P145) -> 0
B146: =SUM(C146:P146) -> #DIV/0! | F146: =F117/$B$152 -> #DIV/0! | H146: =H117/$B$152 -> #DIV/0!
E147: =E118/$B$152 -> #DIV/0! | F147: =F118/$B$152 -> #DIV/0! | G147: =G118/$B$152 -> #DIV/0! | H147: =H118/$B$152 -> #DIV/0! | I147: =I118/$B$152 -> #DIV/0! | J147: =J118/$B$152 -> #DIV/0! | K147: =K118/$B$152 -> #DIV/0! | L147: =L118/$B$152 -> #DIV/0! | ... P147: =P118/$B$152 -> #DIV/0!
B149: =1-(B147/B125) -> #DIV/0!

Sheet FLUJO
D1: 0 | E1: 1 | F1: 2 | G1: 3 | H1: 4 | I1: 5 | J1: 6 | K1: 7 | L1: 8 | M1: 9 | N1: 10 | O1: 11 | P1: 12
C3: Instalación | D3: Instalación | E3: Mes 1 | F3: Mes 2 | G3: Mes 3 | H3: Mes 4 | I3: Mes 5 | J3: Mes 6 | K3: Mes 7 | L3: Mes 8 | M3: Mes 9 | N3: Mes 10 | O3: Mes 11 | P3: Mes 12 | R3: =SUM(R6:R10) -> 38550162 | T3: =R3*1.16 -> 44718188 | V3: =+R3/$E$38 -> 2133379.2 | X3: =V3*1.16 -> 2474719.9
E4: ENE | F4: FEB | G4: MAR | H4: ABR | I4: MAY | J4: JUN | K4: JUL | L4: AGO | M4: SEP | N4: OCT | O4: NOV | P4: DIC | R4: TOTAL PROYECTO (MN) | T4: TOTAL PROYECTO IVA (MN) | V4: TOTAL PROYECTO (USD) | X4: TOTAL PROYECTO IVA (USD)
A5: Ingresos (MN) | E5: 31 | F5: 29 | G5: 31 | H5: 30 | I5: 30 | J5: 31 | K5: 31 | L5: 31 | M5: 30 | N5: 31 | O5: 30 | P5: 31
A6: =PREMISAS!C7 -> OBRA CIVIL | C6: ='F08 INGRESOS'!M8 -> 1880684 | D6: ='F08 INGRESOS'!N8 -> 0 | E6: ='F08 INGRESOS'!O8 -> 0 | F6: ='F08 INGRESOS'!P8 -> 0 | G6: ='F08 INGRESOS'!Q8 -> 0 | H6: ='F08 INGRESOS'!R8 -> 0 | I6: ='F08 INGRESOS'!S8 -> 0 | J6: ='F08 INGRESOS'!T8 -> 0 | ... P6: ='F08 INGRESOS'!Z8 -> 0 | R6: =SUM(C6:P6) -> 1880684 | T6: =R6*1.16 -> 2181593.5 | V6: =+R6/$E$38 -> 104077.7 | X6: =V6*1.16 -> 120730.13
A7: =PREMISAS!#REF! -> #REF! | C7: ='F08 INGRESOS'!M9 -> 0 | D7: ='F08 INGRESOS'!N9 -> 20766930 | E7: ='F08 INGRESOS'!O9 -> 0 | F7: ='F08 INGRESOS'!P9 -> 0 | G7: ='F08 INGRESOS'!Q9 -> 0 | H7: ='F08 INGRESOS'!R9 -> 0 | I7: ='F08 INGRESOS'!S9 -> 0 | J7: ='F08 INGRESOS'!T9 -> 0 | ... P7: ='F08 INGRESOS'!Z9 -> 0 | R7: =SUM(C7:P7) -> 20766930 | T7: =R7*1.16 -> 24089639 | V7: =+R7/$E$38 -> 1149249 | X7: =V7*1.16 -> 1333128.9
A8: =PREMISAS!C8 -> OBRA ELÉCTRICA | C8: ='F08 INGRESOS'!M10 -> 15902548 | D8: ='F08 INGRESOS'!N10 -> 0 | E8: ='F08 INGRESOS'!O10 -> 0 | F8: ='F08 INGRESOS'!P10 -> 0 | G8: ='F08 INGRESOS'!Q10 -> 0 | H8: ='F08 INGRESOS'!R10 -> 0 | I8: ='F08 INGRESOS'!S10 -> 0 | J8: ='F08 INGRESOS'!T10 -> 0 | ... P8: ='F08 INGRESOS'!Z10 -> 0 | R8: =SUM(C8:P8) -> 15902548 | T8: =R8*1.16 -> 18446956 | V8: =+R8/$E$38 -> 880052.49 | X8: =V8*1.16 -> 1020860.9
A9: =PREMISAS!C9 -> OBRA MECÁNICA | C9: ='F08 INGRESOS'!M11 -> 0 | D9: ='F08 INGRESOS'!N11 -> 0 | E9: ='F08 INGRESOS'!O11 -> 0 | F9: ='F08 INGRESOS'!P11 -> 0 | G9: ='F08 INGRESOS'!Q11 -> 0 | H9: ='F08 INGRESOS'!R11 -> 0 | I9: ='F08 INGRESOS'!S11 -> 0 | J9: ='F08 INGRESOS'!T11 -> 0 | ... P9: ='F08 INGRESOS'!Z11 -> 0 | R9: =SUM(C9:P9) -> 0 | T9: =R9*1.16 -> 0 | V9: =+R9/$E$38 -> 0 | X9: =V9*1.16 -> 0
A10: =PREMISAS!C11 -> - | C10: ='F08 INGRESOS'!M12 -> 0 | D10: ='F08 INGRESOS'!N12 -> 0 | E10: ='F08 INGRESOS'!O12 -> 0 | F10: ='F08 INGRESOS'!P12 -> 0 | G10: ='F08 INGRESOS'!Q12 -> 0 | H10: ='F08 INGRESOS'!R12 -> 0 | I10: ='F08 INGRESOS'!S12 -> 0 | J10: ='F08 INGRESOS'!T12 -> 0 | ... P10: ='F08 INGRESOS'!Z12 -> 0 | R10: =SUM(C10:P10) -> 0 | T10: =R10*1.16 -> 0 | V10: =+R10/$E$38 -> 0 | X10: =V10*1.16 -> 0
A11: =PREMISAS!C12 -> Conceptos extraordinarios | E11: ='F08 INGRESOS'!O13 -> 0 | F11: ='F08 INGRESOS'!P13 -> 0 | G11: ='F08 INGRESOS'!Q13 -> 0 | H11: ='F08 INGRESOS'!R13 -> 0 | I11: ='F08 INGRESOS'!S13 -> 0 | J11: ='F08 INGRESOS'!T13 -> 0 | K11: ='F08 INGRESOS'!U13 -> 0 | L11: ='F08 INGRESOS'!V13 -> 0 | ... P11: ='F08 INGRESOS'!Z13 -> 0 | R11: =SUM(C11:P11) -> 0 | T11: =R11*1.16 -> 0 | V11: =+R11/$E$38 -> 0 | X11: =V11*1.16 -> 0
A12: Ingresos Totales (MN) | C12: =SUM(C6:C11) -> 17783233 | D12: =SUM(D6:D11) -> 20766930 | E12: =SUM(E6:E11) -> 0 | F12: =SUM(F6:F11) -> 0 | G12: =SUM(G6:G11) -> 0 | H12: =SUM(H6:H11) -> 0 | I12: =SUM(I6:I11) -> 0 | J12: =SUM(J6:J11) -> 0 | ... P12: =SUM(P6:P11) -> 0 | R12: =SUM(C12:P12) -> 38550162
A14: Ingresos Totales (MN) IVA | C14: =+C12*1.16 -> 20628550 | D14: =+D12*1.16 -> 24089639 | E14: =+E12*1.16 -> 0 | F14: =+F12*1.16 -> 0 | G14: =+G12*1.16 -> 0 | H14: =+H12*1.16 -> 0 | I14: =+I12*1.16 -> 0 | J14: =+J12*1.16 -> 0 | ... P14: =+P12*1.16 -> 0 | R14: =SUM(C14:P14) -> 44718188
A16: Egresos (MX)
A17: OPEX | C17: =EGRESOS!D37 -> 3583494.2 | D17: =EGRESOS!E37 -> 2965507.6 | E17: =EGRESOS!F37 -> 0 | F17: =EGRESOS!G37 -> 0 | G17: =EGRESOS!H37 -> 0 | H17: =EGRESOS!I37 -> 0 | I17: =EGRESOS!J37 -> 0 | J17: =EGRESOS!K37 -> 0 | ... P17: =EGRESOS!Q37 -> 0 | R17: =SUM(C17:P17) -> 6549001.8 | V17: =+R17/$E$38 -> 362424 | X17: =+V17*1.16 -> 420411.85
A18: FINANCIAMIENTO
A19: CAPEX | C19: =EGRESOS!D35 -> 16714398 | D19: =EGRESOS!E35 -> 0 | E19: =EGRESOS!F35 -> 0 | F19: =EGRESOS!G35 -> 0 | G19: =EGRESOS!H35 -> 0 | H19: =EGRESOS!I35 -> 0 | I19: =EGRESOS!J35 -> 0 | J19: =EGRESOS!K35 -> 0 | ... P19: =EGRESOS!Q35 -> 0 | R19: =SUM(C19:P19) -> 16714398 | V19: =+R19/$E$38 -> 924980.5 | X19: =+V19*1.16 -> 1072977.4
A21: Egresos Totales (MN) | C21: =SUM(C17:C20) -> 20297892 | D21: =SUM(D17:D20) -> 2965507.6 | E21: =SUM(E17:E20) -> 0 | F21: =SUM(F17:F20) -> 0 | G21: =SUM(G17:G20) -> 0 | H21: =SUM(H17:H20) -> 0 | I21: =SUM(I17:I20) -> 0 | J21: =SUM(J17:J20) -> 0 | ... P21: =SUM(P17:P20) -> 0 | R21: =SUM(C21:P21) -> 23263399 | T21: =+R21*1.16 -> 26985543 | V21: =+R21/$E$38 -> 1287404.5 | X21: =+V21*1.16 -> 1493389.2
A23: Egresos Totales (MN) IVA | C23: =+C21*1.16 -> 23545554 | D23: =+D21*1.16 -> 3439988.8 | E23: =+E21*1.16 -> 0 | F23: =+F21*1.16 -> 0 | G23: =+G21*1.16 -> 0 | H23: =+H21*1.16 -> 0 | I23: =+I21*1.16 -> 0 | J23: =+J21*1.16 -> 0 | ... P23: =+P21*1.16 -> 0 | R23: =SUM(C23:P23) -> 26985543 | T23: =+R23*1.16 -> 31303230 | V23: =+R23/$E$38 -> 1493389.2 | X23: =+V23*1.16 -> 1732331.5
A25: FLUJO EFECTIVO | C25: =C12-C21 -> -2514659.2 | D25: =D12-D21 -> 17801422 | E25: =E12-E21 -> 0 | F25: =F12-F21 -> 0 | G25: =G12-G21 -> 0 | H25: =H12-H21 -> 0 | I25: =I12-I21 -> 0 | J25: =J12-J21 -> 0 | ... P25: =P12-P21 -> 0
A27: FLUJO EFECTIVO IVA | C27: =+C25*1.16 -> -2917004.7 | D27: =+D25*1.16 -> 20649650 | E27: =+E25*1.16 -> 0 | F27: =+F25*1.16 -> 0 | G27: =+G25*1.16 -> 0 | H27: =+H25*1.16 -> 0 | I27: =+I25*1.16 -> 0 | J27: =+J25*1.16 -> 0 | ... P27: =+P25*1.16 -> 0
A29: FLUJO ACUMULADO | C29: =+C25 -> -2514659.2 | D29: =+D25+C29 -> 15286763 | E29: =+E25+D29 -> 15286763 | F29: =+F25+E29 -> 15286763 | G29: =+G25+F29 -> 15286763 | H29: =+H25+G29 -> 15286763 | I29: =+I25+H29 -> 15286763 | J29: =+J25+I29 -> 15286763 | K29: =+K25+J29 -> 15286763 | ... P29: =+P25+O29 -> 15286763
A31: FLUJO ACUMULADO IVA | C31: =+C29*1.16 -> -2917004.7 | D31: =+D29*1.16 -> 17732645 | E31: =+E29*1.16 -> 17732645 | F31: =+F29*1.16 -> 17732645 | G31: =+G29*1.16 -> 17732645 | H31: =+H29*1.16 -> 17732645 | I31: =+I29*1.16 -> 17732645 | J31: =+J29*1.16 -> 17732645 | ... P31: =+P29*1.16 -> 17732645
C33: OPEX Promedio | D33: =AVERAGE(C17:P17) -> 467785.84
C34: CAPEX | D34: =SUM(C19:G19) -> 16714398
C35: Opex Total | D35: =SUM(C17:P17) -> 6549001.8
C37: FACTORES DE SENSIBILIDAD | G37: RESULTADOS (MMMN)
C38: Tipo de Cambio | E38: =PREMISAS!D18 -> 18.07 | I38: Total Ingresos | J38: =SUM(R12)/1000000 -> 38.550162
F39: USD | I39: Total Egresos | J39: =SUM(R21)/1000000 -> 23.263399
F40: USD
C41: Equipo sup. | F41: USD
C42: Instalación | F42: USD
C43: Gas lp | F43: (USD/L)
C44: Desinstalación | F44: USD
C45: Telemetría | F45: USD
C47: Préstamo | F47: USD | G47: EBTDA Acumulado | H47: =(R12-R21)/1000000 -> 15.286763 | I47: EBTDA Anual | J47: =H47/E51 -> 10.191175
C48: Capital de trabajo | E48: =MIN(C31:P31) -> -2917004.7 | G48: VPN | H48: =(NPV(E49/18,D25:P25))/1000000 -> 17.683532 | I48: VPN Anual | J48: =H48/E51 -> 11.789021
C49: Tasa de VPN y VPI Anual | E49: 0.12 | G49: VPI | H49: =(NPV(E49/18,D19:P19))/1000000 -> 0
C50: Meses de Préstamo | G50: Punto de Equilibrio | I50: meses
C51: Años del proyecto | E51: 1.5 | G51: TIR | H51: =XIRR(D25:P25,D4:P4) -> #VALUE! | I51: %
G52: Utilidades | H52: =+H47/J38 -> 0.39654212
C53: OPEX mensual (MMMN) | E53: =((AVERAGE(C17:P17)/1000000)) -> 0.46778584
C54: CAPEX total (MMMN) | E54: =R19/1000000 -> 16.714398 | G54: VPN/VPI | H54: =H48/H49 -> #DIV/0!

Sheet EGRESOS
A2: REFERENCIA EGRESO - JD EDWARDS
D4: Instalación | E4: Instalación | F4: Mes 1 | G4: Mes 2 | H4: Mes 3 | I4: Mes 4 | J4: Mes 5 | K4: Mes 6 | L4: Mes 7 | M4: Mes 8 | N4: Mes 9 | O4: Mes 10 | P4: Mes 11 | Q4: Mes 12
D5: ABR | E5: MAY | F5: JUN | G5: JUL | H5: AGO | I5: SEP | J5: OCT | K5: NOV | L5: DIC | M5: ENE | N5: FEB | O5: MAR | P5: ABR | Q5: MAY | R5: TOTAL PROYECTO (MXN) | T5: TOTAL PROYECTO (USD)
D6: 30 | E6: 31 | F6: 20 | G6: 31 | H6: 31 | I6: 30 | J6: 31 | K6: 30 | L6: 31 | M6: 30 | N6: 31 | O6: 30 | P6: 31 | Q6: 31
A8: INVERSIÓN | D8: ='F00 INVERSIÓN'!L43 -> 16714398 | E8: ='F00 INVERSIÓN'!M43 -> 0 | F8: ='F00 INVERSIÓN'!N43 -> 0 | G8: ='F00 INVERSIÓN'!O43 -> 0 | H8: ='F00 INVERSIÓN'!P43 -> 0 | I8: ='F00 INVERSIÓN'!Q43 -> 0 | J8: ='F00 INVERSIÓN'!R43 -> 0 | K8: ='F00 INVERSIÓN'!S43 -> 0 | ... Q8: ='F00 INVERSIÓN'!Y43 -> 0 | R8: =SUM(D8:Q8) -> 16714398 | T8: =R8/$E$42 -> 924980.5 | V8: ='F00 INVERSIÓN'!L45 -> 16714398 | W8: =SERVICIO!B13 -> 16714398 | X8: =V8-R8 -> 0 | Y8: =V8-W8 -> 0
B9: ACTIVOS
A10: NOMINA Y ADICIONALES | D10: ='F01 NÓMINA'!X20+'F01 EPP'!M19+'F01 UNIFORMES'!M15 -> 651198.78 | E10: ='F01 NÓMINA'!Y20+'F01 EPP'!N19+'F01 UNIFORMES'!N15 -> 678534.54 | F10: ='F01 NÓMINA'!Z20+'F01 EPP'!O19+'F01 UNIFORMES'!O15 -> 0 | G10: ='F01 NÓMINA'!AA20+'F01 EPP'!P19+'F01 UNIFORMES'!P15 -> 0 | H10: ='F01 NÓMINA'!AB20+'F01 EPP'!Q19+'F01 UNIFORMES'!Q15 -> 0 | I10: ='F01 NÓMINA'!AC20+'F01 EPP'!R19+'F01 UNIFORMES'!R15 -> 0 | J10: ='F01 NÓMINA'!AD20+'F01 EPP'!S19+'F01 UNIFORMES'!S15 -> 0 | K10: ='F01 NÓMINA'!AE20+'F01 EPP'!T19+'F01 UNIFORMES'!T15 -> 0 | ... Q10: ='F01 NÓMINA'!AK20+'F01 EPP'!Z19+'F01 UNIFORMES'!Z15 -> 0 | R10: =SUM(D10:Q10) -> 1329733.3 | T10: =R10/$E$42 -> 73587.898 | V10: ='F01 NÓMINA'!X22+'F01 EPP'!M21+'F01 UNIFORMES'!M17 -> 1329733.3 | W10: ='F01 NÓMINA'!X22+'F01 EPP'!M21+'F01 UNIFORMES'!M17 -> 1329733.3 | X10: =V10-R10 -> 0 | Y10: =V10-W10 -> 0
B11: NÓMINA + EPP + UNIFORMES
A12: INMUEBLES Y SERVICIOS | D12: ='F02 INMUEBLES Y S'!N18 -> 0 | E12: ='F02 INMUEBLES Y S'!O18 -> 0 | F12: ='F02 INMUEBLES Y S'!P18 -> 0 | G12: ='F02 INMUEBLES Y S'!Q18 -> 0 | H12: ='F02 INMUEBLES Y S'!R18 -> 0 | I12: ='F02 INMUEBLES Y S'!S18 -> 0 | J12: ='F02 INMUEBLES Y S'!T18 -> 0 | K12: ='F02 INMUEBLES Y S'!U18 -> 0 | ... Q12: ='F02 INMUEBLES Y S'!AA18 -> 0 | R12: =SUM(D12:Q12) -> 0 | T12: =R12/$E$42 -> 0 | V12: ='F02 INMUEBLES Y S'!N20 -> 0 | W12: =SERVICIO!B23 -> 0 | X12: =V12-R12 -> 0 | Y12: =V12-W12 -> 0
B13: INMUEBLES
A14: TELEFONIA Y COMUNICACIÓN | D14: ='F03 COM Y EQ COM'!L36 -> 0 | E14: ='F03 COM Y EQ COM'!M36 -> 0 | F14: ='F03 COM Y EQ COM'!N36 -> 0 | G14: ='F03 COM Y EQ COM'!O36 -> 0 | H14: ='F03 COM Y EQ COM'!P36 -> 0 | I14: ='F03 COM Y EQ COM'!Q36 -> 0 | J14: ='F03 COM Y EQ COM'!R36 -> 0 | K14: ='F03 COM Y EQ COM'!S36 -> 0 | ... Q14: ='F03 COM Y EQ COM'!Y36 -> 0 | R14: =SUM(D14:Q14) -> 0 | T14: =R14/$E$42 -> 0 | V14: ='F03 COM Y EQ COM'!L38 -> 0 | W14: =SERVICIO!B82 -> 0 | X14: =V14-R14 -> 0 | Y14: =V14-W14 -> 0
B15: COM Y EQ COM
A16: VEHICULOS Y COMBUSTIBLE | D16: ='F04 VEHÍCULOS Y COMB. '!V25 -> 150400 | E16: ='F04 VEHÍCULOS Y COMB. '!W25 -> 150400 | F16: ='F04 VEHÍCULOS Y COMB. '!X25 -> 0 | G16: ='F04 VEHÍCULOS Y COMB. '!Y25 -> 0 | H16: ='F04 VEHÍCULOS Y COMB. '!Z25 -> 0 | I16: ='F04 VEHÍCULOS Y COMB. '!AA25 -> 0 | J16: ='F04 VEHÍCULOS Y COMB. '!AB25 -> 0 | K16: ='F04 VEHÍCULOS Y COMB. '!AC25 -> 0 | ... Q16: ='F04 VEHÍCULOS Y COMB. '!AI25 -> 0 | R16: =SUM(D16:Q16) -> 300800 | T16: =R16/$E$42 -> 16646.375 | V16: ='F04 VEHÍCULOS Y COMB. '!V27 -> 300800 | W16: =SERVICIO!B153 -> 300800 | X16: =V16-R16 -> 0 | Y16: =V16-W16 -> 0
B17: VEHÍCULOS Y COMB
A18: VIATICOS | D18: ='F05 VIÁTICOS'!K28 -> 806647.15 | E18: ='F05 VIÁTICOS'!L28 -> 806647.15 | F18: ='F05 VIÁTICOS'!M28 -> 0 | G18: ='F05 VIÁTICOS'!N28 -> 0 | H18: ='F05 VIÁTICOS'!O28 -> 0 | I18: ='F05 VIÁTICOS'!P28 -> 0 | J18: ='F05 VIÁTICOS'!Q28 -> 0 | K18: ='F05 VIÁTICOS'!R28 -> 0 | ... Q18: ='F05 VIÁTICOS'!X28 -> 0 | R18: =SUM(D18:Q18) -> 1613294.3 | T18: =R18/$E$42 -> 89280.26 | V18: ='F05 VIÁTICOS'!K30 -> 1613294.3 | W18: =SERVICIO!B161 -> 1613294.3 | X18: =V18-R18 -> 0 | Y18: =V18-W18 -> 0
B19: VIATICOS CAJA CHICA Y REEMBOLSO
A20: MAT, SERV & EQUIPO | D20: ='F06 (MAT,SERV & EQUIPO)'!M44 -> 10498.67 | E20: ='F06 (MAT,SERV & EQUIPO)'!N44 -> 10498.67 | F20: ='F06 (MAT,SERV & EQUIPO)'!O44 -> 0 | G20: ='F06 (MAT,SERV & EQUIPO)'!P44 -> 0 | H20: ='F06 (MAT,SERV & EQUIPO)'!Q44 -> 0 | I20: ='F06 (MAT,SERV & EQUIPO)'!R44 -> 0 | J20: ='F06 (MAT,SERV & EQUIPO)'!S44 -> 0 | K20: ='F06 (MAT,SERV & EQUIPO)'!T44 -> 0 | ... Q20: ='F06 (MAT,SERV & EQUIPO)'!Z44 -> 0 | R20: =SUM(D20:Q20) -> 20997.34 | T20: =R20/$E$42 -> 1162 | V20: ='F06 (MAT,SERV & EQUIPO)'!M46 -> 20997.34 | W20: =SERVICIO!B75 -> 20997.34 | X20: =V20-R20 -> 0 | Y20: =V20-W20 -> 0
B21: MAT,SERV & EQUIPO
A22: SERVICIOS | D22: ='F07 OPERAC. (MAT,SERV & EQUIPO)'!L117 -> 1959720.8 | E22: ='F07 OPERAC. (MAT,SERV & EQUIPO)'!M117 -> 1281872.5 | F22: ='F07 OPERAC. (MAT,SERV & EQUIPO)'!N117 -> 0 | G22: ='F07 OPERAC. (MAT,SERV & EQUIPO)'!O117 -> 0 | H22: ='F07 OPERAC. (MAT,SERV & EQUIPO)'!P117 -> 0 | I22: ='F07 OPERAC. (MAT,SERV & EQUIPO)'!Q117 -> 0 | J22: ='F07 OPERAC. (MAT,SERV & EQUIPO)'!R117 -> 0 | K22: ='F07 OPERAC. (MAT,SERV & EQUIPO)'!S117 -> 0 | ... Q22: ='F07 OPERAC. (MAT,SERV & EQUIPO)'!Y117 -> 0 | R22: =SUM(D22:Q22) -> 3241593.3 | T22: =R22/$E$42 -> 179390.88 | V22: ='F07 OPERAC. (MAT,SERV & EQUIPO)'!L119 -> 3241593.3 | W22: =SERVICIO!B146 -> 3241593.3 | X22: =V22-R22 -> 0 | Y22: =V22-W22 -> 0
B23: MAT,SERV & EQUIPO
A24: ACTIVOS (CONSTRUCCION) | R24: =SUM(D24:Q24) -> 0 | X24: =V24-R24 -> 0 | Y24: =V24-W24 -> 0
A26: MATERIALES (OPERACION) | D26: ='F07 OPERAC. (MAT,SERV & EQUIPO)'!L44 -> 5028.76 | E26: ='F07 OPERAC. (MAT,SERV & EQUIPO)'!M44 -> 5028.76 | F26: ='F07 OPERAC. (MAT,SERV & EQUIPO)'!N44 -> 0 | G26: ='F07 OPERAC. (MAT,SERV & EQUIPO)'!O44 -> 0 | H26: ='F07 OPERAC. (MAT,SERV & EQUIPO)'!P44 -> 0 | I26: ='F07 OPERAC. (MAT,SERV & EQUIPO)'!Q44 -> 0 | J26: ='F07 OPERAC. (MAT,SERV & EQUIPO)'!R44 -> 0 | K26: ='F07 OPERAC. (MAT,SERV & EQUIPO)'!S44 -> 0 | ... Q26: ='F07 OPERAC. (MAT,SERV & EQUIPO)'!Y44 -> 0 | R26: =SUM(D26:Q26) -> 10057.52 | T26: =R26/$E$42 -> 556.58661 | V26: ='F07 OPERAC. (MAT,SERV & EQUIPO)'!L46 -> 10057.52 | W26: =SERVICIO!B30+SERVICIO!B31 -> 10057.52 | X26: =V26-R26 -> 0 | Y26: =V26-W26 -> 0
B27: SERVICIOS AGRICOLAS Y ENSERES MENORES
A28: SERVICIOS (OPERACION) | D28: ='F07 OPERAC. (MAT,SERV & EQUIPO)'!L195 -> 0 | E28: ='F07 OPERAC. (MAT,SERV & EQUIPO)'!M195 -> 0 | F28: ='F07 OPERAC. (MAT,SERV & EQUIPO)'!N195 -> 0 | G28: ='F07 OPERAC. (MAT,SERV & EQUIPO)'!O195 -> 0 | H28: ='F07 OPERAC. (MAT,SERV & EQUIPO)'!P195 -> 0 | I28: ='F07 OPERAC. (MAT,SERV & EQUIPO)'!Q195 -> 0 | J28: ='F07 OPERAC. (MAT,SERV & EQUIPO)'!R195 -> 0 | K28: ='F07 OPERAC. (MAT,SERV & EQUIPO)'!S195 -> 0 | ... Q28: ='F07 OPERAC. (MAT,SERV & EQUIPO)'!Y195 -> 0 | R28: =SUM(D28:Q28) -> 0 | T28: =R28/$E$42 -> 0 | V28: ='F07 OPERAC. (MAT,SERV & EQUIPO)'!L197 -> 0 | W28: =SERVICIO!B36+SERVICIO!B39+SERVICIO!B77+SERVICIO!B147+SERVICIO!B149 -> 0 | X28: =V28-R28 -> 0 | Y28: =V28-W28 -> 0
B29: ENSERES MENORES DIVERSOS, INSUMOS AGRICOLAS
A30: ACTIVOS (OPERACION) (Computadoras) | D30: ='F03 COM Y EQ COM'!L49 -> 0 | E30: ='F03 COM Y EQ COM'!M49 -> 32526 | F30: ='F03 COM Y EQ COM'!N49 -> 0 | G30: ='F03 COM Y EQ COM'!O49 -> 0 | H30: ='F03 COM Y EQ COM'!P49 -> 0 | I30: ='F03 COM Y EQ COM'!Q49 -> 0 | J30: ='F03 COM Y EQ COM'!R49 -> 0 | K30: ='F03 COM Y EQ COM'!S49 -> 0 | ... Q30: ='F03 COM Y EQ COM'!Y49 -> 0 | R30: =SUM(D30:Q30) -> 32526 | T30: =R30/$E$42 -> 1800 | V30: ='F03 COM Y EQ COM'!L51 -> 32526 | W30: =SERVICIO!B28 -> 32526 | X30: =V30-R30 -> 0 | Y30: =V30-W30 -> 0
B31: EQUIPO DE COMPUTO Y ARRENDAMIENTO DE EQ. COMPUTO
A33: EGRESO TOTAL MENSUAL | D33: =SUM(D8:D30) -> 20297892 | E33: =SUM(E8:E30) -> 2965507.6 | F33: =SUM(F8:F30) -> 0 | G33: =SUM(G8:G30) -> 0 | H33: =SUM(H8:H30) -> 0 | I33: =SUM(I8:I30) -> 0 | J33: =SUM(J8:J30) -> 0 | K33: =SUM(K8:K30) -> 0 | ... Q33: =SUM(Q8:Q30) -> 0 | R33: =SUM(D33:Q33) -> 23263399 | T33: =R33/$E$42 -> 1287404.5 | V33: =SERVICIO!B162 -> 23263399 | X33: =V33-R33 -> 0
A35: CAPEX TOTAL MENSUAL | D35: =D8 -> 16714398 | E35: =E8 -> 0 | F35: =F8 -> 0 | G35: =G8 -> 0 | H35: =H8 -> 0 | I35: =I8 -> 0 | J35: =J8 -> 0 | K35: =K8 -> 0 | ... Q35: =Q8 -> 0 | R35: =SUM(D35:Q35) -> 16714398 | T35: =R35/$E$42 -> 924980.5
A37: OPEX TOTAL MENSUAL | D37: =+D33-D35 -> 3583494.2 | E37: =+E33-E35 -> 2965507.6 | F37: =+F33-F35 -> 0 | G37: =+G33-G35 -> 0 | H37: =+H33-H35 -> 0 | I37: =+I33-I35 -> 0 | J37: =+J33-J35 -> 0 | K37: =+K33-K35 -> 0 | ... Q37: =+Q33-Q35 -> 0 | R37: =SUM(D37:Q37) -> 6549001.8 | T37: =R37/$E$42 -> 362424
A39: OPEX TOTAL MENSUAL REAL | R39: =SUM(D39:Q39) -> 0 | T39: =+R39*PREMISAS!$D$18 -> 0
D41: =SERVICIO!A195 -> Premisas
D42: =SERVICIO!A196 -> Paridad | E42: =SERVICIO!B196 -> 18.07
D43: =SERVICIO!A197 -> Mes | E43: =SERVICIO!B197 -> 30.4
D44: =SERVICIO!A198 -> Periodo Pago (días) | E44: =SERVICIO!B198 -> 30
D45: =SERVICIO!A199 -> Gas lp | E45: =SERVICIO!B199 -> 0
D46: =SERVICIO!A200 -> Gasolina Magna | E46: =SERVICIO!B200 -> 22
D47: =SERVICIO!A201 -> Diesel | E47: =SERVICIO!B201 -> 23

Sheet F08 INGRESOS
B2: INGRESOS
B5: RESUMEN | C5: PARTIDA | D5: CONCEPTO | E5: UNIDAD | F5: CANTIDAD | G5: IMPORTE SERVICIO Y DIA | H5: IMPORTE TOTAL | I5: IMPORTE | J5: IMPORTE TOTAL | K5: TOTAL C/IVA | M5: Instalación | N5: Instalación | O5: Mes 1 | P5: Mes 2 | Q5: Mes 3 | R5: Mes 4 | S5: Mes 5 | T5: Mes 6 | U5: Mes 7 | V5: Mes 8 | W5: Mes 9 | X5: Mes 10 | Y5: Mes 11 | Z5: Mes 12
O6: ENE | P6: FEB | Q6: MAR | R6: ABR | S6: MAY | T6: JUN | U6: JUL | V6: AGO | W6: SEP | X6: OCT | Y6: NOV | Z6: DIC
G7: [USD] | H7: [USD] | I7: [MN] | J7: [MN] | K7: [MN] | O7: 31 | P7: 29 | Q7: 31 | R7: 30 | S7: 30 | T7: 31 | U7: 31 | V7: 31 | W7: 30 | X7: 31 | Y7: 30 | Z7: 31
B8: FACTURACION | C8: 1.2 | D8: Servicio de diseño, interconexión eléctrica, pruebas y puesta en operación de equipos de bombeo electrocentrífugo horizontal de 10,000-20,000 BPD. | E8: Servicio | F8: =PREMISAS!G7 -> 1 | G8: =PREMISAS!H7 -> 104077.7 | H8: =G8*F8 -> 104077.7 | I8: =PREMISAS!I7 -> 1880684 | J8: =F8*I8 -> 1880684 | K8: =J8*1.16 -> 2181593.5 | M8: =PREMISAS!M7 -> 1880684 | N8: =PREMISAS!N7 -> 0 | O8: =PREMISAS!O7 -> 0 | P8: =PREMISAS!P7 -> 0 | Q8: =PREMISAS!Q7 -> 0 | R8: =PREMISAS!R7 -> 0 | S8: =PREMISAS!S7 -> 0 | T8: =PREMISAS!T7 -> 0 | ... Z8: =PREMISAS!Z7 -> 0
B9: FACTURACION | C9: 2.2 | D9: Variador de frecuencia para 300 KW/375 KVA. | E9: Día | F9: =PREMISAS!G8 -> 1 | G9: =PREMISAS!H8 -> 1149249 | H9: =G9*F9 -> 1149249 | I9: =PREMISAS!I8 -> 20766930 | J9: =F9*I9 -> 20766930 | K9: =J9*1.16 -> 24089639 | M9: =PREMISAS!M8 -> 0 | N9: =PREMISAS!N8 -> 20766930 | O9: =PREMISAS!O8 -> 0 | P9: =PREMISAS!P8 -> 0 | Q9: =PREMISAS!Q8 -> 0 | R9: =PREMISAS!R8 -> 0 | S9: =PREMISAS!S8 -> 0 | T9: =PREMISAS!T8 -> 0 | ... Z9: =PREMISAS!Z8 -> 0
B10: FACTURACION | C10: 2.6 | D10: Generador de energía a gas de 300 KW/375 KVA | E10: Día | F10: =PREMISAS!G9 -> 1 | G10: =PREMISAS!H9 -> 880052.49 | H10: =G10*F10 -> 880052.49 | I10: =PREMISAS!I9 -> 15902548 | J10: =F10*I10 -> 15902548 | K10: =J10*1.16 -> 18446956 | M10: =PREMISAS!M9 -> 15902548 | N10: =PREMISAS!N9 -> 0 | O10: =PREMISAS!O9 -> 0 | P10: =PREMISAS!P9 -> 0 | Q10: =PREMISAS!Q9 -> 0 | R10: =PREMISAS!R9 -> 0 | S10: =PREMISAS!S9 -> 0 | T10: =PREMISAS!T9 -> 0 | ... Z10: =PREMISAS!Z9 -> 0
B11: FACTURACION | C11: 2.6 | D11: Generador de energía a gas de 300 KW/375 KVA a disposición. | E11: Día | F11: =PREMISAS!G10 -> 1 | G11: =PREMISAS!H10 -> 0 | H11: =G11*F11 -> 0 | I11: =PREMISAS!I10 -> 0 | J11: =F11*I11 -> 0 | K11: =J11*1.16 -> 0 | M11: =PREMISAS!M10 -> 0 | N11: =PREMISAS!N10 -> 0 | O11: =PREMISAS!O10 -> 0 | P11: =PREMISAS!P10 -> 0 | Q11: =PREMISAS!Q10 -> 0 | R11: =PREMISAS!R10 -> 0 | S11: =PREMISAS!S10 -> 0 | T11: =PREMISAS!T10 -> 0 | ... Z11: =PREMISAS!Z10 -> 0
B12: FACTURACION | C12: 2.7 | D12: Patín con bomba electrocentrífuga horizontal con gasto de 10,000-20,000 BPD incluye la operación continua. | E12: Día | F12: =PREMISAS!G11 -> 0 | G12: =PREMISAS!H11 -> 0 | H12: =G12*F12 -> 0 | I12: =PREMISAS!I11 -> 0 | J12: =F12*I12 -> 0 | K12: =J12*1.16 -> 0 | M12: =PREMISAS!M11 -> 0 | N12: =PREMISAS!N11 -> 0 | O12: =PREMISAS!O11 -> 0 | P12: =PREMISAS!P11 -> 0 | Q12: =PREMISAS!Q11 -> 0 | R12: =PREMISAS!R11 -> 0 | S12: =PREMISAS!S11 -> 0 | T12: =PREMISAS!T11 -> 0 | ... Z12: =PREMISAS!Z11 -> 0
B13: FACTURACION | C13: 2.7 | D13: Patín con bomba electrocentrífuga horizontal con gasto de 20,000-30,000 BPD incluye la operación continua. | E13: Día | F13: =PREMISAS!G12 -> 1 | G13: =PREMISAS!H12 -> 2034857.9 | H13: =G13*F13 -> 2034857.9 | I13: =PREMISAS!I12 -> 36769882 | J13: =F13*I13 -> 36769882 | K13: =J13*1.16 -> 42653064 | M13: =PREMISAS!M12 -> 0 | N13: =PREMISAS!N12 -> 36769882 | O13: =PREMISAS!O12 -> 0 | P13: =PREMISAS!P12 -> 0 | Q13: =PREMISAS!Q12 -> 0 | R13: =PREMISAS!R12 -> 0 | S13: =PREMISAS!S12 -> 0 | T13: =PREMISAS!T12 -> 0 | ... Z13: =PREMISAS!Z12 -> 0
B16: =PREMISAS!C17 -> Premisas | K16: Total Mensual [MN] | M16: =SUM(M8:M14) -> 17783233 | N16: =SUM(N8:N14) -> 57536812 | O16: =SUM(O8:O14) -> 0 | P16: =SUM(P8:P14) -> 0 | Q16: =SUM(Q8:Q14) -> 0 | R16: =SUM(R8:R14) -> 0 | S16: =SUM(S8:S14) -> 0 | T16: =SUM(T8:T14) -> 0 | ... Z16: =SUM(Z8:Z14) -> 0
B17: =PREMISAS!C18 -> Paridad | C17: =PREMISAS!D18 -> 18.07 | K17: Total Mensual [USD] | M17: =M16/$C$17 -> 984130.19 | N17: =N16/$C$17 -> 3184106.9 | O17: =O16/$C$17 -> 0 | P17: =P16/$C$17 -> 0 | Q17: =Q16/$C$17 -> 0 | R17: =R16/$C$17 -> 0 | S17: =S16/$C$17 -> 0 | T17: =T16/$C$17 -> 0 | ... Z17: =Z16/$C$17 -> 0
B18: =PREMISAS!C19 -> Mes | C18: =PREMISAS!D19 -> 30.4 | K18: Total [MN] | M18: =SUM(M16:Z16) -> 75320045
B19: =PREMISAS!C20 -> Periodo Pago (días) | C19: =PREMISAS!D20 -> 30 | K19: Total [USD] | M19: =M18/C17 -> 4168237.1
B20: =PREMISAS!C21 -> Gas lp | C20: =PREMISAS!D21 -> 0
B21: =PREMISAS!C22 -> Gasolina Magna | C21: =PREMISAS!D22 -> 22
B22: =PREMISAS!C23 -> Diesel | C22: =PREMISAS!D23 -> 23

Sheet F00 INVERSIÓN
B2: INVERSIÓN
B5: RESUMEN | C5: DESCRIPCIÓN 1 | D5: UNIDAD | E5: CANTIDAD | F5: IMPORTE SERVICIO Y DIA | G5: IMPORTE TOTAL | H5: IMPORTE | I5: IMPORTE TOTAL | J5: TOTAL C/IVA | L5: Instalación | M5: Instalación | N5: Mes 1 | O5: Mes 2 | P5: Mes 3 | Q5: Mes 4 | R5: Mes 5 | S5: Mes 6 | T5: Mes 7 | U5: Mes 8 | V5: Mes 9 | W5: Mes 10 | X5: Mes 11 | Y5: Mes 12
N6: ENE | O6: FEB | P6: MAR | Q6: ABR | R6: MAY | S6: JUN | T6: JUL | U6: AGO | V6: SEP | W6: OCT | X6: NOV | Y6: DIC
F7: [USD] | G7: [USD] | H7: [MN] | I7: [MN] | J7: [MN] | N7: 31 | O7: 29 | P7: 31 | Q7: 30 | R7: 30 | S7: 31 | T7: 31 | U7: 31 | V7: 30 | W7: 31 | X7: 30 | Y7: 31
B8: EQUIPO DE TRANSPORTE | E8: 0 | F8: 0 | G8: =E8*F8 -> 0 | H8: =F8*$C$44 -> 0 | I8: =E8*H8 -> 0 | J8: =I8*1.16 -> 0 | L8: 0 | M8: =I8 -> 0 | N8: 0 | O8: 0 | P8: 0 | Q8: 0 | R8: 0 | S8: 0 | T8: 0 | U8: 0 | V8: 0 | W8: 0 | X8: 0 | Y8: 0
B9: EQUIPO DE TRANSPORTE | C9: Camionetas | E9: 0 | F9: 32025.45 | G9: =E9*F9 -> 0 | H9: =F9*$C$44 -> 578699.88 | I9: =E9*H9 -> 0 | J9: =I9*1.16 -> 0 | L9: 0 | M9: =I9 -> 0 | N9: 0 | O9: 0 | P9: 0 | Q9: 0 | R9: 0 | T9: 0 | U9: 0 | V9: 0 | W9: 0 | X9: 0 | Y9: 0
B10: EQUIPO DE TRANSPORTE | E10: 0 | F10: 76812.4 | G10: =E10*F10 -> 0 | H10: =F10*$C$44 -> 1388000.1 | I10: =E10*H10 -> 0 | J10: =I10*1.16 -> 0 | L10: 0 | M10: 0 | N10: 0 | O10: 0 | Q10: 0 | R10: 0 | S10: 0 | T10: 0 | U10: 0 | V10: 0 | W10: 0 | X10: 0 | Y10: 0
B11: EQUIPO DE TRANSPORTE | E11: 0 | F11: 0 | G11: =E11*F11 -> 0 | H11: =F11*$C$44 -> 0 | I11: =E11*H11 -> 0 | J11: =I11*1.16 -> 0 | L11: 0 | M11: 0 | N11: =I11 -> 0 | O11: 0 | P11: 0 | Q11: 0 | R11: 0 | S11: 0 | T11: 0 | U11: 0 | V11: 0 | W11: 0 | X11: 0 | Y11: 0
L12: =SUM(L8:L11) -> 0 | M12: =SUM(M8:M11) -> 0 | N12: =SUM(N8:N11) -> 0 | O12: =SUM(O8:O11) -> 0 | P12: =SUM(P8:P11) -> 0 | Q12: =SUM(Q8:Q11) -> 0 | R12: =SUM(R8:R11) -> 0 | S12: =SUM(S8:S11) -> 0 | ... Y12: =SUM(Y8:Y11) -> 0
B14: EQUIPO DE MOBILIARIO | C14: Comisionamiento Gen | E14: 0 | F14: 6500 | G14: =E14*F14 -> 0 | H14: =F14*$C$44 -> 117455 | I14: =E14*H14 -> 0 | J14: =I14*1.16 -> 0 | L14: 0 | M14: =I14 -> 0 | N14: 0 | O14: 0 | P14: 0 | Q14: 0 | R14: 0 | S14: 0 | T14: 0 | U14: 0 | V14: 0 | W14: 0 | X14: 0 | Y14: 0
B15: EQUIPO DE MOBILIARIO | C15: Material de Seguridad | E15: 0 | F15: 3500 | G15: =E15*F15 -> 0 | H15: =F15*$C$44 -> 63245 | I15: =E15*H15 -> 0 | J15: =I15*1.16 -> 0 | L15: 0 | M15: 0 | N15: 0 | O15: 0 | P15: 0 | Q15: 0 | R15: 0 | S15: 0 | T15: 0 | U15: 0 | V15: 0 | W15: 0 | X15: 0 | Y15: 0
B16: EQUIPO DE MOBILIARIO | C16: Herramienta Manual | E16: 0 | F16: 11538.46 | G16: =E16*F16 -> 0 | H16: =F16*$C$44 -> 208499.97 | I16: =E16*H16 -> 0 | J16: =I16*1.16 -> 0 | L16: =I16 -> 0 | M16: 0 | N16: 0 | O16: 0 | P16: 0 | Q16: 0 | S16: 0 | T16: 0 | U16: 0 | V16: 0 | W16: 0 | X16: 0 | Y16: 0
B17: EQUIPO DE MOBILIARIO | C17: Comisionamiento HPS | E17: 0 | F17: 2000 | G17: =E17*F17 -> 0 | H17: =F17*$C$44 -> 36140 | I17: =E17*H17 -> 0 | J17: =I17*1.16 -> 0 | L17: 0 | M17: 0 | N17: =I17 -> 0 | O17: 0 | P17: 0 | Q17: 0 | R17: 0 | S17: 0 | T17: 0 | U17: 0 | V17: 0 | W17: 0 | X17: 0 | Y17: 0
L18: =SUM(L14:L17) -> 0 | M18: =SUM(M14:M17) -> 0 | N18: =SUM(N14:N17) -> 0 | O18: =SUM(O14:O17) -> 0 | P18: =SUM(P14:P17) -> 0 | Q18: =SUM(Q14:Q17) -> 0 | R18: =SUM(R14:R17) -> 0 | S18: =SUM(S14:S17) -> 0 | ... Y18: =SUM(Y14:Y17) -> 0
B20: MAQUINARIA Y EQUIPO 1 | E20: 0 | F20: 176089.03 | G20: =E20*F20 -> 0 | H20: =F20*$C$44 -> 3181928.8 | I20: =E20*H20 -> 0 | J20: =I20*1.16 -> 0 | L20: =I20 -> 0 | M20: 0 | N20: 0 | O20: 0 | P20: 0 | Q20: 0 | R20: 0 | S20: 0 | T20: 0 | U20: 0 | V20: 0 | W20: 0 | X20: 0 | Y20: 0
B21: MAQUINARIA Y EQUIPO 2 | E21: 0 | F21: 79961.3 | G21: =E21*F21 -> 0 | H21: =F21*$C$44 -> 1444900.7 | I21: =E21*H21 -> 0 | J21: =I21*1.16 -> 0 | L21: =I21 -> 0 | M21: 0 | N21: 0 | O21: 0 | P21: 0 | Q21: 0 | R21: 0 | S21: 0 | T21: 0 | U21: 0 | V21: 0 | W21: 0 | X21: 0 | Y21: 0
B22: MAQUINARIA Y EQUIPO 3 | E22: 0 | F22: 513000 | G22: =E22*F22 -> 0 | H22: =F22*$C$44 -> 9269910 | I22: =E22*H22 -> 0 | J22: =I22*1.16 -> 0 | L22: =I22 -> 0 | M22: 0 | N22: 0 | O22: 0 | P22: 0 | Q22: 0 | S22: 0 | T22: 0 | U22: 0 | V22: 0 | W22: 0 | X22: 0 | Y22: 0
B23: MAQUINARIA Y EQUIPO 4 | E23: 0 | F23: 49960 | G23: =E23*F23 -> 0 | H23: =F23*$C$44 -> 902777.2 | I23: =E23*H23 -> 0 | J23: =I23*1.16 -> 0 | L23: 0 | M23: =I23 -> 0 | N23: 0 | O23: 0 | P23: 0 | Q23: 0 | R23: 0 | S23: 0 | T23: 0 | U23: 0 | V23: 0 | W23: 0 | X23: 0 | Y23: 0
B24: MAQUINARIA Y EQUIPO 5 | E24: 0 | F24: 50000 | G24: =E24*F24 -> 0 | H24: =F24*$C$44 -> 903500 | I24: =E24*H24 -> 0 | J24: =I24*1.16 -> 0 | L24: 0 | M24: =I24 -> 0 | N24: 0 | O24: 0 | P24: 0 | Q24: 0 | R24: 0 | S24: 0 | T24: 0 | U24: 0 | V24: 0 | W24: 0 | X24: 0 | Y24: 0
B25: MAQUINARIA Y EQUIPO 6 | E25: 0 | F25: 160487 | G25: =E25*F25 -> 0 | H25: =F25*$C$44 -> 2900000 | I25: =E25*H25 -> 0 | J25: =I25*1.16 -> 0 | L25: =I25*0.5 -> 0 | M25: =L25 -> 0 | N25: 0 | O25: 0 | P25: 0 | Q25: 0 | R25: 0 | S25: 0 | T25: 0 | U25: 0 | V25: 0 | W25: 0 | X25: 0 | Y25: 0
B26: MAQUINARIA Y EQUIPO 7 | C26: Servicios | D26: RICCSSA | E26: 0 | F26: 49255.23 | G26: =E26*F26 -> 0 | H26: =F26*$C$44 -> 890042.01 | I26: =E26*H26 -> 0 | J26: =I26*1.16 -> 0 | L26: =I26 -> 0 | M26: 0 | N26: 0 | O26: 0 | P26: 0 | Q26: 0 | R26: 0 | S26: 0 | T26: 0 | U26: 0 | V26: 0 | W26: 0 | X26: 0 | Y26: 0
B27: MAQUINARIA Y EQUIPO 11 | C27: Servicio de obra | D27: RICCSSA | E27: 0 | F27: 26563.36 | G27: =E27*F27 -> 0 | H27: =F27*$C$44 -> 479999.92 | I27: =E27*H27 -> 0 | J27: =I27*1.16 -> 0 | L27: =I27 -> 0 | M27: 0 | N27: 0 | O27: 0 | P27: 0 | Q27: 0 | R27: 0 | S27: 0 | T27: 0 | U27: 0 | V27: 0 | W27: 0 | X27: 0 | Y27: 0
L28: =SUM(L20:L27) -> 0 | M28: =SUM(M20:M27) -> 0 | N28: =SUM(N20:N27) -> 0 | O28: =SUM(O20:O27) -> 0 | P28: =SUM(P20:P27) -> 0 | Q28: =SUM(Q20:Q27) -> 0 | R28: =SUM(R20:R27) -> 0 | S28: =SUM(S20:S27) -> 0 | ... Y28: =SUM(Y20:Y27) -> 0
B30: OTROS ACTIVOS | C30: Obra mecanica | D30: Geolis | E30: 1 | F30: 130261.96 | G30: =E30*F30 -> 130261.96 | H30: =F30*$C$44 -> 2353833.7 | I30: =E30*H30 -> 2353833.7 | J30: =I30*1.16 -> 2730447.1 | L30: =I30 -> 2353833.7 | M30: 0 | N30: 0 | O30: 0 | P30: 0 | Q30: 0 | R30: 0 | S30: 0 | T30: 0 | U30: 0 | V30: 0 | W30: 0 | X30: 0 | Y30: 0
B31: OTROS ACTIVOS | C31: Obra electrica | D31: Geolis | E31: 1 | F31: 214720.53 | G31: =E31*F31 -> 214720.53 | H31: =F31*$C$44 -> 3880000 | I31: =E31*H31 -> 3880000 | J31: =I31*1.16 -> 4500800 | L31: =I31 -> 3880000 | M31: 0 | N31: 0 | O31: 0 | P31: 0 | Q31: 0 | R31: 0 | S31: 0 | T31: 0 | U31: 0 | V31: 0 | W31: 0 | X31: 0 | Y31: 0
B32: OTROS ACTIVOS | C32: Servicios | D32: Geolis | E32: 0 | F32: 88695.55 | G32: =E32*F32 -> 0 | H32: =F32*$C$44 -> 1602728.6 | I32: =E32*H32 -> 0 | J32: =I32*1.16 -> 0 | L32: =I32 -> 0 | M32: 0 | N32: 0 | O32: 0 | P32: 0 | Q32: 0 | R32: 0 | S32: 0 | T32: 0 | U32: 0 | V32: 0 | W32: 0 | X32: 0 | Y32: 0
B33: OTROS ACTIVOS | C33: Generador | D33: Geolis | E33: 1 | F33: 579998 | G33: =E33*F33 -> 579998 | H33: =F33*$C$44 -> 10480564 | I33: =E33*H33 -> 10480564 | J33: =I33*1.16 -> 12157454 | L33: =I33 -> 10480564
B34: OTROS ACTIVOS | C34: Refaccionamiento | D34: Geolis | E34: 0 | F34: 87242.9 | G34: =E34*F34 -> 0 | H34: =F34*$C$44 -> 1576479.2 | I34: =E34*H34 -> 0 | J34: =I34*1.16 -> 0 | L34: =I34 -> 0 | M34: 0 | N34: 0 | O34: 0 | P34: 0 | Q34: 0 | R34: 0 | S34: 0 | T34: 0 | U34: 0 | V34: 0 | W34: 0 | X34: 0 | Y34: 0
L35: =SUM(L30:L34) -> 16714398 | M35: =SUM(M30:M34) -> 0 | N35: =SUM(N30:N34) -> 0 | O35: =SUM(O30:O34) -> 0 | P35: =SUM(P30:P34) -> 0 | Q35: =SUM(Q30:Q34) -> 0 | R35: =SUM(R30:R34) -> 0 | S35: =SUM(S30:S34) -> 0 | ... Y35: =SUM(Y30:Y34) -> 0
B37: SOFTWARE Y LICICENCIAS | E37: 0 | F37: 0 | G37: =E37*F37 -> 0 | H37: =F37*$C$44 -> 0 | I37: =E37*H37 -> 0 | J37: =I37*1.16 -> 0 | L37: 0 | M37: 0 | N37: 0 | O37: 0 | P37: 0 | Q37: 0 | R37: 0 | S37: 0 | T37: 0 | U37: 0 | V37: 0 | W37: 0 | X37: 0 | Y37: 0
B38: SOFTWARE Y LICICENCIAS | E38: 0 | F38: 0 | G38: =E38*F38 -> 0 | H38: =F38*$C$44 -> 0 | I38: =E38*H38 -> 0 | J38: =I38*1.16 -> 0 | L38: 0 | M38: 0 | N38: 0 | O38: 0 | P38: 0 | Q38: 0 | R38: 0 | S38: 0 | T38: 0 | U38: 0 | V38: 0 | W38: 0 | X38: 0 | Y38: 0
B39: SOFTWARE Y LICICENCIAS | E39: 0 | F39: 0 | G39: =E39*F39 -> 0 | H39: =F39*$C$44 -> 0 | I39: =E39*H39 -> 0 | J39: =I39*1.16 -> 0 | L39: 0 | M39: 0 | N39: 0 | O39: 0 | P39: 0 | Q39: 0 | R39: 0 | S39: 0 | T39: 0 | U39: 0 | V39: 0 | W39: 0 | X39: 0 | Y39: 0
B40: SOFTWARE Y LICICENCIAS | E40: 0 | F40: 0 | G40: =E40*F40 -> 0 | H40: =F40*$C$44 -> 0 | I40: =E40*H40 -> 0 | J40: =I40*1.16 -> 0 | L40: 0 | M40: 0 | N40: 0 | O40: 0 | P40: 0 | Q40: 0 | R40: 0 | S40: 0 | T40: 0 | U40: 0 | V40: 0 | W40: 0 | X40: 0 | Y40: 0
L41: =SUM(L37:L40) -> 0 | M41: =SUM(M37:M40) -> 0 | N41: =SUM(N37:N40) -> 0 | O41: =SUM(O37:O40) -> 0 | P41: =SUM(P37:P40) -> 0 | Q41: =SUM(Q37:Q40) -> 0 | R41: =SUM(R37:R40) -> 0 | S41: =SUM(S37:S40) -> 0 | ... Y41: =SUM(Y37:Y40) -> 0
B43: ='F08 INGRESOS'!B16 -> Premisas | J43: Total Mensual [MN] | L43: =L41+L35+L28+L18+L12 -> 16714398 | M43: =M41+M35+M28+M18+M12 -> 0 | N43: =N41+N35+N28+N18+N12 -> 0 | O43: =O41+O35+O28+O18+O12 -> 0 | P43: =P41+P35+P28+P18+P12 -> 0 | Q43: =Q41+Q35+Q28+Q18+Q12 -> 0 | R43: =R41+R35+R28+R18+R12 -> 0 | S43: =S41+S35+S28+S18+S12 -> 0 | ... Y43: =Y41+Y35+Y28+Y18+Y12 -> 0
B44: ='F08 INGRESOS'!B17 -> Paridad | C44: ='F08 INGRESOS'!C17 -> 18.07 | J44: Total Mensual [USD] | L44: =L43/$C$44 -> 924980.5 | M44: =M43/$C$44 -> 0 | N44: =N43/$C$44 -> 0 | O44: =O43/$C$44 -> 0 | P44: =P43/$C$44 -> 0 | Q44: =Q43/$C$44 -> 0 | R44: =R43/$C$44 -> 0 | S44: =S43/$C$44 -> 0 | ... Y44: =Y43/$C$44 -> 0
B45: ='F08 INGRESOS'!B18 -> Mes | C45: ='F08 INGRESOS'!C18 -> 30.4 | J45: Total [MN] | L45: =SUM(L43:Y43) -> 16714398
B46: ='F08 INGRESOS'!B19 -> Periodo Pago (días) | C46: ='F08 INGRESOS'!C19 -> 30 | J46: Total [USD] | L46: =L45/$C$44 -> 924980.5
B47: ='F08 INGRESOS'!B20 -> Gas lp | C47: ='F08 INGRESOS'!C20 -> 0
B48: ='F08 INGRESOS'!B21 -> Gasolina Magna | C48: ='F08 INGRESOS'!C21 -> 22
B49: ='F08 INGRESOS'!B22 -> Diesel | C49: ='F08 INGRESOS'!C22 -> 23
D57: 2353833.7 | E57: =D57/18.07 -> 130261.96
D58: 3880000 | E58: =D58/18.07 -> 214720.53
B87: Linea de 12 a 4 | C87: 1265058
B88: Linea de 16 a 6 | C88: 1553586.8
C89: =SUM(C87:C88) -> 2818644.8
C91: =SUM(C85,C89) -> 2818644.8

Sheet F01 NÓMINA
B2: NÓMINA
B5: RESUMEN | C5: NOMBRE | D5: PUESTO | E5: UNIDAD | F5: CANTIDAD | G5: SALARIO | H5: IMPUESTOS | I5: COSTO REAL C/IMP. | K5: AGUINALDO | L5: FONDO DE AHORRO | M5: UTILIDADES | N5: DESPENSA | O5: VIVIENDA | P5: ISR | Q5: VACACIONES | R5: IMPORTE | S5: IMPORTE TOTAL | T5: IMPORTE | U5: IMPORTE TOTAL | V5: TOTAL C/IVA | X5: Instalación | Y5: Instalación | Z5: Mes 1 | AA5: Mes 2 | AB5: Mes 3 | AC5: Mes 4 | AD5: Mes 5 | AE5: Mes 6 | AF5: Mes 7 | AG5: Mes 8 | AH5: Mes 9 | AI5: Mes 10 | AJ5: Mes 11 | AK5: Mes 12
Z6: ENE | AA6: FEB | AB6: MAR | AC6: ABR | AD6: MAY | AE6: JUN | AF6: JUL | AG6: AGO | AH6: SEP | AI6: OCT | AJ6: NOV | AK6: DIC
R7: [USD] | S7: [USD] | T7: [MN] | U7: [MN] | V7: [MN] | Z7: 31 | AA7: 29 | AB7: 31 | AC7: 30 | AD7: 30 | AE7: 31 | AF7: 31 | AG7: 31 | AH7: 30 | AI7: 31 | AJ7: 30 | AK7: 31
B8: NOMINA Y ADICIONALES | D8: SUPERVISOR DE OBRA | F8: 1 | G8: 24000 | H8: 1 | I8: =G8*(1+H8) -> 48000 | K8: =G8 -> 24000 | L8: =G8/4 -> 6000 | M8: =G8/2 -> 12000 | N8: 0 | O8: 0 | Q8: =(G8/30.4)*6 -> 4736.8421 | R8: =T8/$C$21 -> 2678.1813 | S8: =R8*F8 -> 2678.1813 | T8: =I8+O8+(Q8/12) -> 48394.737 | U8: =T8*F8 -> 48394.737 | V8: =U8*1.16 -> 56137.895 | X8: =$U$8 -> 48394.737 | Y8: =$U$8 -> 48394.737 | Z8: 0 | AA8: 0 | AB8: 0 | AC8: 0 | AD8: 0 | AE8: 0 | AF8: 0 | AG8: 0 | AH8: 0 | AI8: 0 | AJ8: 0 | AK8: 0
B9: NOMINA Y ADICIONALES | D9: CABO | F9: 1 | G9: 22000 | H9: 1 | I9: =G9*(1+H9) -> 44000 | K9: =G9 -> 22000 | L9: =G9/4 -> 5500 | M9: =G9/2 -> 11000 | N9: 0 | O9: 0 | Q9: =(G9/30.4)*6 -> 4342.1053 | R9: =T9/$C$21 -> 2454.9996 | S9: =R9*F9 -> 2454.9996 | T9: =I9+O9+(Q9/12) -> 44361.842 | U9: =T9*F9 -> 44361.842 | V9: =U9*1.16 -> 51459.737 | X9: =$U$9 -> 44361.842 | Y9: =$U$9 -> 44361.842 | Z9: 0 | AA9: 0 | AB9: 0 | AC9: 0 | AD9: 0 | AE9: 0 | AF9: 0 | AG9: 0 | AH9: 0 | AI9: 0 | AJ9: 0 | AK9: 0
B10: NOMINA Y ADICIONALES | D10: SOLDADOR | F10: 2 | G10: 20000 | H10: 1 | I10: =G10*(1+H10) -> 40000 | K10: =G10 -> 20000 | L10: =G10/4 -> 5000 | M10: =G10/2 -> 10000 | N10: 0 | O10: 0 | Q10: =(G10/30.4)*6 -> 3947.3684 | R10: =T10/$C$21 -> 2231.8178 | S10: =R10*F10 -> 4463.6356 | T10: =I10+O10+(Q10/12) -> 40328.947 | U10: =T10*F10 -> 80657.895 | V10: =U10*1.16 -> 93563.158 | X10: =U10 -> 80657.895 | Y10: =$U$10 -> 80657.895 | Z10: 0 | AA10: 0 | AB10: 0 | AC10: 0 | AD10: 0 | AE10: 0 | AF10: 0 | AG10: 0 | AH10: 0 | AI10: 0 | AJ10: 0 | AK10: 0
B11: NOMINA Y ADICIONALES | D11: TUBERO | F11: 1 | G11: 20000 | H11: 1 | I11: =G11*(1+H11) -> 40000 | K11: =G11 -> 20000 | L11: =G11/4 -> 5000 | M11: =G11/2 -> 10000 | N11: 0 | O11: 0 | Q11: =(G11/30.4)*6 -> 3947.3684 | R11: =T11/$C$21 -> 2231.8178 | S11: =R11*F11 -> 2231.8178 | T11: =I11+O11+(Q11/12) -> 40328.947 | U11: =T11*F11 -> 40328.947 | V11: =U11*1.16 -> 46781.579 | X11: =$U$11 -> 40328.947 | Y11: =$U$11 -> 40328.947 | Z11: 0 | AA11: 0 | AB11: 0 | AC11: 0 | AD11: 0 | AE11: 0 | AF11: 0 | AG11: 0 | AH11: 0 | AI11: 0 | AJ11: 0 | AK11: 0
B12: NOMINA Y ADICIONALES | D12: PAILERO | F12: 1 | G12: 20000 | H12: 1 | I12: =G12*(1+H12) -> 40000 | K12: =G12 -> 20000 | L12: =G12/4 -> 5000 | M12: =G12/2 -> 10000 | N12: 0 | O12: 0 | Q12: =(G12/30.4)*6 -> 3947.3684 | R12: =T12/$C$21 -> 2231.8178 | S12: =R12*F12 -> 2231.8178 | T12: =I12+O12+(Q12/12) -> 40328.947 | U12: =T12*F12 -> 40328.947 | V12: =U12*1.16 -> 46781.579 | X12: =$U$12 -> 40328.947 | Y12: =$U$12 -> 40328.947 | Z12: 0 | AA12: 0 | AB12: 0 | AC12: 0 | AD12: 0 | AE12: 0 | AF12: 0 | AG12: 0 | AH12: 0 | AI12: 0 | AJ12: 0 | AK12: 0
B13: NOMINA Y ADICIONALES | D13: CADISTA | F13: 1 | G13: 20000 | H13: 1 | I13: =G13*(1+H13) -> 40000 | K13: =G13 -> 20000 | L13: =G13/4 -> 5000 | M13: =G13/2 -> 10000 | N13: 0 | O13: 0 | Q13: =(G13/30.4)*6 -> 3947.3684 | R13: =T13/$C$21 -> 2231.8178 | S13: =R13*F13 -> 2231.8178 | T13: =I13+O13+(Q13/12) -> 40328.947 | U13: =T13*F13 -> 40328.947 | V13: =U13*1.16 -> 46781.579 | X13: =$U$13 -> 40328.947 | Y13: =$U$13 -> 40328.947 | Z13: 0 | AA13: 0 | AB13: 0 | AC13: 0 | AD13: 0 | AE13: 0 | AF13: 0 | AG13: 0 | AH13: 0 | AI13: 0 | AJ13: 0 | AK13: 0
B14: NOMINA Y ADICIONALES | D14: ESPECIALISTA DE CALIDAD | F14: 1 | G14: 25000 | H14: 1 | I14: =G14*(1+H14) -> 50000 | K14: =G14 -> 25000 | L14: =G14/4 -> 6250 | M14: =G14/2 -> 12500 | N14: 0 | O14: 0 | Q14: =(G14/30.4)*6 -> 4934.2105 | R14: =T14/$C$21 -> 2789.7722 | S14: =R14*F14 -> 2789.7722 | T14: =I14+O14+(Q14/12) -> 50411.184 | U14: =T14*F14 -> 50411.184 | V14: =U14*1.16 -> 58476.974 | X14: =$U$14 -> 50411.184 | Y14: =$U$14 -> 50411.184 | Z14: 0 | AA14: 0 | AB14: 0 | AC14: 0 | AD14: 0 | AE14: 0 | AF14: 0 | AG14: 0 | AH14: 0 | AI14: 0 | AJ14: 0 | AK14: 0
B15: NOMINA Y ADICIONALES | D15: AUXILIAR DE CALIDAD | F15: 1 | G15: 18000 | H15: 1 | I15: =G15*(1+H15) -> 36000 | K15: =G15 -> 18000 | L15: =G15/4 -> 4500 | M15: =G15/2 -> 9000 | N15: 0 | O15: 0 | Q15: =(G15/30.4)*6 -> 3552.6316 | R15: =T15/$C$21 -> 2008.636 | S15: =R15*F15 -> 2008.636 | T15: =I15+O15+(Q15/12) -> 36296.053 | U15: =T15*F15 -> 36296.053 | V15: =U15*1.16 -> 42103.421 | X15: =U15 -> 36296.053 | Y15: =$U$15 -> 36296.053 | Z15: 0 | AA15: 0 | AB15: 0 | AC15: 0 | AD15: 0 | AE15: 0 | AF15: 0 | AG15: 0 | AH15: 0 | AI15: 0 | AJ15: 0 | AK15: 0
B16: NOMINA Y ADICIONALES | D16: AUXILIAR ADMINISTRATIO | F16: 1 | G16: 18000 | H16: 1 | I16: =G16*(1+H16) -> 36000 | K16: =G16 -> 18000 | L16: =G16/4 -> 4500 | M16: =G16/2 -> 9000 | N16: 0 | O16: 0 | Q16: =(G16/30.4)*6 -> 3552.6316 | R16: =T16/$C$21 -> 2008.636 | S16: =R16*F16 -> 2008.636 | T16: =I16+O16+(Q16/12) -> 36296.053 | U16: =T16*F16 -> 36296.053 | V16: =U16*1.16 -> 42103.421 | X16: =$U$16 -> 36296.053 | Y16: =$U$16 -> 36296.053 | Z16: 0 | AA16: 0 | AB16: 0 | AC16: 0 | AD16: 0 | AE16: 0 | AF16: 0 | AG16: 0 | AH16: 0 | AI16: 0 | AJ16: 0 | AK16: 0
B17: NOMINA Y ADICIONALES | D17: Electricos | F17: 1 | G17: 129500 | H17: 1 | I17: =G17*(1+H17) -> 259000 | K17: =G17 -> 129500 | L17: =G17/4 -> 32375 | M17: =G17/2 -> 64750 | N17: 0 | O17: 0 | Q17: =(G17/30.4)*6 -> 25559.211 | R17: =T17/$C$21 -> 14451.02 | S17: =R17*F17 -> 14451.02 | T17: =I17+O17+(Q17/12) -> 261129.93 | U17: =T17*F17 -> 261129.93 | V17: =U17*1.16 -> 302910.72 | X17: 0 | Y17: =U17 -> 261129.93 | Z17: 0 | AA17: 0 | AB17: 0 | AC17: 0 | AD17: 0 | AE17: 0 | AF17: 0 | AG17: 0 | AH17: 0 | AI17: 0 | AJ17: 0 | AK17: 0
B18: NOMINA Y ADICIONALES | G18: 0 | H18: 1 | I18: =G18*(1+H18) -> 0 | K18: =G18 -> 0 | L18: =G18/4 -> 0 | M18: =G18/2 -> 0 | N18: 0 | O18: 0 | Q18: =(G18/30.4)*6 -> 0 | R18: =T18/$C$21 -> 0 | S18: =R18*F18 -> 0 | T18: =I18+O18+(Q18/12) -> 0 | U18: =T18*F18 -> 0 | V18: =U18*1.16 -> 0 | X18: =U18 -> 0 | Y18: 0 | Z18: 0 | AA18: 0 | AB18: 0 | AC18: 0 | AD18: 0 | AE18: 0 | AF18: 0 | AG18: 0 | AH18: 0 | AI18: 0 | AJ18: 0 | AK18: 0
B20: ='F00 INVERSIÓN'!B43 -> Premisas | V20: Total Mensual [MN] | X20: =SUM(X8:X18) -> 417404.61 | Y20: =SUM(Y8:Y18) -> 678534.54 | Z20: =SUM(Z8:Z18) -> 0 | AA20: =SUM(AA8:AA18) -> 0 | AB20: =SUM(AB8:AB18) -> 0 | AC20: =SUM(AC8:AC18) -> 0 | AD20: =SUM(AD8:AD18) -> 0 | AE20: =SUM(AE8:AE18) -> 0 | ... AK20: =SUM(AK8:AK18) -> 0
B21: ='F00 INVERSIÓN'!B44 -> Paridad | C21: ='F00 INVERSIÓN'!C44 -> 18.07 | V21: Total Mensual [USD] | X21: =X20/$C$21 -> 23099.314 | Y21: =Y20/$C$21 -> 37550.334 | Z21: =Z20/$C$21 -> 0 | AA21: =AA20/$C$21 -> 0 | AB21: =AB20/$C$21 -> 0 | AC21: =AC20/$C$21 -> 0 | AD21: =AD20/$C$21 -> 0 | AE21: =AE20/$C$21 -> 0 | ... AK21: =AK20/$C$21 -> 0
B22: ='F00 INVERSIÓN'!B45 -> Mes | C22: ='F00 INVERSIÓN'!C45 -> 30.4 | V22: Total [MN] | X22: =SUM(X20:AK20) -> 1095939.1
B23: ='F00 INVERSIÓN'!B46 -> Periodo Pago (días) | C23: ='F00 INVERSIÓN'!C46 -> 30 | V23: Total [USD] | X23: =X22/C21 -> 60649.648
B24: ='F00 INVERSIÓN'!B47 -> Gas lp | C24: ='F00 INVERSIÓN'!C47 -> 0
B25: ='F00 INVERSIÓN'!B48 -> Gasolina Magna | C25: ='F00 INVERSIÓN'!C48 -> 22
B26: ='F00 INVERSIÓN'!B49 -> Diesel | C26: ='F00 INVERSIÓN'!C49 -> 23
B27: Nómina | C27: 0.8
B29: Aguinaldo
B30: Utilidades

Sheet F01 EPP
B2: EPP
B5: RESUMEN | C5: NOMBRE | D5: PUESTO | E5: UNIDAD | F5: CANTIDAD | G5: IMPORTE | H5: IMPORTE TOTAL | I5: IMPORTE | J5: IMPORTE TOTAL | K5: TOTAL C/IVA | M5: Instalación | N5: Instalación | O5: Mes 1 | P5: Mes 2 | Q5: Mes 3 | R5: Mes 4 | S5: Mes 5 | T5: Mes 6 | U5: Mes 7 | V5: Mes 8 | W5: Mes 9 | X5: Mes 10 | Y5: Mes 11 | Z5: Mes 12
O6: ENE | P6: FEB | Q6: MAR | R6: ABR | S6: MAY | T6: JUN | U6: JUL | V6: AGO | W6: SEP | X6: OCT | Y6: NOV | Z6: DIC
G7: [USD] | H7: [USD] | I7: [MN] | J7: [MN] | K7: [MN] | O7: 31 | P7: 29 | Q7: 31 | R7: 30 | S7: 30 | T7: 31 | U7: 31 | V7: 31 | W7: 30 | X7: 31 | Y7: 30 | Z7: 31
B8: ROPA Y ARTICULOS DE PROTECCION | C8: SUPERVISOR DE OBRA | F8: 1 | G8: 862.55 | H8: =F8*G8 -> 862.55 | I8: =G8*$C$20 -> 15586.278 | J8: =F8*I8 -> 15586.278 | K8: =J8*1.16 -> 18080.083 | M8: =J8 -> 15586.278 | N8: 0 | O8: 0 | P8: 0 | Q8: 0 | R8: 0 | S8: 0 | T8: 0 | U8: 0 | V8: 0 | W8: 0 | X8: 0 | Y8: 0 | Z8: 0
B9: ROPA Y ARTICULOS DE PROTECCION | C9: CABO | F9: 1 | G9: 862.55 | H9: =F9*G9 -> 862.55 | I9: =G9*$C$20 -> 15586.278 | J9: =F9*I9 -> 15586.278 | K9: =J9*1.16 -> 18080.083 | M9: =J9 -> 15586.278 | N9: 0 | O9: 0 | P9: 0 | Q9: 0 | R9: 0 | S9: 0 | T9: 0 | U9: 0 | V9: 0 | W9: 0 | X9: 0 | Y9: 0 | Z9: 0
B10: ROPA Y ARTICULOS DE PROTECCION | C10: SOLDADOR | F10: 1 | G10: 862.55 | H10: =F10*G10 -> 862.55 | I10: =G10*$C$20 -> 15586.278 | J10: =F10*I10 -> 15586.278 | K10: =J10*1.16 -> 18080.083 | M10: =J10 -> 15586.278 | N10: 0 | O10: 0 | P10: 0 | Q10: 0 | R10: 0 | S10: 0 | T10: 0 | U10: 0 | V10: 0 | W10: 0 | X10: 0 | Y10: 0 | Z10: 0
B11: ROPA Y ARTICULOS DE PROTECCION | C11: TUBERO | F11: 1 | G11: 862.55 | H11: =F11*G11 -> 862.55 | I11: =G11*$C$20 -> 15586.278 | J11: =F11*I11 -> 15586.278 | K11: =J11*1.16 -> 18080.083 | M11: =J11 -> 15586.278 | N11: 0 | O11: 0 | P11: 0 | Q11: 0 | R11: 0 | S11: 0 | T11: 0 | U11: 0 | V11: 0 | W11: 0 | X11: 0 | Y11: 0 | Z11: 0
B12: ROPA Y ARTICULOS DE PROTECCION | C12: PAILERO | F12: 1 | G12: 862.55 | H12: =F12*G12 -> 862.55 | I12: =G12*$C$20 -> 15586.278 | J12: =F12*I12 -> 15586.278 | K12: =J12*1.16 -> 18080.083 | M12: =J12 -> 15586.278 | N12: 0 | O12: 0 | P12: 0 | Q12: 0 | R12: 0 | S12: 0 | T12: 0 | U12: 0 | V12: 0 | W12: 0 | X12: 0 | Y12: 0 | Z12: 0
B13: ROPA Y ARTICULOS DE PROTECCION | C13: CADISTA | F13: 1 | G13: 862.55 | H13: =F13*G13 -> 862.55 | I13: =G13*$C$20 -> 15586.278 | J13: =F13*I13 -> 15586.278 | K13: =J13*1.16 -> 18080.083 | M13: =J13 -> 15586.278 | N13: 0 | O13: 0 | P13: 0 | Q13: 0 | R13: 0 | S13: 0 | T13: 0 | U13: 0 | V13: 0 | W13: 0 | X13: 0 | Y13: 0 | Z13: 0
B14: ROPA Y ARTICULOS DE PROTECCION | C14: ESPECIALISTA DE CALIDAD | F14: 1 | G14: 862.55 | H14: =F14*G14 -> 862.55 | I14: =G14*$C$20 -> 15586.278 | J14: =F14*I14 -> 15586.278 | K14: =J14*1.16 -> 18080.083 | M14: =J14 -> 15586.278 | N14: 0 | O14: 0 | P14: 0 | Q14: 0 | R14: 0 | S14: 0 | T14: 0 | U14: 0 | V14: 0 | W14: 0 | X14: 0 | Y14: 0 | Z14: 0
B15: ROPA Y ARTICULOS DE PROTECCION | C15: AUXILIAR DE CALIDAD | F15: 1 | G15: 862.55 | H15: =F15*G15 -> 862.55 | I15: =G15*$C$20 -> 15586.278 | J15: =F15*I15 -> 15586.278 | K15: =J15*1.16 -> 18080.083 | M15: =J15 -> 15586.278 | N15: 0 | O15: 0 | P15: 0 | Q15: 0 | R15: 0 | S15: 0 | T15: 0 | U15: 0 | V15: 0 | W15: 0 | X15: 0 | Y15: 0 | Z15: 0
B16: ROPA Y ARTICULOS DE PROTECCION | C16: AUXILIAR ADMINISTRATIO | F16: 1 | G16: 862.55 | H16: =F16*G16 -> 862.55 | I16: =G16*$C$20 -> 15586.278 | J16: =F16*I16 -> 15586.278 | K16: =J16*1.16 -> 18080.083 | M16: =J16 -> 15586.278 | N16: 0 | O16: 0 | P16: 0 | Q16: 0 | R16: 0 | S16: 0 | T16: 0 | U16: 0 | V16: 0 | W16: 0 | X16: 0 | Y16: 0 | Z16: 0
B17: ROPA Y ARTICULOS DE PROTECCION | C17: Electricos | F17: 6 | G17: 862.55 | H17: =F17*G17 -> 5175.3 | I17: =G17*$C$20 -> 15586.278 | J17: =F17*I17 -> 93517.671 | K17: =J17*1.16 -> 108480.5 | M17: =J17 -> 93517.671 | N17: 0 | O17: 0 | P17: =O17 -> 0 | Q17: =P17 -> 0 | R17: =Q17 -> 0 | S17: =R17 -> 0 | T17: =S17 -> 0 | U17: =T17 -> 0 | V17: =U17 -> 0 | W17: =V17 -> 0 | X17: =W17 -> 0 | Y17: 0 | Z17: =Y17 -> 0
B19: ='F01 NÓMINA'!B20 -> Premisas | K19: Total Mensual [MN] | M19: =SUM(M8:M17) -> 233794.18 | N19: =SUM(N8:N17) -> 0 | O19: =SUM(O8:O17) -> 0 | P19: =SUM(P8:P17) -> 0 | Q19: =SUM(Q8:Q17) -> 0 | R19: =SUM(R8:R17) -> 0 | S19: =SUM(S8:S17) -> 0 | T19: =SUM(T8:T17) -> 0 | ... Z19: =SUM(Z8:Z17) -> 0
B20: ='F01 NÓMINA'!B21 -> Paridad | C20: ='F01 NÓMINA'!C21 -> 18.07 | K20: Total Mensual [USD] | M20: =M19/$C$20 -> 12938.25 | N20: =N19/20 -> 0 | O20: =O19/20 -> 0 | P20: =P19/20 -> 0 | Q20: =Q19/20 -> 0 | R20: =R19/20 -> 0 | S20: =S19/20 -> 0 | T20: =T19/20 -> 0 | U20: =U19/20 -> 0 | ... Z20: =Z19/20 -> 0
B21: ='F01 NÓMINA'!B22 -> Mes | C21: ='F01 NÓMINA'!C22 -> 30.4 | K21: Total [MN] | M21: =SUM(M19:Z19) -> 233794.18
B22: ='F01 NÓMINA'!B23 -> Periodo Pago (días) | C22: ='F01 NÓMINA'!C23 -> 30 | K22: Total [USD] | M22: =M21/$C$20 -> 12938.25
B23: ='F01 NÓMINA'!B24 -> Gas lp | C23: ='F01 NÓMINA'!C24 -> 0
B24: ='F01 NÓMINA'!B25 -> Gasolina Magna | C24: ='F01 NÓMINA'!C25 -> 22
B25: ='F01 NÓMINA'!B26 -> Diesel | C25: ='F01 NÓMINA'!C26 -> 23
B27: 500 | C27: =B27/$C$20 -> 27.670172
B28: 600 | C28: =B28/$C$20 -> 33.204206
B29: 700 | C29: =B29/$C$20 -> 38.73824
B30: 800 | C30: =B30/$C$20 -> 44.272274
B31: 900 | C31: =B31/$C$20 -> 49.806309
B32: 1000 | C32: =B32/$C$20 -> 55.340343

Sheet F01 UNIFORMES
B2: UNIFORMES
B5: UNIFORMES | C5: NOMBRE | D5: PUESTO | E5: UNIDAD | F5: CANTIDAD | G5: IMPORTE | H5: IMPORTE TOTAL | I5: IMPORTE | J5: IMPORTE TOTAL | K5: TOTAL C/IVA | M5: Instalación | N5: Instalación | O5: Mes 1 | P5: Mes 2 | Q5: Mes 3 | R5: Mes 4 | S5: Mes 5 | T5: Mes 6 | U5: Mes 7 | V5: Mes 8 | W5: Mes 9 | X5: Mes 10 | Y5: Mes 11 | Z5: Mes 12
O6: ENE | P6: FEB | Q6: MAR | R6: ABR | S6: MAY | T6: JUN | U6: JUL | V6: AGO | W6: SEP | X6: OCT | Y6: NOV | Z6: DIC
G7: [USD] | H7: [USD] | I7: [MN] | J7: [MN] | K7: [MN] | O7: 31 | P7: 29 | Q7: 31 | R7: 30 | S7: 30 | T7: 31 | U7: 31 | V7: 31 | W7: 30 | X7: 31 | Y7: 30 | Z7: 31
B8: UNIFORMES | D8: Supervisor | F8: 0 | G8: 50 | H8: =F8*G8 -> 0 | I8: =G8*$C$21 -> 903.5 | J8: =(F8*I8)/12 -> 0 | K8: =J8*1.16 -> 0 | M8: 0 | N8: =$J$8 -> 0 | O8: =$J$8 -> 0 | P8: =$J$8 -> 0 | Q8: =$J$8 -> 0 | R8: =$J$8 -> 0 | S8: =$J$8 -> 0 | T8: =$J$8 -> 0 | U8: =$J$8 -> 0 | ... Z8: =$J$8 -> 0
B9: UNIFORMES | D9: Seguridad | F9: 0 | G9: 50 | H9: =F9*G9 -> 0 | I9: =G9*$C$21 -> 903.5 | J9: =(F9*I9)/12 -> 0 | K9: =J9*1.16 -> 0 | M9: 0 | N9: =J9 -> 0 | O9: =J9 -> 0 | P9: =O9 -> 0 | Q9: =P9 -> 0 | R9: =Q9 -> 0 | S9: =R9 -> 0 | T9: =S9 -> 0 | U9: =T9 -> 0 | V9: =U9 -> 0 | W9: =V9 -> 0 | ... Z9: =Y9 -> 0
B10: UNIFORMES | D10: Auxiliar Administrativo | F10: 0 | G10: 50 | H10: =F10*G10 -> 0 | I10: =G10*$C$21 -> 903.5 | J10: =(F10*I10)/12 -> 0 | K10: =J10*1.16 -> 0 | M10: 0 | N10: 0 | O10: =J10 -> 0 | P10: =O10 -> 0 | Q10: =P10 -> 0 | R10: =Q10 -> 0 | S10: =R10 -> 0 | T10: =S10 -> 0 | U10: =T10 -> 0 | V10: =U10 -> 0 | W10: =V10 -> 0 | ... Z10: =Y10 -> 0
B11: UNIFORMES | F11: 0 | G11: 42 | H11: =F11*G11 -> 0 | I11: =G11*$C$21 -> 758.94 | J11: =(F11*I11)/12 -> 0 | K11: =J11*1.16 -> 0 | M11: 0 | N11: =J11 -> 0 | O11: =J11 -> 0 | P11: =O11 -> 0 | Q11: =P11 -> 0 | R11: =Q11 -> 0 | S11: =R11 -> 0 | T11: =S11 -> 0 | U11: =T11 -> 0 | V11: =U11 -> 0 | W11: =V11 -> 0 | ... Z11: =Y11 -> 0
B12: UNIFORMES | F12: 0 | G12: 42 | H12: =F12*G12 -> 0 | I12: =G12*$C$21 -> 758.94 | J12: =(F12*I12)/12 -> 0 | K12: =J12*1.16 -> 0 | M12: 0 | N12: =J12 -> 0 | O12: =J12 -> 0 | P12: =O12 -> 0 | Q12: =P12 -> 0 | R12: =Q12 -> 0 | S12: =R12 -> 0 | T12: =S12 -> 0 | U12: =T12 -> 0 | V12: =U12 -> 0 | W12: =V12 -> 0 | ... Z12: =Y12 -> 0
B13: UNIFORMES | F13: 0 | G13: 42 | H13: =F13*G13 -> 0 | I13: =G13*$C$21 -> 758.94 | J13: =(F13*I13)/12 -> 0 | K13: =J13*1.16 -> 0 | M13: 0 | N13: =J13 -> 0 | O13: =J13 -> 0 | P13: =O13 -> 0 | Q13: =P13 -> 0 | R13: =Q13 -> 0 | S13: =R13 -> 0 | T13: =S13 -> 0 | U13: =T13 -> 0 | V13: =U13 -> 0 | W13: =V13 -> 0 | ... Z13: =Y13 -> 0
K15: Total Mensual [MN] | M15: =SUM(M8:M13) -> 0 | N15: =SUM(N8:N13) -> 0 | O15: =SUM(O8:O13) -> 0 | P15: =SUM(P8:P13) -> 0 | Q15: =SUM(Q8:Q13) -> 0 | R15: =SUM(R8:R13) -> 0 | S15: =SUM(S8:S13) -> 0 | T15: =SUM(T8:T13) -> 0 | ... Z15: =SUM(Z8:Z13) -> 0
K16: Total Mensual [USD] | M16: =M15/PREMISAS!$D$18 -> 0 | N16: =N15/PREMISAS!$D$18 -> 0 | O16: =O15/PREMISAS!$D$18 -> 0 | P16: =P15/PREMISAS!$D$18 -> 0 | Q16: =Q15/PREMISAS!$D$18 -> 0 | R16: =R15/PREMISAS!$D$18 -> 0 | S16: =S15/PREMISAS!$D$18 -> 0 | T16: =T15/PREMISAS!$D$18 -> 0 | ... Z16: =Z15/PREMISAS!$D$18 -> 0
K17: Total [MN] | M17: =SUM(M15:Z15) -> 0
K18: Total [USD] | M18: =M17/20 -> 0
B20: ='F01 EPP'!B19 -> Premisas
B21: ='F01 EPP'!B20 -> Paridad | C21: ='F01 EPP'!C20 -> 18.07
B22: ='F01 EPP'!B21 -> Mes | C22: ='F01 EPP'!C21 -> 30.4
B23: ='F01 EPP'!B22 -> Periodo Pago (días) | C23: ='F01 EPP'!C22 -> 30
B24: ='F01 EPP'!B23 -> Gas lp | C24: ='F01 EPP'!C23 -> 0
B25: ='F01 EPP'!B24 -> Gasolina Magna | C25: ='F01 EPP'!C24 -> 22
B26: ='F01 EPP'!B25 -> Diesel | C26: ='F01 EPP'!C25 -> 23
B28: 750 | C28: =B28/$C$21 -> 41.505257

Sheet F02 INMUEBLES Y S
B2: INMUEBLES Y SERVICIOS
B5: RESUMEN | C5: DESCRIPCIÓN 1 | D5: DESCRIPCIÓN 2 | E5: UBICACIÓN | F5: CANTIDAD | G5: IMPORTE | H5: IMPORTE TOTAL | I5: IMPORTE | J5: IMPORTE TOTAL | K5: TOTAL C/IVA | L5: GASTO POR TRABAJADOR C/IVA | N5: Instalación | O5: Instalación | P5: Mes 1 | Q5: Mes 2 | R5: Mes 3 | S5: Mes 4 | T5: Mes 5 | U5: Mes 6 | V5: Mes 7 | W5: Mes 8 | X5: Mes 9 | Y5: Mes 10 | Z5: Mes 11 | AA5: Mes 12
P6: ENE | Q6: FEB | R6: MAR | S6: ABR | T6: MAY | U6: JUN | V6: JUL | W6: AGO | X6: SEP | Y6: OCT | Z6: NOV | AA6: DIC
G7: [USD] | H7: [USD] | I7: [MN] | J7: [MN] | K7: [MN] | P7: 31 | Q7: 29 | R7: 31 | S7: 30 | T7: 30 | U7: 31 | V7: 31 | W7: 31 | X7: 30 | Y7: 31 | Z7: 30 | AA7: 31
B8: ARRENDAMIENTO DE INMUEBLES | C8: Casa staff | F8: 0 | G8: 664.08 | H8: =F8*G8 -> 0 | I8: 17000 | J8: =I8*F8 -> 0 | K8: =J8*1.16 -> 0 | L8: 0 | N8: 0 | O8: 0 | P8: =J8 -> 0 | Q8: =J8 -> 0 | R8: =Q8 -> 0 | S8: =R8 -> 0 | T8: =S8 -> 0 | U8: =T8 -> 0 | V8: =U8 -> 0 | W8: =V8 -> 0 | X8: =W8 -> 0 | Y8: =X8 -> 0 | ... AA8: =Z8 -> 0
B9: ENERGIA ELECTRICA | F9: 0 | G9: 400 | H9: =F9*G9 -> 0 | I9: =G9*$C$19 -> 7228 | J9: =(F9*I9) -> 0 | K9: =J9*1.16 -> 0 | L9: 0 | N9: 0 | O9: 0 | P9: =J9 -> 0 | Q9: =J9 -> 0 | R9: =Q9 -> 0 | S9: =R9 -> 0 | T9: =S9 -> 0 | U9: =T9 -> 0 | V9: =U9 -> 0 | W9: =V9 -> 0 | X9: =W9 -> 0 | Y9: =X9 -> 0 | ... AA9: =Z9 -> 0
B10: RENTA DE CASAS NO DEDUCIBLE | F10: 0 | G10: 0 | H10: =F10*G10 -> 0 | I10: =G10*$C$19 -> 0 | J10: =(F10*I10) -> 0 | K10: =J10*1.16 -> 0 | L10: 0 | N10: 0 | O10: =J10*0.5 -> 0 | P10: =I10 -> 0 | Q10: =P10 -> 0 | R10: =Q10 -> 0 | S10: =R10 -> 0 | T10: =S10 -> 0 | U10: =T10 -> 0 | V10: =U10 -> 0 | W10: =V10 -> 0 | X10: =W10 -> 0 | ... AA10: =Z10 -> 0
B11: SERVICIOS DE LIMPIEZA | F11: 0 | G11: 58 | H11: =F11*G11 -> 0 | I11: =G11*$C$19 -> 1048.06 | J11: =(F11*I11) -> 0 | K11: =J11*1.16 -> 0 | L11: 0 | N11: 0 | P11: =J11 -> 0 | Q11: =J11 -> 0 | R11: =Q11 -> 0 | S11: =R11 -> 0 | T11: =S11 -> 0 | U11: =T11 -> 0 | V11: =U11 -> 0 | W11: =V11 -> 0 | X11: =W11 -> 0 | Y11: =X11 -> 0 | ... AA11: =Z11 -> 0
B12: SERVICIOS DE VIGILANCIA | F12: 0 | G12: 36 | H12: =F12*G12 -> 0 | I12: =G12*$C$19 -> 650.52 | J12: =(F12*I12)/12 -> 0 | K12: =J12*1.16 -> 0 | L12: 0 | N12: 0 | O12: 0 | P12: 0 | Q12: 0 | R12: 0 | S12: 0 | T12: 0 | U12: 0 | V12: 0 | W12: 0 | X12: 0 | Y12: 0 | Z12: 0 | AA12: 0
B13: SERVICIOS DE FOSAS Y AGUA POTABLE | F13: 0 | G13: 750 | H13: =F13*G13 -> 0 | I13: =C19*G13 -> 13552.5 | J13: =I13*F13 -> 0 | K13: =J13*1.16 -> 0 | L13: 0 | N13: 0 | O13: 0 | P13: =J13 -> 0 | Q13: =P13 -> 0 | R13: =Q13 -> 0 | S13: =R13 -> 0 | T13: =S13 -> 0 | U13: =T13 -> 0 | V13: =U13 -> 0 | W13: =V13 -> 0 | X13: =W13 -> 0 | Y13: =J13 -> 0 | Z13: =Y13 -> 0 | AA13: =Z13 -> 0
B14: TELEFONIA FIJA | C14: Internet | F14: 0 | G14: 85 | H14: =F14*G14 -> 0 | I14: =G14*$C$19 -> 1535.95 | J14: =(F14*I14) -> 0 | K14: =J14*1.16 -> 0 | L14: 0 | N14: 0 | O14: 0 | P14: =J14 -> 0 | Q14: =P14 -> 0 | R14: =Q14 -> 0 | S14: =R14 -> 0 | T14: =S14 -> 0 | U14: =T14 -> 0 | V14: =U14 -> 0 | W14: =V14 -> 0 | X14: =W14 -> 0 | ... AA14: =Z14 -> 0
B15: AGUA Y ALCANTARILLADO | F15: 0 | G15: 120 | H15: =F15*G15 -> 0 | I15: =G15*$C$19 -> 2168.4 | J15: =(F15*I15) -> 0 | K15: =J15*1.16 -> 0 | L15: 0 | N15: 0 | O15: 0 | P15: =J15 -> 0 | Q15: =P15 -> 0 | R15: =Q15 -> 0 | S15: =R15 -> 0 | T15: =S15 -> 0 | U15: =T15 -> 0 | V15: =U15 -> 0 | W15: =V15 -> 0 | X15: =W15 -> 0 | ... AA15: =Z15 -> 0
B16: ARRENDAMIENTO DE OF. MOVILES | C16: Camper operativo | F16: 0 | G16: 774.76 | H16: =F16*G16 -> 0 | I16: =G16*$C$19 -> 13999.913 | J16: =(F16*I16) -> 0 | K16: =J16*1.16 -> 0 | L16: 0 | N16: 0 | O16: =$J$16 -> 0 | P16: =$J$16 -> 0 | Q16: =$J$16 -> 0 | R16: =$J$16 -> 0 | S16: 0 | T16: 0 | U16: 0 | V16: 0 | W16: 0 | X16: 0 | Y16: 0 | Z16: =Y16 -> 0 | AA16: =Z16 -> 0
B18: ='F01 UNIFORMES'!B20 -> Premisas | L18: Total Mensual [MN] | N18: =SUM(N8:N16) -> 0 | O18: =SUM(O8:O16) -> 0 | P18: =SUM(P8:P16) -> 0 | Q18: =SUM(Q8:Q16) -> 0 | R18: =SUM(R8:R16) -> 0 | S18: =SUM(S8:S16) -> 0 | T18: =SUM(T8:T16) -> 0 | U18: =SUM(U8:U16) -> 0 | ... AA18: =SUM(AA8:AA16) -> 0
B19: ='F01 UNIFORMES'!B21 -> Paridad | C19: ='F01 UNIFORMES'!C21 -> 18.07 | L19: Total Mensual [USD] | N19: =N18/$C$19 -> 0 | O19: =O18/PREMISAS!$D$18 -> 0 | P19: =P18/PREMISAS!$D$18 -> 0 | Q19: =Q18/PREMISAS!$D$18 -> 0 | R19: =R18/PREMISAS!$D$18 -> 0 | S19: =S18/PREMISAS!$D$18 -> 0 | T19: =T18/PREMISAS!$D$18 -> 0 | U19: =U18/PREMISAS!$D$18 -> 0 | V19: =V18/PREMISAS!$D$18 -> 0 | ... AA19: =AA18/PREMISAS!$D$18 -> 0
B20: ='F01 UNIFORMES'!B22 -> Mes | C20: ='F01 UNIFORMES'!C22 -> 30.4 | L20: Total [MN] | N20: =SUM(N18:AA18) -> 0
B21: ='F01 UNIFORMES'!B23 -> Periodo Pago (días) | C21: ='F01 UNIFORMES'!C23 -> 30 | L21: Total [USD] | N21: =N20/$C$19 -> 0
B22: ='F01 UNIFORMES'!B24 -> Gas lp | C22: ='F01 UNIFORMES'!C24 -> 0
B23: ='F01 UNIFORMES'!B25 -> Gasolina Magna | C23: ='F01 UNIFORMES'!C25 -> 22
B24: ='F01 UNIFORMES'!B26 -> Diesel | C24: ='F01 UNIFORMES'!C26 -> 23
B27: Optimizar casas staff

Sheet F03 COM Y EQ COM
B2: COMUNICACIÓN Y EQUIPO DE COMPUTO
B5: RESUMEN | C5: DESCRIPCIÓN 1 | D5: UNIDAD | E5: CANTIDAD | F5: IMPORTE | G5: IMPORTE TOTAL | H5: IMPORTE | I5: IMPORTE TOTAL | J5: TOTAL C/IVA | L5: Instalación | M5: Instalación | N5: Mes 1 | O5: Mes 2 | P5: Mes 3 | Q5: Mes 4 | R5: Mes 5 | S5: Mes 6 | T5: Mes 7 | U5: Mes 8 | V5: Mes 9 | W5: Mes 10 | X5: Mes 11 | Y5: Mes 12
N6: ENE | O6: FEB | P6: MAR | Q6: ABR | R6: MAY | S6: JUN | T6: JUL | U6: AGO | V6: SEP | W6: OCT | X6: ABR | Y6: MAY
F7: [USD] | G7: [USD] | H7: [MN] | I7: [MN] | J7: [MN] | N7: 31 | O7: 29 | P7: 31 | Q7: 30 | R7: 30 | S7: 31 | T7: 31 | U7: 31 | V7: 30 | W7: 31 | X7: 31 | Y7: 31
B8: SERV TELEFONIA CELULAR | C8: Supervisor | E8: 0 | F8: 45 | G8: =E8*F8 -> 0 | H8: =F8*$C$50 -> 813.15 | I8: =(E8*H8) -> 0 | J8: =I8*1.16 -> 0 | L8: 0 | M8: =$I$8 -> 0 | N8: =$I$8 -> 0 | O8: =$I$8 -> 0 | P8: =$I$8 -> 0 | Q8: =$I$8 -> 0 | R8: =$I$8 -> 0 | S8: =$I$8 -> 0 | T8: =$I$8 -> 0 | ... Y8: =$I$8 -> 0
B9: SERV TELEFONIA CELULAR | C9: Operación | E9: 0 | F9: 45 | G9: =E9*F9 -> 0 | H9: =F9*$C$50 -> 813.15 | I9: =(E9*H9) -> 0 | J9: =I9*1.16 -> 0 | L9: 0 | M9: =$I$9 -> 0 | N9: =$I$9 -> 0 | O9: =$I$9 -> 0 | P9: =$I$9 -> 0 | Q9: =$I$9 -> 0 | R9: =$I$9 -> 0 | S9: =$I$9 -> 0 | T9: =$I$9 -> 0 | ... Y9: =$I$9 -> 0
B10: SERV TELEFONIA CELULAR | C10: Seguridad | E10: 1 | F10: 45 | G10: =E10*F10 -> 45 | H10: =F10*$C$50 -> 813.15 | I10: =(E10*H10) -> 813.15 | J10: =I10*1.16 -> 943.254 | L10: 0 | M10: 0 | N10: 0 | O10: 0 | P10: 0 | Q10: 0 | R10: 0 | S10: 0 | T10: 0 | U10: 0 | V10: 0 | W10: 0 | X10: 0 | Y10: 0
J12: Total Mensual [MN] | L12: =SUM(L8:L10) -> 0 | M12: =SUM(M8:M10) -> 0 | N12: =SUM(N8:N10) -> 0 | O12: =SUM(O8:O10) -> 0 | P12: =SUM(P8:P10) -> 0 | Q12: =SUM(Q8:Q10) -> 0 | R12: =SUM(R8:R10) -> 0 | S12: =SUM(S8:S10) -> 0 | ... Y12: =SUM(Y8:Y10) -> 0
J13: Total Mensual [USD] | L13: =L12/$C$50 -> 0 | M13: =M12/$C$50 -> 0 | N13: =N12/$C$50 -> 0 | O13: =O12/$C$50 -> 0 | P13: =P12/$C$50 -> 0 | Q13: =Q12/$C$50 -> 0 | R13: =R12/$C$50 -> 0 | S13: =S12/$C$50 -> 0 | ... Y13: =Y12/$C$50 -> 0
J14: Total [MN] | L14: =SUM(L12:Y12) -> 0
J15: Total [USD] | L15: =L14/$C$50 -> 0
B17: SERVICIO DE BANDA ANCHA | E17: 0 | F17: 28 | G17: =E17*F17 -> 0 | H17: =F17*$C$50 -> 505.96 | I17: =(E17*H17) -> 0 | J17: =I17*1.16 -> 0 | L17: 0 | M17: =L17 -> 0 | N17: =I17 -> 0 | O17: =N17 -> 0 | P17: 0 | Q17: =P17 -> 0 | R17: =Q17 -> 0 | S17: =R17 -> 0 | T17: =S17 -> 0 | U17: =T17 -> 0 | V17: =U17 -> 0 | W17: =V17 -> 0 | X17: =W17 -> 0 | Y17: =I17 -> 0
B18: SERVICIO DE BANDA ANCHA | E18: 0 | F18: 0 | G18: =E18*F18 -> 0 | H18: =F18*$C$50 -> 0 | I18: =(E18*H18) -> 0 | J18: =I18*1.16 -> 0 | L18: =I18 -> 0 | M18: =L18 -> 0 | N18: =M18 -> 0 | O18: =N18 -> 0 | P18: =O18 -> 0 | Q18: =P18 -> 0 | R18: =Q18 -> 0 | S18: =R18 -> 0 | T18: =S18 -> 0 | ... Y18: =X18 -> 0
B19: SERVICIO DE BANDA ANCHA | E19: 0 | F19: 0 | G19: =E19*F19 -> 0 | H19: =F19*$C$50 -> 0 | I19: =(E19*H19) -> 0 | J19: =I19*1.16 -> 0 | L19: =I19 -> 0 | M19: =L19 -> 0 | N19: =M19 -> 0 | O19: =N19 -> 0 | P19: =O19 -> 0 | Q19: =P19 -> 0 | R19: =Q19 -> 0 | S19: =R19 -> 0 | T19: =S19 -> 0 | ... Y19: =X19 -> 0
J21: Total Mensual [MN] | L21: =SUM(L17:L19) -> 0 | M21: =SUM(M17:M19) -> 0 | N21: =SUM(N17:N19) -> 0 | O21: =SUM(O17:O19) -> 0 | P21: =SUM(P17:P19) -> 0 | Q21: =SUM(Q17:Q19) -> 0 | R21: =SUM(R17:R19) -> 0 | S21: =SUM(S17:S19) -> 0 | ... Y21: =SUM(Y17:Y19) -> 0
J22: Total Mensual [USD] | L22: =L21/$C$50 -> 0 | M22: =M21/$C$50 -> 0 | N22: =N21/$C$50 -> 0 | O22: =O21/$C$50 -> 0 | P22: =P21/$C$50 -> 0 | Q22: =Q21/$C$50 -> 0 | R22: =R21/$C$50 -> 0 | S22: =S21/$C$50 -> 0 | ... Y22: =Y21/$C$50 -> 0
J23: Total [MN] | L23: =SUM(L21:Y21) -> 0
J24: Total [USD] | L24: =L23/$C$50 -> 0
B26: SERVICIO DE RADIOCOMUNICACION | C26: Telemetría (Trans.) | E26: 0 | F26: 500 | G26: =E26*F26 -> 0 | H26: =F26*$C$50 -> 9035 | I26: =(E26*H26) -> 0 | J26: =I26*1.16 -> 0 | L26: 0 | M26: =$I$26 -> 0 | N26: =$I$26 -> 0 | O26: =$I$26 -> 0 | P26: =$I$26 -> 0 | Q26: =$I$26 -> 0 | R26: =$I$26 -> 0 | S26: =$I$26 -> 0 | T26: =$I$26 -> 0 | ... Y26: =$I$26 -> 0
B27: SERVICIO DE RADIOCOMUNICACION | E27: 0 | F27: 0 | G27: =E27*F27 -> 0 | H27: =F27*$C$50 -> 0 | I27: =(E27*H27) -> 0 | J27: =I27*1.16 -> 0 | L27: =I27 -> 0 | M27: =L27 -> 0 | N27: =M27 -> 0 | O27: =N27 -> 0 | P27: =O27 -> 0 | Q27: =P27 -> 0 | R27: =Q27 -> 0 | S27: =R27 -> 0 | T27: =S27 -> 0 | ... Y27: =X27 -> 0
B28: SERVICIO DE RADIOCOMUNICACION | E28: 0 | F28: 0 | G28: =E28*F28 -> 0 | H28: =F28*$C$50 -> 0 | I28: =(E28*H28) -> 0 | J28: =I28*1.16 -> 0 | L28: =I28 -> 0 | M28: =L28 -> 0 | N28: =M28 -> 0 | O28: =N28 -> 0 | P28: =O28 -> 0 | Q28: =P28 -> 0 | R28: =Q28 -> 0 | S28: =R28 -> 0 | T28: =S28 -> 0 | ... Y28: =X28 -> 0
J30: Total Mensual [MN] | L30: =SUM(L26:L28) -> 0 | M30: =SUM(M26:M28) -> 0 | N30: =SUM(N26:N28) -> 0 | O30: =SUM(O26:O28) -> 0 | P30: =SUM(P26:P28) -> 0 | Q30: =SUM(Q26:Q28) -> 0 | R30: =SUM(R26:R28) -> 0 | S30: =SUM(S26:S28) -> 0 | ... Y30: =SUM(Y26:Y28) -> 0
J31: Total Mensual [USD] | L31: =L30/$C$50 -> 0 | M31: =M30/$C$50 -> 0 | N31: =N30/$C$50 -> 0 | O31: =O30/$C$50 -> 0 | P31: =P30/$C$50 -> 0 | Q31: =Q30/$C$50 -> 0 | R31: =R30/$C$50 -> 0 | S31: =S30/$C$50 -> 0 | ... Y31: =Y30/$C$50 -> 0
J32: Total [MN] | L32: =SUM(L30:Y30) -> 0
J33: Total [USD] | L33: =L32/$C$50 -> 0
B36: EQUIPO DE COMPUTO (Adquisición) ARRENDAMIENTO DE EQ. COMPUTO | J36: Total Mensual [MN] | L36: =L21+L12+L30 -> 0 | M36: =M21+M12+M30 -> 0 | N36: =N21+N12+N30 -> 0 | O36: =O21+O12+O30 -> 0 | P36: =P21+P12+P30 -> 0 | Q36: =Q21+Q12+Q30 -> 0 | R36: =R21+R12+R30 -> 0 | S36: =S21+S12+S30 -> 0 | ... Y36: =Y21+Y12+Y30 -> 0
J37: Total Mensual [USD] | L37: =L36/$C$50 -> 0 | M37: =M36/$C$50 -> 0 | N37: =N36/$C$50 -> 0 | O37: =O36/$C$50 -> 0 | P37: =P36/$C$50 -> 0 | Q37: =Q36/$C$50 -> 0 | R37: =R36/$C$50 -> 0 | S37: =S36/$C$50 -> 0 | ... Y37: =Y36/$C$50 -> 0
J38: Total [MN] | L38: =SUM(L36:Y36) -> 0
J39: Total [USD] | L39: =L38/$C$50 -> 0
B41: EQUIPO DE COMPUTO
B42: RESUMEN | C42: DESCRIPCIÓN 1 | D42: UNIDAD | E42: CANTIDAD | F42: IMPORTE | G42: IMPORTE TOTAL | H42: IMPORTE | I42: IMPORTE TOTAL | J42: TOTAL C/IVA | L42: Instalación | M42: Instalación | N42: Mes 1 | O42: Mes 2 | P42: Mes 3 | Q42: Mes 4 | R42: Mes 5 | S42: Mes 6 | T42: Mes 7 | U42: Mes 8 | V42: Mes 9 | W42: Mes 10 | X42: Mes 11 | Y42: Mes 12
N43: ENE | O43: FEB | P43: MAR | Q43: ABR | R43: MAY | S43: JUN | T43: JUL | U43: AGO | V43: SEP | W43: OCT | X43: ABR | Y43: MAY
F44: [USD] | G44: [USD] | H44: [MN] | I44: [MN] | J44: [MN] | N44: 31 | O44: 29 | P44: 31 | Q44: 30 | R44: 30 | S44: 31 | T44: 31 | U44: 31 | V44: 30 | W44: 31 | X44: 31 | Y44: 31
B45: EQUIPO DE COMPUTO (Adquisición) | E45: 1 | F45: 1800 | G45: =E45*F45 -> 1800 | H45: =F45*$C$50 -> 32526 | I45: =(E45*H45) -> 32526 | J45: =I45*1.16 -> 37730.16 | L45: 0 | M45: =I45 -> 32526 | N45: 0 | O45: 0 | P45: 0 | Q45: 0 | R45: 0 | S45: 0 | T45: 0 | U45: 0 | V45: 0 | W45: 0 | X45: 0 | Y45: 0
B46: ARRENDAMIENTO DE EQ. COMPUTO | E46: 0 | F46: 0 | G46: =E46*F46 -> 0 | H46: =F46*$C$50 -> 0 | I46: =(E46*H46) -> 0 | J46: =I46*1.16 -> 0 | L46: =I46 -> 0 | M46: =L46 -> 0 | N46: =M46 -> 0 | O46: =N46 -> 0 | P46: =O46 -> 0 | Q46: =P46 -> 0 | R46: =Q46 -> 0 | S46: =R46 -> 0 | T46: =S46 -> 0 | ... Y46: =X46 -> 0
B49: ='F02 INMUEBLES Y S'!B18 -> Premisas | J49: Total Mensual [MN] | L49: =SUM(L45:L46) -> 0 | M49: =SUM(M45:M46) -> 32526 | N49: =SUM(N45:N46) -> 0 | O49: =SUM(O45:O46) -> 0 | P49: =SUM(P45:P46) -> 0 | Q49: =SUM(Q45:Q46) -> 0 | R49: =SUM(R45:R46) -> 0 | S49: =SUM(S45:S46) -> 0 | ... Y49: =SUM(Y45:Y46) -> 0
B50: ='F02 INMUEBLES Y S'!B19 -> Paridad | C50: ='F02 INMUEBLES Y S'!C19 -> 18.07 | J50: Total Mensual [USD] | L50: =L49/$C$50 -> 0
B51: ='F02 INMUEBLES Y S'!B20 -> Mes | C51: ='F02 INMUEBLES Y S'!C20 -> 30.4 | J51: Total [MN] | L51: =SUM(L49:Y49) -> 32526
B52: ='F02 INMUEBLES Y S'!B21 -> Periodo Pago (días) | C52: ='F02 INMUEBLES Y S'!C21 -> 30 | J52: Total [USD] | L52: =L51/$C$50 -> 1800
B53: ='F02 INMUEBLES Y S'!B22 -> Gas lp | C53: ='F02 INMUEBLES Y S'!C22 -> 0
B54: ='F02 INMUEBLES Y S'!B23 -> Gasolina Magna | C54: ='F02 INMUEBLES Y S'!C23 -> 22
B55: ='F02 INMUEBLES Y S'!B24 -> Diesel | C55: ='F02 INMUEBLES Y S'!C24 -> 23

Sheet F04 VEHÍCULOS Y COMB. 
B2: VEHICULOS Y COMBUSTIBLE
B5: NOMBRE | C5: RENTA | D5: VERIFICACIÓN | E5: SINIESTROS | F5: TENENCIA | G5: MANTTO (10,000 KM) | H5: LLANTAS | I5: GPS | J5: SEGURO | L5: SUBTOTAL | N5: TIPO DE COMBUSTIBLE | O5: PRECIO X LITRO | P5: LITROS / SEMANA | Q5: TOTAL GASOLINA MES S/IVA MN | R5: TOTAL GASOLINA MES C/IVA | S5: TOTAL MENSUAL MXN | T5: TOTAL MENSUAL USD | V5: Instalación | W5: Instalación | X5: Mes 1 | Y5: Mes 2 | Z5: Mes 3 | AA5: Mes 4 | AB5: Mes 5 | AC5: Mes 6 | AD5: Mes 7 | AE5: Mes 8 | AF5: Mes 9 | AG5: Mes 10 | AH5: Mes 11 | AI5: Mes 12
V6: - | W6: - | X6: ENE | Y6: FEB | Z6: MAR | AA6: ABR | AB6: MAY | AC6: JUN | AD6: JUL | AE6: AGO | AF6: SEP | AG6: OCT | AH6: NOV | AI6: DIC
V7: - | W7: - | X7: 31 | Y7: 29 | Z7: 31 | AA7: 30 | AB7: 30 | AC7: 31 | AD7: 31 | AE7: 31 | AF7: 30 | AG7: 31 | AH7: 30 | AI7: 31
B8: SUPERVISOR | C8: 0 | D8: 100 | E8: 0 | F8: 100 | G8: 7000 | H8: 1000 | I8: 500 | J8: 2000 | L8: =SUM(C8:J8) -> 10700 | V8: 0 | W8: 0 | X8: 0 | Y8: =X8 -> 0 | Z8: =Y8 -> 0 | AA8: 0 | AB8: =AA8 -> 0 | AC8: =AB8 -> 0 | AD8: =AC8 -> 0 | AE8: =AD8 -> 0 | AF8: =AE8 -> 0 | AG8: =AF8 -> 0 | AH8: 0 | AI8: =AH8 -> 0
B9: SUPERVISOR | C9: 0 | D9: 100 | E9: 0 | F9: 100 | G9: 7000 | H9: 1000 | I9: 500 | J9: 2000 | L9: =SUM(C9:J9) -> 10700 | V9: 0 | W9: 0 | X9: 0 | Y9: =X9 -> 0 | Z9: =Y9 -> 0 | AA9: 0 | AB9: =AA9 -> 0 | AC9: =AB9 -> 0 | AD9: =AC9 -> 0 | AE9: 0 | AF9: =AE9 -> 0 | AG9: =AF9 -> 0 | AH9: =AG9 -> 0 | AI9: =AH9 -> 0
B10: SUPERVISOR | C10: 0 | D10: 100 | E10: 0 | F10: 100 | G10: 7000 | H10: 1000 | I10: 500 | J10: 2000 | L10: =SUM(C10:J10) -> 10700 | V10: 0 | W10: 0 | X10: 0 | Y10: =X10 -> 0 | Z10: =Y10 -> 0 | AA10: 0 | AB10: =AA10 -> 0 | AC10: =AB10 -> 0 | AD10: =AC10 -> 0 | AE10: 0 | AF10: =AE10 -> 0 | AG10: =AF10 -> 0 | AH10: =AG10 -> 0 | AI10: =AH10 -> 0
B11: SUPERVISOR | C11: 0 | D11: 100 | E11: 0 | F11: 100 | G11: 7000 | H11: 1000 | I11: 500 | J11: 2000 | L11: =SUM(C11:J11) -> 10700 | V11: 0 | W11: 0 | X11: 0 | Y11: =X11 -> 0 | Z11: =Y11 -> 0 | AA11: 0 | AB11: =AA11 -> 0 | AC11: =AB11 -> 0 | AD11: =AC11 -> 0 | AE11: 0 | AF11: =AE11 -> 0 | AG11: =AF11 -> 0 | AH11: =AG11 -> 0 | AI11: =AH11 -> 0
B12: VAN PARA OP | D12: 100 | F12: 100 | G12: 7000 | H12: 1000 | I12: 500 | J12: 2000 | L12: =SUM(C12:J12) -> 10700 | V12: 0 | W12: 0 | X12: 0 | Y12: =X12 -> 0 | Z12: =Y12 -> 0 | AA12: 0 | AB12: =AA12 -> 0 | AC12: =AB12 -> 0 | AD12: =AC12 -> 0 | AE12: 0 | AF12: =AE12 -> 0 | AG12: =AF12 -> 0 | AH12: =AG12 -> 0 | AI12: =AH12 -> 0
B13: REPRESENTANTE TA | D13: 100 | E13: 0 | F13: 100 | G13: 7000 | H13: 1000 | I13: 500 | J13: 2000 | L13: =SUM(C13:J13) -> 10700 | V13: 0 | W13: =V13 -> 0 | X13: 0 | Y13: =X13 -> 0 | Z13: =Y13 -> 0 | AA13: 0 | AB13: =AA13 -> 0 | AC13: =AB13 -> 0 | AD13: =AC13 -> 0 | AE13: 0 | AF13: =AE13 -> 0 | AG13: =AF13 -> 0 | AH13: =AG13 -> 0 | AI13: =AH13 -> 0
N15: Gasolina 42 | O15: =$C$30 -> 23.5 | P15: 200 | Q15: =O15*P15*4 -> 18800 | R15: =Q15*1.16 -> 21808 | S15: =L8+Q15 -> 29500 | T15: =S15/$C$26 -> 1632.5401 | V15: =Q15 -> 18800 | W15: =Q15 -> 18800 | X15: 0 | Y15: =X15 -> 0 | Z15: =Y15 -> 0 | AA15: 0 | AB15: =AA15 -> 0 | AC15: =AB15 -> 0 | AD15: =AC15 -> 0 | AE15: =AD15 -> 0 | AF15: =AE15 -> 0 | AG15: =AF15 -> 0 | AH15: =AG15 -> 0 | AI15: =AH15 -> 0
N16: Gasolina soldadores | O16: =$C$30 -> 23.5 | P16: 1200 | Q16: =O16*P16*4 -> 112800 | R16: =Q16*1.16 -> 130848 | S16: =L9+R16 -> 141548 | T16: =S16/$C$26 -> 7833.3149 | V16: =Q16 -> 112800 | W16: =Q16 -> 112800 | X16: 0 | Y16: =X16 -> 0 | Z16: =Y16 -> 0 | AA16: 0 | AB16: =AA16 -> 0 | AC16: =AB16 -> 0 | AD16: =AC16 -> 0 | AE16: =AD16 -> 0 | AF16: =AE16 -> 0 | AG16: =AF16 -> 0 | AH16: =AG16 -> 0 | AI16: =AH16 -> 0
N17: Gasolina 41 | O17: =$C$30 -> 23.5 | P17: 200 | Q17: =O17*P17*4 -> 18800 | R17: =Q17*1.16 -> 21808 | S17: =L11+R17 -> 32508 | T17: =S17/$C$26 -> 1799.0039 | V17: =Q17 -> 18800 | W17: =Q17 -> 18800 | X17: 0 | Y17: =X17 -> 0 | Z17: =Y17 -> 0 | AA17: 0 | AB17: =AA17 -> 0 | AC17: =AB17 -> 0 | AD17: =AC17 -> 0 | AE17: =AD17 -> 0 | AF17: =AE17 -> 0 | AG17: =AF17 -> 0 | AH17: =AG17 -> 0 | AI17: =AH17 -> 0
O18: =$C$30 -> 23.5 | P18: 0 | Q18: =O18*P18*4 -> 0 | R18: =Q18*1.16 -> 0 | S18: =L13+R18 -> 10700 | T18: =S18/$C$26 -> 592.14167 | V18: 0 | W18: =V18 -> 0 | X18: =Q18 -> 0 | Y18: =X18 -> 0 | Z18: =Y18 -> 0 | AA18: =Z18 -> 0 | AB18: =AA18 -> 0 | AC18: =AB18 -> 0 | AD18: =AC18 -> 0 | AE18: =AD18 -> 0 | AF18: =AE18 -> 0 | ... AI18: =AH18 -> 0
T20: Total Mensual [MN] | V20: =SUM(V8:V13) -> 0 | W20: =SUM(W8:W13) -> 0 | X20: =SUM(X8:X13) -> 0 | Y20: =SUM(Y8:Y13) -> 0 | Z20: =SUM(Z8:Z13) -> 0 | AA20: =SUM(AA8:AA13) -> 0 | AB20: =SUM(AB8:AB13) -> 0 | AC20: =SUM(AC8:AC13) -> 0 | ... AI20: =SUM(AI8:AI13) -> 0
T21: Total Mensual [USD] | V21: =V20/$C$26 -> 0 | W21: =W20/$C$26 -> 0 | X21: =X20/$C$26 -> 0 | Y21: =Y20/$C$26 -> 0 | Z21: =Z20/$C$26 -> 0 | AA21: =AA20/$C$26 -> 0 | AB21: =AB20/$C$26 -> 0 | AC21: =AC20/$C$26 -> 0 | ... AI21: =AI20/$C$26 -> 0
T22: Total [MN] | V22: =SUM(V15:V18) -> 150400 | W22: =SUM(W15:W18) -> 150400 | X22: =SUM(X15:X18) -> 0 | Y22: =SUM(Y15:Y18) -> 0 | Z22: =SUM(Z15:Z18) -> 0 | AA22: =SUM(AA15:AA18) -> 0 | AB22: =SUM(AB15:AB18) -> 0 | AC22: =SUM(AC15:AC18) -> 0 | ... AI22: =SUM(AI15:AI18) -> 0
T23: Total [USD] | V23: =V22/$C$26 -> 8323.1876 | W23: =W22/$C$26 -> 8323.1876 | X23: =X22/$C$26 -> 0 | Y23: =Y22/$C$26 -> 0 | Z23: =Z22/$C$26 -> 0 | AA23: =AA22/$C$26 -> 0 | AB23: =AB22/$C$26 -> 0 | AC23: =AC22/$C$26 -> 0 | ... AI23: =AI22/$C$26 -> 0
B25: ='F03 COM Y EQ COM'!B49 -> Premisas | T25: Total Mensual [MN] | V25: =SUM(V20+V22) -> 150400 | W25: =SUM(W20+W22) -> 150400 | X25: =SUM(X20,X22) -> 0 | Y25: =SUM(Y20,Y22) -> 0 | Z25: =SUM(Z20,Z22) -> 0 | AA25: =SUM(AA20,AA22) -> 0 | AB25: =SUM(AB20,AB22) -> 0 | AC25: =SUM(AC20,AC22) -> 0 | AD25: =SUM(AD20,AD22) -> 0 | AE25: =SUM(AE20,AE22) -> 0 | ... AI25: =SUM(AI20,AI22) -> 0
B26: ='F03 COM Y EQ COM'!B50 -> Paridad | C26: ='F03 COM Y EQ COM'!C50 -> 18.07 | T26: Total Mensual [USD] | V26: =V25/$C$26 -> 8323.1876 | W26: =W25/$C$26 -> 8323.1876 | X26: =X25/$C$26 -> 0 | Y26: =Y25/$C$26 -> 0 | Z26: =Z25/$C$26 -> 0 | AA26: =AA25/$C$26 -> 0 | AB26: =AB25/$C$26 -> 0 | AC26: =AC25/$C$26 -> 0 | ... AI26: =AI25/$C$26 -> 0
B27: ='F03 COM Y EQ COM'!B51 -> Mes | C27: ='F03 COM Y EQ COM'!C51 -> 30.4 | T27: Total [MN] | V27: =SUM(V25:AI25) -> 300800
B28: ='F03 COM Y EQ COM'!B52 -> Periodo Pago (días) | C28: ='F03 COM Y EQ COM'!C52 -> 30 | T28: Total [USD] | V28: =V27/$C$26 -> 16646.375
B29: ='F03 COM Y EQ COM'!B53 -> Gas lp | C29: ='F03 COM Y EQ COM'!C53 -> 0
B30: ='F03 COM Y EQ COM'!B54 -> Gasolina Magna | C30: 23.5
B31: ='F03 COM Y EQ COM'!B55 -> Diesel | C31: ='F03 COM Y EQ COM'!C55 -> 23
C37: -

Sheet F05 VIÁTICOS
B2: VIATICOS
B5: RESUMEN | C5: UNIDAD | D5: CANTIDAD | E5: IMPORTE | F5: IMPORTE TOTAL | G5: IMPORTE | H5: IMPORTE TOTAL | I5: TOTAL C/IVA | K5: Instalación | L5: Instalación | M5: Mes 1 | N5: Mes 2 | O5: Mes 3 | P5: Mes 4 | Q5: Mes 5 | R5: Mes 6 | S5: Mes 7 | T5: Mes 8 | U5: Mes 9 | V5: Mes 10 | W5: Mes 11 | X5: Mes 12
K6: - | L6: - | M6: ENE | N6: FEB | O6: MAR | P6: ABR | Q6: MAY | R6: JUN | S6: JUL | T6: AGO | U6: SEP | V6: OCT | W6: NOV | X6: DIC
E7: [USD] | F7: [USD] | G7: [MN] | H7: [MN] | I7: [MN] | K7: - | L7: - | M7: 31 | N7: 29 | O7: 31 | P7: 30 | Q7: 30 | R7: 31 | S7: 31 | T7: 31 | U7: 30 | V7: 31 | W7: 30 | X7: 31
B8: ALIMENTACION | D8: 15 | E8: 1250 | F8: =D8*E8 -> 18750 | G8: =E8*$C$29 -> 22587.5 | H8: =(D8*G8) -> 338812.5 | I8: =H8*1.16 -> 393022.5 | K8: =H8 -> 338812.5 | L8: =H8 -> 338812.5 | M8: 0 | N8: =M8 -> 0 | O8: 0 | P8: =O8 -> 0 | Q8: =P8 -> 0 | R8: =Q8 -> 0 | S8: =R8 -> 0 | T8: =S8 -> 0 | U8: =T8 -> 0 | V8: =U8 -> 0 | W8: =V8 -> 0 | X8: =W8 -> 0
B9: CASETAS PUENTES Y PEAJES | D9: 3 | E9: 172.66 | F9: =D9*E9 -> 517.98 | G9: =E9*$C$29 -> 3119.9662 | H9: =(D9*G9) -> 9359.8986 | I9: =H9*1.16 -> 10857.482 | K9: =H9 -> 9359.8986 | L9: =K9 -> 9359.8986 | M9: 0 | N9: =M9 -> 0 | O9: 0 | P9: =O9 -> 0 | Q9: =P9 -> 0 | R9: =Q9 -> 0 | S9: =R9 -> 0 | T9: =S9 -> 0 | U9: =T9 -> 0 | V9: =U9 -> 0 | W9: =V9 -> 0 | X9: =W9 -> 0
B10: SERV DE TRANSPORTAC AEREA | D10: 0 | E10: 221.36137 | F10: =D10*E10 -> 0 | G10: =E10*$C$29 -> 4000 | H10: =(D10*G10) -> 0 | I10: =H10*1.16 -> 0 | K10: 0 | L10: =K10 -> 0 | M10: 0 | N10: =M10 -> 0 | O10: 0 | P10: =O10 -> 0 | Q10: =P10 -> 0 | R10: =Q10 -> 0 | S10: =R10 -> 0 | T10: =S10 -> 0 | U10: =T10 -> 0 | V10: =U10 -> 0 | W10: =V10 -> 0 | X10: =W10 -> 0
B11: SERV DE TRANSPORTAC TERRESTRE | D11: 0 | E11: 120 | F11: =D11*E11 -> 0 | G11: =E11*$C$29 -> 2168.4 | H11: =(D11*G11) -> 0 | I11: =H11*1.16 -> 0 | K11: 0 | L11: =K11 -> 0 | M11: 0 | N11: =M11 -> 0 | O11: 0 | P11: =O11 -> 0 | Q11: =P11 -> 0 | R11: =Q11 -> 0 | S11: =R11 -> 0 | T11: =S11 -> 0 | U11: =T11 -> 0 | V11: =U11 -> 0 | W11: =V11 -> 0 | X11: =W11 -> 0
B12: SERVICIOS DE HOSPEDAJE | D12: 15 | E12: 1664.81 | F12: =D12*E12 -> 24972.15 | G12: =E12*$C$29 -> 30083.117 | H12: =(D12*G12) -> 451246.75 | I12: =H12*1.16 -> 523446.23 | K12: =H12 -> 451246.75 | L12: =K12 -> 451246.75 | M12: 0 | N12: =M12 -> 0 | O12: 0 | P12: =O12 -> 0 | Q12: =P12 -> 0 | R12: =Q12 -> 0 | S12: =R12 -> 0 | T12: =S12 -> 0 | U12: =T12 -> 0 | V12: =U12 -> 0 | W12: =V12 -> 0 | X12: =W12 -> 0
I14: Total Mensual [MN] | K14: =SUM(K8:K12) -> 799419.15 | L14: =SUM(L8:L12) -> 799419.15 | M14: =SUM(M8:M12) -> 0 | N14: =SUM(N8:N12) -> 0 | O14: =SUM(O8:O12) -> 0 | P14: =SUM(P8:P12) -> 0 | Q14: =SUM(Q8:Q12) -> 0 | R14: =SUM(R8:R12) -> 0 | ... X14: =SUM(X8:X12) -> 0
I15: Total Mensual [USD] | K15: =K14/$C$29 -> 44240.13 | L15: =L14/20 -> 39970.957 | M15: =M14/20 -> 0 | N15: =N14/20 -> 0 | O15: =O14/20 -> 0 | P15: =P14/20 -> 0 | Q15: =Q14/20 -> 0 | R15: =R14/20 -> 0 | S15: =S14/20 -> 0 | ... X15: =X14/20 -> 0
I16: Total [MN] | K16: =SUM(K14:X14) -> 1598838.3
I17: Total [USD] | K17: =K16/$C$29 -> 88480.26
B20: CAJA CHICA | D20: 0 | E20: 2500 | F20: =E20*D20 -> 0 | G20: =F20*C29 -> 0 | H20: =G20*D20 -> 0 | I20: =H20*1.16 -> 0 | K20: 0 | L20: =K20 -> 0 | M20: 0 | N20: =M20 -> 0 | O20: 0 | P20: =O20 -> 0 | Q20: =P20 -> 0 | R20: =Q20 -> 0 | S20: =R20 -> 0 | T20: =S20 -> 0 | U20: =T20 -> 0 | V20: =U20 -> 0 | W20: =V20 -> 0 | X20: =W20 -> 0
B21: REEMBOLSOS | D21: 1 | E21: 400 | F21: =E21*D21 -> 400 | G21: =E21*C29 -> 7228 | H21: =G21*D21 -> 7228 | I21: =H21*1.16 -> 8384.48 | K21: =H21 -> 7228 | L21: =H21 -> 7228 | M21: 0 | N21: =M21 -> 0 | O21: =N21 -> 0 | P21: 0 | Q21: =P21 -> 0 | R21: 0 | S21: =R21 -> 0 | T21: =S21 -> 0 | U21: =T21 -> 0 | V21: =U21 -> 0 | W21: =V21 -> 0 | X21: =W21 -> 0
I23: Total Mensual [MN] | K23: =SUM(K20:K21) -> 7228 | L23: =SUM(L20:L21) -> 7228 | M23: =SUM(M20:M21) -> 0 | N23: =SUM(N20:N21) -> 0 | O23: =SUM(O20:O21) -> 0 | P23: =SUM(P20:P21) -> 0 | Q23: =SUM(Q20:Q21) -> 0 | R23: =SUM(R20:R21) -> 0 | ... X23: =SUM(X20:X21) -> 0
I24: Total Mensual [USD] | K24: =K23/$C$29 -> 400 | L24: =L23/$C$29 -> 400 | M24: =M23/$C$29 -> 0 | N24: =N23/$C$29 -> 0 | O24: =O23/$C$29 -> 0 | P24: =P23/$C$29 -> 0 | Q24: =Q23/$C$29 -> 0 | R24: =R23/$C$29 -> 0 | ... X24: =X23/$C$29 -> 0
I25: Total [MN] | K25: =SUM(K23:X23) -> 14456
I26: Total [USD] | K26: =K25/20 -> 722.8
B28: ='F04 VEHÍCULOS Y COMB. '!B25 -> Premisas | I28: Total Mensual [MN] | K28: =SUM(K23+K14) -> 806647.15 | L28: =SUM(L23+L14) -> 806647.15 | M28: =SUM(M23+M14) -> 0 | N28: =SUM(N23+N14) -> 0 | O28: =SUM(O23+O14) -> 0 | P28: =SUM(P23+P14) -> 0 | Q28: =SUM(Q23+Q14) -> 0 | R28: =SUM(R23+R14) -> 0 | ... X28: =SUM(X23+X14) -> 0
B29: ='F04 VEHÍCULOS Y COMB. '!B26 -> Paridad | C29: ='F04 VEHÍCULOS Y COMB. '!C26 -> 18.07 | I29: Total Mensual [USD] | K29: =K28/$C$29 -> 44640.13 | L29: =L28/$C$29 -> 44640.13 | M29: =M28/$C$29 -> 0 | N29: =N28/$C$29 -> 0 | O29: =O28/$C$29 -> 0 | P29: =P28/$C$29 -> 0 | Q29: =Q28/$C$29 -> 0 | R29: =R28/$C$29 -> 0 | ... X29: =X28/$C$29 -> 0
B30: ='F04 VEHÍCULOS Y COMB. '!B27 -> Mes | C30: ='F04 VEHÍCULOS Y COMB. '!C27 -> 30.4 | I30: Total [MN] | K30: =SUM(K28:X28) -> 1613294.3
B31: ='F04 VEHÍCULOS Y COMB. '!B28 -> Periodo Pago (días) | C31: ='F04 VEHÍCULOS Y COMB. '!C28 -> 30 | I31: Total [USD] | K31: =K30/$C$29 -> 89280.26
B32: ='F04 VEHÍCULOS Y COMB. '!B29 -> Gas lp | C32: ='F04 VEHÍCULOS Y COMB. '!C29 -> 0
B33: ='F04 VEHÍCULOS Y COMB. '!B30 -> Gasolina Magna | C33: ='F04 VEHÍCULOS Y COMB. '!C30 -> 23.5
B34: ='F04 VEHÍCULOS Y COMB. '!B31 -> Diesel | C34: ='F04 VEHÍCULOS Y COMB. '!C31 -> 23

Sheet F06 (MAT,SERV & EQUIPO)
B2: MATERIALES, SERVICIOS Y EQUIPO DE CONSTRUCCION
B5: MATERIALES | G5: IMPORTE | H5: IMPORTE TOTAL | I5: IMPORTE | J5: IMPORTE TOTAL | K5: TOTAL C/IVA | M5: Instalación | N5: Instalación | O5: Mes 1 | P5: Mes 2 | Q5: Mes 3 | R5: Mes 4 | S5: Mes 5 | T5: Mes 6 | U5: Mes 7 | V5: Mes 8 | W5: Mes 9 | X5: Mes 10 | Y5: Mes 11 | Z5: Mes 12
B6: RESUMEN | C6: DESCRIPCIÓN 1 | D6: DESCRIPCIÓN 2 | E6: UNIDAD | F6: CANTIDAD | M6: - | N6: - | O6: ENE | P6: FEB | Q6: MAR | R6: ABR | S6: MAY | T6: JUN | U6: JUL | V6: AGO | W6: SEP | X6: OCT | Y6: NOV | Z6: DIC
G7: [USD] | H7: [USD] | I7: [MN] | J7: [MN] | K7: [MN] | M7: - | N7: - | O7: 31 | P7: 29 | Q7: 31 | R7: 30 | S7: 30 | T7: 31 | U7: 31 | V7: 31 | W7: 30 | X7: 31 | Y7: 30 | Z7: 31
B8: ABRASIVOS (THINER/DESENGRASANTE/W40) | C8: Desengrasante | F8: 7 | G8: 83 | H8: =F8*G8 -> 581 | I8: =G8*$C$45 -> 1499.81 | J8: =(F8*I8) -> 10498.67 | K8: =J8*1.16 -> 12178.457 | L8: =H8 -> 581 | M8: =J8 -> 10498.67 | N8: =J8 -> 10498.67 | O8: 0 | P8: 0 | Q8: 0 | R8: 0 | S8: 0 | T8: 0 | U8: 0 | V8: 0 | W8: 0 | X8: 0 | Y8: 0 | Z8: 0
B9: ACEITE LUBRICANTE P/MAQUINARIA (100+120) | F9: 0 | G9: 5750 | H9: =F9*G9 -> 0 | I9: =G9*$C$45 -> 103902.5 | J9: =(F9*I9) -> 0 | K9: =J9*1.16 -> 0 | L9: =H9 -> 0 | M9: 0 | N9: =J9 -> 0 | O9: 0 | P9: 0 | Q9: 0 | R9: 0 | S9: 0 | T9: 0 | U9: 0 | V9: 0 | W9: 0 | X9: 0 | Y9: 0 | Z9: 0
B10: ACEITES Y LUBRICANTES | F10: 0 | G10: 5750 | H10: =F10*G10 -> 0 | I10: =G10*$C$45 -> 103902.5 | J10: =(F10*I10) -> 0 | K10: =J10*1.16 -> 0 | L10: =H10 -> 0 | M10: 0 | N10: =J10 -> 0 | O10: 0 | P10: 0 | Q10: 0 | R10: 0 | S10: 0 | T10: 0 | U10: 0 | V10: 0 | W10: 0 | X10: 0 | Y10: 0 | Z10: 0
B11: AISLANTES IMPERM REFRA | F11: 0 | G11: 0 | H11: =F11*G11 -> 0 | I11: =G11*$C$45 -> 0 | J11: =(F11*I11) -> 0 | K11: =J11*1.16 -> 0 | L11: =H11 -> 0 | M11: 0 | N11: =M11 -> 0 | O11: 0 | P11: 0 | Q11: 0 | R11: 0 | S11: 0 | T11: 0 | U11: 0 | V11: 0 | W11: 0 | X11: 0 | Y11: 0 | Z11: 0
B12: BANDA CADEN TRANS COPL | F12: 0 | G12: 0 | H12: =F12*G12 -> 0 | I12: =G12*$C$45 -> 0 | J12: =(F12*I12) -> 0 | K12: =J12*1.16 -> 0 | L12: =H12 -> 0 | M12: 0 | N12: =M12 -> 0 | O12: 0 | P12: 0 | Q12: 0 | R12: 0 | S12: 0 | T12: 0 | U12: 0 | V12: 0 | W12: 0 | X12: 0 | Y12: 0 | Z12: 0
B13: CONEXIONES PARA TUBERIA | C13: Conexiones tubing | F13: 0 | G13: 4722.22 | H13: =F13*G13 -> 0 | I13: =G13*$C$45 -> 85330.515 | J13: =(F13*I13) -> 0 | K13: =J13*1.16 -> 0 | L13: =H13 -> 0 | M13: 0 | N13: =J13 -> 0 | O13: 0 | P13: 0 | Q13: 0 | R13: 0 | S13: 0 | T13: 0 | U13: 0 | V13: 0 | W13: 0 | X13: 0 | Y13: 0 | Z13: 0
B14: EMPAQUETAD JTAS Y SELLOS | F14: 0 | G14: 7194.2446 | H14: =F14*G14 -> 0 | I14: =G14*$C$45 -> 130000 | J14: =(F14*I14) -> 0 | K14: =J14*1.16 -> 0 | L14: =H14 -> 0 | M14: 0 | N14: =M14 -> 0 | O14: 0 | P14: 0 | Q14: 0 | R14: 0 | S14: 0 | T14: 0 | U14: 0 | V14: 0 | W14: 0 | X14: 0 | Y14: 0 | Z14: 0
B15: ENVASES | F15: 0 | G15: 0 | H15: =F15*G15 -> 0 | I15: =G15*$C$45 -> 0 | J15: =(F15*I15) -> 0 | K15: =J15*1.16 -> 0 | L15: =H15 -> 0 | M15: 0 | N15: =M15 -> 0 | O15: 0 | P15: 0 | Q15: 0 | R15: 0 | S15: 0 | T15: 0 | U15: 0 | V15: 0 | W15: 0 | X15: 0 | Y15: 0 | Z15: 0
B16: FIBRAS HILOS Y TELAS | C16: Trapo industrial | F16: 0 | G16: 27.670172 | H16: =F16*G16 -> 0 | I16: =G16*$C$45 -> 500 | J16: =(F16*I16) -> 0 | K16: =J16*1.16 -> 0 | L16: =H16 -> 0 | M16: =J16 -> 0 | N16: =M16 -> 0 | O16: 0 | P16: 0 | Q16: 0 | R16: 0 | S16: 0 | T16: 0 | U16: 0 | V16: 0 | W16: 0 | X16: 0 | Y16: 0 | Z16: 0
B17: GRASAS | F17: 0 | G17: 150 | H17: =F17*G17 -> 0 | I17: =G17*$C$45 -> 2710.5 | J17: =(F17*I17) -> 0 | K17: =J17*1.16 -> 0 | L17: =H17 -> 0 | M17: =J17 -> 0 | N17: 0 | O17: 0 | P17: 0 | Q17: 0 | R17: 0 | S17: 0 | T17: 0 | U17: 0 | V17: 0 | W17: 0 | X17: 0 | Y17: 0 | Z17: 0
B18: HERRAMIENTAS MANUALES | C18: Herramienta | F18: 0 | G18: 84138.894 | H18: =F18*G18 -> 0 | I18: =G18*$C$45 -> 1520389.8 | J18: =(F18*I18) -> 0 | K18: =J18*1.16 -> 0 | L18: =H18 -> 0 | M18: =J18 -> 0 | N18: 0 | O18: 0 | P18: 0 | Q18: 0 | R18: 0 | S18: 0 | T18: 0 | U18: 0 | V18: 0 | W18: 0 | X18: 0 | Y18: 0 | Z18: 0
B19: INSTRUM DE MEDICION Y CONTROL | F19: 0 | G19: 830.10515 | H19: =F19*G19 -> 0 | I19: =G19*$C$45 -> 15000 | J19: =(F19*I19) -> 0 | K19: =J19*1.16 -> 0 | L19: =H19 -> 0 | M19: 0 | N19: =M19 -> 0 | O19: 0 | P19: 0 | Q19: 0 | R19: 0 | S19: 0 | T19: 0 | U19: 0 | V19: 0 | W19: 0 | X19: 0 | Y19: 0 | Z19: 0
B20: INSTRUM DE MEDICION Y CONTROL | C20: Manometros | F20: 0 | G20: 1200 | H20: =F20*G20 -> 0 | I20: =G20*$C$45 -> 21684 | J20: =(F20*I20) -> 0 | K20: =J20*1.16 -> 0 | L20: =H20 -> 0 | M20: =J20 -> 0 | N20: 0 | O20: 0 | P20: 0 | Q20: 0 | R20: 0 | S20: 0 | T20: 0 | U20: 0 | V20: 0 | W20: 0 | X20: 0 | Y20: 0 | Z20: 0
B21: MANGUERAS, CONEXIONES | F21: 0 | G21: 0 | H21: =F21*G21 -> 0 | I21: =G21*$C$45 -> 0 | J21: =(F21*I21) -> 0 | K21: =J21*1.16 -> 0 | L21: =H21 -> 0 | M21: 0 | N21: =M21 -> 0 | O21: 0 | P21: 0 | Q21: 0 | R21: 0 | S21: 0 | T21: 0 | U21: 0 | V21: 0 | W21: 0 | X21: 0 | Y21: 0 | Z21: 0
B22: MATERIAL ELECTRICO | F22: 0 | G22: 100 | H22: =F22*G22 -> 0 | I22: =G22*$C$45 -> 1807 | J22: =(F22*I22) -> 0 | K22: =J22*1.16 -> 0 | L22: =H22 -> 0 | M22: 0 | N22: =M22 -> 0 | O22: 0 | P22: 0 | Q22: 0 | R22: 0 | S22: 0 | T22: 0 | U22: 0 | V22: 0 | W22: 0 | X22: 0 | Y22: 0 | Z22: 0
B23: MATERIAL PARA LA CONSTRUCCION | F23: 0 | G23: 55.340343 | H23: =F23*G23 -> 0 | I23: =G23*$C$45 -> 1000 | J23: =(F23*I23) -> 0 | K23: =J23*1.16 -> 0 | L23: =H23 -> 0 | M23: 0 | N23: =M23 -> 0 | O23: 0 | P23: 0 | Q23: 0 | R23: 0 | S23: 0 | T23: 0 | U23: 0 | V23: 0 | W23: 0 | X23: 0 | Y23: 0 | Z23: 0
B24: MATERIALES Y ART P/MANTENIMIENTO | F24: 0 | G24: 55.34 | H24: =G24*F24 -> 0 | I24: =G24*$C$45 -> 999.9938 | J24: =(F24*I24) -> 0 | K24: =J24*1.16 -> 0 | L24: =H24 -> 0 | M24: 0 | N24: =M24 -> 0 | O24: 0 | P24: 0 | Q24: 0 | R24: 0 | S24: 0 | T24: 0 | U24: 0 | V24: 0 | W24: 0 | X24: 0 | Y24: 0 | Z24: 0
B25: METALES | F25: 0 | G25: 138.35086 | H25: =F25*G25 -> 0 | I25: =G25*$C$45 -> 2500 | J25: =(F25*I25) -> 0 | K25: =J25*1.16 -> 0 | L25: =H25 -> 0 | M25: 0 | N25: =M25 -> 0 | O25: 0 | P25: 0 | Q25: 0 | R25: 0 | S25: 0 | T25: 0 | U25: 0 | V25: 0 | W25: 0 | X25: 0 | Y25: 0 | Z25: 0
B26: MATERIAL PARA LA CONSTRUCCION | F26: 0 | G26: 2500 | H26: =F26*G26 -> 0 | I26: =G26*$C$45 -> 45175 | J26: =(F26*I26) -> 0 | K26: =J26*1.16 -> 0 | L26: =H26 -> 0 | M26: 0 | N26: =M26 -> 0 | O26: 0 | P26: 0 | Q26: 0 | R26: 0 | S26: 0 | T26: 0 | U26: 0 | V26: 0 | W26: 0 | X26: 0 | Y26: 0 | Z26: 0
B27: PARTES ACCES Y MAT P/LABORATORIO | F27: 0 | G27: 0 | H27: =F27*G27 -> 0 | I27: =G27*$C$45 -> 0 | J27: =(F27*I27) -> 0 | K27: =J27*1.16 -> 0 | L27: =H27 -> 0 | M27: 0 | N27: =M27 -> 0 | O27: 0 | P27: 0 | Q27: 0 | R27: 0 | S27: 0 | T27: 0 | U27: 0 | V27: 0 | W27: 0 | X27: 0 | Y27: 0 | Z27: 0
B28: PARTES ACCES Y REFAC P/ LUBRICANTES | F28: 0 | G28: 0 | H28: =F28*G28 -> 0 | I28: =G28*$C$45 -> 0 | J28: =(F28*I28) -> 0 | K28: =J28*1.16 -> 0 | L28: =H28 -> 0 | M28: 0 | N28: =M28 -> 0 | O28: 0 | P28: 0 | Q28: 0 | R28: 0 | S28: 0 | T28: 0 | U28: 0 | V28: 0 | W28: 0 | X28: 0 | Y28: 0 | Z28: 0
B29: PARTES ELECT, ACCES Y REFACC | F29: 0 | G29: 2500 | H29: =F29*G29 -> 0 | I29: =G29*$C$45 -> 45175 | J29: =(F29*I29) -> 0 | K29: =J29*1.16 -> 0 | L29: =H29 -> 0 | M29: 0 | N29: =M29 -> 0 | O29: 0 | P29: 0 | Q29: 0 | R29: 0 | S29: 0 | T29: 0 | U29: 0 | V29: 0 | W29: 0 | X29: 0 | Y29: 0 | Z29: 0
B30: PARTES Y REFAC TELECOM Y VIDEO (TELEMETRÍA) | F30: 0 | G30: 2000 | H30: =F30*G30 -> 0 | I30: =G30*$C$45 -> 36140 | J30: =(F30*I30) -> 0 | K30: =J30*1.16 -> 0 | L30: =H30 -> 0 | M30: 0 | N30: =M30 -> 0 | O30: 0 | P30: 0 | Q30: 0 | R30: 0 | S30: 0 | T30: 0 | U30: 0 | V30: 0 | W30: 0 | X30: 0 | Y30: 0 | Z30: 0
B31: PARTES Y REFACCION C/INCENDIO | F31: 0 | G31: 0 | H31: =F31*G31 -> 0 | I31: =G31*$C$45 -> 0 | J31: =(F31*I31) -> 0 | K31: =J31*1.16 -> 0 | L31: =H31 -> 0 | M31: 0 | N31: =M31 -> 0 | O31: 0 | P31: 0 | Q31: 0 | R31: 0 | S31: 0 | T31: 0 | U31: 0 | V31: 0 | W31: 0 | X31: 0 | Y31: 0 | Z31: 0
B32: PASTA PEGAMENTO OTRO COMPUESTO | F32: 0 | G32: 0 | H32: =F32*G32 -> 0 | I32: =G32*$C$45 -> 0 | J32: =(F32*I32) -> 0 | K32: =J32*1.16 -> 0 | L32: =H32 -> 0 | M32: 0 | N32: =M32 -> 0 | O32: 0 | P32: 0 | Q32: 0 | R32: 0 | S32: 0 | T32: 0 | U32: 0 | V32: 0 | W32: 0 | X32: 0 | Y32: 0 | Z32: 0
B33: PINTURA Y OTROS RECUBRIMIENTOS | C33: Pintura | F33: 0 | G33: 19421.79 | H33: =F33*G33 -> 0 | I33: =G33*$C$45 -> 350951.75 | J33: =(F33*I33) -> 0 | K33: =J33*1.16 -> 0 | L33: =H33 -> 0 | M33: =J33 -> 0 | N33: 0 | O33: 0 | P33: 0 | Q33: 0 | R33: 0 | S33: 0 | T33: 0 | U33: 0 | V33: 0 | W33: 0 | X33: 0 | Y33: 0 | Z33: 0
B34: REFAC P/INSTRUM DE MED Y CONTROL | F34: 0 | G34: 0 | H34: =F34*G34 -> 0 | I34: =G34*$C$45 -> 0 | J34: =(F34*I34) -> 0 | K34: =J34*1.16 -> 0 | L34: =H34 -> 0 | M34: 0 | N34: =M34 -> 0 | O34: 0 | P34: 0 | Q34: 0 | R34: 0 | S34: 0 | T34: 0 | U34: 0 | V34: 0 | W34: 0 | X34: 0 | Y34: 0 | Z34: 0
B35: REFACC Y ACCES PARA VALVULAS | F35: 0 | G35: 1000 | H35: =F35*G35 -> 0 | I35: =G35*$C$45 -> 18070 | J35: =(F35*I35) -> 0 | K35: =J35*1.16 -> 0 | L35: =H35 -> 0 | M35: 0 | N35: =M35 -> 0 | O35: 0 | P35: 0 | Q35: 0 | R35: 0 | S35: 0 | T35: 0 | U35: 0 | V35: 0 | W35: 0 | X35: 0 | Y35: 0 | Z35: 0
B36: REFACC Y ACCESORIO PARA HERRAMIENTA | F36: 0 | G36: 0 | H36: =F36*G36 -> 0 | I36: =G36*$C$45 -> 0 | J36: =(F36*I36) -> 0 | K36: =J36*1.16 -> 0 | L36: =H36 -> 0 | M36: 0 | N36: =M36 -> 0 | O36: 0 | P36: 0 | Q36: 0 | R36: 0 | S36: 0 | T36: 0 | U36: 0 | V36: 0 | W36: 0 | X36: 0 | Y36: 0 | Z36: 0
B37: REFACCIONES P/MAQUINARIA | F37: 0 | G37: 0 | H37: =F37*G37 -> 0 | I37: =G37*$C$45 -> 0 | J37: =(F37*I37) -> 0 | K37: =J37*1.16 -> 0 | L37: =H37 -> 0 | M37: 0 | N37: =M37 -> 0 | O37: 0 | P37: 0 | Q37: 0 | R37: 0 | S37: 0 | T37: 0 | U37: 0 | V37: 0 | W37: 0 | X37: 0 | Y37: 0 | Z37: 0
B38: RODAM ACCES Y SELLOS P/ ACEITE | F38: 0 | G38: 0 | H38: =F38*G38 -> 0 | I38: =G38*$C$45 -> 0 | J38: =(F38*I38) -> 0 | K38: =J38*1.16 -> 0 | L38: =H38 -> 0 | M38: 0 | N38: =M38 -> 0 | O38: 0 | P38: 0 | Q38: 0 | R38: 0 | S38: 0 | T38: 0 | U38: 0 | V38: 0 | W38: 0 | X38: 0 | Y38: 0 | Z38: 0
B39: SUSTANCIAS QUIMICAS | F39: 0 | G39: 0 | H39: =F39*G39 -> 0 | I39: =G39*$C$45 -> 0 | J39: =(F39*I39) -> 0 | K39: =J39*1.16 -> 0 | L39: =H39 -> 0 | M39: 0 | N39: =M39 -> 0 | O39: 0 | P39: 0 | Q39: 0 | R39: 0 | S39: 0 | T39: 0 | U39: 0 | V39: 0 | W39: 0 | X39: 0 | Y39: 0 | Z39: 0
B40: TORNILLERIA Y ARTICULO | F40: 0 | G40: 0 | H40: =F40*G40 -> 0 | I40: =G40*$C$45 -> 0 | J40: =(F40*I40) -> 0 | K40: =J40*1.16 -> 0 | L40: =H40 -> 0 | M40: 0 | N40: =M40 -> 0 | O40: 0 | P40: 0 | Q40: 0 | R40: 0 | S40: 0 | T40: 0 | U40: 0 | V40: 0 | W40: 0 | X40: 0 | Y40: 0 | Z40: 0
B41: TUBERIAS | C41: Corte de tuberia | F41: 0 | G41: 3320.43 | H41: =F41*G41 -> 0 | I41: =G41*$C$45 -> 60000.17 | J41: =(F41*I41) -> 0 | K41: =J41*1.16 -> 0 | L41: =H41 -> 0 | M41: 0 | N41: =J41 -> 0 | O41: 0 | P41: 0 | Q41: 0 | R41: 0 | S41: 0 | T41: 0 | U41: 0 | V41: 0 | W41: 0 | X41: 0 | Y41: 0 | Z41: 0
B42: VALVULAS | F42: 0 | G42: 100 | H42: =F42*G42 -> 0 | I42: =G42*$C$45 -> 1807 | J42: =(F42*I42) -> 0 | K42: =J42*1.16 -> 0 | L42: =H42 -> 0 | M42: 0 | N42: =M42 -> 0 | O42: 0 | P42: 0 | Q42: 0 | R42: 0 | S42: 0 | T42: 0 | U42: 0 | V42: 0 | W42: 0 | X42: 0 | Y42: 0 | Z42: 0
B44: ='F05 VIÁTICOS'!B28 -> Premisas | K44: Total Mensual [MN] | M44: =SUM(M8:M42) -> 10498.67 | N44: =SUM(N8:N42) -> 10498.67 | O44: =SUM(O8:O42) -> 0 | P44: =SUM(P8:P42) -> 0 | Q44: =SUM(Q8:Q42) -> 0 | R44: =SUM(R8:R42) -> 0 | S44: =SUM(S8:S42) -> 0 | T44: =SUM(T8:T42) -> 0 | ... Z44: =SUM(Z8:Z42) -> 0
B45: ='F05 VIÁTICOS'!B29 -> Paridad | C45: ='F05 VIÁTICOS'!C29 -> 18.07 | K45: Total Mensual [USD] | M45: =M44/$C$45 -> 581 | N45: =N44/$C$45 -> 581 | O45: =O44/$C$45 -> 0 | P45: =P44/$C$45 -> 0 | Q45: =Q44/$C$45 -> 0 | R45: =R44/$C$45 -> 0 | S45: =S44/$C$45 -> 0 | T45: =T44/$C$45 -> 0 | ... Z45: =Z44/$C$45 -> 0
B46: ='F05 VIÁTICOS'!B30 -> Mes | C46: ='F05 VIÁTICOS'!C30 -> 30.4 | K46: Total [MN] | M46: =SUM(M44:Z44) -> 20997.34
B47: ='F05 VIÁTICOS'!B31 -> Periodo Pago (días) | C47: ='F05 VIÁTICOS'!C31 -> 30 | K47: Total [USD] | M47: =M46/$C$45 -> 1162
B48: ='F05 VIÁTICOS'!B32 -> Gas lp | C48: ='F05 VIÁTICOS'!C32 -> 0
B49: ='F05 VIÁTICOS'!B33 -> Gasolina Magna | C49: ='F05 VIÁTICOS'!C33 -> 23.5
B50: ='F05 VIÁTICOS'!B34 -> Diesel | C50: ='F05 VIÁTICOS'!C34 -> 23

Sheet F07 OPERAC. (MAT,SERV & EQUIPO)
B2: MATERIALES, SERVICIOS Y EQUIPO DE OPERACIÓN
B5: RESUMEN | C5: DESCRIPCIÓN 1 | D5: UBICACIÓN | E5: CANTIDAD | F5: IMPORTE | G5: IMPORTE TOTAL | H5: IMPORTE | I5: IMPORTE TOTAL | J5: TOTAL C/IVA | L5: Instalación | M5: Instalación | N5: Mes 1 | O5: Mes 2 | P5: Mes 3 | Q5: Mes 4 | R5: Mes 5 | S5: Mes 6 | T5: Mes 7 | U5: Mes 8 | V5: Mes 9 | W5: Mes 10 | X5: Mes 11 | Y5: Mes 12
L6: - | M6: - | N6: ENE | O6: FEB | P6: MAR | Q6: ABR | R6: MAY | S6: JUN | T6: JUL | U6: AGO | V6: SEP | W6: OCT | X6: NOV | Y6: DIC
F7: [USD] | G7: [USD] | H7: [MN] | I7: [MN] | J7: [MN] | L7: - | M7: - | N7: 31 | O7: 29 | P7: 31 | Q7: 30 | R7: 30 | S7: 31 | T7: 31 | U7: 31 | V7: 30 | W7: 31 | X7: 30 | Y7: 31
B8: ENSERES MENORES DIVERSOS (Acondicionamiento de casas) | C8: Escoba y Trapeador | E8: 2 | F8: 20 | G8: =E8*F8 -> 40 | H8: =F8*$C$200 -> 361.4 | I8: =(E8*H8) -> 722.8 | J8: =I8*1.16 -> 838.448 | L8: =I8 -> 722.8 | M8: =I8 -> 722.8 | N8: 0 | O8: =N8 -> 0 | P8: =O8 -> 0
B9: ENSERES MENORES DIVERSOS (Acondicionamiento de casas) | C9: Bolsas de basura | E9: 2 | F9: 13.835086 | G9: =E9*F9 -> 27.670172 | H9: =F9*$C$200 -> 250 | I9: =(E9*H9) -> 500 | J9: =I9*1.16 -> 580 | L9: =I9 -> 500 | M9: =I9 -> 500 | N9: 0 | O9: =N9 -> 0 | P9: =O9 -> 0
B10: ENSERES MENORES DIVERSOS (Acondicionamiento de casas) | C10: Bote de basura | E10: 2 | F10: 55.340343 | G10: =E10*F10 -> 110.68069 | H10: =F10*$C$200 -> 1000 | I10: =(E10*H10) -> 2000 | J10: =I10*1.16 -> 2320 | L10: =I10 -> 2000 | M10: =I10 -> 2000 | N10: 0 | O10: 0 | P10: =O10 -> 0
B11: ENSERES MENORES DIVERSOS (Acondicionamiento de casas) | C11: Kit de limpieza de baño | E11: 2 | F11: 14 | G11: =E11*F11 -> 28 | H11: =F11*$C$200 -> 252.98 | I11: =(E11*H11) -> 505.96 | J11: =I11*1.16 -> 586.9136 | L11: =I11 -> 505.96 | M11: =I11 -> 505.96 | N11: 0 | O11: =N11 -> 0 | P11: =O11 -> 0
B12: ENSERES MENORES DIVERSOS (Acondicionamiento de casas) | C12: Cubeta | E12: 2 | F12: 2.7670172 | G12: =E12*F12 -> 5.5340343 | H12: =F12*$C$200 -> 50 | I12: =(E12*H12) -> 100 | J12: =I12*1.16 -> 116 | L12: =I12 -> 100 | M12: =I12 -> 100 | N12: 0 | O12: =N12 -> 0 | P12: =O12 -> 0
B13: ENSERES MENORES DIVERSOS (Acondicionamiento de casas) | C13: Cloro | E13: 2 | F13: 13.835086 | G13: =E13*F13 -> 27.670172 | H13: =F13*$C$200 -> 250 | I13: =(E13*H13) -> 500 | J13: =I13*1.16 -> 580 | L13: =I13 -> 500 | M13: =I13 -> 500 | N13: 0 | O13: =N13 -> 0 | P13: =O13 -> 0
B14: ENSERES MENORES DIVERSOS (Acondicionamiento de casas) | C14: Jabon | E14: 2 | F14: 5.5340343 | G14: =E14*F14 -> 11.068069 | H14: =F14*$C$200 -> 100 | I14: =(E14*H14) -> 200 | J14: =I14*1.16 -> 232 | L14: =I14 -> 200 | M14: =I14 -> 200 | N14: 0 | O14: =N14 -> 0 | P14: =O14 -> 0
B15: ENSERES MENORES DIVERSOS (Acondicionamiento de casas) | C15: Fabuloso o Pino | E15: 2 | F15: 13.835086 | G15: =E15*F15 -> 27.670172 | H15: =F15*$C$200 -> 250 | I15: =(E15*H15) -> 500 | J15: =I15*1.16 -> 580 | L15: =I15 -> 500 | M15: =I15 -> 500 | N15: 0 | O15: =N15 -> 0 | P15: =O15 -> 0
J17: Total Mensual [MN] | L17: =SUM(L8:L15) -> 5028.76 | M17: =SUM(M8:M15) -> 5028.76 | N17: =SUM(N8:N15) -> 0 | O17: =SUM(O8:O15) -> 0 | P17: =SUM(P8:P15) -> 0 | Q17: =SUM(Q8:Q15) -> 0 | R17: =SUM(R8:R15) -> 0 | S17: =SUM(S8:S15) -> 0 | ... Y17: =SUM(Y8:Y15) -> 0
J18: Total Mensual [USD] | L18: =L17/$C$200 -> 278.2933 | M18: =M17/$C$200 -> 278.2933 | N18: =N17/$C$200 -> 0 | O18: =O17/$C$200 -> 0 | P18: =P17/$C$200 -> 0 | Q18: =Q17/$C$200 -> 0 | R18: =R17/$C$200 -> 0 | S18: =S17/$C$200 -> 0 | ... Y18: =Y17/$C$200 -> 0
J19: Total [MN] | L19: =SUM(L17:Y17) -> 10057.52
J20: Total [USD] | L20: =L19/$C$200 -> 556.58661
F22: =EGRESOS!R26 -> 10057.52 | G22: MATERIALES (OPERACION) | J22: Total Mensual [MN] | L22: =L17 -> 5028.76 | M22: =M17 -> 5028.76 | N22: =N17 -> 0 | O22: =O17 -> 0 | P22: =P17 -> 0 | Q22: =Q17 -> 0 | R22: =R17 -> 0 | S22: =S17 -> 0 | ... Y22: =Y17 -> 0
J23: Total Mensual [USD] | L23: =L22/$C$200 -> 278.2933 | M23: =M22/$C$200 -> 278.2933 | N23: =N22/$C$200 -> 0 | O23: =O22/$C$200 -> 0 | P23: =P22/$C$200 -> 0 | Q23: =Q22/$C$200 -> 0 | R23: =R22/$C$200 -> 0 | S23: =S22/$C$200 -> 0 | ... Y23: =Y22/$C$200 -> 0
J24: Total [MN] | L24: =SUM(L22:Y22) -> 10057.52
J25: Total [USD] | L25: =L24/$C$200 -> 556.58661
B28: INSUMOS AGRICOLAS
B29: RESUMEN | C29: DESCRIPCIÓN 1 | D29: UNIDAD | E29: CANTIDAD | F29: IMPORTE | G29: IMPORTE TOTAL | H29: IMPORTE | I29: IMPORTE TOTAL | J29: TOTAL C/IVA | L29: Instalación | M29: Instalación | N29: Mes 1 | O29: Mes 2 | P29: Mes 3 | Q29: Mes 4 | R29: Mes 5 | S29: Mes 6 | T29: Mes 7 | U29: Mes 8 | V29: Mes 9 | W29: Mes 10 | X29: Mes 11 | Y29: Mes 12
L30: - | M30: - | N30: ENE | O30: FEB | P30: MAR | Q30: ABR | R30: MAY | S30: JUN | T30: JUL | U30: AGO | V30: SEP | W30: OCT | X30: NOV | Y30: DIC
F31: [USD] | G31: [USD] | H31: [MN] | I31: [MN] | J31: [MN] | L31: - | M31: - | N31: 31 | O31: 29 | P31: 31 | Q31: 30 | R31: 30 | S31: 31 | T31: 31 | U31: 31 | V31: 30 | W31: 31 | X31: 30 | Y31: 31
B32: INSUMOS AGRICOLAS | E32: 0 | F32: 11.068069 | G32: =E32*F32 -> 0 | H32: =F32*$C$200 -> 200 | I32: =(E32*H32) -> 0 | J32: =I32*1.16 -> 0 | L32: 0 | M32: =L32 -> 0 | N32: =M32 -> 0 | O32: =N32 -> 0 | P32: =O32 -> 0 | Q32: =P32 -> 0 | R32: =Q32 -> 0 | S32: =R32 -> 0 | T32: =S32 -> 0 | ... Y32: =X32 -> 0
B33: INSUMOS AGRICOLAS | E33: 0 | F33: 83.010515 | G33: =E33*F33 -> 0 | H33: =F33*$C$200 -> 1500 | I33: =(E33*H33) -> 0 | J33: =I33*1.16 -> 0 | L33: 0 | M33: =L33 -> 0 | N33: =M33 -> 0 | O33: =N33 -> 0 | P33: =O33 -> 0 | Q33: =P33 -> 0 | R33: =Q33 -> 0 | S33: =R33 -> 0 | T33: =S33 -> 0 | ... Y33: =X33 -> 0
B34: INSUMOS AGRICOLAS | E34: 0 | F34: 5.5340343 | G34: =E34*F34 -> 0 | H34: =F34*$C$200 -> 100 | I34: =(E34*H34) -> 0 | J34: =I34*1.16 -> 0 | L34: 0 | M34: =L34 -> 0 | N34: =M34 -> 0 | O34: =N34 -> 0 | P34: =O34 -> 0 | Q34: =P34 -> 0 | R34: =Q34 -> 0 | S34: =R34 -> 0 | T34: =S34 -> 0 | ... Y34: =X34 -> 0
B35: INSUMOS AGRICOLAS | E35: 0 | F35: 55.340343 | G35: =E35*F35 -> 0 | H35: =F35*$C$200 -> 1000 | I35: =(E35*H35) -> 0 | J35: =I35*1.16 -> 0 | L35: 0 | M35: =L35 -> 0 | N35: =M35 -> 0 | O35: =N35 -> 0 | P35: =O35 -> 0 | Q35: =P35 -> 0 | R35: =Q35 -> 0 | S35: =R35 -> 0 | T35: =S35 -> 0 | ... Y35: =X35 -> 0
B36: INSUMOS AGRICOLAS | E36: 0 | F36: 2.7670172 | G36: =E36*F36 -> 0 | H36: =F36*$C$200 -> 50 | I36: =(E36*H36) -> 0 | J36: =I36*1.16 -> 0 | L36: 0 | M36: =L36 -> 0 | N36: =M36 -> 0 | O36: =N36 -> 0 | P36: =O36 -> 0 | Q36: =P36 -> 0 | R36: =Q36 -> 0 | S36: =R36 -> 0 | T36: =S36 -> 0 | ... Y36: =X36 -> 0
B37: INSUMOS AGRICOLAS | E37: 0 | F37: 55.340343 | G37: =E37*F37 -> 0 | H37: =F37*$C$200 -> 1000 | I37: =(E37*H37) -> 0 | J37: =I37*1.16 -> 0 | L37: 0 | M37: =L37 -> 0 | N37: =M37 -> 0 | O37: =N37 -> 0 | P37: =O37 -> 0 | Q37: =P37 -> 0 | R37: =Q37 -> 0 | S37: =R37 -> 0 | T37: =S37 -> 0 | ... Y37: =X37 -> 0
J39: Total Mensual [MN] | L39: =SUM(L32:L37) -> 0 | M39: =SUM(M32:M37) -> 0 | N39: =SUM(N32:N37) -> 0 | O39: =SUM(O32:O37) -> 0 | P39: =SUM(P32:P37) -> 0 | Q39: =SUM(Q32:Q37) -> 0 | R39: =SUM(R32:R37) -> 0 | S39: =SUM(S32:S37) -> 0 | ... Y39: =SUM(Y32:Y37) -> 0
J40: Total Mensual [USD] | L40: =L39/$C$200 -> 0 | M40: =M39/$C$200 -> 0 | N40: =N39/$C$200 -> 0 | O40: =O39/$C$200 -> 0 | P40: =P39/$C$200 -> 0 | Q40: =Q39/$C$200 -> 0 | R40: =R39/$C$200 -> 0 | S40: =S39/$C$200 -> 0 | ... Y40: =Y39/$C$200 -> 0
J41: Total [MN] | L41: =SUM(L39:W39) -> 0
J42: Total [USD] | L42: =L41/$C$200 -> 0
F44: =SERVICIO!B31 -> 0 | G44: MATERIALES (OPERACION) | J44: Total Mensual [MN] | L44: =L39+L17 -> 5028.76 | M44: =M39+M17 -> 5028.76 | N44: =N39+N17 -> 0 | O44: =O39+O17 -> 0 | P44: =P39+P17 -> 0 | Q44: =Q39+Q17 -> 0 | R44: =R39+R17 -> 0 | S44: =S39+S17 -> 0 | ... Y44: =Y39+Y17 -> 0
J45: Total Mensual [USD] | L45: =L44/$C$200 -> 278.2933 | M45: =M44/$C$200 -> 278.2933 | N45: =N44/$C$200 -> 0 | O45: =O44/$C$200 -> 0 | P45: =P44/$C$200 -> 0 | Q45: =Q44/$C$200 -> 0 | R45: =R44/$C$200 -> 0 | S45: =S44/$C$200 -> 0 | ... Y45: =Y44/$C$200 -> 0
J46: Total [MN] | L46: =SUM(L44:Y44) -> 10057.52
J47: Total [USD] | L47: =L46/$C$200 -> 556.58661
B49: SERVICIOS
B50: RESUMEN | C50: DESCRIPCIÓN 1 | D50: UNIDAD | E50: CANTIDAD | F50: IMPORTE | G50: IMPORTE TOTAL | H50: IMPORTE | I50: IMPORTE TOTAL | J50: TOTAL C/IVA | L50: Instalación | M50: Instalación | N50: Mes 1 | O50: Mes 2 | P50: Mes 3 | Q50: Mes 4 | R50: Mes 5 | S50: Mes 6 | T50: Mes 7 | U50: Mes 8 | V50: Mes 9 | W50: Mes 10 | X50: Mes 11 | Y50: Mes 12
L51: - | M51: - | N51: ENE | O51: FEB | P51: MAR | Q51: ABR | R51: MAY | S51: JUN | T51: JUL | U51: AGO | V51: SEP | W51: OCT | X51: NOV | Y51: DIC
F52: [USD] | G52: [USD] | H52: [MN] | I52: [MN] | J52: [MN] | L52: - | M52: - | N52: 31 | O52: 29 | P52: 31 | Q52: 30 | R52: 30 | S52: 31 | T52: 31 | U52: 31 | V52: 30 | W52: 31 | X52: 30 | Y52: 31
B53: ACONDICION DE CASA HABITACION | E53: 0 | F53: 4000 | G53: =E53*F53 -> 0 | H53: =F53*$C$200 -> 72280 | I53: =(E53*H53) -> 0 | J53: =I53*1.16 -> 0 | L53: 0 | M53: =$I$53 -> 0 | N53: =$I$53 -> 0 | O53: =$I$53 -> 0 | P53: =$I$53 -> 0 | Q53: 0 | R53: 0 | S53: 0 | T53: 0 | U53: 0 | V53: 0 | W53: 0 | X53: 0 | Y53: 0
B54: ADICION Y MODIFIC DE MATERIAL | E54: 0 | F54: 0 | G54: =E54*F54 -> 0 | H54: =F54*$C$200 -> 0 | I54: =(E54*H54) -> 0 | J54: =I54*1.16 -> 0 | L54: 0 | M54: =L54 -> 0 | N54: =M54 -> 0 | O54: 0 | P54: =O54 -> 0 | Q54: 0 | R54: 0 | S54: 0 | T54: 0 | U54: 0 | V54: 0 | W54: 0 | X54: 0 | Y54: 0
B55: ADQUISICION TARJET COMBUSTIBLE | E55: 1 | F55: 50 | G55: =E55*F55 -> 50 | H55: =F55*$C$200 -> 903.5 | I55: =(E55*H55) -> 903.5 | J55: =I55*1.16 -> 1048.06 | L55: =I55 -> 903.5 | M55: 0 | N55: 0 | O55: 0 | P55: =O55 -> 0 | Q55: 0 | R55: 0 | S55: 0 | T55: 0 | U55: 0 | V55: 0 | W55: 0 | X55: 0 | Y55: 0
B56: ANALISIS CAUSA RAIZ | E56: 0 | F56: 1660.2103 | G56: =E56*F56 -> 0 | H56: =F56*$C$200 -> 30000 | I56: =(E56*H56) -> 0 | J56: =I56*1.16 -> 0 | M56: =L56 -> 0 | N56: 0 | O56: 0 | P56: 0 | Q56: 0 | R56: 0 | S56: 0 | T56: 0 | U56: 0 | V56: 0 | W56: 0 | X56: 0 | Y56: 0
B57: ANALISIS DE RIESGO | C57: ARP | E57: 0 | F57: 8879.02 | G57: =E57*F57 -> 0 | H57: =F57*$C$200 -> 160443.89 | I57: =(E57*H57) -> 0 | J57: =I57*1.16 -> 0 | L57: 0 | M57: =J57 -> 0 | N57: 0 | O57: 0 | P57: 0 | Q57: 0 | R57: 0 | S57: 0 | T57: 0 | U57: 0 | V57: 0 | W57: 0 | X57: 0 | Y57: 0
B58: ANALISIS DE VIBRACION | E58: 0 | F58: 1106.8069 | G58: =E58*F58 -> 0 | H58: =F58*$C$200 -> 20000 | I58: =(E58*H58) -> 0 | J58: =I58*1.16 -> 0 | L58: 0 | M58: =L58 -> 0 | N58: 0 | O58: =N58 -> 0 | P58: =O58 -> 0 | Q58: 0 | R58: 0 | S58: 0 | T58: 0 | U58: 0 | V58: 0 | W58: 0 | X58: 0 | Y58: 0
B59: BASES LICITACION Y CONCURSOS | E59: 0 | F59: 0 | G59: =E59*F59 -> 0 | H59: =F59*$C$200 -> 0 | I59: =(E59*H59) -> 0 | J59: =I59*1.16 -> 0 | L59: 0 | M59: =L59 -> 0 | N59: =M59 -> 0 | O59: =N59 -> 0 | P59: =O59 -> 0 | Q59: 0 | R59: 0 | S59: 0 | T59: 0 | U59: 0 | V59: 0 | W59: 0 | X59: 0 | Y59: 0
B60: CARGOS EXTRAORDINARIOS | E60: 0 | F60: 1200 | G60: =E60*F60 -> 0 | H60: =F60*$C$200 -> 21684 | I60: =(E60*H60) -> 0 | J60: =I60*1.16 -> 0 | L60: 0 | M60: =L60 -> 0 | N60: 0 | O60: 0 | P60: 0 | Q60: 0 | R60: 0 | S60: 0 | T60: 0 | U60: 0 | V60: 0 | W60: 0 | X60: 0 | Y60: 0
B61: CERTIFICACION | C61: Maquinas de soldar y soldadores | E61: 0 | F61: 12479.2 | G61: =E61*F61 -> 0 | H61: =F61*$C$200 -> 225499.14 | I61: =(E61*H61) -> 0 | J61: =I61*1.16 -> 0 | L61: =I61 -> 0 | M61: 0 | N61: 0 | O61: =N61 -> 0 | P61: =O61 -> 0 | Q61: 0 | R61: 0 | S61: 0 | T61: 0 | U61: 0 | V61: 0 | W61: 0 | X61: 0 | Y61: 0
B62: COLOCACION DE PILOTE | E62: 0 | F62: 6000 | G62: =E62*F62 -> 0 | H62: =F62*$C$200 -> 108420 | I62: =(E62*H62) -> 0 | J62: =I62*1.16 -> 0 | L62: 0 | M62: =L62 -> 0 | N62: 0 | O62: 0 | P62: =O62 -> 0 | Q62: 0 | R62: 0 | S62: 0 | T62: 0 | U62: 0 | V62: 0 | W62: 0 | X62: 0 | Y62: 0
B63: CORREOS Y MENSAJERIAS | E63: 0 | F63: 27.670172 | G63: =E63*F63 -> 0 | H63: =F63*$C$200 -> 500 | I63: =(E63*H63) -> 0 | J63: =I63*1.16 -> 0 | L63: 0 | M63: 0 | N63: 0 | O63: =N63 -> 0 | P63: =O63 -> 0 | Q63: 0 | R63: 0 | S63: 0 | T63: 0 | U63: 0 | V63: 0 | W63: 0 | X63: 0 | Y63: 0
B64: CUOTAS Y SUSCRIPCIONES | E64: 0 | F64: 0 | G64: =E64*F64 -> 0 | H64: =F64*$C$200 -> 0 | I64: =(E64*H64) -> 0 | J64: =I64*1.16 -> 0 | L64: 0 | M64: =L64 -> 0 | N64: =M64 -> 0 | O64: =N64 -> 0 | P64: =O64 -> 0 | Q64: 0 | R64: 0 | S64: 0 | T64: 0 | U64: 0 | V64: 0 | W64: 0 | X64: 0 | Y64: 0
B65: DEDUCIBLE POR SINIESTRO | E65: 0 | F65: 2224.29 | G65: =E65*F65 -> 0 | H65: =F65*$C$200 -> 40192.92 | I65: =(E65*H65) -> 0 | J65: =I65*1.16 -> 0 | L65: =I65 -> 0 | M65: 0 | N65: =M65 -> 0 | O65: =N65 -> 0 | P65: =O65 -> 0 | Q65: 0 | R65: 0 | S65: 0 | T65: 0 | U65: 0 | V65: 0 | W65: 0 | X65: 0 | Y65: 0
B66: DESARROLLO DE SOFTWARE | E66: 0 | F66: 0 | G66: =E66*F66 -> 0 | H66: =F66*$C$200 -> 0 | I66: =(E66*H66) -> 0 | J66: =I66*1.16 -> 0 | L66: 0 | M66: =L66 -> 0 | N66: =M66 -> 0 | O66: =N66 -> 0 | P66: =O66 -> 0 | Q66: 0 | R66: 0 | S66: 0 | T66: 0 | U66: 0 | V66: 0 | W66: 0 | X66: 0 | Y66: 0
B67: FIANZAS | E67: 0 | F67: 0 | G67: =E67*F67 -> 0 | H67: =F67*$C$200 -> 0 | I67: =(E67*H67) -> 0 | J67: =I67*1.16 -> 0 | L67: 0 | M67: =L67 -> 0 | N67: =M67 -> 0 | O67: =N67 -> 0 | P67: =O67 -> 0 | Q67: 0 | R67: 0 | S67: 0 | T67: 0 | U67: 0 | V67: 0 | W67: 0 | X67: 0 | Y67: 0
B68: FLETES EXTRANJEROS | C68: Frontera - Geolis - Sitio | E68: 1 | F68: 107279.78 | G68: =E68*F68 -> 107279.78 | H68: =F68*$C$200 -> 1938545.7 | I68: =(E68*H68) -> 1938545.7 | J68: =I68*1.16 -> 2248713 | L68: =I68 -> 1938545.7 | M68: 0 | N68: 0 | O68: 0 | P68: =O68 -> 0 | Q68: 0 | R68: 0 | S68: 0 | T68: 0 | U68: 0 | V68: 0 | W68: 0 | X68: 0 | Y68: 0
B69: FLETES NACIONALES | C69: Fletes nacionales | E69: 0 | F69: 4524.62 | G69: =E69*F69 -> 0 | H69: =F69*$C$200 -> 81759.883 | I69: =(E69*H69) -> 0 | J69: =I69*1.16 -> 0 | L69: =I69 -> 0 | M69: 0 | N69: 0 | O69: 0 | P69: =O69 -> 0 | Q69: 0 | R69: 0 | S69: 0 | T69: 0 | U69: 0 | V69: 0 | W69: 0 | X69: 0 | Y69: 0
B70: GASTOS DE IMPORTACION | C70: Importación Hoss | E70: 0 | F70: 8219.02 | G70: =E70*F70 -> 0 | H70: =F70*$C$200 -> 148517.69 | I70: =(E70*H70) -> 0 | J70: =I70*1.16 -> 0 | L70: =I70 -> 0 | M70: 0 | N70: =M70 -> 0 | O70: =N70 -> 0 | P70: =O70 -> 0 | Q70: 0 | R70: 0 | S70: 0 | T70: 0 | U70: 0 | V70: 0 | W70: 0 | X70: 0 | Y70: 0
B71: GTO EXPED DE SEG/TRAMITE | E71: 0 | F71: 83239.85 | G71: =E71*F71 -> 0 | H71: =F71*$C$200 -> 1504144.1 | I71: =(E71*H71) -> 0 | J71: =I71*1.16 -> 0 | L71: =I71 -> 0 | M71: 0 | N71: =M71 -> 0 | O71: =N71 -> 0 | P71: =O71 -> 0 | Q71: 0 | R71: 0 | S71: 0 | T71: 0 | U71: 0 | V71: 0 | W71: 0 | X71: 0 | Y71: 0
B72: HIELO Y AGUA | E72: 1 | F72: 178 | G72: =E72*F72 -> 178 | H72: =F72*$C$200 -> 3216.46 | I72: =(E72*H72) -> 3216.46 | J72: =I72*1.16 -> 3731.0936 | L72: =I72 -> 3216.46 | M72: =I72 -> 3216.46 | N72: 0 | O72: =N72 -> 0 | P72: =O72 -> 0 | Q72: 0 | R72: 0 | S72: 0 | T72: 0 | U72: 0 | V72: 0 | W72: 0 | X72: 0 | Y72: 0
B73: HONORARIOS A PERSONA FISICA | E73: 0 | F73: 0 | G73: =E73*F73 -> 0 | H73: =F73*$C$200 -> 0 | I73: =(E73*H73) -> 0 | J73: =I73*1.16 -> 0 | L73: 0 | M73: =L73 -> 0 | N73: =M73 -> 0 | O73: =N73 -> 0 | P73: =O73 -> 0 | Q73: 0 | R73: 0 | S73: 0 | T73: 0 | U73: 0 | V73: 0 | W73: 0 | X73: 0 | Y73: 0
B74: IMPUESTOS Y DERECHOS | C74: Impuestos GEN | E74: 0 | F74: 83239.85 | G74: =E74*F74 -> 0 | H74: =F74*$C$200 -> 1504144.1 | I74: =(E74*H74) -> 0 | J74: =I74*1.16 -> 0 | L74: =I74 -> 0 | M74: 0 | N74: =M74 -> 0 | O74: =N74 -> 0 | P74: =O74 -> 0 | Q74: 0 | R74: 0 | S74: 0 | T74: 0 | U74: 0 | V74: 0 | W74: 0 | X74: 0 | Y74: 0
B75: INTERNET Y DATOS | E75: 0 | F75: 58 | G75: =E75*F75 -> 0 | H75: =F75*$C$200 -> 1048.06 | I75: =(E75*H75) -> 0 | J75: =I75*1.16 -> 0 | L75: 0 | M75: =I75 -> 0 | N75: =I75 -> 0 | O75: =N75 -> 0 | P75: =O75 -> 0 | Q75: 0 | R75: 0 | S75: 0 | T75: 0 | U75: 0 | V75: 0 | W75: 0 | X75: 0 | Y75: 0
B76: MANIOBRAS | D76: Maniobras de posicionamiento | E76: 1 | F76: 65817.422 | G76: =E76*F76 -> 65817.422 | H76: =F76*$C$200 -> 1189320.8 | I76: =(E76*H76) -> 1189320.8 | J76: =I76*1.16 -> 1379612.2 | L76: 0 | M76: =I76 -> 1189320.8 | N76: 0 | O76: 0 | P76: =O76 -> 0 | Q76: 0 | R76: 0 | S76: 0 | T76: 0 | U76: 0 | V76: 0 | W76: 0 | X76: 0 | Y76: 0
B77: MANTENIMIENTO A VEHICULOS | E77: 0 | F77: 500 | G77: =E77*F77 -> 0 | H77: =F77*$C$200 -> 9035 | I77: =(E77*H77) -> 0 | J77: =I77*1.16 -> 0 | L77: 0 | M77: =L77 -> 0 | N77: =J77 -> 0 | O77: =N77 -> 0 | P77: =O77 -> 0 | Q77: 0 | R77: 0 | S77: 0 | T77: 0 | U77: 0 | V77: 0 | W77: 0 | X77: 0 | Y77: 0
B78: MANTTO A EQUIPOS DE SEGURIDAD | E78: 0 | F78: 2213.6137 | G78: =E78*F78 -> 0 | H78: =F78*$C$200 -> 40000 | I78: =(E78*H78) -> 0 | J78: =I78*1.16 -> 0 | L78: 0 | M78: =L78 -> 0 | N78: 0 | O78: 0 | P78: =N78 -> 0 | Q78: 0 | R78: 0 | S78: 0 | T78: 0 | U78: 0 | V78: 0 | W78: 0 | X78: 0 | Y78: 0
B79: MANTTO DE MOBILIARIO Y EQUIPO | E79: 0 | F79: 0 | G79: =E79*F79 -> 0 | H79: =F79*$C$200 -> 0 | I79: =(E79*H79) -> 0 | J79: =I79*1.16 -> 0 | L79: 0 | M79: =L79 -> 0 | N79: =$M$79 -> 0 | O79: =N79 -> 0 | P79: =O79 -> 0 | Q79: 0 | R79: 0 | S79: 0 | T79: 0 | U79: 0 | V79: 0 | W79: 0 | X79: 0 | Y79: 0
B80: MANTTO PREV A EQUIPOS DE MEDICION | E80: 0 | F80: 0 | G80: =E80*F80 -> 0 | H80: =F80*$C$200 -> 0 | I80: =(E80*H80) -> 0 | J80: =I80*1.16 -> 0 | L80: 0 | M80: =L80 -> 0 | N80: =M80 -> 0 | O80: =N80 -> 0 | P80: =O80 -> 0 | Q80: 0 | R80: 0 | S80: 0 | T80: 0 | U80: 0 | V80: 0 | W80: 0 | X80: 0 | Y80: 0
B81: MANTTO Y ACONDICION DE CAMPER | E81: 0 | F81: 500 | G81: =E81*F81 -> 0 | H81: =F81*$C$200 -> 9035 | I81: =(E81*H81) -> 0 | J81: =I81*1.16 -> 0 | L81: 0 | M81: 0 | N81: =I81 -> 0 | O81: =N81 -> 0 | P81: =O81 -> 0 | Q81: 0 | R81: 0 | S81: 0 | T81: 0 | U81: 0 | V81: 0 | W81: 0 | X81: 0 | Y81: 0
B82: MECANICA DE SUELOS | E82: 0 | F82: 0 | G82: =E82*F82 -> 0 | H82: =F82*$C$200 -> 0 | I82: =(E82*H82) -> 0 | J82: =I82*1.16 -> 0 | L82: 0 | M82: =L82 -> 0 | N82: =M82 -> 0 | O82: =N82 -> 0 | P82: =O82 -> 0 | Q82: 0 | R82: 0 | S82: 0 | T82: 0 | U82: 0 | V82: 0 | W82: 0 | X82: 0 | Y82: 0
B83: OTROS DERECHOS | E83: 0 | F83: 0 | G83: =E83*F83 -> 0 | H83: =F83*$C$200 -> 0 | I83: =(E83*H83) -> 0 | J83: =I83*1.16 -> 0 | L83: 0 | M83: =L83 -> 0 | N83: =M83 -> 0 | O83: =N83 -> 0 | P83: =O83 -> 0 | Q83: 0 | R83: 0 | S83: 0 | T83: 0 | U83: 0 | V83: 0 | W83: 0 | X83: 0 | Y83: 0
B84: PACMA PEMEX EXPLORACION | E84: 0 | F84: 0 | G84: =E84*F84 -> 0 | H84: =F84*$C$200 -> 0 | I84: =(E84*H84) -> 0 | J84: =I84*1.16 -> 0 | L84: 0 | M84: =L84 -> 0 | N84: =M84 -> 0 | O84: =N84 -> 0 | P84: =O84 -> 0 | Q84: 0 | R84: 0 | S84: 0 | T84: 0 | U84: 0 | V84: 0 | W84: 0 | X84: 0 | Y84: 0
B85: PAGO DE RECARGOS | E85: 0 | F85: 3600 | G85: =E85*F85 -> 0 | H85: =F85*$C$200 -> 65052 | I85: =(E85*H85) -> 0 | J85: =I85*1.16 -> 0 | L85: 0 | M85: =L85 -> 0 | N85: =$I$85 -> 0 | O85: =N85 -> 0 | P85: =O85 -> 0 | Q85: 0 | R85: 0 | S85: 0 | T85: 0 | U85: 0 | V85: 0 | W85: 0 | X85: 0 | Y85: 0
B86: RECARGA DE GASES INDUSTRIALES | C86: Oxicorte | E86: 1 | F86: 943.84 | G86: =E86*F86 -> 943.84 | H86: =F86*$C$200 -> 17055.189 | I86: =(E86*H86) -> 17055.189 | J86: =I86*1.16 -> 19784.019 | L86: =I86 -> 17055.189 | M86: =I86 -> 17055.189 | N86: 0 | O86: 0 | P86: 0 | Q86: 0 | R86: 0 | S86: 0 | T86: 0 | U86: 0 | V86: 0 | W86: 0 | X86: 0 | Y86: 0
B87: RENTA DE MAQUINARIA Y EQUIPO | E87: 0 | F87: 85800 | G87: =E87*F87 -> 0 | H87: =F87*$C$200 -> 1550406 | I87: =(E87*H87) -> 0 | J87: =I87*1.16 -> 0 | L87: 0 | M87: =I87 -> 0 | N87: =I87 -> 0 | O87: =N87 -> 0 | P87: =I87 -> 0 | Q87: 0 | R87: 0 | S87: 0 | T87: 0 | U87: 0 | V87: 0 | W87: 0 | X87: 0 | Y87: 0
B88: RENTA DE SANITARIOS | C88: Sanitarios + Fosa + Recolección | E88: 0 | F88: 1493.35 | G88: =E88*F88 -> 0 | H88: =F88*$C$200 -> 26984.834 | I88: =(E88*H88) -> 0 | J88: =I88*1.16 -> 0 | L88: 0 | M88: =I88 -> 0 | N88: =I88 -> 0 | O88: =N88 -> 0 | P88: =O88 -> 0 | Q88: 0 | R88: 0 | S88: 0 | T88: 0 | U88: 0 | V88: 0 | W88: 0 | X88: 0 | Y88: 0
B89: REPARACIONES | E89: 0 | F89: 0 | G89: =E89*F89 -> 0 | H89: =F89*$C$200 -> 0 | I89: =(E89*H89) -> 0 | J89: =I89*1.16 -> 0 | L89: 0 | M89: =L89 -> 0 | N89: =M89 -> 0 | O89: =N89 -> 0 | P89: =O89 -> 0 | Q89: 0 | R89: 0 | S89: 0 | T89: 0 | U89: 0 | V89: 0 | W89: 0 | X89: 0 | Y89: 0
B90: SEGUROS | E90: 0 | F90: 0 | G90: =E90*F90 -> 0 | H90: =F90*$C$200 -> 0 | I90: =(E90*H90) -> 0 | J90: =I90*1.16 -> 0 | L90: 0 | M90: =L90 -> 0 | N90: =M90 -> 0 | O90: =N90 -> 0 | P90: =O90 -> 0 | Q90: 0 | R90: 0 | S90: 0 | T90: 0 | U90: 0 | V90: 0 | W90: 0 | X90: 0 | Y90: 0
B91: SERV DE DISEÑO Y ROTULACION | C91: Rotulación | E91: 0 | F91: 276.70172 | G91: =E91*F91 -> 0 | H91: =F91*$C$200 -> 5000 | I91: =(E91*H91) -> 0 | J91: =I91*1.16 -> 0 | L91: 0 | M91: =L91 -> 0 | N91: 0 | O91: =I91 -> 0 | P91: 0 | Q91: 0 | R91: 0 | S91: 0 | T91: 0 | U91: 0 | V91: 0 | W91: 0 | X91: 0 | Y91: 0
B92: SERV DE DISPOS DE RESIDUOS | C92: Recolección de trapos | E92: 0 | F92: 1000 | G92: =E92*F92 -> 0 | H92: =F92*$C$200 -> 18070 | I92: =(E92*H92) -> 0 | J92: =I92*1.16 -> 0 | L92: 0 | M92: =L92 -> 0 | N92: =I92 -> 0 | O92: 0 | P92: =O92 -> 0 | Q92: 0 | R92: 0 | S92: 0 | T92: 0 | U92: 0 | V92: 0 | W92: 0 | X92: 0 | Y92: 0
B93: SERV DE MANTO A INSTALACIONES (INSTALACIÓN | E93: 0 | F93: 0 | G93: =E93*F93 -> 0 | H93: =F93*$C$200 -> 0 | I93: =(E93*H93) -> 0 | J93: =I93*1.16 -> 0 | L93: 0 | M93: =L93 -> 0 | N93: =M93 -> 0 | O93: =N93 -> 0 | P93: =O93 -> 0 | Q93: 0 | R93: 0 | S93: 0 | T93: 0 | U93: 0 | V93: 0 | W93: 0 | X93: 0 | Y93: 0
B94: SERV DE RECARGA DE EXTINTORES | E94: 0 | F94: 0 | G94: =E94*F94 -> 0 | H94: =F94*$C$200 -> 0 | I94: =(E94*H94) -> 0 | J94: =I94*1.16 -> 0 | L94: 0 | M94: =L94 -> 0 | N94: =M94 -> 0 | O94: =N94 -> 0 | P94: =O94 -> 0 | Q94: 0 | R94: 0 | S94: 0 | T94: 0 | U94: 0 | V94: 0 | W94: 0 | X94: 0 | Y94: 0
B95: SERV DE TRANSMISION DE DATOS | C95: Telemetría por tercero | E95: 0 | F95: 600 | G95: =E95*F95 -> 0 | H95: =F95*$C$200 -> 10842 | I95: =(E95*H95) -> 0 | J95: =I95*1.16 -> 0 | L95: 0 | M95: =L95 -> 0 | N95: =I95 -> 0 | O95: =N95 -> 0 | P95: =O95 -> 0 | Q95: 0 | R95: 0 | S95: 0 | T95: 0 | U95: 0 | V95: 0 | W95: 0 | X95: 0 | Y95: 0
B96: SERV PROFES DE PERSONA MORAL | E96: 0 | F96: 2767.0172 | G96: =E96*F96 -> 0 | H96: =F96*$C$200 -> 50000 | I96: =(E96*H96) -> 0 | J96: =I96*1.16 -> 0 | L96: 0 | M96: =L96 -> 0 | N96: =M96 -> 0 | O96: =N96 -> 0 | P96: =O96 -> 0 | Q96: 0 | R96: 0 | S96: 0 | T96: 0 | U96: 0 | V96: 0 | W96: 0 | X96: 0 | Y96: 0
B97: SERV Y MANTTO A EQ INFORMATICO | E97: 0 | F97: 0 | G97: =E97*F97 -> 0 | H97: =F97*$C$200 -> 0 | I97: =(E97*H97) -> 0 | J97: =I97*1.16 -> 0 | L97: 0 | M97: =L97 -> 0 | N97: =M97 -> 0 | O97: =N97 -> 0 | P97: =O97 -> 0 | Q97: 0 | R97: 0 | S97: 0 | T97: 0 | U97: 0 | V97: 0 | W97: 0 | X97: 0 | Y97: 0
B98: SERVICIO DE AUTOLAVADO | C98: Unidad vehicular | E98: 0 | F98: 5.5340343 | G98: =E98*F98 -> 0 | H98: =F98*$C$200 -> 100 | I98: =(E98*H98) -> 0 | J98: =I98*1.16 -> 0 | L98: =I98 -> 0 | M98: =I98 -> 0 | N98: 0 | O98: =N98 -> 0 | P98: =O98 -> 0 | Q98: 0 | R98: 0 | S98: 0 | T98: 0 | U98: 0 | V98: 0 | W98: 0 | X98: 0 | Y98: 0
B99: SERVICIO DE EQPO Y MAQUINARIA | E99: 0 | F99: 800 | G99: =E99*F99 -> 0 | H99: =F99*$C$200 -> 14456 | I99: =(E99*H99) -> 0 | J99: =I99*1.16 -> 0 | L99: 0 | M99: =L99 -> 0 | N99: =I99 -> 0 | O99: =N99 -> 0 | P99: =O99 -> 0 | Q99: 0 | R99: 0 | S99: 0 | T99: 0 | U99: 0 | V99: 0 | W99: 0 | X99: 0 | Y99: 0
B100: SERVICIO REPRESENTACION LEGAL | E100: 0 | F100: 0 | G100: =E100*F100 -> 0 | H100: =F100*$C$200 -> 0 | I100: =(E100*H100) -> 0 | J100: =I100*1.16 -> 0 | L100: 0 | M100: =L100 -> 0 | N100: =M100 -> 0 | O100: =N100 -> 0 | P100: =O100 -> 0 | Q100: 0 | R100: 0 | S100: 0 | T100: 0 | U100: 0 | V100: 0 | W100: 0 | X100: 0 | Y100: 0
B101: SERVICIOS DE BANQUETERIA | E101: 0 | F101: 0 | G101: =E101*F101 -> 0 | H101: =F101*$C$200 -> 0 | I101: =(E101*H101) -> 0 | J101: =I101*1.16 -> 0 | L101: 0 | M101: =L101 -> 0 | N101: =M101 -> 0 | O101: =N101 -> 0 | P101: =O101 -> 0 | Q101: 0 | R101: 0 | S101: 0 | T101: 0 | U101: 0 | V101: 0 | W101: 0 | X101: 0 | Y101: 0
B102: SERVICIOS DE COPIADO | E102: 0 | F102: 0 | G102: =E102*F102 -> 0 | H102: =F102*$C$200 -> 0 | I102: =(E102*H102) -> 0 | J102: =I102*1.16 -> 0 | L102: 0 | M102: =L102 -> 0 | N102: =M102 -> 0 | O102: =N102 -> 0 | P102: =O102 -> 0 | Q102: 0 | R102: 0 | S102: 0 | T102: 0 | U102: 0 | V102: 0 | W102: 0 | X102: 0 | Y102: 0
B103: SERVICIOS DE TAXI | E103: 0 | F103: 0 | G103: =E103*F103 -> 0 | H103: =F103*$C$200 -> 0 | I103: =(E103*H103) -> 0 | J103: =I103*1.16 -> 0 | L103: 0 | M103: =L103 -> 0 | N103: =M103 -> 0 | O103: =N103 -> 0 | P103: =O103 -> 0 | Q103: 0 | R103: 0 | S103: 0 | T103: 0 | U103: 0 | V103: 0 | W103: 0 | X103: 0 | Y103: 0
B104: SERVICIOS PREOPERATIVOS | E104: 0 | F104: 0 | G104: =E104*F104 -> 0 | H104: =F104*$C$200 -> 0 | I104: =(E104*H104) -> 0 | J104: =I104*1.16 -> 0 | L104: 0 | M104: =L104 -> 0 | N104: =M104 -> 0 | O104: =N104 -> 0 | P104: =O104 -> 0 | Q104: 0 | R104: 0 | S104: 0 | T104: 0 | U104: 0 | V104: 0 | W104: 0 | X104: 0 | Y104: 0
B105: SERVICIOS RADIOGRAFICOS | E105: 1 | F105: 4000 | G105: =E105*F105 -> 4000 | H105: =F105*$C$200 -> 72280 | I105: =(E105*H105) -> 72280 | J105: =I105*1.16 -> 83844.8 | L105: 0 | M105: =I105 -> 72280 | N105: 0 | O105: 0 | P105: 0 | Q105: 0 | R105: 0 | S105: 0 | T105: 0 | U105: 0 | V105: 0 | W105: 0 | X105: 0 | Y105: 0
B106: TENENCIA | E106: 0 | F106: 0 | G106: =E106*F106 -> 0 | H106: =F106*$C$200 -> 0 | I106: =(E106*H106) -> 0 | J106: =I106*1.16 -> 0 | L106: 0 | M106: =L106 -> 0 | N106: =M106 -> 0 | O106: =N106 -> 0 | P106: =O106 -> 0 | Q106: 0 | R106: 0 | S106: 0 | T106: 0 | U106: 0 | V106: 0 | W106: 0 | X106: 0 | Y106: 0
B107: TOPOGRAFIA | E107: 0 | F107: 0 | G107: =E107*F107 -> 0 | H107: =F107*$C$200 -> 0 | I107: =(E107*H107) -> 0 | J107: =I107*1.16 -> 0 | L107: 0 | M107: =L107 -> 0 | N107: =M107 -> 0 | O107: =N107 -> 0 | P107: =O107 -> 0 | Q107: 0 | R107: 0 | S107: 0 | T107: 0 | U107: 0 | V107: 0 | W107: 0 | X107: 0 | Y107: 0
B108: VERIFICACIONES | E108: 0 | F108: 0 | G108: =E108*F108 -> 0 | H108: =F108*$C$200 -> 0 | I108: =(E108*H108) -> 0 | J108: =I108*1.16 -> 0 | L108: 0 | M108: =L108 -> 0 | N108: =M108 -> 0 | O108: =N108 -> 0 | P108: =O108 -> 0 | Q108: 0 | R108: 0 | S108: 0 | T108: 0 | U108: 0 | V108: 0 | W108: 0 | X108: 0 | Y108: 0
B109: ASESORIA ESPECIAL INTERNA | C109: Acesoria JE | E109: 0 | F109: 2300 | G109: =E109*F109 -> 0 | H109: =F109*$C$200 -> 41561 | I109: =(E109*H109) -> 0 | J109: =I109*1.16 -> 0 | L109: 0 | N109: =I109*0.5 -> 0 | O109: =N109 -> 0 | P109: =O109 -> 0 | Q109: 0 | R109: 0 | S109: 0 | T109: 0 | U109: 0 | V109: 0 | W109: 0 | X109: 0 | Y109: 0
B110: ASESORIA ESPECIAL OPERATIVA | C110: Sindicato | E110: 0 | F110: 2500 | G110: =E110*F110 -> 0 | H110: =F110*$C$200 -> 45175 | I110: =(E110*H110) -> 0 | J110: =I110*1.16 -> 0 | L110: 0 | M110: =L110 -> 0 | N110: =I110 -> 0 | O110: 0 | P110: =O110 -> 0 | Q110: 0 | R110: 0 | S110: 0 | T110: 0 | U110: 0 | V110: 0 | W110: 0 | X110: 0 | Y110: 0
...
