Workbook

Sheet RESUMEN GENERAL
A2: GEOLIS · Área de Tecnología de la Información
A3: PRESUPUESTO DE EGRESOS — PRIMER SEMESTRE 2026 | Enero – Junio
A5: Período: | B5: Enero – Junio 2026
A6: Elaboró: | B6: Coordinación de Innovación y técnologia
A8: TC de referencia USD/MXN: | C8: 19.5
A9: EGRESOS POR RUBRO — DISTRIBUCIÓN MENSUAL | Importes en Pesos Mexicanos (MXN)
A10: RUBRO | B10: TIPO | C10: TOTAL SEMESTRAL | D10: ENE | E10: FEB | F10: MAR | G10: ABR | H10: MAY | I10: JUN | J10: % DEL TOTAL
A11: EQUIPO DE CÓMPUTO | B11: CAPEX | C11: =D11+E11+F11+G11+H11+I11 -> 3374235 | D11: 2053968 | E11: 0 | F11: 403344 | G11: 538788 | H11: 378135 | I11: 0 | J11: =C11/C21 -> 0.67759916
A12: ACCESORIOS Y PERIFÉRICOS | B12: CAPEX | C12: =D12+E12+F12+G12+H12+I12 -> 339384 | D12: 0 | E12: 0 | F12: 113828 | G12: 170120 | H12: 36000 | I12: 19436 | J12: =C12/C21 -> 0.068153615
A13: INFRAESTRUCTURA DE RED | B13: CAPEX | C13: =D13+E13+F13+G13+H13+I13 -> 108793 | D13: 0 | E13: 0 | F13: 0 | G13: 0 | H13: 0 | I13: 108793 | J13: =C13/C21 -> 0.021847336
A14: LICENCIAMIENTO MXN | B14: OPEX | C14: =D14+E14+F14+G14+H14+I14 -> 200724.99 | D14: 58120 | E14: 142205.99 | F14: 0 | G14: 0 | H14: 0 | I14: 399 | J14: =C14/C21 -> 0.040308717
A15: LICENCIAMIENTO USD (MXN) | B15: OPEX | C15: =D15+E15+F15+G15+H15+I15 -> 358489.56 | D15: 43699.5 | E15: 19656 | F15: 0 | G15: 0 | H15: 295134.06 | I15: 0 | J15: =C15/C21 -> 0.07199031
A16: INTERNET | B16: OPEX | C16: =D16+E16+F16+G16+H16+I16 -> 50380.02 | D16: 8396.67 | E16: 8396.67 | F16: 8396.67 | G16: 8396.67 | H16: 8396.67 | I16: 8396.67 | J16: =C16/C21 -> 0.010117096
A17: STARLINK | B17: OPEX | C17: =D17+E17+F17+G17+H17+I17 -> 406350 | D17: 67725 | E17: 67725 | F17: 67725 | G17: 67725 | H17: 67725 | I17: 67725 | J17: =C17/C21 -> 0.081601435
A18: IMPRESORAS EN RENTA | B18: OPEX | C18: =D18+E18+F18+G18+H18+I18 -> 141335.29 | D18: =SUMIF('F07 IMPRESORAS'!$C$5:$C$22,"Enero",'F07 IMPRESORAS'!$H$5:$H$22) -> 12101.61 | E18: =SUMIF('F07 IMPRESORAS'!$C$5:$C$22,"Febrero",'F07 IMPRESORAS'!$H$5:$H$22) -> 38867.17 | F18: =SUMIF('F07 IMPRESORAS'!$C$5:$C$22,"Marzo",'F07 IMPRESORAS'!$H$5:$H$22) -> 49896.52 | G18: =SUMIF('F07 IMPRESORAS'!$C$5:$C$22,"Abril",'F07 IMPRESORAS'!$H$5:$H$22) -> 40469.99 | H18: =SUMIF('F07 IMPRESORAS'!$C$5:$C$22,"Mayo",'F07 IMPRESORAS'!$H$5:$H$22) -> 0 | I18: =SUMIF('F07 IMPRESORAS'!$C$5:$C$22,"Junio",'F07 IMPRESORAS'!$H$5:$H$22) -> 0 | J18: =C18/C21 -> 0.028382336
A19: TOTAL CAPEX | C19: =C11+C12+C13 -> 3822412 | D19: =D11+D12+D13 -> 2053968 | E19: =E11+E12+E13 -> 0 | F19: =F11+F12+F13 -> 517172 | G19: =G11+G12+G13 -> 708908 | H19: =H11+H12+H13 -> 414135 | I19: =I11+I12+I13 -> 128229 | J19: =C19/C21 -> 0.76760011
A20: TOTAL OPEX | C20: =C14+C15+C16+C17+C18 -> 1157279.9 | D20: =D14+D15+D16+D17+D18 -> 190042.78 | E20: =E14+E15+E16+E17+E18 -> 276850.83 | F20: =F14+F15+F16+F17+F18 -> 126018.19 | G20: =G14+G15+G16+G17+G18 -> 116591.66 | H20: =H14+H15+H16+H17+H18 -> 371255.73 | I20: =I14+I15+I16+I17+I18 -> 76520.67 | J20: =C20/C21 -> 0.23239989
A21: TOTAL GENERAL — PESOS MEXICANOS | C21: =C19+C20 -> 4979691.9 | D21: =D19+D20 -> 2244010.8 | E21: =E19+E20 -> 276850.83 | F21: =F19+F20 -> 643190.19 | G21: =G19+G20 -> 825499.66 | H21: =H19+H20 -> 785390.73 | I21: =I19+I20 -> 204749.67 | J21: 100%

Sheet F01 EQUIPO COMPUTO
B1: F01 EQUIPO COMPUTO — Laptops y Equipos de Cómputo — Geolis y Cuervito
B4: Mes | C4: Modelo / Concepto | D4: CAPEX / OPEX | E4: Cantidad | F4: Costo Unitario (MXN) | G4: Monto Presupuestado (MXN)
B5: Enero | C5: Laptop Dell Pro — Geolis | D5: CAPEX | E5: 52 | F5: 25209 | G5: =E5*F5 -> 1310868
B6: Enero | C6: Laptop Dell Pro Plus — Geolis | D6: CAPEX | E6: 16 | F6: 33861 | G6: =E6*F6 -> 541776
B7: Enero | C7: Laptop Dell Pro Max — Geolis | D7: CAPEX | E7: 4 | F7: 50331 | G7: =E7*F7 -> 201324
B8: Marzo | C8: Laptop Dell Pro — Cuervito | D8: CAPEX | E8: 16 | F8: 25209 | G8: =E8*F8 -> 403344
B9: Abril | C9: Laptop Dell Pro — Geolis | D9: CAPEX | E9: 16 | F9: 25209 | G9: =E9*F9 -> 403344
B10: Abril | C10: Laptop Dell Pro Plus — Geolis | D10: CAPEX | E10: 4 | F10: 33861 | G10: =E10*F10 -> 135444
B11: Mayo | C11: Laptop Dell Pro — Geolis | D11: CAPEX | E11: 8 | F11: 25209 | G11: =E11*F11 -> 201672
B12: Mayo | C12: Laptop Dell Pro — Cuervito | D12: CAPEX | E12: 7 | F12: 25209 | G12: =E12*F12 -> 176463
B13: TOTAL DEL RUBRO | E13: =SUM(E5:E12) -> 123 | F13: =SUM(F5:F12) -> 244098 | G13: =SUM(G5:G12) -> 3374235

Sheet F02 ACCESORIOS
C1: F02 ACCESORIOS — Monitores, Teclados, Docking Stations y Periféricos
C4: Mes | D4: Modelo / Concepto | E4: CAPEX / OPEX | F4: Cantidad | G4: Costo Unitario (MXN) | H4: Monto Presupuestado (MXN)
C5: Marzo | D5: Kit Teclado/Mouse Dell KM3322W | E5: CAPEX | F5: 56 | G5: 408 | H5: =F5*G5 -> 22848
C6: Marzo | D6: Monitor Dell SE2425HM | E6: CAPEX | F6: 20 | G6: 2000 | H6: =F6*G6 -> 40000
C7: Marzo | D7: Monitor Dell SE2725HM | E7: CAPEX | F7: 20 | G7: 2549 | H7: =F7*G7 -> 50980
C8: Abril | D8: Kit Teclado/Mouse Dell KM3322W | E8: CAPEX | F8: 20 | G8: 408 | H8: =F8*G8 -> 8160
C9: Abril | D9: Monitor Dell P2725H | E9: CAPEX | F9: 20 | G9: 4859 | H9: =F9*G9 -> 97180
C10: Abril | D10: Docking Station WD25 | E10: CAPEX | F10: 20 | G10: 3239 | H10: =F10*G10 -> 64780
C11: Mayo | D11: Monitor Dell S3225QS | E11: CAPEX | F11: 4 | G11: 9000 | H11: =F11*G11 -> 36000
C12: Junio | D12: Monitor Dell P2725H (adicional) | E12: CAPEX | F12: 3 | G12: 4589 | H12: =F12*G12 -> 13767
C13: Junio | D13: Kit Teclado/Mouse KM3322W (adic.) | E13: CAPEX | F13: 2 | G13: 430 | H13: =F13*G13 -> 860
C14: Junio | D14: Docking Station DA305 | E14: CAPEX | F14: 1 | G14: 1009 | H14: =F14*G14 -> 1009
C15: Junio | D15: Plaud — Grabador IA | E15: CAPEX | F15: 1 | G15: 3800 | H15: =F15*G15 -> 3800
C16: TOTAL DEL RUBRO | F16: =SUM(F5:F15) -> 167 | G16: =SUM(G5:G15) -> 32291 | H16: =SUM(H5:H15) -> 339384

Sheet F03 LICENCIAS MXN
C1: F03 LICENCIAS MXN — Licenciamiento de Software — Pesos Mexicanos
C3: Mes | D3: Software / Servicio | E3: Modalidad | F3: CAPEX/OPEX | G3: Licencias | H3: Costo Unitario (MXN) | I3: Monto Presupuestado (MXN)
C4: Enero | D4: MS Office 365 — Negocios | E4: Mensual | F4: OPEX | G4: 25 | H4: 183 | I4: =G4*H4 -> 4575
C5: Enero | D5: MS Office 365 — Exchange geolis | E5: Mensual | F5: OPEX | G5: 2 | H5: 89 | I5: =G5*H5 -> 178
C7: Febrero | D7: MS Office 365 — Exchange geolisener | E7: Mensual | F7: OPEX | G7: 13 | H7: 89 | I7: =G7*H7 -> 1157
C8: Enero | D8: MS Office 365 — Teams | E8: Mensual | F8: OPEX | G8: 25 | H8: 75 | I8: =G8*H8 -> 1875
C9: Febrero | D9: MS Office 365 — Project | E9: Mensual | F9: OPEX | G9: 1 | H9: 678 | I9: =G9*H9 -> 678
C10: Febrero | D10: MS Office 365 — OneDrive | E10: Mensual | F10: OPEX | G10: 1 | H10: 113 | I10: =G10*H10 -> 113
C11: Enero | D11: Adobe — Acrobat Standard | E11: Mensual | F11: OPEX | G11: 16 | H11: 299 | I11: =G11*H11 -> 4784
C12: Junio | D12: Adobe — Acrobat Pro | E12: Mensual | F12: OPEX | G12: 1 | H12: 399 | I12: =G12*H12 -> 399
C13: Enero | D13: Adobe — Creative Cloud | E13: Mensual | F13: OPEX | G13: 3 | H13: 1500 | I13: =G13*H13 -> 4500
C14: Enero | D14: Correos .mx — POP | E14: Mensual | F14: OPEX | G14: 324 | H14: 120 | I14: =G14*H14 -> 38880
C15: Enero | D15: Antivirus — Cortex | E15: Mensual | F15: OPEX | G15: 26 | H15: 128 | I15: =G15*H15 -> 3328
C16: Febrero | D16: LinkedIn — SalesNavigator Core | E16: Mensual | F16: OPEX | G16: 1 | H16: 2194.99 | I16: =G16*H16 -> 2194.99
... C19: Febrero | D19: Autodesk — AutoCAD LT | E19: Anual | F19: OPEX | G19: 1 | H19: 6335 | I19: =G19*H19 -> 6335
C20: LICENCIAMIENTO USD — Convertido a Pesos Mexicanos (TC = 19.50)
C21: Enero | D21: ChatGPT — Business | E21: Mensual | F21: OPEX | G21: 15 | H21: 585 | I21: =G21*H21 -> 8775
C22: Mayo | D22: Claude — Pro Team | E22: Mensual | F22: OPEX | G22: 4 | H22: 487.5 | I22: =G22*H22 -> 1950
C23: Enero | D23: Office TimeLine — Plus | E23: Anual | F23: OPEX | G23: 3 | H23: 11641.5 | I23: =G23*H23 -> 34924.5
C24: Febrero | D24: ClickUp — Business | E24: Anual | F24: OPEX | G24: 7 | H24: 2808 | I24: =G24*H24 -> 19656
C25: Mayo | D25: Solidworks | E25: Anual | F25: OPEX | G25: 1 | H25: 293184.06 | I25: =G25*H25 -> 293184.06
C26: SUBTOTAL LICENCIAMIENTO MXN | H26: =SUM(H4:H19) -> 38678.99 | I26: =SUM(I4:I19) -> 200724.99
C27: TOTAL DEL RUBRO (MXN + USD convertido) | I27: =I26+SUM(I21:I25) -> 559214.55

Sheet F05 INFRAESTRUCTURA RED
C1: F05 INFRAESTRUCTURA RED — Equipos de Red e Infraestructura — Starlinks y Switches
C4: Mes | D4: Concepto | E4: CAPEX/OPEX | F4: Cantidad | G4: Costo Unitario (MXN) | H4: Monto Presupuestado (MXN)
C5: Junio | D5: Starlink Residencial | E5: CAPEX | F5: 1 | G5: 10500 | H5: =F5*G5 -> 10500
C6: Junio | D6: Starlink Mini | E6: CAPEX | F6: 1 | G6: 7000 | H6: =F6*G6 -> 7000
C7: Junio | D7: Starlink Residencial | E7: CAPEX | F7: 1 | G7: 8074 | H7: =F7*G7 -> 8074
C8: Junio | D8: Starlink Marítimo | E8: CAPEX | F8: 2 | G8: 32189 | H8: =F8*G8 -> 64378
C9: Junio | D9: Starlink Mini | E9: CAPEX | F9: 1 | G9: 4999 | H9: =F9*G9 -> 4999
C10: Junio | D10: UPS Industronic IND RP 1101 | E10: CAPEX | F10: 1 | G10: 5223 | H10: =F10*G10 -> 5223
C11: Junio | D11: Switch Cisco Business 220 | E11: CAPEX | F11: 1 | G11: 8619 | H11: =F11*G11 -> 8619
C12: TOTAL DEL RUBRO | F12: =SUM(F5:F11) -> 8 | G12: =SUM(G5:G11) -> 76604 | H12: =SUM(H5:H11) -> 108793

Sheet F06 TELECOMUNICACIONES
B1: F06 TELECOMUNICACIONES — Internet, Starlink OPEX y Servicio Satelital
B4: Zona / Sitio | C4: ISP / Proveedor | D4: Plan | E4: CAPEX/OPEX | F4: Mensual (MXN) | G4: Semestral (MXN)
B5: Villahermosa — Los Mangos | C5: Totalplay | D5: Infinitum | E5: OPEX | F5: 2418 | G5: =F5*6 -> 14508
B6: Villahermosa — Los Mangos | C6: Telmex | D6: Infinitum | E6: OPEX | F6: 640.5 | G6: =F6*6 -> 3843
B7: Villahermosa — Paraíso | C7: Telmex | D7: Infinitum | E7: OPEX | F7: 932.17 | G7: =F7*6 -> 5593.02
B8: Veracruz — Plaza Sol | C8: Telmex | D8: Infinitum | E8: OPEX | F8: 465.5 | G8: =F8*6 -> 2793
B9: Veracruz — Plaza Sol | C9: Telmex | D9: Infinitum | E9: OPEX | F9: 1108.33 | G9: =F9*6 -> 6649.98
B10: Veracruz — Plaza Sol | C10: Megacable | D10: Megacable | E10: OPEX | F10: 1900 | G10: =F10*6 -> 11400
B11: Ciudad del Carmen | C11: Telmex | D11: Infinitum | E11: OPEX | F11: 932.17 | G11: =F11*6 -> 5593.02
B12: TOTAL DEL RUBRO | F12: =SUM(F5:F11) -> 8396.67 | G12: =SUM(G5:G11) -> 50380.02
B14: STARLINK — OPEX MENSUAL (43 UNIDADES ACTIVAS)
B15: 43 unidades activas (cuentas 1-4) | C15: Starlink Business | D15: Mensual / campo operativo | E15: OPEX | F15: 67725 | G15: =F15*6 -> 406350
B16: 2 unidades pendientes (KUA, ZCH) | C16: Starlink Business | D16: Pendiente activación | E16: OPEX | F16: 0 | G16: 0

Sheet F07 IMPRESORAS
C1: F07 IMPRESORAS — Renta de Equipos de Impresión Multifuncional (COPYVER)
C4: Mes | D4: Equipo / Ubicación | E4: Centro de Costos | F4: No. Factura | G4: CAPEX/OPEX | H4: Importe Facturado (MXN)
C5: Enero | D5: TK3552 GEOLIS VERACRUZ | E5: C15ADMIN | F5: B27999 | G5: OPEX | H5: 3709.02
C6: Enero | D6: TA 2554ci PEMEX BECH LITORAL PARAÍSO | E6: F218357 | F6: B27999 | G6: OPEX | H6: 8392.59
C7: Febrero | D7: TK3552 GEOLIS VERACRUZ | E7: C18ADMIN | F7: B28556 | G7: OPEX | H7: 6677.09
C8: Febrero | D8: IR ADV-C5560i PARAÍSO TABASCO | E8: F218357 | F8: B28556 | G8: OPEX | H8: 20214.18
C9: Febrero | D9: TA 308ci VILLAHERMOSA MANGOS | E9: C18ADMIN | F9: B28556 | G9: OPEX | H9: 1240.16
C10: Febrero | D10: TA 2554ci PEMEX BECH LITORAL PARAÍSO | E10: F218357 | F10: B28556 | G10: OPEX | H10: 6920.07
C11: Febrero | D11: TA 2554ci REYNOSA | E11: F218383 | F11: B28556 | G11: OPEX | H11: 3815.67
C12: Marzo | D12: TK3552 GEOLIS VERACRUZ | E12: C18ADMIN | F12: B28653 | G12: OPEX | H12: 3905.11
C13: Marzo | D13: IR ADV-C5560i PARAÍSO TABASCO | E13: F218357 | F13: B28653 | G13: OPEX | H13: 14813.86
C14: Marzo | D14: TA 308ci VILLAHERMOSA MANGOS | E14: C18ADMIN | F14: B28653 | G14: OPEX | H14: 17935.54
C15: Marzo | D15: TA 2554ci PEMEX BECH LITORAL PARAÍSO | E15: F218357 | F15: B28653 | G15: OPEX | H15: 7628.55
C16: Marzo | D16: TA 2554ci COWORKING | E16: F218383 | F16: B28653 | G16: OPEX | H16: 5613.46
... C22: Junio | D22: Renta equipos multifuncionales (4 sedes) — factura pendiente de recepción | E22: N/D | F22: Pendiente | G22: OPEX | H22: 0
C24: TOTAL DEL RUBRO | H24: =SUM(H5:H22) -> 141335.29
