Workbook

Sheet USD
A1: GEOLIS SA DE CV
A2: Proyecto: colocar unidad de negocio
A3: INGRESOS 2025
A4: Descripcion | B4: Total Presupuestado | C4: Enero Pre | D4: Febrero Pre | E4: Marzo Pre | F4: Abril Pre | G4: Mayo Pre | H4: Junio Pre | I4: Julio Pre | J4: Agosto Pre | K4: Septiembre Pre | L4: Octubre Pre | M4: Noviembre Pre | N4: Diciembre Pre
A5: FACTURACION | B5: =SUM(C5:N5) -> 46339701 | C5: 4113505.5 | D5: 3839271.8 | E5: 4113505.5 | F5: 3980811.8 | G5: 4113505.5 | H5: 3980811.8 | I5: 4113505.5 | J5: 4113505.5 | K5: 3980811.8 | L5: 4113505.5 | M5: 3163455.9 | N5: 2713505.5
A7: EGRESOS 2025
A8: Descripcion | B8: Total Presupuestado | C8: Enero Pre | D8: Febrero Pre | E8: Marzo Pre | F8: Abril Pre | G8: Mayo Pre | H8: Junio Pre | I8: Julio Pre | J8: Agosto Pre | K8: Septiembre Pre | L8: Octubre Pre | M8: Noviembre Pre | N8: Diciembre Pre
A9: EQUIPO DE TRANSPORTE | B9: =SUM(C9:N9) -> 94000 | C9: =+'[1]F00 INV'!Q33+'[1]F00 INV'!Q16 -> 22800 | D9: =+'[1]F00 INV'!R33+'[1]F00 INV'!R16 -> 22800 | E9: =+'[1]F00 INV'!S33+'[1]F00 INV'!S16 -> 48400 | F9: =+'[1]F00 INV'!T46+'[1]F00 INV'!T47 -> 0 | G9: =+'[1]F00 INV'!U46+'[1]F00 INV'!U47 -> 0 | H9: =+'[1]F00 INV'!V46+'[1]F00 INV'!V47 -> 0 | I9: =+'[1]F00 INV'!W46+'[1]F00 INV'!W47 -> 0 | J9: =+'[1]F00 INV'!X46+'[1]F00 INV'!X47 -> 0 | K9: =+'[1]F00 INV'!Y46+'[1]F00 INV'!Y47 -> 0 | L9: =+'[1]F00 INV'!Z46+'[1]F00 INV'!Z47 -> 0 | M9: =+'[1]F00 INV'!AA46+'[1]F00 INV'!AA47 -> 0 | N9: =+'[1]F00 INV'!AB46+'[1]F00 INV'!AB47 -> 0
A10: EQUIPO DE MOBILIARIO | B10: =SUM(C10:N10) -> 416000 | C10: ='[1]F00 INV'!Q10+'[1]F00 INV'!Q11+'[1]F00 INV'!Q55+'[1]F00 INV'!Q35 -> 129000 | D10: ='[1]F00 INV'!R10+'[1]F00 INV'!R11+'[1]F00 INV'!R55+'[1]F00 INV'!R35 -> 139000 | E10: ='[1]F00 INV'!S10+'[1]F00 INV'!S11+'[1]F00 INV'!S55+'[1]F00 INV'!S35 -> 142000 | F10: ='[1]F00 INV'!T10+'[1]F00 INV'!T11+'[1]F00 INV'!T55+'[1]F00 INV'!T35 -> 3000 | G10: ='[1]F00 INV'!U10+'[1]F00 INV'!U11+'[1]F00 INV'!U55+'[1]F00 INV'!U35 -> 3000 | H10: ='[1]F00 INV'!V10+'[1]F00 INV'!V11+'[1]F00 INV'!V55+'[1]F00 INV'!V35 -> 0 | I10: ='[1]F00 INV'!W10+'[1]F00 INV'!W11+'[1]F00 INV'!W55+'[1]F00 INV'!W35 -> 0 | J10: ='[1]F00 INV'!X10+'[1]F00 INV'!X11+'[1]F00 INV'!X55+'[1]F00 INV'!X35 -> 0 | ... N10: ='[1]F00 INV'!AB10+'[1]F00 INV'!AB11+'[1]F00 INV'!AB55+'[1]F00 INV'!AB35 -> 0
A11: MAQUINARIA Y EQUIPO | B11: =SUM(C11:N11) -> 2094000 | C11: =+'[1]F00 INV'!Q54+'[1]F00 INV'!Q50+'[1]F00 INV'!Q49+'[1]F00 INV'!Q39+'[1]F00 INV'!Q30+'[1]F00 INV'!Q31+'[1]F00 INV'!Q32+'[1]F00 INV'!Q33+'[1]F00 INV'!Q29+'[1]F00 INV'!Q27+'[1]F00 INV'!Q25+'[1]F00 INV'!Q19+'[1]F00 INV'!Q18+'[1]F00 INV'!Q17+'[1]F00 INV'!Q16+'[1]F00 INV'!Q9 -> 580300 | D11: =+'[1]F00 INV'!R54+'[1]F00 INV'!R50+'[1]F00 INV'!R49+'[1]F00 INV'!R39+'[1]F00 INV'!R30+'[1]F00 INV'!R31+'[1]F00 INV'!R32+'[1]F00 INV'!R33+'[1]F00 INV'!R29+'[1]F00 INV'!R27+'[1]F00 INV'!R25+'[1]F00 INV'!R19+'[1]F00 INV'!R18+'[1]F00 INV'!R17+'[1]F00 INV'!R16+'[1]F00 INV'!R9 -> 637800 | E11: =+'[1]F00 INV'!S54+'[1]F00 INV'!S50+'[1]F00 INV'!S49+'[1]F00 INV'!S39+'[1]F00 INV'!S30+'[1]F00 INV'!S31+'[1]F00 INV'!S32+'[1]F00 INV'!S33+'[1]F00 INV'!S29+'[1]F00 INV'!S27+'[1]F00 INV'!S25+'[1]F00 INV'!S19+'[1]F00 INV'!S18+'[1]F00 INV'!S17+'[1]F00 INV'!S16+'[1]F00 INV'!S9 -> 530900 | F11: =+'[1]F00 INV'!T54+'[1]F00 INV'!T50+'[1]F00 INV'!T49+'[1]F00 INV'!T39+'[1]F00 INV'!T30+'[1]F00 INV'!T31+'[1]F00 INV'!T32+'[1]F00 INV'!T33+'[1]F00 INV'!T29+'[1]F00 INV'!T27+'[1]F00 INV'!T25+'[1]F00 INV'!T19+'[1]F00 INV'!T18+'[1]F00 INV'!T17+'[1]F00 INV'!T16+'[1]F00 INV'!T9 -> 315000 | G11: =+'[1]F00 INV'!U54+'[1]F00 INV'!U50+'[1]F00 INV'!U49+'[1]F00 INV'!U39+'[1]F00 INV'!U30+'[1]F00 INV'!U31+'[1]F00 INV'!U32+'[1]F00 INV'!U33+'[1]F00 INV'!U29+'[1]F00 INV'!U27+'[1]F00 INV'!U25+'[1]F00 INV'!U19+'[1]F00 INV'!U18+'[1]F00 INV'!U17+'[1]F00 INV'!U16+'[1]F00 INV'!U9 -> 15000 | H11: =+'[1]F00 INV'!V54+'[1]F00 INV'!V50+'[1]F00 INV'!V49+'[1]F00 INV'!V39+'[1]F00 INV'!V30+'[1]F00 INV'!V31+'[1]F00 INV'!V32+'[1]F00 INV'!V33+'[1]F00 INV'!V29+'[1]F00 INV'!V27+'[1]F00 INV'!V25+'[1]F00 INV'!V19+'[1]F00 INV'!V18+'[1]F00 INV'!V17+'[1]F00 INV'!V16+'[1]F00 INV'!V9 -> 15000 | I11: =+'[1]F00 INV'!W54+'[1]F00 INV'!W50+'[1]F00 INV'!W49+'[1]F00 INV'!W39+'[1]F00 INV'!W30+'[1]F00 INV'!W31+'[1]F00 INV'!W32+'[1]F00 INV'!W33+'[1]F00 INV'!W29+'[1]F00 INV'!W27+'[1]F00 INV'!W25+'[1]F00 INV'!W19+'[1]F00 INV'!W18+'[1]F00 INV'!W17+'[1]F00 INV'!W16+'[1]F00 INV'!W9 -> 0 | J11: =+'[1]F00 INV'!X54+'[1]F00 INV'!X50+'[1]F00 INV'!X49+'[1]F00 INV'!X39+'[1]F00 INV'!X30+'[1]F00 INV'!X31+'[1]F00 INV'!X32+'[1]F00 INV'!X33+'[1]F00 INV'!X29+'[1]F00 INV'!X27+'[1]F00 INV'!X25+'[1]F00 INV'!X19+'[1]F00 INV'!X18+'[1]F00 INV'!X17+'[1]F00 INV'!X16+'[1]F00 INV'!X9 -> 0 | ... N11: =+'[1]F00 INV'!AB54+'[1]F00 INV'!AB50+'[1]F00 INV'!AB49+'[1]F00 INV'!AB39+'[1]F00 INV'!AB30+'[1]F00 INV'!AB31+'[1]F00 INV'!AB32+'[1]F00 INV'!AB33+'[1]F00 INV'!AB29+'[1]F00 INV'!AB27+'[1]F00 INV'!AB25+'[1]F00 INV'!AB19+'[1]F00 INV'!AB18+'[1]F00 INV'!AB17+'[1]F00 INV'!AB16+'[1]F00 INV'!AB9 -> 0
A12: OTROS ACTIVOS | B12: =SUM(C12:N12) -> 2755000 | C12: =+'[1]F00 INV'!Q36+'[1]F00 INV'!Q40+'[1]F00 INV'!Q53 -> 450000 | D12: =+'[1]F00 INV'!R36+'[1]F00 INV'!R40+'[1]F00 INV'!R53 -> 455000 | E12: =+'[1]F00 INV'!S36+'[1]F00 INV'!S40+'[1]F00 INV'!S53 -> 500000 | F12: =+'[1]F00 INV'!T36+'[1]F00 INV'!T40+'[1]F00 INV'!T53 -> 450000 | G12: =+'[1]F00 INV'!U36+'[1]F00 INV'!U40+'[1]F00 INV'!U53 -> 450000 | H12: =+'[1]F00 INV'!V36+'[1]F00 INV'!V40+'[1]F00 INV'!V53 -> 450000 | I12: =+'[1]F00 INV'!W36+'[1]F00 INV'!W40+'[1]F00 INV'!W53 -> 0 | J12: =+'[1]F00 INV'!X36+'[1]F00 INV'!X40+'[1]F00 INV'!X53 -> 0 | ... N12: =+'[1]F00 INV'!AB36+'[1]F00 INV'!AB40+'[1]F00 INV'!AB53 -> 0
A13: SOFTWARE Y LICICENCIAS | B13: =SUM(C13:N13) -> 0
A14: ACTIVOS | B14: =SUM(B9:B13) -> 5359000 | C14: =SUM(C9:C13) -> 1182100 | D14: =SUM(D9:D13) -> 1254600 | E14: =SUM(E9:E13) -> 1221300 | F14: =SUM(F9:F13) -> 768000 | G14: =SUM(G9:G13) -> 468000 | H14: =SUM(H9:H13) -> 465000 | I14: =SUM(I9:I13) -> 0 | ... N14: =SUM(N9:N13) -> 0 | P14: Mobiliario de oficina
A15: ARRENDAMIENTO DE INMUEBLES | B15: =SUM(C15:N15) -> 80000 | C15: =('[1]F02 INM Y SERV'!F9+'[1]F02 INM Y SERV'!F10+'[1]F02 INM Y SERV'!F11)/[1]FLUJO!$E$43 -> 6666.6667 | D15: =+C15 -> 6666.6667 | E15: =+D15 -> 6666.6667 | F15: =+E15 -> 6666.6667 | G15: =+F15 -> 6666.6667 | H15: =+G15 -> 6666.6667 | I15: =+H15 -> 6666.6667 | J15: =+I15 -> 6666.6667 | K15: =+J15 -> 6666.6667 | ... N15: =+M15 -> 6666.6667
A16: ENERGIA ELECTRICA | B16: =SUM(C16:N16) -> 22295.082 | C16: =('[1]F02 INM Y SERV'!H9+'[1]F02 INM Y SERV'!H10+'[1]F02 INM Y SERV'!H11)/[1]FLUJO!$E$43 -> 1857.9235 | D16: =+C16 -> 1857.9235 | E16: =+D16 -> 1857.9235 | F16: =+E16 -> 1857.9235 | G16: =+F16 -> 1857.9235 | H16: =+G16 -> 1857.9235 | I16: =+H16 -> 1857.9235 | J16: =+I16 -> 1857.9235 | K16: =+J16 -> 1857.9235 | ... N16: =+M16 -> 1857.9235
A17: RENTA DE CASAS NO DEDUCIBLE | B17: =SUM(C17:N17) -> 0
A18: SERVICIOS DE LIMPIEZA | B18: =SUM(C18:N18) -> 17062.295 | C18: =('[1]F02 INM Y SERV'!P9+'[1]F02 INM Y SERV'!P10+'[1]F02 INM Y SERV'!P11)/[1]FLUJO!$E$43 -> 1421.8579 | D18: =+C18 -> 1421.8579 | E18: =+D18 -> 1421.8579 | F18: =+E18 -> 1421.8579 | G18: =+F18 -> 1421.8579 | H18: =+G18 -> 1421.8579 | I18: =+H18 -> 1421.8579 | J18: =+I18 -> 1421.8579 | K18: =+J18 -> 1421.8579 | ... N18: =+M18 -> 1421.8579
A19: SERVICIOS DE VIGILANCIA | B19: =SUM(C19:N19) -> 19672.131 | C19: =('[1]F02 INM Y SERV'!O9+'[1]F02 INM Y SERV'!O10+'[1]F02 INM Y SERV'!O11)/[1]FLUJO!$E$43 -> 1639.3443 | D19: =+C19 -> 1639.3443 | E19: =+D19 -> 1639.3443 | F19: =+E19 -> 1639.3443 | G19: =+F19 -> 1639.3443 | H19: =+G19 -> 1639.3443 | I19: =+H19 -> 1639.3443 | J19: =+I19 -> 1639.3443 | K19: =+J19 -> 1639.3443 | ... N19: =+M19 -> 1639.3443
A20: SERVICIOS DE FUMIGACION | B20: =SUM(C20:N20) -> 0
A21: TELEFONIA FIJA | B21: =SUM(C21:N21) -> 0
A22: AGUA Y ALCANTARILLADO | B22: =SUM(C22:N22) -> 0
A23: ARRENDAMIENTO DE OF. MOVILES | B23: =SUM(C23:N23) -> 0
A24: ARRENDA DE INMUEBLES Y SERV | B24: =SUM(B15:B23) -> 139029.51 | C24: =SUM(C15:C23) -> 11585.792 | D24: =SUM(D15:D23) -> 11585.792 | E24: =SUM(E15:E23) -> 11585.792 | F24: =SUM(F15:F23) -> 11585.792 | G24: =SUM(G15:G23) -> 11585.792 | H24: =SUM(H15:H23) -> 11585.792 | I24: =SUM(I15:I23) -> 11585.792 | ... N24: =SUM(N15:N23) -> 11585.792 | P24: renta casa staff villahermosa, servicio de limpieza
A25: ROPA Y ARTICULOS DE PROTECCION | B25: =SUM(C25:N25) -> 342013.26 | C25: =+'[1]F01 NÓM'!$O$137 -> 24423.099 | D25: =+C25 -> 24423.099 | E25: =+'[1]F01 NÓM'!$O$138 -> 29316.707 | F25: =+E25 -> 29316.707 | G25: =+F25 -> 29316.707 | H25: =+G25 -> 29316.707 | I25: =+H25 -> 29316.707 | J25: =+I25 -> 29316.707 | K25: =+J25 -> 29316.707 | L25: =+K25 -> 29316.707 | M25: =+L25 -> 29316.707 | N25: =+M25 -> 29316.707
A26: ARTICULOS DE SEGURIDAD | B26: =B25 -> 342013.26 | C26: =C25 -> 24423.099 | D26: =D25 -> 24423.099 | E26: =E25 -> 29316.707 | F26: =F25 -> 29316.707 | G26: =G25 -> 29316.707 | H26: =H25 -> 29316.707 | I26: =I25 -> 29316.707 | ... N26: =N25 -> 29316.707 | P26: overoles, botas, lentes, porta credencial
A27: EQUIPO DE COMPUTO (Adquisición) | B27: =SUM(C27:N27) -> 9180.6557 | C27: =+'[1]F03 COM Y EQ COM'!J51 -> 9180.6557 | D27: =+'[1]F03 COM Y EQ COM'!K51 -> 0 | E27: =+'[1]F03 COM Y EQ COM'!L51 -> 0 | F27: =+'[1]F03 COM Y EQ COM'!M51 -> 0 | G27: =+'[1]F03 COM Y EQ COM'!N51 -> 0 | H27: =+'[1]F03 COM Y EQ COM'!O51 -> 0 | I27: =+'[1]F03 COM Y EQ COM'!P51 -> 0 | J27: =+'[1]F03 COM Y EQ COM'!Q51 -> 0 | ... N27: =+'[1]F03 COM Y EQ COM'!U51 -> 0
A28: ARRENDAMIENTO DE EQ. COMPUTO | B28: =SUM(C28:N28) -> 0
A29: EQUIPO DE COMPUTO | B29: =SUM(B27:B28) -> 9180.6557 | C29: =SUM(C27:C28) -> 9180.6557 | D29: =SUM(D27:D28) -> 0 | E29: =SUM(E27:E28) -> 0 | F29: =SUM(F27:F28) -> 0 | G29: =SUM(G27:G28) -> 0 | H29: =SUM(H27:H28) -> 0 | I29: =SUM(I27:I28) -> 0 | ... N29: =SUM(N27:N28) -> 0
A30: ENSERES MENORES DIVERSOS (Acondicionamiento de casas) | B30: =SUM(C30:N30) -> 0
A31: EQUIPOS Y ENSERES | B31: =B30 -> 0 | C31: =C30 -> 0 | D31: =D30 -> 0 | E31: =E30 -> 0 | F31: =F30 -> 0 | G31: =G30 -> 0 | H31: =H30 -> 0 | I31: =I30 -> 0 | ... N31: =N30 -> 0
A32: INSUMOS AGRICOLAS | B32: =SUM(C32:N32) -> 0
A33: PAPELERIA Y UTILES DE OFICINA | B33: =SUM(C33:N33) -> 24000 | C33: =+'[1]F07 OPERAC'!M8+'[1]F07 OPERAC'!M9 -> 2000 | D33: =+'[1]F07 OPERAC'!N8+'[1]F07 OPERAC'!N9 -> 2000 | E33: =+'[1]F07 OPERAC'!O8+'[1]F07 OPERAC'!O9 -> 2000 | F33: =+'[1]F07 OPERAC'!P8+'[1]F07 OPERAC'!P9 -> 2000 | G33: =+'[1]F07 OPERAC'!Q8+'[1]F07 OPERAC'!Q9 -> 2000 | H33: =+'[1]F07 OPERAC'!R8+'[1]F07 OPERAC'!R9 -> 2000 | I33: =+'[1]F07 OPERAC'!S8+'[1]F07 OPERAC'!S9 -> 2000 | J33: =+'[1]F07 OPERAC'!T8+'[1]F07 OPERAC'!T9 -> 2000 | ... N33: =+'[1]F07 OPERAC'!X8+'[1]F07 OPERAC'!X9 -> 2000
A34: ARTICULOS DE ASEO Y SANITARIOS | B34: =SUM(C34:N34) -> 90000 | C34: =+'[1]F07 OPERAC'!M58+'[1]F07 OPERAC'!M59+'[1]F07 OPERAC'!M60 -> 7500 | D34: =+'[1]F07 OPERAC'!N58+'[1]F07 OPERAC'!N59+'[1]F07 OPERAC'!N60 -> 7500 | E34: =+'[1]F07 OPERAC'!O58+'[1]F07 OPERAC'!O59+'[1]F07 OPERAC'!O60 -> 7500 | F34: =+'[1]F07 OPERAC'!P58+'[1]F07 OPERAC'!P59+'[1]F07 OPERAC'!P60 -> 7500 | G34: =+'[1]F07 OPERAC'!Q58+'[1]F07 OPERAC'!Q59+'[1]F07 OPERAC'!Q60 -> 7500 | H34: =+'[1]F07 OPERAC'!R58+'[1]F07 OPERAC'!R59+'[1]F07 OPERAC'!R60 -> 7500 | I34: =+'[1]F07 OPERAC'!S58+'[1]F07 OPERAC'!S59+'[1]F07 OPERAC'!S60 -> 7500 | J34: =+'[1]F07 OPERAC'!T58+'[1]F07 OPERAC'!T59+'[1]F07 OPERAC'!T60 -> 7500 | ... N34: =+'[1]F07 OPERAC'!X58+'[1]F07 OPERAC'!X59+'[1]F07 OPERAC'!X60 -> 7500
A35: ARTICULOS DE CAFETERIA | B35: =SUM(C35:N35) -> 54000 | C35: =+'[1]F07 OPERAC'!M10 -> 9000 | D35: =+'[1]F07 OPERAC'!N10 -> 0 | E35: =+'[1]F07 OPERAC'!O10 -> 9000 | F35: =+'[1]F07 OPERAC'!P10 -> 0 | G35: =+'[1]F07 OPERAC'!Q10 -> 9000 | H35: =+'[1]F07 OPERAC'!R10 -> 0 | I35: =+'[1]F07 OPERAC'!S10 -> 9000 | J35: =+'[1]F07 OPERAC'!T10 -> 0 | ... N35: =+'[1]F07 OPERAC'!X10 -> 0
A36: ARTICULOS DIGITALES Y DE COMPUTO | B36: =SUM(C36:N36) -> 0
A37: INSUMOS DE OFICINA | B37: =SUM(B33:B36) -> 168000 | C37: =SUM(C33:C36) -> 18500 | D37: =SUM(D33:D36) -> 9500 | E37: =SUM(E33:E36) -> 18500 | F37: =SUM(F33:F36) -> 9500 | G37: =SUM(G33:G36) -> 18500 | H37: =SUM(H33:H36) -> 9500 | I37: =SUM(I33:I36) -> 18500 | ... N37: =SUM(N33:N36) -> 9500
A38: SERVICIOS DE MERCADOTECNIA | B38: =SUM(C38:N38) -> 0
A39: PUBLICIDAD Y PROPAGANDA | B39: =SUM(C39:N39) -> 0
A40: MARKETING | B40: =SUM(B38:B39) -> 0 | C40: =SUM(C38:C39) -> 0 | D40: =SUM(D38:D39) -> 0 | E40: =SUM(E38:E39) -> 0 | F40: =SUM(F38:F39) -> 0 | G40: =SUM(G38:G39) -> 0 | H40: =SUM(H38:H39) -> 0 | I40: =SUM(I38:I39) -> 0 | ... N40: =SUM(N38:N39) -> 0 | P40: Servicio mensual Jimena, publicación en periodico o revista digital, renovacion anual en el directorio de la industria enegetica y extras
A41: ABRASIVOS | B41: =SUM(C41:N41) -> 0
A42: ACEITE LUBRICANTE P/MAQUINARIA | B42: =SUM(C42:N42) -> 0
A43: ACEITES Y LUBRICANTES | B43: =SUM(C43:N43) -> 234000 | C43: =+'[1]F07 OPERAC'!M66+'[1]F07 OPERAC'!M65 -> 42000 | D43: =+'[1]F07 OPERAC'!N66+'[1]F07 OPERAC'!N65 -> 12000 | E43: =+'[1]F07 OPERAC'!O66+'[1]F07 OPERAC'!O65 -> 12000 | F43: =+'[1]F07 OPERAC'!P66+'[1]F07 OPERAC'!P65 -> 12000 | G43: =+'[1]F07 OPERAC'!Q66+'[1]F07 OPERAC'!Q65 -> 42000 | H43: =+'[1]F07 OPERAC'!R66+'[1]F07 OPERAC'!R65 -> 12000 | I43: =+'[1]F07 OPERAC'!S66+'[1]F07 OPERAC'!S65 -> 12000 | J43: =+'[1]F07 OPERAC'!T66+'[1]F07 OPERAC'!T65 -> 12000 | ... N43: =+'[1]F07 OPERAC'!X66+'[1]F07 OPERAC'!X65 -> 12000
A44: AISLANTES IMPERM REFRA | B44: =SUM(C44:N44) -> 0
A45: BANDA CADEN TRANS COPL | B45: =SUM(C45:N45) -> 0
A46: CONEXIONES PARA TUBERIA | B46: =SUM(C46:N46) -> 0
A47: EMPAQUETAD JTAS Y SELLOS | B47: =SUM(C47:N47) -> 0
A48: ENVASES | B48: =SUM(C48:N48) -> 0
A49: FIBRAS HILOS Y TELAS | B49: =SUM(C49:N49) -> 4200 | C49: =+'[1]F00 INV'!Q44 -> 0 | D49: =+'[1]F00 INV'!R44 -> 4200 | E49: =+'[1]F00 INV'!S44 -> 0 | F49: =+'[1]F00 INV'!T44 -> 0 | G49: =+'[1]F00 INV'!U44 -> 0 | H49: =+'[1]F00 INV'!V44 -> 0 | I49: =+'[1]F00 INV'!W44 -> 0 | J49: =+'[1]F00 INV'!X44 -> 0 | ... N49: =+'[1]F00 INV'!AB44 -> 0
A50: GRASAS | B50: =SUM(C50:N50) -> 0
A51: HERRAMIENTAS MANUALES | B51: =SUM(C51:N51) -> 90000 | C51: =+'[1]F00 INV'!Q43+'[1]F00 INV'!Q41+'[1]F00 INV'!Q42 -> 0 | D51: =+'[1]F00 INV'!R43+'[1]F00 INV'!R41+'[1]F00 INV'!R42 -> 90000 | E51: =+'[1]F00 INV'!S43+'[1]F00 INV'!S41+'[1]F00 INV'!S42 -> 0 | F51: =+'[1]F00 INV'!T43+'[1]F00 INV'!T41+'[1]F00 INV'!T42 -> 0 | G51: =+'[1]F00 INV'!U43+'[1]F00 INV'!U41+'[1]F00 INV'!U42 -> 0 | H51: =+'[1]F00 INV'!V43+'[1]F00 INV'!V41+'[1]F00 INV'!V42 -> 0 | I51: =+'[1]F00 INV'!W43+'[1]F00 INV'!W41+'[1]F00 INV'!W42 -> 0 | J51: =+'[1]F00 INV'!X43+'[1]F00 INV'!X41+'[1]F00 INV'!X42 -> 0 | ... N51: =+'[1]F00 INV'!AB43+'[1]F00 INV'!AB41+'[1]F00 INV'!AB42 -> 0
A52: INSTRUM DE MEDICION Y CONTROL | B52: =SUM(C52:N52) -> 75000 | C52: =+'[1]F00 INV'!Q24 -> 0 | D52: =+'[1]F00 INV'!R24 -> 75000 | E52: =+'[1]F00 INV'!S24 -> 0 | F52: =+'[1]F00 INV'!T24 -> 0 | G52: =+'[1]F00 INV'!U24 -> 0 | H52: =+'[1]F00 INV'!V24 -> 0 | I52: =+'[1]F00 INV'!W24 -> 0 | J52: =+'[1]F00 INV'!X24 -> 0 | ... N52: =+'[1]F00 INV'!AB24 -> 0
A53: LLANTAS, CAMARAS Y ACCESORIOS | B53: =SUM(C53:N53) -> 0
A54: MANGUERAS, CONEXIONES | B54: =SUM(C54:N54) -> 0
A55: MATERIAL ELECTRICO | B55: =SUM(C55:N55) -> 763934.43 | C55: =+'[1]F00 INV'!Q23+'[1]F00 INV'!Q51 -> 150000 | D55: =+'[1]F00 INV'!R23+'[1]F00 INV'!R51 -> 313934.43 | E55: =+'[1]F00 INV'!S23+'[1]F00 INV'!S51 -> 150000 | F55: =+'[1]F00 INV'!T23+'[1]F00 INV'!T51 -> 150000 | G55: =+'[1]F00 INV'!U23+'[1]F00 INV'!U51 -> 0 | H55: =+'[1]F00 INV'!V23+'[1]F00 INV'!V51 -> 0 | I55: =+'[1]F00 INV'!W23+'[1]F00 INV'!W51 -> 0 | J55: =+'[1]F00 INV'!X23+'[1]F00 INV'!X51 -> 0 | ... N55: =+'[1]F00 INV'!AB23+'[1]F00 INV'!AB51 -> 0
A56: MATERIAL PARA LA CONSTRUCCION | B56: =SUM(C56:N56) -> 0
A57: MATERIALES Y ART P/MANTENIMIENTO | B57: =SUM(C57:N57) -> 250000 | C57: =+'[1]F00 INV'!Q48 -> 50000 | D57: =+'[1]F00 INV'!R48 -> 50000 | E57: =+'[1]F00 INV'!S48 -> 50000 | F57: =+'[1]F00 INV'!T48 -> 50000 | G57: =+'[1]F00 INV'!U48 -> 50000 | H57: =+'[1]F00 INV'!V48 -> 0 | I57: =+'[1]F00 INV'!W48 -> 0 | J57: =+'[1]F00 INV'!X48 -> 0 | ... N57: =+'[1]F00 INV'!AB48 -> 0
A58: METALES | B58: =SUM(C58:N58) -> 0
A59: PART REP ACCES Y PROD P/VEHIC | B59: =SUM(C59:N59) -> 0
A60: PARTES ACCES Y MAT P/LABORATORIO | B60: =SUM(C60:N60) -> 0
A61: PARTES ACCES Y REFAC P/ LUBRICANTES | B61: =SUM(C61:N61) -> 0
A62: PARTES ELECT, ACCES Y REFACC | B62: =SUM(C62:N62) -> 0
A63: PARTES Y REFAC TELECOM Y VIDEO | B63: =SUM(C63:N63) -> 0
A64: PARTES Y REFACCION C/INCENDIO | B64: =SUM(C64:N64) -> 0
A65: PASTA PEGAMENTO OTRO COMPUESTO | B65: =SUM(C65:N65) -> 0
A66: PINTURA Y OTROS RECUBRIMIENTOS | B66: =SUM(C66:N66) -> 60000 | C66: =+'[1]F00 INV'!Q26 -> 0 | D66: =+'[1]F00 INV'!R26 -> 15000 | E66: =+'[1]F00 INV'!S26 -> 0 | F66: =+'[1]F00 INV'!T26 -> 0 | G66: =+'[1]F00 INV'!U26 -> 0 | H66: =+'[1]F00 INV'!V26 -> 0 | I66: =+'[1]F00 INV'!W26 -> 15000 | J66: =+'[1]F00 INV'!X26 -> 0 | ... N66: =+'[1]F00 INV'!AB26 -> 0
A67: REFAC P/INSTRUM DE MED Y CONTROL | B67: =SUM(C67:N67) -> 0
A68: REFACC Y ACCES PARA VALVULAS | B68: =SUM(C68:N68) -> 0
A69: REFACC Y ACCESORIO PARA HERRAMIENTA | B69: =SUM(C69:N69) -> 0
A70: REFACCIONES P/MAQUINARIA | B70: =SUM(C70:N70) -> 612000 | C70: =+'[1]F00 INV'!Q34+'[1]F00 INV'!Q12+'[1]F07 OPERAC'!M61+'[1]F07 OPERAC'!M62+'[1]F07 OPERAC'!M63+'[1]F07 OPERAC'!M64 -> 115000 | D70: =+'[1]F00 INV'!R34+'[1]F00 INV'!R12+'[1]F07 OPERAC'!N61+'[1]F07 OPERAC'!N62+'[1]F07 OPERAC'!N63+'[1]F07 OPERAC'!N64 -> 53000 | E70: =+'[1]F00 INV'!S34+'[1]F00 INV'!S12+'[1]F07 OPERAC'!O61+'[1]F07 OPERAC'!O62+'[1]F07 OPERAC'!O63+'[1]F07 OPERAC'!O64 -> 23000 | F70: =+'[1]F00 INV'!T34+'[1]F00 INV'!T12+'[1]F07 OPERAC'!P61+'[1]F07 OPERAC'!P62+'[1]F07 OPERAC'!P63+'[1]F07 OPERAC'!P64 -> 68000 | G70: =+'[1]F00 INV'!U34+'[1]F00 INV'!U12+'[1]F07 OPERAC'!Q61+'[1]F07 OPERAC'!Q62+'[1]F07 OPERAC'!Q63+'[1]F07 OPERAC'!Q64 -> 23000 | H70: =+'[1]F00 INV'!V34+'[1]F00 INV'!V12+'[1]F07 OPERAC'!R61+'[1]F07 OPERAC'!R62+'[1]F07 OPERAC'!R63+'[1]F07 OPERAC'!R64 -> 70000 | I70: =+'[1]F00 INV'!W34+'[1]F00 INV'!W12+'[1]F07 OPERAC'!S61+'[1]F07 OPERAC'!S62+'[1]F07 OPERAC'!S63+'[1]F07 OPERAC'!S64 -> 65000 | J70: =+'[1]F00 INV'!X34+'[1]F00 INV'!X12+'[1]F07 OPERAC'!T61+'[1]F07 OPERAC'!T62+'[1]F07 OPERAC'!T63+'[1]F07 OPERAC'!T64 -> 20000 | ... N70: =+'[1]F00 INV'!AB34+'[1]F00 INV'!AB12+'[1]F07 OPERAC'!X61+'[1]F07 OPERAC'!X62+'[1]F07 OPERAC'!X63+'[1]F07 OPERAC'!X64 -> 20000
A71: RODAM ACCES Y SELLOS P/ ACEITE | B71: =SUM(C71:N71) -> 0
A72: SUSTANCIAS QUIMICAS | B72: =SUM(C72:N72) -> 0
A73: TORNILLERIA Y ARTICULO | B73: =SUM(C73:N73) -> 0
A74: TUBERIAS | B74: =SUM(C74:N74) -> 890000 | C74: =+'[1]F00 INV'!Q52+'[1]F00 INV'!Q20+'[1]F00 INV'!Q21+'[1]F00 INV'!Q22 -> 200000 | D74: =+'[1]F00 INV'!R52+'[1]F00 INV'!R20+'[1]F00 INV'!R21+'[1]F00 INV'!R22 -> 290000 | E74: =+'[1]F00 INV'!S52+'[1]F00 INV'!S20+'[1]F00 INV'!S21+'[1]F00 INV'!S22 -> 200000 | F74: =+'[1]F00 INV'!T52+'[1]F00 INV'!T20+'[1]F00 INV'!T21+'[1]F00 INV'!T22 -> 200000 | G74: =+'[1]F00 INV'!U52+'[1]F00 INV'!U20+'[1]F00 INV'!U21+'[1]F00 INV'!U22 -> 0 | H74: =+'[1]F00 INV'!V52+'[1]F00 INV'!V20+'[1]F00 INV'!V21+'[1]F00 INV'!V22 -> 0 | I74: =+'[1]F00 INV'!W52+'[1]F00 INV'!W20+'[1]F00 INV'!W21+'[1]F00 INV'!W22 -> 0 | J74: =+'[1]F00 INV'!X52+'[1]F00 INV'!X20+'[1]F00 INV'!X21+'[1]F00 INV'!X22 -> 0 | ... N74: =+'[1]F00 INV'!AB52+'[1]F00 INV'!AB20+'[1]F00 INV'!AB21+'[1]F00 INV'!AB22 -> 0
A75: VALVULAS | B75: =SUM(C75:N75) -> 0
A76: MATERIALES | B76: =SUM(B41:B75) -> 2979134.4 | C76: =SUM(C41:C75) -> 557000 | D76: =SUM(D41:D75) -> 903134.43 | E76: =SUM(E41:E75) -> 435000 | F76: =SUM(F41:F75) -> 480000 | G76: =SUM(G41:G75) -> 115000 | H76: =SUM(H41:H75) -> 82000 | I76: =SUM(I41:I75) -> 92000 | ... N76: =SUM(N41:N75) -> 32000
A77: MATERIAL PRIMEROS AUXILIOS | B77: =SUM(C77:N77) -> 0
A78: MATERIALES DE SALUD | B78: =B77 -> 0 | C78: =C77 -> 0 | D78: =D77 -> 0 | E78: =E77 -> 0 | F78: =F77 -> 0 | G78: =G77 -> 0 | H78: =H77 -> 0 | I78: =I77 -> 0 | ... N78: =N77 -> 0
A79: NOMINA Y ADICIONALES | B79: =SUM(C79:N79) -> 4012131.3 | C79: =+'[1]F01 NÓM'!S138-C25 -> 291666.78 | D79: =+'[1]F01 NÓM'!T138-D25 -> 293595.51 | E79: =+'[1]F01 NÓM'!U138-E25 -> 342686.9 | F79: =+'[1]F01 NÓM'!V138-F25 -> 342686.9 | G79: =+'[1]F01 NÓM'!W138-G25 -> 342686.9 | H79: =+'[1]F01 NÓM'!X138-H25 -> 342686.9 | I79: =+'[1]F01 NÓM'!Y138-I25 -> 342686.9 | J79: =+'[1]F01 NÓM'!Z138-J25 -> 342686.9 | ... N79: =+'[1]F01 NÓM'!AD138-N25 -> 342686.9
A80: SERV TELEFONIA CELULAR | B80: =SUM(C80:N80) -> 6437.1585 | C80: =+SUM('[1]F03 COM Y EQ COM'!J8:J26) -> 513.6612 | D80: =+SUM('[1]F03 COM Y EQ COM'!K8:K26) -> 513.6612 | E80: =+SUM('[1]F03 COM Y EQ COM'!L8:L26) -> 540.98361 | F80: =+SUM('[1]F03 COM Y EQ COM'!M8:M26) -> 540.98361 | G80: =+SUM('[1]F03 COM Y EQ COM'!N8:N26) -> 540.98361 | H80: =+SUM('[1]F03 COM Y EQ COM'!O8:O26) -> 540.98361 | I80: =+SUM('[1]F03 COM Y EQ COM'!P8:P26) -> 540.98361 | J80: =+SUM('[1]F03 COM Y EQ COM'!Q8:Q26) -> 540.98361 | ... N80: =+SUM('[1]F03 COM Y EQ COM'!U8:U26) -> 540.98361
A81: SERVICIO DE BANDA ANCHA | B81: =SUM(C81:N81) -> 0
A82: SERVICIO DE RADIOCOMUNICACION | B82: =SUM(C82:N82) -> 0
A83: SERV TELEFONIA CELULAR Y RADIO | B83: =SUM(B80:B82) -> 6437.1585 | C83: =SUM(C80:C82) -> 513.6612 | D83: =SUM(D80:D82) -> 513.6612 | E83: =SUM(E80:E82) -> 540.98361 | F83: =SUM(F80:F82) -> 540.98361 | G83: =SUM(G80:G82) -> 540.98361 | H83: =SUM(H80:H82) -> 540.98361 | I83: =SUM(I80:I82) -> 540.98361 | ... N83: =SUM(N80:N82) -> 540.98361
A84: ACONDICION DE CASA HABITACION | B84: =SUM(C84:N84) -> 0 | H84: =+'[1]F00 INV'!V10+'[1]F00 INV'!V11 -> 0 | I84: =+'[1]F00 INV'!W10+'[1]F00 INV'!W11 -> 0 | J84: =+'[1]F00 INV'!X10+'[1]F00 INV'!X11 -> 0 | K84: =+'[1]F00 INV'!Y10+'[1]F00 INV'!Y11 -> 0 | L84: =+'[1]F00 INV'!Z10+'[1]F00 INV'!Z11 -> 0 | M84: =+'[1]F00 INV'!AA10+'[1]F00 INV'!AA11 -> 0 | N84: =+'[1]F00 INV'!AB10+'[1]F00 INV'!AB11 -> 0
A85: ADICION Y MODIFIC DE MATERIAL | B85: =SUM(C85:N85) -> 0
A86: ADQUISICION TARJET COMBUSTIBLE | B86: =SUM(C86:N86) -> 0 | P86: 10 tarjetas de combustible
A87: ANALISIS CAUSA RAIZ | B87: =SUM(C87:N87) -> 0
A88: ANALISIS DE RIESGO | B88: =SUM(C88:N88) -> 12000 | C88: =+'[1]F00 INV'!Q47 -> 0 | D88: =+'[1]F00 INV'!R47 -> 12000 | E88: =+'[1]F00 INV'!S47 -> 0 | F88: =+'[1]F00 INV'!T47 -> 0 | G88: =+'[1]F00 INV'!U47 -> 0 | H88: =+'[1]F00 INV'!V47 -> 0 | I88: =+'[1]F00 INV'!W47 -> 0 | J88: =+'[1]F00 INV'!X47 -> 0 | ... N88: =+'[1]F00 INV'!AB47 -> 0
A89: ANALISIS DE VIBRACION | B89: =SUM(C89:N89) -> 0
A90: BASES LICITACION Y CONCURSOS | B90: =SUM(C90:N90) -> 0
A91: CARGOS EXTRAORDINARIOS | B91: =SUM(C91:N91) -> 0
A92: CERTIFICACION | B92: =SUM(C92:N92) -> 100000 | C92: ='[1]F07 OPERAC'!Q43+'[1]F07 OPERAC'!Q44 -> 0 | D92: ='[1]F07 OPERAC'!R43+'[1]F07 OPERAC'!R44 -> 20000 | E92: ='[1]F07 OPERAC'!S43+'[1]F07 OPERAC'!S44 -> 0 | F92: ='[1]F07 OPERAC'!T43+'[1]F07 OPERAC'!T44 -> 20000 | G92: ='[1]F07 OPERAC'!U43+'[1]F07 OPERAC'!U44 -> 20000 | H92: ='[1]F07 OPERAC'!V43+'[1]F07 OPERAC'!V44 -> 0 | I92: ='[1]F07 OPERAC'!W43+'[1]F07 OPERAC'!W44 -> 20000 | J92: ='[1]F07 OPERAC'!X43+'[1]F07 OPERAC'!X44 -> 20000 | ... N92: ='[1]F07 OPERAC'!AB43+'[1]F07 OPERAC'!AB44 -> 0
A93: COLOCACION DE PILOTE | B93: =SUM(C93:N93) -> 0
A94: CORREOS Y MENSAJERIAS | B94: =SUM(C94:N94) -> 0
A95: CUOTAS Y SUSCRIPCIONES | B95: =SUM(C95:N95) -> 0 | P95: zoom, renovación dropbox, renovación licencias SNAP, renovación antivirus, renovación office, servicio anual de hosting web, correo electronico y dominio, cemefi, inscripcion congreso villahermosa, congreso colombia inscripción, renovación plataforma de licitaciones, renovación aquiles, renovacion plataforma proveedores colombia
A96: DEDUCIBLE POR SINIESTRO | B96: =SUM(C96:N96) -> 0
A97: DESARROLLO DE SOFTWARE | B97: =SUM(C97:N97) -> 0
A98: FIANZAS | B98: =SUM(C98:N98) -> 0
A99: FLETES EXTRANJEROS | B99: =SUM(C99:N99) -> 15000 | C99: =+'[1]F00 INV'!Q14 -> 0 | D99: =+'[1]F00 INV'!R14 -> 15000 | E99: =+'[1]F00 INV'!S14 -> 0 | F99: =+'[1]F00 INV'!T14 -> 0 | G99: =+'[1]F00 INV'!U14 -> 0 | H99: =+'[1]F00 INV'!V14 -> 0 | I99: =+'[1]F00 INV'!W14 -> 0 | J99: =+'[1]F00 INV'!X14 -> 0 | ... N99: =+'[1]F00 INV'!AB14 -> 0
A100: FLETES NACIONALES | B100: =SUM(C100:N100) -> 107000 | C100: =+'[1]F00 INV'!Q15+'[1]F07 OPERAC'!M45 -> 6000 | D100: =+'[1]F00 INV'!R15+'[1]F07 OPERAC'!N45 -> 41000 | E100: =+'[1]F00 INV'!S15+'[1]F07 OPERAC'!O45 -> 6000 | F100: =+'[1]F00 INV'!T15+'[1]F07 OPERAC'!P45 -> 6000 | G100: =+'[1]F00 INV'!U15+'[1]F07 OPERAC'!Q45 -> 6000 | H100: =+'[1]F00 INV'!V15+'[1]F07 OPERAC'!R45 -> 6000 | I100: =+'[1]F00 INV'!W15+'[1]F07 OPERAC'!S45 -> 6000 | J100: =+'[1]F00 INV'!X15+'[1]F07 OPERAC'!T45 -> 6000 | ... N100: =+'[1]F00 INV'!AB15+'[1]F07 OPERAC'!X45 -> 6000
A101: GASTOS DE IMPORTACION | B101: =SUM(C101:N101) -> 182800 | C101: =+'[1]F00 INV'!Q13 -> 0 | D101: =+'[1]F00 INV'!R13 -> 182800 | E101: =+'[1]F00 INV'!S13 -> 0 | F101: =+'[1]F00 INV'!T13 -> 0 | G101: =+'[1]F00 INV'!U13 -> 0 | H101: =+'[1]F00 INV'!V13 -> 0 | I101: =+'[1]F00 INV'!W13 -> 0 | J101: =+'[1]F00 INV'!X13 -> 0 | ... N101: =+'[1]F00 INV'!AB13 -> 0
...

Sheet MN
A1: GEOLIS SA DE CV | C1: 18.3
A2: Proyecto: PRC LITORAL
A3: INGRESOS 2025
A4: Descripcion | B4: Total Presupuestado | C4: Enero Pre | D4: Febrero Pre | E4: Marzo Pre | F4: Abril Pre | G4: Mayo Pre | H4: Junio Pre | I4: Julio Pre | J4: Agosto Pre | K4: Septiembre Pre | L4: Octubre Pre | M4: Noviembre Pre | N4: Diciembre Pre
A5: FACTURACION | B5: =SUM(C5:N5) -> 848016537 | C5: =+USD!C5*MN!$C$1 -> 75277151 | D5: =+USD!D5*MN!$C$1 -> 70258674 | E5: =+USD!E5*MN!$C$1 -> 75277151 | F5: =+USD!F5*MN!$C$1 -> 72848855 | G5: =+USD!G5*MN!$C$1 -> 75277151 | H5: =+USD!H5*MN!$C$1 -> 72848855 | I5: =+USD!I5*MN!$C$1 -> 75277151 | J5: =+USD!J5*MN!$C$1 -> 75277151 | ... N5: =+USD!N5*MN!$C$1 -> 49657151
A7: EGRESOS 2025
A8: Descripcion | B8: Total Presupuestado | C8: Enero Pre | D8: Febrero Pre | E8: Marzo Pre | F8: Abril Pre | G8: Mayo Pre | H8: Junio Pre | I8: Julio Pre | J8: Agosto Pre | K8: Septiembre Pre | L8: Octubre Pre | M8: Noviembre Pre | N8: Diciembre Pre
A9: EQUIPO DE TRANSPORTE | B9: =SUM(C9:N9) -> 1720200 | C9: =+USD!C9*MN!$C$1 -> 417240 | D9: =+USD!D9*MN!$C$1 -> 417240 | E9: =+USD!E9*MN!$C$1 -> 885720 | F9: =+USD!F9*MN!$C$1 -> 0 | G9: =+USD!G9*MN!$C$1 -> 0 | H9: =+USD!H9*MN!$C$1 -> 0 | I9: =+USD!I9*MN!$C$1 -> 0 | J9: =+USD!J9*MN!$C$1 -> 0 | ... N9: =+USD!N9*MN!$C$1 -> 0
A10: EQUIPO DE MOBILIARIO | B10: =SUM(C10:N10) -> 1830000 | C10: =+USD!C9*MN!$C$1 -> 417240 | D10: =+USD!D9*MN!$C$1 -> 417240 | E10: =+USD!E9*MN!$C$1 -> 885720 | F10: =+USD!F10*MN!$C$1 -> 54900 | G10: =+USD!G10*MN!$C$1 -> 54900 | H10: =+USD!H10*MN!$C$1 -> 0 | I10: =+USD!I10*MN!$C$1 -> 0 | J10: =+USD!J10*MN!$C$1 -> 0 | K10: =+USD!K10*MN!$C$1 -> 0 | L10: =+USD!L10*MN!$C$1 -> 0 | M10: =+USD!M10*MN!$C$1 -> 0 | N10: =+USD!N10*MN!$C$1 -> 0
A11: MAQUINARIA Y EQUIPO | B11: =SUM(C11:N11) -> 38320200 | C11: =+USD!C11*MN!$C$1 -> 10619490 | D11: =+USD!D11*MN!$C$1 -> 11671740 | E11: =+USD!E11*MN!$C$1 -> 9715470 | F11: =+USD!F11*MN!$C$1 -> 5764500 | G11: =+USD!G11*MN!$C$1 -> 274500 | H11: =+USD!H11*MN!$C$1 -> 274500 | I11: =+USD!I11*MN!$C$1 -> 0 | J11: =+USD!J11*MN!$C$1 -> 0 | ... N11: =+USD!N11*MN!$C$1 -> 0
A12: OTROS ACTIVOS | B12: =SUM(C12:N12) -> 50416500 | C12: =+USD!C12*MN!$C$1 -> 8235000 | D12: =+USD!D12*MN!$C$1 -> 8326500 | E12: =+USD!E12*MN!$C$1 -> 9150000 | F12: =+USD!F12*MN!$C$1 -> 8235000 | G12: =+USD!G12*MN!$C$1 -> 8235000 | H12: =+USD!H12*MN!$C$1 -> 8235000 | I12: =+USD!I12*MN!$C$1 -> 0 | J12: =+USD!J12*MN!$C$1 -> 0 | ... N12: =+USD!N12*MN!$C$1 -> 0
A13: SOFTWARE Y LICICENCIAS | B13: =SUM(C13:N13) -> 0 | C13: =+USD!C13*MN!$C$1 -> 0 | D13: =+USD!D13*MN!$C$1 -> 0 | E13: =+USD!E13*MN!$C$1 -> 0 | F13: =+USD!F13*MN!$C$1 -> 0 | G13: =+USD!G13*MN!$C$1 -> 0 | H13: =+USD!H13*MN!$C$1 -> 0 | I13: =+USD!I13*MN!$C$1 -> 0 | J13: =+USD!J13*MN!$C$1 -> 0 | ... N13: =+USD!N13*MN!$C$1 -> 0
A14: ACTIVOS | B14: =SUM(B9:B13) -> 92286900 | C14: =SUM(C9:C13) -> 19688970 | D14: =SUM(D9:D13) -> 20832720 | E14: =SUM(E9:E13) -> 20636910 | F14: =SUM(F9:F13) -> 14054400 | G14: =SUM(G9:G13) -> 8564400 | H14: =SUM(H9:H13) -> 8509500 | I14: =SUM(I9:I13) -> 0 | ... N14: =SUM(N9:N13) -> 0 | P14: Mobiliario de oficina
A15: ARRENDAMIENTO DE INMUEBLES | B15: =SUM(C15:N15) -> 1464000 | C15: =+USD!C15*MN!$C$1 -> 122000 | D15: =+USD!D15*MN!$C$1 -> 122000 | E15: =+USD!E15*MN!$C$1 -> 122000 | F15: =+USD!F15*MN!$C$1 -> 122000 | G15: =+USD!G15*MN!$C$1 -> 122000 | H15: =+USD!H15*MN!$C$1 -> 122000 | I15: =+USD!I15*MN!$C$1 -> 122000 | J15: =+USD!J15*MN!$C$1 -> 122000 | ... N15: =+USD!N15*MN!$C$1 -> 122000
A16: ENERGIA ELECTRICA | B16: =SUM(C16:N16) -> 408000 | C16: =+USD!C16*MN!$C$1 -> 34000 | D16: =+USD!D16*MN!$C$1 -> 34000 | E16: =+USD!E16*MN!$C$1 -> 34000 | F16: =+USD!F16*MN!$C$1 -> 34000 | G16: =+USD!G16*MN!$C$1 -> 34000 | H16: =+USD!H16*MN!$C$1 -> 34000 | I16: =+USD!I16*MN!$C$1 -> 34000 | J16: =+USD!J16*MN!$C$1 -> 34000 | ... N16: =+USD!N16*MN!$C$1 -> 34000
A17: RENTA DE CASAS NO DEDUCIBLE | B17: =SUM(C17:N17) -> 0 | C17: =+USD!C17*MN!$C$1 -> 0 | D17: =+USD!D17*MN!$C$1 -> 0 | E17: =+USD!E17*MN!$C$1 -> 0 | F17: =+USD!F17*MN!$C$1 -> 0 | G17: =+USD!G17*MN!$C$1 -> 0 | H17: =+USD!H17*MN!$C$1 -> 0 | I17: =+USD!I17*MN!$C$1 -> 0 | J17: =+USD!J17*MN!$C$1 -> 0 | ... N17: =+USD!N17*MN!$C$1 -> 0
A18: SERVICIOS DE LIMPIEZA | B18: =SUM(C18:N18) -> 312240 | C18: =+USD!C18*MN!$C$1 -> 26020 | D18: =+USD!D18*MN!$C$1 -> 26020 | E18: =+USD!E18*MN!$C$1 -> 26020 | F18: =+USD!F18*MN!$C$1 -> 26020 | G18: =+USD!G18*MN!$C$1 -> 26020 | H18: =+USD!H18*MN!$C$1 -> 26020 | I18: =+USD!I18*MN!$C$1 -> 26020 | J18: =+USD!J18*MN!$C$1 -> 26020 | ... N18: =+USD!N18*MN!$C$1 -> 26020
A19: SERVICIOS DE VIGILANCIA | B19: =SUM(C19:N19) -> 360000 | C19: =+USD!C19*MN!$C$1 -> 30000 | D19: =+USD!D19*MN!$C$1 -> 30000 | E19: =+USD!E19*MN!$C$1 -> 30000 | F19: =+USD!F19*MN!$C$1 -> 30000 | G19: =+USD!G19*MN!$C$1 -> 30000 | H19: =+USD!H19*MN!$C$1 -> 30000 | I19: =+USD!I19*MN!$C$1 -> 30000 | J19: =+USD!J19*MN!$C$1 -> 30000 | ... N19: =+USD!N19*MN!$C$1 -> 30000
A20: SERVICIOS DE FUMIGACION | B20: =SUM(C20:N20) -> 0 | C20: =+USD!C20*MN!$C$1 -> 0 | D20: =+USD!D20*MN!$C$1 -> 0 | E20: =+USD!E20*MN!$C$1 -> 0 | F20: =+USD!F20*MN!$C$1 -> 0 | G20: =+USD!G20*MN!$C$1 -> 0 | H20: =+USD!H20*MN!$C$1 -> 0 | I20: =+USD!I20*MN!$C$1 -> 0 | J20: =+USD!J20*MN!$C$1 -> 0 | ... N20: =+USD!N20*MN!$C$1 -> 0
A21: TELEFONIA FIJA | B21: =SUM(C21:N21) -> 0 | C21: =+USD!C21*MN!$C$1 -> 0 | D21: =+USD!D21*MN!$C$1 -> 0 | E21: =+USD!E21*MN!$C$1 -> 0 | F21: =+USD!F21*MN!$C$1 -> 0 | G21: =+USD!G21*MN!$C$1 -> 0 | H21: =+USD!H21*MN!$C$1 -> 0 | I21: =+USD!I21*MN!$C$1 -> 0 | J21: =+USD!J21*MN!$C$1 -> 0 | ... N21: =+USD!N21*MN!$C$1 -> 0
A22: AGUA Y ALCANTARILLADO | B22: =SUM(C22:N22) -> 0 | C22: =+USD!C22*MN!$C$1 -> 0 | D22: =+USD!D22*MN!$C$1 -> 0 | E22: =+USD!E22*MN!$C$1 -> 0 | F22: =+USD!F22*MN!$C$1 -> 0 | G22: =+USD!G22*MN!$C$1 -> 0 | H22: =+USD!H22*MN!$C$1 -> 0 | I22: =+USD!I22*MN!$C$1 -> 0 | J22: =+USD!J22*MN!$C$1 -> 0 | ... N22: =+USD!N22*MN!$C$1 -> 0
A23: ARRENDAMIENTO DE OF. MOVILES | B23: =SUM(C23:N23) -> 0 | C23: =+USD!C23*MN!$C$1 -> 0 | D23: =+USD!D23*MN!$C$1 -> 0 | E23: =+USD!E23*MN!$C$1 -> 0 | F23: =+USD!F23*MN!$C$1 -> 0 | G23: =+USD!G23*MN!$C$1 -> 0 | H23: =+USD!H23*MN!$C$1 -> 0 | I23: =+USD!I23*MN!$C$1 -> 0 | J23: =+USD!J23*MN!$C$1 -> 0 | ... N23: =+USD!N23*MN!$C$1 -> 0
A24: ARRENDA DE INMUEBLES Y SERV | B24: =SUM(B15:B23) -> 2544240 | C24: =SUM(C15:C23) -> 212020 | D24: =SUM(D15:D23) -> 212020 | E24: =SUM(E15:E23) -> 212020 | F24: =SUM(F15:F23) -> 212020 | G24: =SUM(G15:G23) -> 212020 | H24: =SUM(H15:H23) -> 212020 | I24: =SUM(I15:I23) -> 212020 | ... N24: =SUM(N15:N23) -> 212020 | P24: renta casa staff villahermosa, servicio de limpieza
A25: ROPA Y ARTICULOS DE PROTECCION | B25: =SUM(C25:N25) -> 6258842.7 | C25: =+USD!C25*MN!$C$1 -> 446942.71 | D25: =+USD!D25*MN!$C$1 -> 446942.71 | E25: =+USD!E25*MN!$C$1 -> 536495.73 | F25: =+USD!F25*MN!$C$1 -> 536495.73 | G25: =+USD!G25*MN!$C$1 -> 536495.73 | H25: =+USD!H25*MN!$C$1 -> 536495.73 | I25: =+USD!I25*MN!$C$1 -> 536495.73 | J25: =+USD!J25*MN!$C$1 -> 536495.73 | ... N25: =+USD!N25*MN!$C$1 -> 536495.73
A26: ARTICULOS DE SEGURIDAD | B26: =B25 -> 6258842.7 | C26: =C25 -> 446942.71 | D26: =D25 -> 446942.71 | E26: =E25 -> 536495.73 | F26: =F25 -> 536495.73 | G26: =G25 -> 536495.73 | H26: =H25 -> 536495.73 | I26: =I25 -> 536495.73 | ... N26: =N25 -> 536495.73 | P26: overoles, botas, lentes, porta credencial
A27: EQUIPO DE COMPUTO (Adquisición) | B27: =SUM(C27:N27) -> 168006 | C27: =+USD!C27*MN!$C$1 -> 168006 | D27: =+USD!D27*MN!$C$1 -> 0 | E27: =+USD!E27*MN!$C$1 -> 0 | F27: =+USD!F27*MN!$C$1 -> 0 | G27: =+USD!G27*MN!$C$1 -> 0 | H27: =+USD!H27*MN!$C$1 -> 0 | I27: =+USD!I27*MN!$C$1 -> 0 | J27: =+USD!J27*MN!$C$1 -> 0 | ... N27: =+USD!N27*MN!$C$1 -> 0
A28: ARRENDAMIENTO DE EQ. COMPUTO | B28: =SUM(C28:N28) -> 0 | C28: =+USD!C28*MN!$C$1 -> 0 | D28: =+USD!D28*MN!$C$1 -> 0 | E28: =+USD!E28*MN!$C$1 -> 0 | F28: =+USD!F28*MN!$C$1 -> 0 | G28: =+USD!G28*MN!$C$1 -> 0 | H28: =+USD!H28*MN!$C$1 -> 0 | I28: =+USD!I28*MN!$C$1 -> 0 | J28: =+USD!J28*MN!$C$1 -> 0 | ... N28: =+USD!N28*MN!$C$1 -> 0
A29: EQUIPO DE COMPUTO | B29: =SUM(B27:B28) -> 168006 | C29: =SUM(C27:C28) -> 168006 | D29: =SUM(D27:D28) -> 0 | E29: =SUM(E27:E28) -> 0 | F29: =SUM(F27:F28) -> 0 | G29: =SUM(G27:G28) -> 0 | H29: =SUM(H27:H28) -> 0 | I29: =SUM(I27:I28) -> 0 | ... N29: =SUM(N27:N28) -> 0
A30: ENSERES MENORES DIVERSOS (Acondicionamiento de casas) | B30: =SUM(C30:N30) -> 0 | C30: =+USD!C30*MN!$C$1 -> 0 | D30: =+USD!D30*MN!$C$1 -> 0 | E30: =+USD!E30*MN!$C$1 -> 0 | F30: =+USD!F30*MN!$C$1 -> 0 | G30: =+USD!G30*MN!$C$1 -> 0 | H30: =+USD!H30*MN!$C$1 -> 0 | I30: =+USD!I30*MN!$C$1 -> 0 | J30: =+USD!J30*MN!$C$1 -> 0 | ... N30: =+USD!N30*MN!$C$1 -> 0
A31: EQUIPOS Y ENSERES | B31: =B30 -> 0 | C31: =C30 -> 0 | D31: =D30 -> 0 | E31: =E30 -> 0 | F31: =F30 -> 0 | G31: =G30 -> 0 | H31: =H30 -> 0 | I31: =I30 -> 0 | ... N31: =N30 -> 0
A32: INSUMOS AGRICOLAS | B32: =SUM(C32:N32) -> 0
A33: PAPELERIA Y UTILES DE OFICINA | B33: =SUM(C33:N33) -> 439200 | C33: =+USD!C33*MN!$C$1 -> 36600 | D33: =+USD!D33*MN!$C$1 -> 36600 | E33: =+USD!E33*MN!$C$1 -> 36600 | F33: =+USD!F33*MN!$C$1 -> 36600 | G33: =+USD!G33*MN!$C$1 -> 36600 | H33: =+USD!H33*MN!$C$1 -> 36600 | I33: =+USD!I33*MN!$C$1 -> 36600 | J33: =+USD!J33*MN!$C$1 -> 36600 | ... N33: =+USD!N33*MN!$C$1 -> 36600
A34: ARTICULOS DE ASEO Y SANITARIOS | B34: =SUM(C34:N34) -> 1647000 | C34: =+USD!C34*MN!$C$1 -> 137250 | D34: =+USD!D34*MN!$C$1 -> 137250 | E34: =+USD!E34*MN!$C$1 -> 137250 | F34: =+USD!F34*MN!$C$1 -> 137250 | G34: =+USD!G34*MN!$C$1 -> 137250 | H34: =+USD!H34*MN!$C$1 -> 137250 | I34: =+USD!I34*MN!$C$1 -> 137250 | J34: =+USD!J34*MN!$C$1 -> 137250 | ... N34: =+USD!N34*MN!$C$1 -> 137250
A35: ARTICULOS DE CAFETERIA | B35: =SUM(C35:N35) -> 988200 | C35: =+USD!C35*MN!$C$1 -> 164700 | D35: =+USD!D35*MN!$C$1 -> 0 | E35: =+USD!E35*MN!$C$1 -> 164700 | F35: =+USD!F35*MN!$C$1 -> 0 | G35: =+USD!G35*MN!$C$1 -> 164700 | H35: =+USD!H35*MN!$C$1 -> 0 | I35: =+USD!I35*MN!$C$1 -> 164700 | J35: =+USD!J35*MN!$C$1 -> 0 | ... N35: =+USD!N35*MN!$C$1 -> 0
A36: ARTICULOS DIGITALES Y DE COMPUTO | B36: =SUM(C36:N36) -> 0 | C36: =+USD!C36*MN!$C$1 -> 0 | D36: =+USD!D36*MN!$C$1 -> 0 | E36: =+USD!E36*MN!$C$1 -> 0 | F36: =+USD!F36*MN!$C$1 -> 0 | G36: =+USD!G36*MN!$C$1 -> 0 | H36: =+USD!H36*MN!$C$1 -> 0 | I36: =+USD!I36*MN!$C$1 -> 0 | J36: =+USD!J36*MN!$C$1 -> 0 | ... N36: =+USD!N36*MN!$C$1 -> 0
A37: INSUMOS DE OFICINA | B37: =SUM(B33:B36) -> 3074400 | C37: =SUM(C33:C36) -> 338550 | D37: =SUM(D33:D36) -> 173850 | E37: =SUM(E33:E36) -> 338550 | F37: =SUM(F33:F36) -> 173850 | G37: =SUM(G33:G36) -> 338550 | H37: =SUM(H33:H36) -> 173850 | I37: =SUM(I33:I36) -> 338550 | ... N37: =SUM(N33:N36) -> 173850
A38: SERVICIOS DE MERCADOTECNIA | B38: =SUM(C38:N38) -> 0
A39: PUBLICIDAD Y PROPAGANDA | B39: =SUM(C39:N39) -> 0
A40: MARKETING | B40: =SUM(B38:B39) -> 0 | C40: =SUM(C38:C39) -> 0 | D40: =SUM(D38:D39) -> 0 | E40: =SUM(E38:E39) -> 0 | F40: =SUM(F38:F39) -> 0 | G40: =SUM(G38:G39) -> 0 | H40: =SUM(H38:H39) -> 0 | I40: =SUM(I38:I39) -> 0 | ... N40: =SUM(N38:N39) -> 0 | P40: Servicio mensual Jimena, publicación en periodico o revista digital, renovacion anual en el directorio de la industria enegetica y extras
A41: ABRASIVOS | B41: =SUM(C41:N41) -> 0 | C41: =+USD!C41*MN!$C$1 -> 0 | D41: =+USD!D41*MN!$C$1 -> 0 | E41: =+USD!E41*MN!$C$1 -> 0 | F41: =+USD!F41*MN!$C$1 -> 0 | G41: =+USD!G41*MN!$C$1 -> 0 | H41: =+USD!H41*MN!$C$1 -> 0 | I41: =+USD!I41*MN!$C$1 -> 0 | J41: =+USD!J41*MN!$C$1 -> 0 | ... N41: =+USD!N41*MN!$C$1 -> 0
A42: ACEITE LUBRICANTE P/MAQUINARIA | B42: =SUM(C42:N42) -> 0 | C42: =+USD!C42*MN!$C$1 -> 0 | D42: =+USD!D42*MN!$C$1 -> 0 | E42: =+USD!E42*MN!$C$1 -> 0 | F42: =+USD!F42*MN!$C$1 -> 0 | G42: =+USD!G42*MN!$C$1 -> 0 | H42: =+USD!H42*MN!$C$1 -> 0 | I42: =+USD!I42*MN!$C$1 -> 0 | J42: =+USD!J42*MN!$C$1 -> 0 | ... N42: =+USD!N42*MN!$C$1 -> 0
A43: ACEITES Y LUBRICANTES | B43: =SUM(C43:N43) -> 4282200 | C43: =+USD!C43*MN!$C$1 -> 768600 | D43: =+USD!D43*MN!$C$1 -> 219600 | E43: =+USD!E43*MN!$C$1 -> 219600 | F43: =+USD!F43*MN!$C$1 -> 219600 | G43: =+USD!G43*MN!$C$1 -> 768600 | H43: =+USD!H43*MN!$C$1 -> 219600 | I43: =+USD!I43*MN!$C$1 -> 219600 | J43: =+USD!J43*MN!$C$1 -> 219600 | ... N43: =+USD!N43*MN!$C$1 -> 219600
A44: AISLANTES IMPERM REFRA | B44: =SUM(C44:N44) -> 0 | C44: =+USD!C44*MN!$C$1 -> 0 | D44: =+USD!D44*MN!$C$1 -> 0 | E44: =+USD!E44*MN!$C$1 -> 0 | F44: =+USD!F44*MN!$C$1 -> 0 | G44: =+USD!G44*MN!$C$1 -> 0 | H44: =+USD!H44*MN!$C$1 -> 0 | I44: =+USD!I44*MN!$C$1 -> 0 | J44: =+USD!J44*MN!$C$1 -> 0 | ... N44: =+USD!N44*MN!$C$1 -> 0
A45: BANDA CADEN TRANS COPL | B45: =SUM(C45:N45) -> 0 | C45: =+USD!C45*MN!$C$1 -> 0 | D45: =+USD!D45*MN!$C$1 -> 0 | E45: =+USD!E45*MN!$C$1 -> 0 | F45: =+USD!F45*MN!$C$1 -> 0 | G45: =+USD!G45*MN!$C$1 -> 0 | H45: =+USD!H45*MN!$C$1 -> 0 | I45: =+USD!I45*MN!$C$1 -> 0 | J45: =+USD!J45*MN!$C$1 -> 0 | ... N45: =+USD!N45*MN!$C$1 -> 0
A46: CONEXIONES PARA TUBERIA | B46: =SUM(C46:N46) -> 0 | C46: =+USD!C46*MN!$C$1 -> 0 | D46: =+USD!D46*MN!$C$1 -> 0 | E46: =+USD!E46*MN!$C$1 -> 0 | F46: =+USD!F46*MN!$C$1 -> 0 | G46: =+USD!G46*MN!$C$1 -> 0 | H46: =+USD!H46*MN!$C$1 -> 0 | I46: =+USD!I46*MN!$C$1 -> 0 | J46: =+USD!J46*MN!$C$1 -> 0 | ... N46: =+USD!N46*MN!$C$1 -> 0
A47: EMPAQUETAD JTAS Y SELLOS | B47: =SUM(C47:N47) -> 0 | C47: =+USD!C47*MN!$C$1 -> 0 | D47: =+USD!D47*MN!$C$1 -> 0 | E47: =+USD!E47*MN!$C$1 -> 0 | F47: =+USD!F47*MN!$C$1 -> 0 | G47: =+USD!G47*MN!$C$1 -> 0 | H47: =+USD!H47*MN!$C$1 -> 0 | I47: =+USD!I47*MN!$C$1 -> 0 | J47: =+USD!J47*MN!$C$1 -> 0 | ... N47: =+USD!N47*MN!$C$1 -> 0
A48: ENVASES | B48: =SUM(C48:N48) -> 0 | C48: =+USD!C48*MN!$C$1 -> 0 | D48: =+USD!D48*MN!$C$1 -> 0 | E48: =+USD!E48*MN!$C$1 -> 0 | F48: =+USD!F48*MN!$C$1 -> 0 | G48: =+USD!G48*MN!$C$1 -> 0 | H48: =+USD!H48*MN!$C$1 -> 0 | I48: =+USD!I48*MN!$C$1 -> 0 | J48: =+USD!J48*MN!$C$1 -> 0 | ... N48: =+USD!N48*MN!$C$1 -> 0
A49: FIBRAS HILOS Y TELAS | B49: =SUM(C49:N49) -> 76860 | C49: =+USD!C49*MN!$C$1 -> 0 | D49: =+USD!D49*MN!$C$1 -> 76860 | E49: =+USD!E49*MN!$C$1 -> 0 | F49: =+USD!F49*MN!$C$1 -> 0 | G49: =+USD!G49*MN!$C$1 -> 0 | H49: =+USD!H49*MN!$C$1 -> 0 | I49: =+USD!I49*MN!$C$1 -> 0 | J49: =+USD!J49*MN!$C$1 -> 0 | ... N49: =+USD!N49*MN!$C$1 -> 0
A50: GRASAS | B50: =SUM(C50:N50) -> 0 | C50: =+USD!C50*MN!$C$1 -> 0 | D50: =+USD!D50*MN!$C$1 -> 0 | E50: =+USD!E50*MN!$C$1 -> 0 | F50: =+USD!F50*MN!$C$1 -> 0 | G50: =+USD!G50*MN!$C$1 -> 0 | H50: =+USD!H50*MN!$C$1 -> 0 | I50: =+USD!I50*MN!$C$1 -> 0 | J50: =+USD!J50*MN!$C$1 -> 0 | ... N50: =+USD!N50*MN!$C$1 -> 0
A51: HERRAMIENTAS MANUALES | B51: =SUM(C51:N51) -> 1647000 | C51: =+USD!C51*MN!$C$1 -> 0 | D51: =+USD!D51*MN!$C$1 -> 1647000 | E51: =+USD!E51*MN!$C$1 -> 0 | F51: =+USD!F51*MN!$C$1 -> 0 | G51: =+USD!G51*MN!$C$1 -> 0 | H51: =+USD!H51*MN!$C$1 -> 0 | I51: =+USD!I51*MN!$C$1 -> 0 | J51: =+USD!J51*MN!$C$1 -> 0 | ... N51: =+USD!N51*MN!$C$1 -> 0
A52: INSTRUM DE MEDICION Y CONTROL | B52: =SUM(C52:N52) -> 1372500 | C52: =+USD!C52*MN!$C$1 -> 0 | D52: =+USD!D52*MN!$C$1 -> 1372500 | E52: =+USD!E52*MN!$C$1 -> 0 | F52: =+USD!F52*MN!$C$1 -> 0 | G52: =+USD!G52*MN!$C$1 -> 0 | H52: =+USD!H52*MN!$C$1 -> 0 | I52: =+USD!I52*MN!$C$1 -> 0 | J52: =+USD!J52*MN!$C$1 -> 0 | ... N52: =+USD!N52*MN!$C$1 -> 0
... A75: VALVULAS | B75: =SUM(C75:N75) -> 0 | C75: =+USD!C75*MN!$C$1 -> 0 | D75: =+USD!D75*MN!$C$1 -> 0 | E75: =+USD!E75*MN!$C$1 -> 0 | F75: =+USD!F75*MN!$C$1 -> 0 | G75: =+USD!G75*MN!$C$1 -> 0 | H75: =+USD!H75*MN!$C$1 -> 0 | I75: =+USD!I75*MN!$C$1 -> 0 | J75: =+USD!J75*MN!$C$1 -> 0 | ... N75: =+USD!N75*MN!$C$1 -> 0
A76: MATERIALES | B76: =SUM(B41:B75) -> 54518160 | C76: =SUM(C41:C75) -> 10193100 | D76: =SUM(D41:D75) -> 16527360 | E76: =SUM(E41:E75) -> 7960500 | F76: =SUM(F41:F75) -> 8784000 | G76: =SUM(G41:G75) -> 2104500 | H76: =SUM(H41:H75) -> 1500600 | I76: =SUM(I41:I75) -> 1683600 | ... N76: =SUM(N41:N75) -> 585600
A77: MATERIAL PRIMEROS AUXILIOS | B77: =SUM(C77:N77) -> 0 | C77: =+USD!C77*MN!$C$1 -> 0
A78: MATERIALES DE SALUD | B78: =B77 -> 0 | C78: =C77 -> 0 | D78: =D77 -> 0 | E78: =E77 -> 0 | F78: =F77 -> 0 | G78: =G77 -> 0 | H78: =H77 -> 0 | I78: =I77 -> 0 | ... N78: =N77 -> 0
A79: NOMINA Y ADICIONALES | B79: =SUM(C79:N79) -> 73422002 | C79: =+USD!C79*MN!$C$1 -> 5337502.1 | D79: =+USD!D79*MN!$C$1 -> 5372797.7 | E79: =+USD!E79*MN!$C$1 -> 6271170.2 | F79: =+USD!F79*MN!$C$1 -> 6271170.2 | G79: =+USD!G79*MN!$C$1 -> 6271170.2 | H79: =+USD!H79*MN!$C$1 -> 6271170.2 | I79: =+USD!I79*MN!$C$1 -> 6271170.2 | J79: =+USD!J79*MN!$C$1 -> 6271170.2 | ... N79: =+USD!N79*MN!$C$1 -> 6271170.2
A80: SERV TELEFONIA CELULAR | B80: =SUM(C80:N80) -> 117800 | C80: =+USD!C80*MN!$C$1 -> 9400 | D80: =+USD!D80*MN!$C$1 -> 9400 | E80: =+USD!E80*MN!$C$1 -> 9900 | F80: =+USD!F80*MN!$C$1 -> 9900 | G80: =+USD!G80*MN!$C$1 -> 9900 | H80: =+USD!H80*MN!$C$1 -> 9900 | I80: =+USD!I80*MN!$C$1 -> 9900 | J80: =+USD!J80*MN!$C$1 -> 9900 | ... N80: =+USD!N80*MN!$C$1 -> 9900
A81: SERVICIO DE BANDA ANCHA | B81: =SUM(C81:N81) -> 0 | C81: =+USD!C81*MN!$C$1 -> 0 | D81: =+USD!D81*MN!$C$1 -> 0 | E81: =+USD!E81*MN!$C$1 -> 0 | F81: =+USD!F81*MN!$C$1 -> 0 | G81: =+USD!G81*MN!$C$1 -> 0 | H81: =+USD!H81*MN!$C$1 -> 0 | I81: =+USD!I81*MN!$C$1 -> 0 | J81: =+USD!J81*MN!$C$1 -> 0 | ... N81: =+USD!N81*MN!$C$1 -> 0
A82: SERVICIO DE RADIOCOMUNICACION | B82: =SUM(C82:N82) -> 0 | C82: =+USD!C82*MN!$C$1 -> 0 | D82: =+USD!D82*MN!$C$1 -> 0 | E82: =+USD!E82*MN!$C$1 -> 0 | F82: =+USD!F82*MN!$C$1 -> 0 | G82: =+USD!G82*MN!$C$1 -> 0 | H82: =+USD!H82*MN!$C$1 -> 0 | I82: =+USD!I82*MN!$C$1 -> 0 | J82: =+USD!J82*MN!$C$1 -> 0 | ... N82: =+USD!N82*MN!$C$1 -> 0
A83: SERV TELEFONIA CELULAR Y RADIO | B83: =SUM(B80:B82) -> 117800 | C83: =SUM(C80:C82) -> 9400 | D83: =SUM(D80:D82) -> 9400 | E83: =SUM(E80:E82) -> 9900 | F83: =SUM(F80:F82) -> 9900 | G83: =SUM(G80:G82) -> 9900 | H83: =SUM(H80:H82) -> 9900 | I83: =SUM(I80:I82) -> 9900 | ... N83: =SUM(N80:N82) -> 9900
A84: ACONDICION DE CASA HABITACION | B84: =SUM(C84:N84) -> 0 | C84: =+USD!C84*MN!$C$1 -> 0 | D84: =+USD!D84*MN!$C$1 -> 0 | E84: =+USD!E84*MN!$C$1 -> 0 | F84: =+USD!F84*MN!$C$1 -> 0 | G84: =+USD!G84*MN!$C$1 -> 0 | H84: =+USD!H84*MN!$C$1 -> 0 | I84: =+USD!I84*MN!$C$1 -> 0 | J84: =+USD!J84*MN!$C$1 -> 0 | ... N84: =+USD!N84*MN!$C$1 -> 0
A85: ADICION Y MODIFIC DE MATERIAL | B85: =SUM(C85:N85) -> 0 | C85: =+USD!C85*MN!$C$1 -> 0 | D85: =+USD!D85*MN!$C$1 -> 0 | E85: =+USD!E85*MN!$C$1 -> 0 | F85: =+USD!F85*MN!$C$1 -> 0 | G85: =+USD!G85*MN!$C$1 -> 0 | H85: =+USD!H85*MN!$C$1 -> 0 | I85: =+USD!I85*MN!$C$1 -> 0 | J85: =+USD!J85*MN!$C$1 -> 0 | ... N85: =+USD!N85*MN!$C$1 -> 0
A86: ADQUISICION TARJET COMBUSTIBLE | B86: =SUM(C86:N86) -> 0 | C86: =+USD!C86*MN!$C$1 -> 0 | D86: =+USD!D86*MN!$C$1 -> 0 | E86: =+USD!E86*MN!$C$1 -> 0 | F86: =+USD!F86*MN!$C$1 -> 0 | G86: =+USD!G86*MN!$C$1 -> 0 | H86: =+USD!H86*MN!$C$1 -> 0 | I86: =+USD!I86*MN!$C$1 -> 0 | J86: =+USD!J86*MN!$C$1 -> 0 | ... N86: =+USD!N86*MN!$C$1 -> 0 | P86: 10 tarjetas de combustible
A87: ANALISIS CAUSA RAIZ | B87: =SUM(C87:N87) -> 0 | C87: =+USD!C87*MN!$C$1 -> 0 | D87: =+USD!D87*MN!$C$1 -> 0 | E87: =+USD!E87*MN!$C$1 -> 0 | F87: =+USD!F87*MN!$C$1 -> 0 | G87: =+USD!G87*MN!$C$1 -> 0 | H87: =+USD!H87*MN!$C$1 -> 0 | I87: =+USD!I87*MN!$C$1 -> 0 | J87: =+USD!J87*MN!$C$1 -> 0 | ... N87: =+USD!N87*MN!$C$1 -> 0
A88: ANALISIS DE RIESGO | B88: =SUM(C88:N88) -> 219600 | C88: =+USD!C88*MN!$C$1 -> 0 | D88: =+USD!D88*MN!$C$1 -> 219600 | E88: =+USD!E88*MN!$C$1 -> 0 | F88: =+USD!F88*MN!$C$1 -> 0 | G88: =+USD!G88*MN!$C$1 -> 0 | H88: =+USD!H88*MN!$C$1 -> 0 | I88: =+USD!I88*MN!$C$1 -> 0 | J88: =+USD!J88*MN!$C$1 -> 0 | ... N88: =+USD!N88*MN!$C$1 -> 0
A89: ANALISIS DE VIBRACION | B89: =SUM(C89:N89) -> 0 | C89: =+USD!C89*MN!$C$1 -> 0 | D89: =+USD!D89*MN!$C$1 -> 0 | E89: =+USD!E89*MN!$C$1 -> 0 | F89: =+USD!F89*MN!$C$1 -> 0 | G89: =+USD!G89*MN!$C$1 -> 0 | H89: =+USD!H89*MN!$C$1 -> 0 | I89: =+USD!I89*MN!$C$1 -> 0 | J89: =+USD!J89*MN!$C$1 -> 0 | ... N89: =+USD!N89*MN!$C$1 -> 0
A90: BASES LICITACION Y CONCURSOS | B90: =SUM(C90:N90) -> 0 | C90: =+USD!C90*MN!$C$1 -> 0 | D90: =+USD!D90*MN!$C$1 -> 0 | E90: =+USD!E90*MN!$C$1 -> 0 | F90: =+USD!F90*MN!$C$1 -> 0 | G90: =+USD!G90*MN!$C$1 -> 0 | H90: =+USD!H90*MN!$C$1 -> 0 | I90: =+USD!I90*MN!$C$1 -> 0 | J90: =+USD!J90*MN!$C$1 -> 0 | ... N90: =+USD!N90*MN!$C$1 -> 0
A91: CARGOS EXTRAORDINARIOS | B91: =SUM(C91:N91) -> 0 | C91: =+USD!C91*MN!$C$1 -> 0 | D91: =+USD!D91*MN!$C$1 -> 0 | E91: =+USD!E91*MN!$C$1 -> 0 | F91: =+USD!F91*MN!$C$1 -> 0 | G91: =+USD!G91*MN!$C$1 -> 0 | H91: =+USD!H91*MN!$C$1 -> 0 | I91: =+USD!I91*MN!$C$1 -> 0 | J91: =+USD!J91*MN!$C$1 -> 0 | ... N91: =+USD!N91*MN!$C$1 -> 0
A92: CERTIFICACION | B92: =SUM(C92:N92) -> 1830000 | C92: =+USD!C92*MN!$C$1 -> 0 | D92: =+USD!D92*MN!$C$1 -> 366000 | E92: =+USD!E92*MN!$C$1 -> 0 | F92: =+USD!F92*MN!$C$1 -> 366000 | G92: =+USD!G92*MN!$C$1 -> 366000 | H92: =+USD!H92*MN!$C$1 -> 0 | I92: =+USD!I92*MN!$C$1 -> 366000 | J92: =+USD!J92*MN!$C$1 -> 366000 | ... N92: =+USD!N92*MN!$C$1 -> 0
A93: COLOCACION DE PILOTE | B93: =SUM(C93:N93) -> 0 | C93: =+USD!C93*MN!$C$1 -> 0 | D93: =+USD!D93*MN!$C$1 -> 0 | E93: =+USD!E93*MN!$C$1 -> 0 | F93: =+USD!F93*MN!$C$1 -> 0 | G93: =+USD!G93*MN!$C$1 -> 0 | H93: =+USD!H93*MN!$C$1 -> 0 | I93: =+USD!I93*MN!$C$1 -> 0 | J93: =+USD!J93*MN!$C$1 -> 0 | ... N93: =+USD!N93*MN!$C$1 -> 0
A94: CORREOS Y MENSAJERIAS | B94: =SUM(C94:N94) -> 0 | C94: =+USD!C94*MN!$C$1 -> 0 | D94: =+USD!D94*MN!$C$1 -> 0 | E94: =+USD!E94*MN!$C$1 -> 0 | F94: =+USD!F94*MN!$C$1 -> 0 | G94: =+USD!G94*MN!$C$1 -> 0 | H94: =+USD!H94*MN!$C$1 -> 0 | I94: =+USD!I94*MN!$C$1 -> 0 | J94: =+USD!J94*MN!$C$1 -> 0 | ... N94: =+USD!N94*MN!$C$1 -> 0
A95: CUOTAS Y SUSCRIPCIONES | B95: =SUM(C95:N95) -> 0 | C95: =+USD!C95*MN!$C$1 -> 0 | D95: =+USD!D95*MN!$C$1 -> 0 | E95: =+USD!E95*MN!$C$1 -> 0 | F95: =+USD!F95*MN!$C$1 -> 0 | G95: =+USD!G95*MN!$C$1 -> 0 | H95: =+USD!H95*MN!$C$1 -> 0 | I95: =+USD!I95*MN!$C$1 -> 0 | J95: =+USD!J95*MN!$C$1 -> 0 | ... N95: =+USD!N95*MN!$C$1 -> 0 | P95: zoom, renovación dropbox, renovación licencias SNAP, renovación antivirus, renovación office, servicio anual de hosting web, correo electronico y dominio, cemefi, inscripcion congreso villahermosa, congreso colombia inscripción, renovación plataforma de licitaciones, renovación aquiles, renovacion plataforma proveedores colombia
A96: DEDUCIBLE POR SINIESTRO | B96: =SUM(C96:N96) -> 0 | C96: =+USD!C96*MN!$C$1 -> 0 | D96: =+USD!D96*MN!$C$1 -> 0 | E96: =+USD!E96*MN!$C$1 -> 0 | F96: =+USD!F96*MN!$C$1 -> 0 | G96: =+USD!G96*MN!$C$1 -> 0 | H96: =+USD!H96*MN!$C$1 -> 0 | I96: =+USD!I96*MN!$C$1 -> 0 | J96: =+USD!J96*MN!$C$1 -> 0 | ... N96: =+USD!N96*MN!$C$1 -> 0
A97: DESARROLLO DE SOFTWARE | B97: =SUM(C97:N97) -> 0 | C97: =+USD!C97*MN!$C$1 -> 0 | D97: =+USD!D97*MN!$C$1 -> 0 | E97: =+USD!E97*MN!$C$1 -> 0 | F97: =+USD!F97*MN!$C$1 -> 0 | G97: =+USD!G97*MN!$C$1 -> 0 | H97: =+USD!H97*MN!$C$1 -> 0 | I97: =+USD!I97*MN!$C$1 -> 0 | J97: =+USD!J97*MN!$C$1 -> 0 | ... N97: =+USD!N97*MN!$C$1 -> 0
A98: FIANZAS | B98: =SUM(C98:N98) -> 0 | C98: =+USD!C98*MN!$C$1 -> 0 | D98: =+USD!D98*MN!$C$1 -> 0 | E98: =+USD!E98*MN!$C$1 -> 0 | F98: =+USD!F98*MN!$C$1 -> 0 | G98: =+USD!G98*MN!$C$1 -> 0 | H98: =+USD!H98*MN!$C$1 -> 0 | I98: =+USD!I98*MN!$C$1 -> 0 | J98: =+USD!J98*MN!$C$1 -> 0 | ... N98: =+USD!N98*MN!$C$1 -> 0
A99: FLETES EXTRANJEROS | B99: =SUM(C99:N99) -> 274500 | C99: =+USD!C99*MN!$C$1 -> 0 | D99: =+USD!D99*MN!$C$1 -> 274500 | E99: =+USD!E99*MN!$C$1 -> 0 | F99: =+USD!F99*MN!$C$1 -> 0 | G99: =+USD!G99*MN!$C$1 -> 0 | H99: =+USD!H99*MN!$C$1 -> 0 | I99: =+USD!I99*MN!$C$1 -> 0 | J99: =+USD!J99*MN!$C$1 -> 0 | ... N99: =+USD!N99*MN!$C$1 -> 0
A100: FLETES NACIONALES | B100: =SUM(C100:N100) -> 1958100 | C100: =+USD!C100*MN!$C$1 -> 109800 | D100: =+USD!D100*MN!$C$1 -> 750300 | E100: =+USD!E100*MN!$C$1 -> 109800 | F100: =+USD!F100*MN!$C$1 -> 109800 | G100: =+USD!G100*MN!$C$1 -> 109800 | H100: =+USD!H100*MN!$C$1 -> 109800 | I100: =+USD!I100*MN!$C$1 -> 109800 | J100: =+USD!J100*MN!$C$1 -> 109800 | ... N100: =+USD!N100*MN!$C$1 -> 109800
A101: GASTOS DE IMPORTACION | B101: =SUM(C101:N101) -> 3345240 | C101: =+USD!C101*MN!$C$1 -> 0 | D101: =+USD!D101*MN!$C$1 -> 3345240 | E101: =+USD!E101*MN!$C$1 -> 0 | F101: =+USD!F101*MN!$C$1 -> 0 | G101: =+USD!G101*MN!$C$1 -> 0 | H101: =+USD!H101*MN!$C$1 -> 0 | I101: =+USD!I101*MN!$C$1 -> 0 | J101: =+USD!J101*MN!$C$1 -> 0 | ... N101: =+USD!N101*MN!$C$1 -> 0
A102: GTO EXPED DE SEG/TRAMITE | B102: =SUM(C102:N102) -> 109800 | C102: =+USD!C102*MN!$C$1 -> 0 | D102: =+USD!D102*MN!$C$1 -> 0 | E102: =+USD!E102*MN!$C$1 -> 0 | F102: =+USD!F102*MN!$C$1 -> 0 | G102: =+USD!G102*MN!$C$1 -> 0 | H102: =+USD!H102*MN!$C$1 -> 0 | I102: =+USD!I102*MN!$C$1 -> 0 | J102: =+USD!J102*MN!$C$1 -> 0 | ... N102: =+USD!N102*MN!$C$1 -> 54900
A103: HIELO Y AGUA | B103: =SUM(C103:N103) -> 0 | C103: =+USD!C103*MN!$C$1 -> 0 | D103: =+USD!D103*MN!$C$1 -> 0 | E103: =+USD!E103*MN!$C$1 -> 0 | F103: =+USD!F103*MN!$C$1 -> 0 | G103: =+USD!G103*MN!$C$1 -> 0 | H103: =+USD!H103*MN!$C$1 -> 0 | I103: =+USD!I103*MN!$C$1 -> 0 | J103: =+USD!J103*MN!$C$1 -> 0 | ... N103: =+USD!N103*MN!$C$1 -> 0
A104: HONORARIOS A PERSONA FISICA | B104: =SUM(C104:N104) -> 0 | C104: =+USD!C104*MN!$C$1 -> 0 | D104: =+USD!D104*MN!$C$1 -> 0 | E104: =+USD!E104*MN!$C$1 -> 0 | F104: =+USD!F104*MN!$C$1 -> 0 | G104: =+USD!G104*MN!$C$1 -> 0 | H104: =+USD!H104*MN!$C$1 -> 0 | I104: =+USD!I104*MN!$C$1 -> 0 | J104: =+USD!J104*MN!$C$1 -> 0 | ... N104: =+USD!N104*MN!$C$1 -> 0 | P104: honorarios doctos Assam sucursal Colombia y apostilla de documentos; extra requerimientos de documentos legales para tramites
A105: IMPUESTOS Y DERECHOS | B105: =SUM(C105:N105) -> 0 | C105: =+USD!C105*MN!$C$1 -> 0 | D105: =+USD!D105*MN!$C$1 -> 0 | E105: =+USD!E105*MN!$C$1 -> 0 | F105: =+USD!F105*MN!$C$1 -> 0 | G105: =+USD!G105*MN!$C$1 -> 0 | H105: =+USD!H105*MN!$C$1 -> 0 | I105: =+USD!I105*MN!$C$1 -> 0 | J105: =+USD!J105*MN!$C$1 -> 0 | ... N105: =+USD!N105*MN!$C$1 -> 0
A106: INTERNET Y DATOS | B106: =SUM(C106:N106) -> 208400 | C106: =+USD!C106*MN!$C$1 -> 17366.667 | D106: =+USD!D106*MN!$C$1 -> 17366.667 | E106: =+USD!E106*MN!$C$1 -> 17366.667 | F106: =+USD!F106*MN!$C$1 -> 17366.667 | G106: =+USD!G106*MN!$C$1 -> 17366.667 | H106: =+USD!H106*MN!$C$1 -> 17366.667 | I106: =+USD!I106*MN!$C$1 -> 17366.667 | J106: =+USD!J106*MN!$C$1 -> 17366.667 | ... N106: =+USD!N106*MN!$C$1 -> 17366.667 | P106: internet oficina veracruz
A107: MANIOBRAS | B107: =SUM(C107:N107) -> 0 | C107: =+USD!C107*MN!$C$1 -> 0 | D107: =+USD!D107*MN!$C$1 -> 0 | E107: =+USD!E107*MN!$C$1 -> 0 | F107: =+USD!F107*MN!$C$1 -> 0 | G107: =+USD!G107*MN!$C$1 -> 0 | H107: =+USD!H107*MN!$C$1 -> 0 | I107: =+USD!I107*MN!$C$1 -> 0 | J107: =+USD!J107*MN!$C$1 -> 0 | ... N107: =+USD!N107*MN!$C$1 -> 0
A108: MANTENIMIENTO A VEHICULOS | B108: =SUM(C108:N108) -> 360000 | C108: =+USD!C108*MN!$C$1 -> 30000 | D108: =+USD!D108*MN!$C$1 -> 30000 | E108: =+USD!E108*MN!$C$1 -> 30000 | F108: =+USD!F108*MN!$C$1 -> 30000 | G108: =+USD!G108*MN!$C$1 -> 30000 | H108: =+USD!H108*MN!$C$1 -> 30000 | I108: =+USD!I108*MN!$C$1 -> 30000 | J108: =+USD!J108*MN!$C$1 -> 30000 | ... N108: =+USD!N108*MN!$C$1 -> 30000
A109: MANTTO A EQUIPOS DE SEGURIDAD | B109: =SUM(C109:N109) -> 1098000 | C109: =+USD!C109*MN!$C$1 -> 0 | D109: =+USD!D109*MN!$C$1 -> 0 | E109: =+USD!E109*MN!$C$1 -> 0 | F109: =+USD!F109*MN!$C$1 -> 183000 | G109: =+USD!G109*MN!$C$1 -> 0 | H109: =+USD!H109*MN!$C$1 -> 183000 | I109: =+USD!I109*MN!$C$1 -> 0 | J109: =+USD!J109*MN!$C$1 -> 183000 | ... N109: =+USD!N109*MN!$C$1 -> 183000
A110: MANTTO DE MOBILIARIO Y EQUIPO | B110: =SUM(C110:N110) -> 0 | C110: =+USD!C110*MN!$C$1 -> 0 | D110: =+USD!D110*MN!$C$1 -> 0 | E110: =+USD!E110*MN!$C$1 -> 0 | F110: =+USD!F110*MN!$C$1 -> 0 | G110: =+USD!G110*MN!$C$1 -> 0 | H110: =+USD!H110*MN!$C$1 -> 0 | I110: =+USD!I110*MN!$C$1 -> 0 | J110: =+USD!J110*MN!$C$1 -> 0 | ... N110: =+USD!N110*MN!$C$1 -> 0
A111: MANTTO PREV A EQUIPOS DE MEDICION | B111: =SUM(C111:N111) -> 1098000 | C111: =+USD!C111*MN!$C$1 -> 0 | D111: =+USD!D111*MN!$C$1 -> 0 | E111: =+USD!E111*MN!$C$1 -> 0 | F111: =+USD!F111*MN!$C$1 -> 183000 | G111: =+USD!G111*MN!$C$1 -> 0 | H111: =+USD!H111*MN!$C$1 -> 183000 | I111: =+USD!I111*MN!$C$1 -> 0 | J111: =+USD!J111*MN!$C$1 -> 183000 | ... N111: =+USD!N111*MN!$C$1 -> 183000
A112: MANTTO Y ACONDICION DE CAMPER | B112: =SUM(C112:N112) -> 0 | C112: =+USD!C112*MN!$C$1 -> 0 | D112: =+USD!D112*MN!$C$1 -> 0 | E112: =+USD!E112*MN!$C$1 -> 0 | F112: =+USD!F112*MN!$C$1 -> 0 | G112: =+USD!G112*MN!$C$1 -> 0 | H112: =+USD!H112*MN!$C$1 -> 0 | I112: =+USD!I112*MN!$C$1 -> 0 | J112: =+USD!J112*MN!$C$1 -> 0 | ... N112: =+USD!N112*MN!$C$1 -> 0
A113: MECANICA DE SUELOS | B113: =SUM(C113:N113) -> 0 | C113: =+USD!C113*MN!$C$1 -> 0 | D113: =+USD!D113*MN!$C$1 -> 0 | E113: =+USD!E113*MN!$C$1 -> 0 | F113: =+USD!F113*MN!$C$1 -> 0 | G113: =+USD!G113*MN!$C$1 -> 0 | H113: =+USD!H113*MN!$C$1 -> 0 | I113: =+USD!I113*MN!$C$1 -> 0 | J113: =+USD!J113*MN!$C$1 -> 0 | ... N113: =+USD!N113*MN!$C$1 -> 0
A114: OTROS DERECHOS | B114: =SUM(C114:N114) -> 0 | C114: =+USD!C114*MN!$C$1 -> 0 | D114: =+USD!D114*MN!$C$1 -> 0 | E114: =+USD!E114*MN!$C$1 -> 0 | F114: =+USD!F114*MN!$C$1 -> 0 | G114: =+USD!G114*MN!$C$1 -> 0 | H114: =+USD!H114*MN!$C$1 -> 0 | I114: =+USD!I114*MN!$C$1 -> 0 | J114: =+USD!J114*MN!$C$1 -> 0 | ... N114: =+USD!N114*MN!$C$1 -> 0
A115: PACMA PEMEX EXPLORACION | B115: =SUM(C115:N115) -> 0 | C115: =+USD!C115*MN!$C$1 -> 0 | D115: =+USD!D115*MN!$C$1 -> 0 | E115: =+USD!E115*MN!$C$1 -> 0 | F115: =+USD!F115*MN!$C$1 -> 0 | G115: =+USD!G115*MN!$C$1 -> 0 | H115: =+USD!H115*MN!$C$1 -> 0 | I115: =+USD!I115*MN!$C$1 -> 0 | J115: =+USD!J115*MN!$C$1 -> 0 | ... N115: =+USD!N115*MN!$C$1 -> 0
A116: PAGO DE RECARGOS | B116: =SUM(C116:N116) -> 0 | C116: =+USD!C116*MN!$C$1 -> 0 | D116: =+USD!D116*MN!$C$1 -> 0 | E116: =+USD!E116*MN!$C$1 -> 0 | F116: =+USD!F116*MN!$C$1 -> 0 | G116: =+USD!G116*MN!$C$1 -> 0 | H116: =+USD!H116*MN!$C$1 -> 0 | I116: =+USD!I116*MN!$C$1 -> 0 | J116: =+USD!J116*MN!$C$1 -> 0 | ... N116: =+USD!N116*MN!$C$1 -> 0
A117: RECARGA DE GASES INDUSTRIALES | B117: =SUM(C117:N117) -> 0 | C117: =+USD!C117*MN!$C$1 -> 0 | D117: =+USD!D117*MN!$C$1 -> 0 | E117: =+USD!E117*MN!$C$1 -> 0 | F117: =+USD!F117*MN!$C$1 -> 0 | G117: =+USD!G117*MN!$C$1 -> 0 | H117: =+USD!H117*MN!$C$1 -> 0 | I117: =+USD!I117*MN!$C$1 -> 0 | J117: =+USD!J117*MN!$C$1 -> 0 | ... N117: =+USD!N117*MN!$C$1 -> 0
A118: RENTA DE MAQUINARIA Y EQUIPO | B118: =SUM(C118:N118) -> 111826800 | C118: =+USD!C118*MN!$C$1 -> 10075300 | D118: =+USD!D118*MN!$C$1 -> 10075300 | E118: =+USD!E118*MN!$C$1 -> 10075300 | F118: =+USD!F118*MN!$C$1 -> 10075300 | G118: =+USD!G118*MN!$C$1 -> 8940700 | H118: =+USD!H118*MN!$C$1 -> 8940700 | I118: =+USD!I118*MN!$C$1 -> 8940700 | J118: =+USD!J118*MN!$C$1 -> 8940700 | ... N118: =+USD!N118*MN!$C$1 -> 8940700
... A126: SERV DE TRANSMISION DE DATOS | B126: =SUM(C126:N126) -> 0 | C126: =+USD!C126*MN!$C$1 -> 0 | D126: =+USD!D126*MN!$C$1 -> 0 | E126: =+USD!E126*MN!$C$1 -> 0 | F126: =+USD!F126*MN!$C$1 -> 0 | G126: =+USD!G126*MN!$C$1 -> 0 | H126: =+USD!H126*MN!$C$1 -> 0 | I126: =+USD!I126*MN!$C$1 -> 0 | J126: =+USD!J126*MN!$C$1 -> 0 | ... N126: =+USD!N126*MN!$C$1 -> 0
A127: SERV PROFES DE PERSONA MORAL | B127: =SUM(C127:N127) -> 0 | C127: =+USD!C127*MN!$C$1 -> 0 | D127: =+USD!D127*MN!$C$1 -> 0 | E127: =+USD!E127*MN!$C$1 -> 0 | F127: =+USD!F127*MN!$C$1 -> 0 | G127: =+USD!G127*MN!$C$1 -> 0 | H127: =+USD!H127*MN!$C$1 -> 0 | I127: =+USD!I127*MN!$C$1 -> 0 | J127: =+USD!J127*MN!$C$1 -> 0 | ... N127: =+USD!N127*MN!$C$1 -> 0 | P127: Auditoria estados financieros 2020, estudio de precios de transferencia 2019, estudio de precios de transferencia 2020, gastos Arturo Tangarife Colombia, gastos revisor fiscal Colombia, EQA, reembolsos CIA, asesoria mensual leonides por 6 meses
A128: SERV Y MANTTO A EQ INFORMATICO | B128: =SUM(C128:N128) -> 0 | C128: =+USD!C128*MN!$C$1 -> 0 | D128: =+USD!D128*MN!$C$1 -> 0 | E128: =+USD!E128*MN!$C$1 -> 0 | F128: =+USD!F128*MN!$C$1 -> 0 | G128: =+USD!G128*MN!$C$1 -> 0 | H128: =+USD!H128*MN!$C$1 -> 0 | I128: =+USD!I128*MN!$C$1 -> 0 | J128: =+USD!J128*MN!$C$1 -> 0 | ... N128: =+USD!N128*MN!$C$1 -> 0
A129: SERVICIO DE AUTOLAVADO | B129: =SUM(C129:N129) -> 0 | C129: =+USD!C129*MN!$C$1 -> 0 | D129: =+USD!D129*MN!$C$1 -> 0 | E129: =+USD!E129*MN!$C$1 -> 0 | F129: =+USD!F129*MN!$C$1 -> 0 | G129: =+USD!G129*MN!$C$1 -> 0 | H129: =+USD!H129*MN!$C$1 -> 0 | I129: =+USD!I129*MN!$C$1 -> 0 | J129: =+USD!J129*MN!$C$1 -> 0 | ... N129: =+USD!N129*MN!$C$1 -> 0
A130: SERVICIO DE EQPO Y MAQUINARIA | B130: =SUM(C130:N130) -> 0 | C130: =+USD!C130*MN!$C$1 -> 0 | D130: =+USD!D130*MN!$C$1 -> 0 | E130: =+USD!E130*MN!$C$1 -> 0 | F130: =+USD!F130*MN!$C$1 -> 0 | G130: =+USD!G130*MN!$C$1 -> 0 | H130: =+USD!H130*MN!$C$1 -> 0 | I130: =+USD!I130*MN!$C$1 -> 0 | J130: =+USD!J130*MN!$C$1 -> 0 | ... N130: =+USD!N130*MN!$C$1 -> 0
...
